Workbook
Name labour: #REF!
Name PAY_1: #REF!
Name PAY_2: #REF!
Name PAY_3: #REF!
Name PV: #REF!
Name PVRepair: #REF!
Name q: #REF!
Name Rangetest: #REF!
Name Rep_1: #REF!
Name Rep_2: #REF!
Name Rep_3: #REF!

Sheet AUC Grand Total  Budget 
E2: =F15/C15 -> 4750 | I2: =850*30*6 -> 153000 | J2: =K2*6 -> 180 | K2: 30
G3: =F16/2 -> 4250 | M3: INNER CAMPUS Budget | T3: OUTER CAMPUS Budget | AA3: NEW CAIRO OFF CAMPUS HOUSING Budget | AH3: Maadi Buildings Budget
B4: NC INNER CAMPUS Budget | C4: High | D4: Low | F4: CTC | G4: High Season | I4: Low Season | M4: High | N4: Low | O4: High Season | Q4: Low Season | T4: High | U4: Low | V4: High Season | X4: Low Season | AA4: High | AB4: Low | AC4: High Season | AE4: Low Season | AH4: High | AI4: Low | AJ4: High Season | AL4: Low Season
C5: Head Count | D5: Head Count | G5: Monthly | H5: Annually "8"Months | I5: Monthly | J5: Annually "4"Months | M5: Head Count | N5: Head Count | O5: Monthly | P5: Annually "8"Months | Q5: Monthly | R5: Annually "4"Months | T5: Head Count | U5: Head Count | V5: Monthly | W5: Annually "8"Months | X5: Monthly | Y5: Annually "4"Months | AA5: Head Count | AB5: Head Count | AC5: Monthly | AD5: Annually "8"Months | AE5: Monthly | AF5: Annually "4"Months | AH5: Head Count | AI5: Head Count | AJ5: Monthly | AK5: Annually "8"Months | AL5: Monthly | AM5: Annually "4"Months
B6: HK Manager | C6: 1 | D6: 1 | F6: 32500 | G6: =C6*F6 -> 32500 | H6: =G6*8 -> 260000 | I6: =D6*F6 -> 32500 | J6: =I6*4 -> 130000 | K6: =(O6+V6+AC6+AJ6)-G6 -> 0 | L6: =(Q6+X6+AE6+AL6)-I6 -> 0 | M6: 0.75 | N6: 0.75 | O6: =F6*M6 -> 24375 | P6: =O6*8 -> 195000 | Q6: =N6*F6 -> 24375 | R6: =Q6*4 -> 97500 | T6: 0.25 | U6: 0.25 | V6: =T6*F6 -> 8125 | W6: =V6*8 -> 65000 | X6: =U6*F6 -> 8125 | Y6: =X6*4 -> 32500 | AC6: =AA6*F6 -> 0 | AD6: =AC6*8 -> 0 | AE6: =AB6*F6 -> 0 | AF6: =AE6*4 -> 0 | AJ6: =AH6*F6 -> 0 | AK6: =AJ6*8 -> 0 | AL6: =AI6*F6 -> 0 | AM6: =AL6*4 -> 0
B7: Ass. Manger | C7: 5 | D7: 5 | E7: 15500 | F7: 18500 | G7: =C7*F7 -> 92500 | H7: =G7*8 -> 740000 | I7: =D7*F7 -> 92500 | J7: =I7*4 -> 370000 | K7: =(O7+V7+AC7+AJ7)-G7 -> 0 | L7: =(Q7+X7+AE7+AL7)-I7 -> 0 | M7: 3 | N7: 3 | O7: =F7*M7 -> 55500 | P7: =O7*8 -> 444000 | Q7: =N7*F7 -> 55500 | R7: =Q7*4 -> 222000 | T7: 2 | U7: 2 | V7: =T7*F7 -> 37000 | W7: =V7*8 -> 296000 | X7: =U7*F7 -> 37000 | Y7: =X7*4 -> 148000 | AC7: =AA7*F7 -> 0 | AD7: =AC7*8 -> 0 | AE7: =AB7*F7 -> 0 | AF7: =AE7*4 -> 0 | AJ7: =AH7*F7 -> 0 | AK7: =AJ7*8 -> 0 | AL7: =AI7*F7 -> 0 | AM7: =AL7*4 -> 0
B8: Sienior Supervisor | C8: 5 | D8: 5 | E8: 11000 | F8: 13000 | G8: =C8*F8 -> 65000 | H8: =G8*8 -> 520000 | I8: =D8*F8 -> 65000 | J8: =I8*4 -> 260000 | K8: =(O8+V8+AC8+AJ8)-G8 -> 0 | L8: =(Q8+X8+AE8+AL8)-I8 -> 0 | M8: 3 | N8: 3 | O8: =F8*M8 -> 39000 | P8: =O8*8 -> 312000 | Q8: =N8*F8 -> 39000 | R8: =Q8*4 -> 156000 | T8: 2 | U8: 2 | V8: =T8*F8 -> 26000 | W8: =V8*8 -> 208000 | X8: =U8*F8 -> 26000 | Y8: =X8*4 -> 104000 | AC8: =AA8*F8 -> 0 | AD8: =AC8*8 -> 0 | AE8: =AB8*F8 -> 0 | AF8: =AE8*4 -> 0 | AJ8: =AH8*F8 -> 0 | AK8: =AJ8*8 -> 0 | AL8: =AI8*F8 -> 0 | AM8: =AL8*4 -> 0
B9: Supervisor 8H | C9: =M9+T9+AA9+AH9 -> 28 | D9: =N9+U9+AB9+AI9 -> 14 | E9: 8100 | F9: 8000 | G9: =C9*F9 -> 224000 | H9: =G9*8 -> 1792000 | I9: =D9*F9 -> 112000 | J9: =I9*4 -> 448000 | K9: =(O9+V9+AC9+AJ9)-G9 -> 0 | L9: =(Q9+X9+AE9+AL9)-I9 -> 0 | M9: 21 | N9: 11 | O9: =F9*M9 -> 168000 | P9: =O9*8 -> 1344000 | Q9: =N9*F9 -> 88000 | R9: =Q9*4 -> 352000 | T9: 7 | U9: 3 | V9: =T9*F9 -> 56000 | W9: =V9*8 -> 448000 | X9: =U9*F9 -> 24000 | Y9: =X9*4 -> 96000 | AC9: =AA9*F9 -> 0 | AD9: =AC9*8 -> 0 | AE9: =AB9*F9 -> 0 | AF9: =AE9*4 -> 0 | AJ9: =AH9*F9 -> 0 | AK9: =AJ9*8 -> 0 | AL9: =AI9*F9 -> 0 | AM9: =AL9*4 -> 0
B10: HK Male & Female 8H | C10: =M10+T10+AA10+AH10 -> 282 | D10: =N10+U10+AB10+AI10 -> 134 | E10: 4200 | F10: 4150 | G10: =C10*F10 -> 1170300 | H10: =G10*8 -> 9362400 | I10: =D10*F10 -> 556100 | J10: =I10*4 -> 2224400 | K10: =(O10+V10+AC10+AJ10)-G10 -> 0 | L10: =(Q10+X10+AE10+AL10)-I10 -> 0 | M10: 199 | N10: 95 | O10: =F10*M10 -> 825850 | P10: =O10*8 -> 6606800 | Q10: =N10*F10 -> 394250 | R10: =Q10*4 -> 1577000 | T10: 79 | U10: 35 | V10: =T10*F10 -> 327850 | W10: =V10*8 -> 2622800 | X10: =U10*F10 -> 145250 | Y10: =X10*4 -> 581000 | AA10: 3 | AB10: 3 | AC10: =AA10*F10 -> 12450 | AD10: =AC10*8 -> 99600 | AE10: =AB10*F10 -> 12450 | AF10: =AE10*4 -> 49800 | AH10: 1 | AI10: 1 | AJ10: =AH10*F10 -> 4150 | AK10: =AJ10*8 -> 33200 | AL10: =AI10*F10 -> 4150 | AM10: =AL10*4 -> 16600
B11: Facades Supervisor 8H | C11: =M11+T11+AA11+AH11 -> 1 | D11: =N11+U11+AB11+AI11 -> 1 | F11: 11000 | G11: =C11*F11 -> 11000 | H11: =G11*8 -> 88000 | I11: =D11*F11 -> 11000 | J11: =I11*4 -> 44000 | K11: =(O11+V11+AC11+AJ11)-G11 -> 0 | L11: =(Q11+X11+AE11+AL11)-I11 -> 0 | M11: 0.75 | N11: 0.75 | O11: =F11*M11 -> 8250 | P11: =O11*8 -> 66000 | Q11: =N11*F11 -> 8250 | R11: =Q11*4 -> 33000 | T11: 0.25 | U11: 0.25 | V11: =T11*F11 -> 2750 | W11: =V11*8 -> 22000 | X11: =U11*F11 -> 2750 | Y11: =X11*4 -> 11000 | AC11: =AA11*F11 -> 0 | AD11: =AC11*8 -> 0 | AE11: =AB11*F11 -> 0 | AF11: =AE11*4 -> 0 | AJ11: =AH11*F11 -> 0 | AK11: =AJ11*8 -> 0 | AL11: =AI11*F11 -> 0 | AM11: =AL11*4 -> 0
B12: Facades Labor 8H | C12: =M12+T12+AA12+AH12 -> 4 | D12: =N12+U12+AB12+AI12 -> 4 | F12: 8000 | G12: =C12*F12 -> 32000 | H12: =G12*8 -> 256000 | I12: =D12*F12 -> 32000 | J12: =I12*4 -> 128000 | K12: =(O12+V12+AC12+AJ12)-G12 -> 0 | L12: =(Q12+X12+AE12+AL12)-I12 -> 0 | M12: 3 | N12: 3 | O12: =F12*M12 -> 24000 | P12: =O12*8 -> 192000 | Q12: =N12*F12 -> 24000 | R12: =Q12*4 -> 96000 | T12: 1 | U12: 1 | V12: =T12*F12 -> 8000 | W12: =V12*8 -> 64000 | X12: =U12*F12 -> 8000 | Y12: =X12*4 -> 32000 | AC12: =AA12*F12 -> 0 | AD12: =AC12*8 -> 0 | AE12: =AB12*F12 -> 0 | AF12: =AE12*4 -> 0 | AJ12: =AH12*F12 -> 0 | AK12: =AJ12*8 -> 0 | AL12: =AI12*F12 -> 0 | AM12: =AL12*4 -> 0
B13: Supervisor Waste 8H | C13: =M13+T13+AA13+AH13 -> 3 | D13: =N13+U13+AB13+AI13 -> 3 | F13: 8000 | G13: =C13*F13 -> 24000 | H13: =G13*8 -> 192000 | I13: =D13*F13 -> 24000 | J13: =I13*4 -> 96000 | K13: =(O13+V13+AC13+AJ13)-G13 -> 0 | L13: =(Q13+X13+AE13+AL13)-I13 -> 0 | M13: 2 | N13: 2 | O13: =F13*M13 -> 16000 | P13: =O13*8 -> 128000 | Q13: =N13*F13 -> 16000 | R13: =Q13*4 -> 64000 | T13: 1 | U13: 1 | V13: =T13*F13 -> 8000 | W13: =V13*8 -> 64000 | X13: =U13*F13 -> 8000 | Y13: =X13*4 -> 32000 | AC13: =AA13*F13 -> 0 | AD13: =AC13*8 -> 0 | AE13: =AB13*F13 -> 0 | AF13: =AE13*4 -> 0 | AJ13: =AH13*F13 -> 0 | AK13: =AJ13*8 -> 0 | AL13: =AI13*F13 -> 0 | AM13: =AL13*4 -> 0
B14: Labor Waste 8H | C14: =M14+T14+AA14+AH14 -> 12 | D14: =N14+U14+AB14+AI14 -> 8 | F14: 5000 | G14: =C14*F14 -> 60000 | H14: =G14*8 -> 480000 | I14: =D14*F14 -> 40000 | J14: =I14*4 -> 160000 | K14: =(O14+V14+AC14+AJ14)-G14 -> 0 | L14: =(Q14+X14+AE14+AL14)-I14 -> 0 | M14: 8 | N14: 6 | O14: =F14*M14 -> 40000 | P14: =O14*8 -> 320000 | Q14: =N14*F14 -> 30000 | R14: =Q14*4 -> 120000 | T14: 4 | U14: 2 | V14: =T14*F14 -> 20000 | W14: =V14*8 -> 160000 | X14: =U14*F14 -> 10000 | Y14: =X14*4 -> 40000 | AC14: =AA14*F14 -> 0 | AD14: =AC14*8 -> 0 | AE14: =AB14*F14 -> 0 | AF14: =AE14*4 -> 0 | AJ14: =AH14*F14 -> 0 | AK14: =AJ14*8 -> 0 | AL14: =AI14*F14 -> 0 | AM14: =AL14*4 -> 0
B15: Admin | C15: =M15+T15+AA15+AH15 -> 2 | D15: =N15+U15+AB15+AI15 -> 2 | E15: 10000 | F15: 9500 | G15: =C15*F15 -> 19000 | H15: =G15*8 -> 152000 | I15: =D15*F15 -> 19000 | J15: =I15*4 -> 76000 | K15: =(O15+V15+AC15+AJ15)-G15 -> 0 | L15: =(Q15+X15+AE15+AL15)-I15 -> 0 | M15: 1 | N15: 1 | O15: =F15*M15 -> 9500 | P15: =O15*8 -> 76000 | Q15: =N15*F15 -> 9500 | R15: =Q15*4 -> 38000 | T15: 1 | U15: 1 | V15: =T15*F15 -> 9500 | W15: =V15*8 -> 76000 | X15: =U15*F15 -> 9500 | Y15: =X15*4 -> 38000 | AC15: =AA15*F15 -> 0 | AD15: =AC15*8 -> 0 | AE15: =AB15*F15 -> 0 | AF15: =AE15*4 -> 0 | AJ15: =AH15*F15 -> 0 | AK15: =AJ15*8 -> 0 | AL15: =AI15*F15 -> 0 | AM15: =AL15*4 -> 0
B16: Storekeeper | C16: =M16+T16+AA16+AH16 -> 2 | D16: =N16+U16+AB16+AI16 -> 2 | E16: 10000 | F16: 8500 | G16: =C16*F16 -> 17000 | H16: =G16*8 -> 136000 | I16: =D16*F16 -> 17000 | J16: =I16*4 -> 68000 | K16: =(O16+V16+AC16+AJ16)-G16 -> 0 | L16: =(Q16+X16+AE16+AL16)-I16 -> 0 | M16: 1 | N16: 1 | O16: =F16*M16 -> 8500 | P16: =O16*8 -> 68000 | Q16: =N16*F16 -> 8500 | R16: =Q16*4 -> 34000 | T16: 1 | U16: 1 | V16: =T16*F16 -> 8500 | W16: =V16*8 -> 68000 | X16: =U16*F16 -> 8500 | Y16: =X16*4 -> 34000 | AC16: =AA16*F16 -> 0 | AD16: =AC16*8 -> 0 | AE16: =AB16*F16 -> 0 | AF16: =AE16*4 -> 0 | AJ16: =AH16*F16 -> 0 | AK16: =AJ16*8 -> 0 | AL16: =AI16*F16 -> 0 | AM16: =AL16*4 -> 0
B17: Drivers | C17: =M17+T17+AA17+AH17 -> 6 | D17: =N17+U17+AB17+AI17 -> 6 | E17: 10000 | F17: 8500 | G17: =C17*F17 -> 51000 | H17: =G17*8 -> 408000 | I17: =D17*F17 -> 51000 | J17: =I17*4 -> 204000 | K17: =(O17+V17+AC17+AJ17)-G17 -> 0 | L17: =(Q17+X17+AE17+AL17)-I17 -> 0 | M17: 4 | N17: 4 | O17: =F17*M17 -> 34000 | P17: =O17*8 -> 272000 | Q17: =N17*F17 -> 34000 | R17: =Q17*4 -> 136000 | T17: 2 | U17: 2 | V17: =T17*F17 -> 17000 | W17: =V17*8 -> 136000 | X17: =U17*F17 -> 17000 | Y17: =X17*4 -> 68000 | AC17: =AA17*F17 -> 0 | AD17: =AC17*8 -> 0 | AE17: =AB17*F17 -> 0 | AF17: =AE17*4 -> 0 | AJ17: =AH17*F17 -> 0 | AK17: =AJ17*8 -> 0 | AL17: =AI17*F17 -> 0 | AM17: =AL17*4 -> 0
B18: Trainer | C18: =M18+T18+AA18+AH18 -> 1 | D18: =N18+U18+AB18+AI18 -> 1 | F18: 9500 | G18: =C18*F18 -> 9500 | H18: =G18*8 -> 76000 | I18: =D18*F18 -> 9500 | J18: =I18*4 -> 38000 | K18: =(O18+V18+AC18+AJ18)-G18 -> 0 | L18: =(Q18+X18+AE18+AL18)-I18 -> 0 | M18: 0.75 | N18: 0.75 | O18: =F18*M18 -> 7125 | P18: =O18*8 -> 57000 | Q18: =N18*F18 -> 7125 | R18: =Q18*4 -> 28500 | T18: 0.25 | U18: 0.25 | V18: =T18*F18 -> 2375 | W18: =V18*8 -> 19000 | X18: =U18*F18 -> 2375 | Y18: =X18*4 -> 9500 | AC18: =AA18*F18 -> 0 | AD18: =AC18*8 -> 0 | AE18: =AB18*F18 -> 0 | AF18: =AE18*4 -> 0 | AJ18: =AH18*F18 -> 0 | AK18: =AJ18*8 -> 0 | AL18: =AI18*F18 -> 0 | AM18: =AL18*4 -> 0
B19: Supervisor 8H R | C19: =M19+T19+AA19+AH19 -> 3 | D19: =N19+U19+AB19+AI19 -> 2 | F19: 8000 | G19: =C19*F19 -> 24000 | H19: =G19*8 -> 192000 | I19: =D19*F19 -> 16000 | J19: =I19*4 -> 64000 | K19: =(O19+V19+AC19+AJ19)-G19 -> 0 | L19: =(Q19+X19+AE19+AL19)-I19 -> 0 | M19: 2 | N19: 1 | O19: =F19*M19 -> 16000 | P19: =O19*8 -> 128000 | Q19: =N19*F19 -> 8000 | R19: =Q19*4 -> 32000 | T19: 1 | U19: 1 | V19: =T19*F19 -> 8000 | W19: =V19*8 -> 64000 | X19: =U19*F19 -> 8000 | Y19: =X19*4 -> 32000 | AC19: =AA19*F19 -> 0 | AD19: =AC19*8 -> 0 | AE19: =AB19*F19 -> 0 | AF19: =AE19*4 -> 0 | AJ19: =AH19*F19 -> 0 | AK19: =AJ19*8 -> 0 | AL19: =AI19*F19 -> 0 | AM19: =AL19*4 -> 0
B20: HK Female 8H R | C20: =M20+T20+AA20+AH20 -> 23 | D20: =N20+U20+AB20+AI20 -> 0 | F20: 4150 | G20: =C20*F20 -> 95450 | H20: =G20*8 -> 763600 | I20: =D20*F20 -> 0 | J20: =I20*4 -> 0 | K20: =(O20+V20+AC20+AJ20)-G20 -> 0 | L20: =(Q20+X20+AE20+AL20)-I20 -> 0 | M20: 16 | N20: 0 | O20: =F20*M20 -> 66400 | P20: =O20*8 -> 531200 | Q20: =N20*F20 -> 0 | R20: =Q20*4 -> 0 | T20: 7 | U20: 0 | V20: =T20*F20 -> 29050 | W20: =V20*8 -> 232400 | X20: =U20*F20 -> 0 | Y20: =X20*4 -> 0 | AC20: =AA20*F20 -> 0 | AD20: =AC20*8 -> 0 | AE20: =AB20*F20 -> 0 | AF20: =AE20*4 -> 0 | AJ20: =AH20*F20 -> 0 | AK20: =AJ20*8 -> 0 | AL20: =AI20*F20 -> 0 | AM20: =AL20*4 -> 0
B21: Uniform & PPE
B22: Uniform & PPE | C22: =SUM(C6:C20) -> 378 | D22: =SUM(D6:D20) -> 188 | F22: 450 | G22: =C22*F22 -> 170100 | H22: =G22*8 -> 1360800 | I22: =D22*F22 -> 84600 | J22: =I22*4 -> 338400 | K22: =(O22+V22+AC22+AJ22)-G22 -> 0 | L22: =(Q22+X22+AE22+AL22)-I22 -> 0 | M22: =SUM(M6:M21) -> 265.25 | N22: =SUM(N6:N21) -> 132.25 | O22: =F22*M22 -> 119362.5 | P22: =O22*8 -> 954900 | Q22: =N22*F22 -> 59512.5 | R22: =Q22*4 -> 238050 | T22: =SUM(T6:T21) -> 108.75 | U22: =SUM(U6:U21) -> 51.75 | V22: =T22*F22 -> 48937.5 | W22: =V22*8 -> 391500 | X22: =U22*F22 -> 23287.5 | Y22: =X22*4 -> 93150 | AA22: =SUM(AA6:AA21) -> 3 | AB22: =SUM(AB6:AB21) -> 3 | AC22: =AA22*F22 -> 1350 | AD22: =AC22*8 -> 10800 | AE22: =AB22*F22 -> 1350 | AF22: =AE22*4 -> 5400 | AH22: =SUM(AH6:AH21) -> 1 | AI22: =SUM(AI6:AI21) -> 1 | AJ22: =AH22*F22 -> 450 | AK22: =AJ22*8 -> 3600 | AL22: =AI22*F22 -> 450 | AM22: =AL22*4 -> 1800
B23: Tools and Consumables
B24: Machinery | C24: 1 | D24: 1 | G24: =O24+V24+AC24+AJ24 -> 466131.33 | H24: =G24*8 -> 3729050.7 | I24: =Q24+X24+AE24+AL24 -> 336132 | J24: 814666.67 | K24: =(O24+V24+AC24+AJ24)-G24 -> 0 | L24: =(Q24+X24+AE24+AL24)-I24 -> 0 | O24: 288666 | P24: =O24*8 -> 2309328 | Q24: 203666 | R24: =Q24*4 -> 814664 | V24: 171416 | W24: =V24*8 -> 1371328 | X24: 126416 | Y24: =X24*4 -> 505664 | AC24: 3491 | AD24: =AC24*8 -> 27928 | AE24: 3491.6667 | AF24: =AE24*4 -> 13966.667 | AJ24: 2558.3333 | AK24: =AJ24*8 -> 20466.667 | AL24: 2558.3333 | AM24: =AL24*4 -> 10233.333
B25: Tools | C25: 1 | D25: 1 | G25: =O25+V25+AC25+AJ25 -> 215230.07 | H25: =G25*8 -> 1721840.6 | I25: =Q25+X25+AE25+AL25 -> 155080.93 | J25: 448983.33 | K25: =(O25+V25+AC25+AJ25)-G25 -> 0 | L25: =(Q25+X25+AE25+AL25)-I25 -> 0 | O25: 165200 | P25: =O25*8 -> 1321600 | Q25: 112245 | R25: =Q25*4 -> 448980 | V25: 40443 | W25: =V25*8 -> 323544 | X25: 33248 | Y25: =X25*4 -> 132992 | AC25: 7247 | AD25: =AC25*8 -> 57976 | AE25: 7247.8611 | AF25: =AE25*4 -> 28991.444 | AJ25: 2340.0694 | AK25: =AJ25*8 -> 18720.556 | AL25: 2340.0694 | AM25: =AL25*4 -> 9360.2778
B26: Consumables | C26: 1 | D26: 1 | G26: =O26+V26+AC26+AJ26 -> 834838.31 | H26: =G26*8 -> 6678706.4 | I26: =Q26+X26+AE26+AL26 -> 268267.39 | J26: 597553.04 | K26: =(O26+V26+AC26+AJ26)-G26 -> 0 | L26: =(Q26+X26+AE26+AL26)-I26 -> 0 | O26: 636855 | P26: =O26*8 -> 5094840 | Q26: 149388 | R26: =Q26*4 -> 597552 | V26: 167971 | W26: =V26*8 -> 1343768 | X26: 88867 | Y26: =X26*4 -> 355468 | AC26: 17838 | AD26: =AC26*8 -> 142704 | AE26: 17838.08 | AF26: =AE26*4 -> 71352.32 | AJ26: 12174.305 | AK26: =AJ26*8 -> 97394.44 | AL26: 12174.305 | AM26: =AL26*4 -> 48697.22
B27: Transportation & Vehicles
B28: Bus | C28: =M28+T28+AA28+AH28 -> 10 | D28: =N28+U28+AB28+AI28 -> 5 | E28: 36000 | F28: 36000 | G28: =C28*F28 -> 360000 | H28: =G28*8 -> 2880000 | I28: =D28*F28 -> 180000 | J28: 597553.04 | K28: =(O28+V28+AC28+AJ28)-G28 -> 0 | L28: =(Q28+X28+AE28+AL28)-I28 -> 0 | M28: 8 | N28: 3 | O28: =F28*M28 -> 288000 | P28: =O28*8 -> 2304000 | Q28: =N28*F28 -> 108000 | R28: =Q28*4 -> 432000 | T28: 2 | U28: 2 | V28: =T28*F28 -> 72000 | W28: =V28*8 -> 576000 | X28: =U28*F28 -> 72000 | Y28: =X28*4 -> 288000 | AC28: =AA28*F28 -> 0 | AD28: =AC28*8 -> 0 | AE28: =AB28*F28 -> 0 | AF28: =AE28*4 -> 0 | AJ28: =AH28*F28 -> 0 | AK28: =AJ28*8 -> 0 | AL28: =AI28*F28 -> 0 | AM28: =AL28*4 -> 0
B29: Microbus | C29: =M29+T29+AA29+AH29 -> 0 | D29: =N29+U29+AB29+AI29 -> 0 | E29: 21000 | F29: 21000 | G29: =C29*F29 -> 0 | H29: =G29*8 -> 0 | I29: =D29*F29 -> 0 | J29: 597553.04 | K29: =(O29+V29+AC29+AJ29)-G29 -> 0 | L29: =(Q29+X29+AE29+AL29)-I29 -> 0 | O29: =F29*M29 -> 0 | P29: =O29*8 -> 0 | Q29: =N29*F29 -> 0 | R29: =Q29*4 -> 0 | V29: =T29*F29 -> 0 | W29: =V29*8 -> 0 | X29: =U29*F29 -> 0 | Y29: =X29*4 -> 0 | AD29: =AC29*8 -> 0 | AF29: =AE29*4 -> 0 | AK29: =AJ29*8 -> 0 | AM29: =AL29*4 -> 0
B30: Sidan Car | C30: =M30+T30+AA30+AH30 -> 1 | D30: =N30+U30+AB30+AI30 -> 1 | E30: 13000 | F30: 13000 | G30: =C30*F30 -> 13000 | H30: =G30*8 -> 104000 | I30: =Q30+X30+AE30+AL30 -> 12605 | J30: 597553.04 | K30: =(O30+V30+AC30+AJ30)-G30 -> -395 | L30: =(Q30+X30+AE30+AL30)-I30 -> 0 | M30: 0.75 | N30: 0.75 | O30: 9454 | P30: =O30*8 -> 75632 | Q30: 9454 | R30: =Q30*4 -> 37816 | T30: 0.25 | U30: 0.25 | V30: 3151 | W30: =V30*8 -> 25208 | X30: 3151 | Y30: =X30*4 -> 12604 | AC30: =AA30*F30 -> 0 | AD30: =AC30*8 -> 0 | AE30: =AB30*F30 -> 0 | AF30: =AE30*4 -> 0 | AJ30: =AH30*F30 -> 0 | AK30: =AJ30*8 -> 0 | AL30: =AI30*F30 -> 0 | AM30: =AL30*4 -> 0
B31: Minivan | C31: 3 | D31: 5 | E31: 18000 | F31: 18000 | G31: =C31*F31 -> 54000 | H31: =G31*8 -> 432000 | I31: =Q31+X31+AE31+AL31 -> 87272 | J31: 597553.04 | K31: =(O31+V31+AC31+AJ31)-G31 -> 33272 | L31: =(Q31+X31+AE31+AL31)-I31 -> 0 | M31: 3 | N31: 3 | O31: 65454 | P31: =O31*8 -> 523632 | Q31: 65454 | R31: =Q31*4 -> 261816 | T31: 2 | U31: 2 | V31: 21818 | W31: =V31*8 -> 174544 | X31: 21818 | Y31: =X31*4 -> 87272 | AC31: =AA31*F31 -> 0 | AD31: =AC31*8 -> 0 | AE31: =AB31*F31 -> 0 | AF31: =AE31*4 -> 0 | AJ31: =AH31*F31 -> 0 | AK31: =AJ31*8 -> 0 | AL31: =AI31*F31 -> 0 | AM31: =AL31*4 -> 0
B32: Pick up Car | C32: =M32+T32+AA32+AH32 -> 5 | D32: =N32+U32+AB32+AI32 -> 4 | E32: 20000 | F32: 20000 | G32: =C32*F32 -> 100000 | H32: =G32*8 -> 800000 | I32: =Q32+X32+AE32+AL32 -> 80000 | J32: 597553.04 | K32: =(O32+V32+AC32+AJ32)-G32 -> -1 | L32: =(Q32+X32+AE32+AL32)-I32 -> 0 | M32: 3 | N32: 2 | O32: 56363 | P32: =O32*8 -> 450904 | Q32: 50000 | R32: =Q32*4 -> 200000 | T32: 2 | U32: 2 | V32: 43636 | W32: =V32*8 -> 349088 | X32: 30000 | Y32: =X32*4 -> 120000 | AC32: =AA32*F32 -> 0 | AD32: =AC32*8 -> 0 | AE32: =AB32*F32 -> 0 | AF32: =AE32*4 -> 0 | AJ32: =AH32*F32 -> 0 | AK32: =AJ32*8 -> 0 | AL32: =AI32*F32 -> 0 | AM32: =AL32*4 -> 0
B33: Fule | C33: =M33+T33+AA33+AH33 -> 1 | D33: =N33+U33+AB33+AI33 -> 1 | E33: 12000 | F33: 12000 | G33: =C33*F33 -> 12000 | H33: =G33*8 -> 96000 | I33: =Q33+X33+AE33+AL33 -> 8040 | J33: 597553.04 | K33: =(O33+V33+AC33+AJ33)-G33 -> -1 | L33: =(Q33+X33+AE33+AL33)-I33 -> 0 | M33: 0.75 | N33: 0.5 | O33: 9090 | P33: =O33*8 -> 72720 | Q33: 6000 | R33: =Q33*4 -> 24000 | T33: 0.25 | U33: 0.5 | V33: 2909 | W33: =V33*8 -> 23272 | X33: 2040 | Y33: =X33*4 -> 8160 | AC33: =AA33*F33 -> 0 | AD33: =AC33*8 -> 0 | AE33: =AB33*F33 -> 0 | AF33: =AE33*4 -> 0 | AJ33: =AH33*F33 -> 0 | AK33: =AJ33*8 -> 0 | AL33: =AI33*F33 -> 0 | AM33: =AL33*4 -> 0
B34: IT and Communications
B35: Laptop, Mobile Phone, Printers, SIM Cards - Calls, Data, MIFI and Fingerprints Machine | C35: =M35+T35+AA35+AH35 -> 54 | D35: =N35+U35+AB35+AI35 -> 40 | E35: 350 | F35: 350 | G35: =O35+V35+AC35+AJ35 -> 20087 | H35: =G35*8 -> 160696 | I35: =Q35+X35+AE35+AL35 -> 14610 | J35: 597553.04 | K35: =(O35+V35+AC35+AJ35)-G35 -> 0 | L35: =(Q35+X35+AE35+AL35)-I35 -> 0 | M35: =M6+M7+M8+M9+M11+M13+M15+M16+M17+M18 -> 37.25 | N35: =N6+N7+N8+N9+N11+N13+N15+N16+N17+N18 -> 27.25 | O35: 15084 | P35: =O35*8 -> 120672 | Q35: 11101 | R35: =Q35*4 -> 44404 | T35: =T6+T7+T8+T9+T11+T13+T15+T16+T17+T18 -> 16.75 | U35: =U6+U7+U8+U9+U11+U13+U15+U16+U17+U18 -> 12.75 | V35: 5003 | W35: =V35*8 -> 40024 | X35: 3509 | Y35: =X35*4 -> 14036 | AA35: =AA6+AA7+AA8+AA9+AA11+AA13+AA15+AA16+AA17+AA18 -> 0 | AB35: =AB6+AB7+AB8+AB9+AB11+AB13+AB15+AB16+AB17+AB18 -> 0 | AC35: =AA35*F35 -> 0 | AD35: =AC35*8 -> 0 | AE35: =AB35*F35 -> 0 | AF35: =AE35*4 -> 0 | AH35: =AH6+AH7+AH8+AH9+AH11+AH13+AH15+AH16+AH17+AH18 -> 0 | AI35: =AI6+AI7+AI8+AI9+AI11+AI13+AI15+AI16+AI17+AI18 -> 0 | AJ35: =AH35*F35 -> 0 | AK35: =AJ35*8 -> 0 | AL35: =AI35*F35 -> 0 | AM35: =AL35*4 -> 0
B36: Others "Mobilization&Over Head"
B37: Mobilization and Over Head | C37: =M37+T37+AA37+AH37 -> 0 | D37: 0 | F37: =F31*3 -> 54000 | G37: =O37+V37+AC37+AJ37 -> 0 | H37: =G37*8 -> 0 | I37: =Q37+X37+AE37+AL37 -> 0 | J37: 597555.04 | K37: =(O37+V37+AC37+AJ37)-G37 -> 0 | L37: =(Q37+X37+AE37+AL37)-I37 -> 0 | M37: 0 | N37: 0
B39: Total Cost | G39: =SUM(G6:G37) -> 4172636.7 | H39: =G39*8 -> 33381094 | I39: =SUM(I6:I37) -> 2304207.3 | J39: =I39*4 -> 9216829.3 | K39: =(O39+V39+AC39+AJ39)-G39 -> 32875 | L39: =(Q39+X39+AE39+AL39)-I39 -> 0 | O39: =SUM(O6:O37) -> 2996028.5 | P39: =O39*8 -> 23968228 | Q39: =SUM(Q6:Q37) -> 1521320.5 | R39: =Q39*4 -> 6085282 | V39: =SUM(V6:V37) -> 1145434.5 | W39: =V39*8 -> 9163476 | X39: =SUM(X6:X37) -> 718836.5 | Y39: =X39*4 -> 2875346 | AC39: =SUM(AC6:AC37) -> 42376 | AD39: =AC39*8 -> 339008 | AE39: =SUM(AE6:AE37) -> 42377.608 | AF39: =AE39*4 -> 169510.43 | AJ39: =SUM(AJ6:AJ37) -> 21672.708 | AK39: =AJ39*8 -> 173381.66 | AL39: =SUM(AL6:AL37) -> 21672.708 | AM39: =AL39*4 -> 86690.831
B40: Gross Margin | C40: =G40/G39 -> -1 | D40: =I40/I39 -> -1 | G40: =G41-G39 -> -4172636.7 | H40: =G40*8 -> -33381094 | I40: =I41-I39 -> -2304207.3 | J40: =I40*4 -> -9216829.3 | K40: =(O40+V40+AC40+AJ40)-G40 -> -32875 | L40: =(Q40+X40+AE40+AL40)-I40 -> 0 | O40: =O39*C40 -> -2996028.5 | P40: =O40*8 -> -23968228 | Q40: =Q39*D40 -> -1521320.5 | R40: =Q40*4 -> -6085282 | V40: =V39*C40 -> -1145434.5 | W40: =V40*8 -> -9163476 | X40: =X39*D40 -> -718836.5 | Y40: =X40*4 -> -2875346 | AC40: =AC39*C40 -> -42376 | AD40: =AC40*8 -> -339008 | AE40: =AE39*D40 -> -42377.608 | AF40: =AE40*4 -> -169510.43 | AJ40: =AJ39*C40 -> -21672.708 | AK40: =AJ40*8 -> -173381.66 | AL40: =AL39*D40 -> -21672.708 | AM40: =AL40*4 -> -86690.831
B41: Total Revenue | G41: ='[1]Breakdown '!$C$49 -> 0 | H41: =G41*8 -> 0 | I41: ='[1]Breakdown '!$D$49 -> 0 | J41: =I41*4 -> 0 | K41: =(O41+V41+AC41+AJ41)-G41 -> 0 | L41: =(Q41+X41+AE41+AL41)-I41 -> 0 | O41: =O39+O40 -> 0 | P41: =P39+P40 -> 0 | Q41: =Q39+Q40 -> 0 | R41: =R39+R40 -> 0 | V41: =V39+V40 -> 0 | W41: =W39+W40 -> 0 | X41: =X39+X40 -> 0 | Y41: =Y39+Y40 -> 0 | AC41: =AC39+AC40 -> 0 | AD41: =AD39+AD40 -> 0 | AE41: =AE39+AE40 -> 0 | AF41: =AF39+AF40 -> 0 | AJ41: =AJ39+AJ40 -> 0 | AK41: =AK39+AK40 -> 0 | AL41: =AL39+AL40 -> 0 | AM41: =AM39+AM40 -> 0
B42: Gross Margin % | K42: =(O42+V42+AC42+AJ42)-G42 -> 0
K43: =(O43+V43+AC43+AJ43)-G43 -> 0
K44: =(O44+V44+AC44+AJ44)-G44 -> 0
K45: =(O45+V45+AC45+AJ45)-G45 -> 0
B46: Total Cost Annually | G46: =H39+J39 -> 42597923 | K46: =(O46+V46+AC46+AJ46)-G46 -> 263000 | O46: =P39+R39 -> 30053510 | V46: =W39+Y39 -> 12038822 | AC46: =AD39+AF39 -> 508518.43 | AJ46: =AK39+AM39 -> 260072.49
B47: Gross Margin Annually | G47: =H40+J40 -> -42597923 | K47: =(O47+V47+AC47+AJ47)-G47 -> -263000 | O47: =P40+R40 -> -30053510 | V47: =W40+Y40 -> -12038822 | AC47: =AD40+AF40 -> -508518.43 | AJ47: =AK40+AM40 -> -260072.49
B48: Total Revenue Annually | G48: =G46+G47 -> 0 | K48: =(O48+V48+AC48+AJ48)-G48 -> 0 | O48: =O46+O47 -> 0 | V48: =V46+V47 -> 0 | AC48: =AC46+AC47 -> 0 | AJ48: =AJ46+AJ47 -> 0
B49: Total Revenue Annually W VAT | G49: =G48*1.14 -> 0 | K49: =(O49+V49+AC49+AJ49)-G49 -> 0 | O49: =O48*1.14 -> 0 | V49: =V48*1.14 -> 0 | AC49: =AC48*1.14 -> 0 | AJ49: =AJ48*1.14 -> 0

Sheet Budget Items Summary
B3: Item | C3: Monthly Budget
C4: Low Season | D4: High Season
B5: Manpower Costs - Transportation & Insurance Included | C5: =SUM('AUC Grand Total Budget '!I6:I20)+SUM('AUC Grand Total Budget '!I28:I33) -> 1445517 | D5: =SUM('AUC Grand Total Budget '!G6:G20)+SUM('AUC Grand Total Budget '!G28:G33) -> 2466250
B6: Uniform & PPE's | C6: ='AUC Grand Total Budget '!I22 -> 84600 | D6: ='AUC Grand Total Budget '!G22 -> 170100
B7: Tools | C7: ='AUC Grand Total Budget '!I25 -> 155080.93 | D7: ='AUC Grand Total Budget '!G25 -> 215230.07
B8: Equipment | C8: ='AUC Grand Total Budget '!I24 -> 336132 | D8: ='AUC Grand Total Budget '!G24 -> 466131.33
B9: Consumables | C9: ='AUC Grand Total Budget '!I26 -> 268267.39 | D9: ='AUC Grand Total Budget '!G26 -> 834838.31
B10: IT & Others | C10: ='AUC Grand Total Budget '!I35 -> 14610 | D10: ='AUC Grand Total Budget '!G35 -> 20087
B11: Budgeted Gross Profit | C11: ='AUC Grand Total Budget '!I40 -> -2304207.3 | D11: ='AUC Grand Total Budget '!G40 -> -4172636.7
B12: Total Revenue | C12: =SUM(C5:C11) -> 0 | D12: =SUM(D5:D11) -> 0

Sheet AUC Total Manning
F2: INNER CAMPUS Budget | I2: OUTER CAMPUS Budget | L2: NEW CAIRO OFF CAMPUS HOUSING Budget | O2: Maadi Buildings Budget
F3: High | G3: Low | I3: High | J3: Low | L3: High | M3: Low | O3: High | P3: Low
A4: HK Budget | B4: High Season | C4: Low Season | F4: Head Count | G4: Head Count | I4: Head Count | J4: Head Count | L4: Head Count | M4: Head Count | O4: Head Count | P4: Head Count
A5: HK Manager | B5: =F5+I5+L5+O5 -> 1 | C5: =G5+J5+M5+P5 -> 1 | D5: =(F5+I5+L5+O5)-B5 -> 0 | E5: =(G5+J5+M5+P5)-C5 -> 0 | F5: 0.75 | G5: 0.75 | I5: 0.25 | J5: 0.25
A6: Ass. Manger | B6: =F6+I6+L6+O6 -> 5 | C6: =G6+J6+M6+P6 -> 5 | D6: =(F6+I6+L6+O6)-B6 -> 0 | E6: =(G6+J6+M6+P6)-C6 -> 0 | F6: 3 | G6: 3 | I6: 2 | J6: 2
A7: Sienior Supervisor | B7: =F7+I7+L7+O7 -> 5 | C7: =G7+J7+M7+P7 -> 5 | D7: =(F7+I7+L7+O7)-B7 -> 0 | E7: =(G7+J7+M7+P7)-C7 -> 0 | F7: 3 | G7: 3 | I7: 2 | J7: 2
A8: Supervisor 8H | B8: =F8+I8+L8+O8 -> 28 | C8: =G8+J8+M8+P8 -> 14 | D8: =(F8+I8+L8+O8)-B8 -> 0 | E8: =(G8+J8+M8+P8)-C8 -> 0 | F8: 21 | G8: 11 | I8: 7 | J8: 3
A9: HK Male & Female 8H | B9: =F9+I9+L9+O9 -> 282 | C9: =G9+J9+M9+P9 -> 134 | D9: =(F9+I9+L9+O9)-B9 -> 0 | E9: =(G9+J9+M9+P9)-C9 -> 0 | F9: 199 | G9: 95 | I9: 79 | J9: 35 | L9: 3 | M9: 3 | O9: 1 | P9: 1
A10: Facades Supervisor 8H | B10: =F10+I10+L10+O10 -> 1 | C10: =G10+J10+M10+P10 -> 1 | D10: =(F10+I10+L10+O10)-B10 -> 0 | E10: =(G10+J10+M10+P10)-C10 -> 0 | F10: 0.75 | G10: 0.75 | I10: 0.25 | J10: 0.25
A11: Facades Labor 8H | B11: =F11+I11+L11+O11 -> 4 | C11: =G11+J11+M11+P11 -> 4 | D11: =(F11+I11+L11+O11)-B11 -> 0 | E11: =(G11+J11+M11+P11)-C11 -> 0 | F11: 3 | G11: 3 | I11: 1 | J11: 1
A12: Supervisor Waste 8H | B12: =F12+I12+L12+O12 -> 3 | C12: =G12+J12+M12+P12 -> 3 | D12: =(F12+I12+L12+O12)-B12 -> 0 | E12: =(G12+J12+M12+P12)-C12 -> 0 | F12: 2 | G12: 2 | I12: 1 | J12: 1
A13: Labor Waste 8H | B13: =F13+I13+L13+O13 -> 12 | C13: =G13+J13+M13+P13 -> 8 | D13: =(F13+I13+L13+O13)-B13 -> 0 | E13: =(G13+J13+M13+P13)-C13 -> 0 | F13: 8 | G13: 6 | I13: 4 | J13: 2
A14: Admin | B14: =F14+I14+L14+O14 -> 2 | C14: =G14+J14+M14+P14 -> 2 | D14: =(F14+I14+L14+O14)-B14 -> 0 | E14: =(G14+J14+M14+P14)-C14 -> 0 | F14: 1 | G14: 1 | I14: 1 | J14: 1
A15: Storekeeper | B15: =F15+I15+L15+O15 -> 2 | C15: =G15+J15+M15+P15 -> 2 | D15: =(F15+I15+L15+O15)-B15 -> 0 | E15: =(G15+J15+M15+P15)-C15 -> 0 | F15: 1 | G15: 1 | I15: 1 | J15: 1
A16: Drivers | B16: =F16+I16+L16+O16 -> 6 | C16: =G16+J16+M16+P16 -> 6 | D16: =(F16+I16+L16+O16)-B16 -> 0 | E16: =(G16+J16+M16+P16)-C16 -> 0 | F16: 4 | G16: 4 | I16: 2 | J16: 2
A17: Trainer | B17: =F17+I17+L17+O17 -> 1 | C17: =G17+J17+M17+P17 -> 1 | D17: =(F17+I17+L17+O17)-B17 -> 0 | E17: =(G17+J17+M17+P17)-C17 -> 0 | F17: 0.75 | G17: 0.75 | I17: 0.25 | J17: 0.25
A18: Supervisor 8H R | B18: =F18+I18+L18+O18 -> 3 | C18: =G18+J18+M18+P18 -> 2 | D18: =(F18+I18+L18+O18)-B18 -> 0 | E18: =(G18+J18+M18+P18)-C18 -> 0 | F18: 2 | G18: 1 | I18: 1 | J18: 1
A19: HK Female 8H R | B19: =F19+I19+L19+O19 -> 23 | C19: =G19+J19+M19+P19 -> 0 | D19: =(F19+I19+L19+O19)-B19 -> 0 | E19: =(G19+J19+M19+P19)-C19 -> 0 | F19: 16 | G19: 0 | I19: 7 | J19: 0
B21: =SUM(B5:B17) -> 352 | C21: =SUM(C5:C17) -> 186

Sheet AUC Total Equipment
M3: INNER CAMPUS Budget | T3: OUTER CAMPUS Budget | AA3: NEW CAIRO OFF CAMPUS HOUSING Budget | AH3: Maadi Buildings Budget
B4: HK Budget | C4: High | D4: Low | E4: Deprecation / Moth | F4: Price | G4: High Season | I4: Low Season | M4: High | N4: Low | O4: High Season | Q4: Low Season | T4: High | U4: Low | V4: High Season | X4: Low Season | AA4: High | AB4: Low | AC4: High Season | AE4: Low Season | AH4: High | AI4: Low | AJ4: High Season | AL4: Low Season
C5: QTY. | D5: QTY. | G5: Monthly | H5: Annually "8"Months | I5: Monthly | J5: Annually "4"Months | M5: QTY. | N5: QTY. | O5: Monthly | P5: Annually "8"Months | Q5: Monthly | R5: Annually "4"Months | T5: QTY. | U5: QTY. | V5: Monthly | W5: Annually "8"Months | X5: Monthly | Y5: Annually "4"Months | AA5: QTY. | AB5: QTY. | AC5: Monthly | AD5: Annually "8"Months | AE5: Monthly | AF5: Annually "4"Months | AH5: QTY. | AI5: QTY. | AJ5: Monthly | AK5: Annually "8"Months | AL5: Monthly | AM5: Annually "4"Months
B6: Road Sweeper Truck Rentel | C6: =M6+T6+AA6+AH6 -> 1.5 | D6: =N6+U6+AB6+AI6 -> 1 | E6: 1 | F6: 100000 | G6: =C6*F6/E6 -> 150000 | H6: =G6*8 -> 1200000 | I6: =D6*F6/E6 -> 100000 | J6: =I6*4 -> 400000 | K6: =(O6+V6+AC6+AJ6)-G6 -> 0 | L6: =(Q6+X6+AE6+AL6)-I6 -> 0 | M6: 0.75 | N6: 0.5 | O6: =M6*F6/E6 -> 75000 | P6: =O6*8 -> 600000 | Q6: =N6*F6/E6 -> 50000 | R6: =Q6*4 -> 200000 | T6: 0.75 | U6: 0.5 | V6: =T6*F6/E6 -> 75000 | W6: =V6*8 -> 600000 | X6: =U6*F6/E6 -> 50000 | Y6: =X6*4 -> 200000 | AC6: =AA6*F6/E6 -> 0 | AD6: =AC6*8 -> 0 | AE6: =AB6*F6/E6 -> 0 | AF6: =AE6*4 -> 0 | AJ6: =AH6*F6/E6 -> 0 | AK6: =AJ6*8 -> 0 | AL6: =AI6*F6/E6 -> 0 | AM6: =AL6*4 -> 0
B7: Manlift 15 M Rental | C7: =M7+T7+AA7+AH7 -> 1 | D7: =N7+U7+AB7+AI7 -> 1 | E7: 1 | F7: 45000 | G7: =C7*F7/E7 -> 45000 | H7: =G7*8 -> 360000 | I7: =D7*F7/E7 -> 45000 | J7: =I7*4 -> 180000 | K7: =(O7+V7+AC7+AJ7)-G7 -> 0 | L7: =(Q7+X7+AE7+AL7)-I7 -> 0 | M7: 0 | N7: 0 | O7: =M7*F7/E7 -> 0 | P7: =O7*8 -> 0 | Q7: =N7*F7/E7 -> 0 | R7: =Q7*4 -> 0 | T7: 1 | U7: 1 | V7: =T7*F7/E7 -> 45000 | W7: =V7*8 -> 360000 | X7: =U7*F7/E7 -> 45000 | Y7: =X7*4 -> 180000 | AC7: =AA7*F7/E7 -> 0 | AD7: =AC7*8 -> 0 | AE7: =AB7*F7/E7 -> 0 | AF7: =AE7*4 -> 0 | AJ7: =AH7*F7/E7 -> 0 | AK7: =AJ7*8 -> 0 | AL7: =AI7*F7/E7 -> 0 | AM7: =AL7*4 -> 0
B8: Scissor lift 15 M Rental | C8: =M8+T8+AA8+AH8 -> 1 | D8: =N8+U8+AB8+AI8 -> 0 | E8: 1 | F8: 20000 | G8: =C8*F8/E8 -> 20000 | H8: =G8*8 -> 160000 | I8: =D8*F8/E8 -> 0 | J8: =I8*4 -> 0 | K8: =(O8+V8+AC8+AJ8)-G8 -> 0 | L8: =(Q8+X8+AE8+AL8)-I8 -> 0 | M8: 0 | N8: 0 | O8: =M8*F8/E8 -> 0 | P8: =O8*8 -> 0 | Q8: =N8*F8/E8 -> 0 | R8: =Q8*4 -> 0 | T8: 1 | V8: =T8*F8/E8 -> 20000 | W8: =V8*8 -> 160000 | X8: =U8*F8/E8 -> 0 | Y8: =X8*4 -> 0 | AC8: =AA8*F8/E8 -> 0 | AD8: =AC8*8 -> 0 | AE8: =AB8*F8/E8 -> 0 | AF8: =AE8*4 -> 0 | AJ8: =AH8*F8/E8 -> 0 | AK8: =AJ8*8 -> 0 | AL8: =AI8*F8/E8 -> 0 | AM8: =AL8*4 -> 0
B9: Boom Lift 15 M Rental | C9: =M9+T9+AA9+AH9 -> 1 | D9: =N9+U9+AB9+AI9 -> 0 | E9: 1 | F9: 60000 | G9: =C9*F9/E9 -> 60000 | H9: =G9*8 -> 480000 | I9: =D9*F9/E9 -> 0 | J9: =I9*4 -> 0 | K9: =(O9+V9+AC9+AJ9)-G9 -> 0 | L9: =(Q9+X9+AE9+AL9)-I9 -> 0 | M9: 1 | O9: =M9*F9/E9 -> 60000 | P9: =O9*8 -> 480000 | Q9: =N9*F9/E9 -> 0 | R9: =Q9*4 -> 0 | T9: 0 | U9: 0 | V9: =T9*F9/E9 -> 0 | W9: =V9*8 -> 0 | X9: =U9*F9/E9 -> 0 | Y9: =X9*4 -> 0 | AC9: =AA9*F9/E9 -> 0 | AD9: =AC9*8 -> 0 | AE9: =AB9*F9/E9 -> 0 | AF9: =AE9*4 -> 0 | AJ9: =AH9*F9/E9 -> 0 | AK9: =AJ9*8 -> 0 | AL9: =AI9*F9/E9 -> 0 | AM9: =AL9*4 -> 0
B10: Ride On Scraber | C10: =M10+T10+AA10+AH10 -> 4 | D10: =N10+U10+AB10+AI10 -> 4 | E10: 60 | F10: 900000 | G10: =C10*F10/E10 -> 60000 | H10: =G10*8 -> 480000 | I10: =D10*F10/E10 -> 60000 | J10: =I10*4 -> 240000 | K10: =(O10+V10+AC10+AJ10)-G10 -> 0 | L10: =(Q10+X10+AE10+AL10)-I10 -> 0 | M10: 4 | N10: 4 | O10: =M10*F10/E10 -> 60000 | P10: =O10*8 -> 480000 | Q10: =N10*F10/E10 -> 60000 | R10: =Q10*4 -> 240000 | V10: =T10*F10/E10 -> 0 | W10: =V10*8 -> 0 | X10: =U10*F10/E10 -> 0 | Y10: =X10*4 -> 0 | AC10: =AA10*F10/E10 -> 0 | AD10: =AC10*8 -> 0 | AE10: =AB10*F10/E10 -> 0 | AF10: =AE10*4 -> 0 | AJ10: =AH10*F10/E10 -> 0 | AK10: =AJ10*8 -> 0 | AL10: =AI10*F10/E10 -> 0 | AM10: =AL10*4 -> 0
B11: Manual Push Sweeper | C11: =M11+T11+AA11+AH11 -> 20 | D11: =N11+U11+AB11+AI11 -> 20 | E11: 36 | F11: 33000 | G11: =C11*F11/E11 -> 18333.333 | H11: =G11*8 -> 146666.67 | I11: =D11*F11/E11 -> 18333.333 | J11: =I11*4 -> 73333.333 | K11: =(O11+V11+AC11+AJ11)-G11 -> 0 | L11: =(Q11+X11+AE11+AL11)-I11 -> 0 | M11: 15 | N11: 15 | O11: =M11*F11/E11 -> 13750 | P11: =O11*8 -> 110000 | Q11: =N11*F11/E11 -> 13750 | R11: =Q11*4 -> 55000 | T11: 5 | U11: 5 | V11: =T11*F11/E11 -> 4583.3333 | W11: =V11*8 -> 36666.667 | X11: =U11*F11/E11 -> 4583.3333 | Y11: =X11*4 -> 18333.333 | AC11: =AA11*F11/E11 -> 0 | AD11: =AC11*8 -> 0 | AE11: =AB11*F11/E11 -> 0 | AF11: =AE11*4 -> 0 | AJ11: =AH11*F11/E11 -> 0 | AK11: =AJ11*8 -> 0 | AL11: =AI11*F11/E11 -> 0 | AM11: =AL11*4 -> 0
B12: Facades Cleaner | C12: =M12+T12+AA12+AH12 -> 1 | D12: =N12+U12+AB12+AI12 -> 1 | E12: 60 | F12: 220000 | G12: =C12*F12/E12 -> 3666.6667 | H12: =G12*8 -> 29333.333 | I12: =D12*F12/E12 -> 3666.6667 | J12: =I12*4 -> 14666.667 | K12: =(O12+V12+AC12+AJ12)-G12 -> 0 | L12: =(Q12+X12+AE12+AL12)-I12 -> 0 | M12: 1 | N12: 1 | O12: =M12*F12/E12 -> 3666.6667 | P12: =O12*8 -> 29333.333 | Q12: =N12*F12/E12 -> 3666.6667 | R12: =Q12*4 -> 14666.667 | V12: =T12*F12/E12 -> 0 | W12: =V12*8 -> 0 | X12: =U12*F12/E12 -> 0 | Y12: =X12*4 -> 0 | AC12: =AA12*F12/E12 -> 0 | AD12: =AC12*8 -> 0 | AE12: =AB12*F12/E12 -> 0 | AF12: =AE12*4 -> 0 | AJ12: =AH12*F12/E12 -> 0 | AK12: =AJ12*8 -> 0 | AL12: =AI12*F12/E12 -> 0 | AM12: =AL12*4 -> 0
B13: Buzzi Machine | C13: =M13+T13+AA13+AH13 -> 8 | D13: =N13+U13+AB13+AI13 -> 8 | E13: 60 | F13: 45000 | G13: =C13*F13/E13 -> 6000 | H13: =G13*8 -> 48000 | I13: =D13*F13/E13 -> 6000 | J13: =I13*4 -> 24000 | K13: =(O13+V13+AC13+AJ13)-G13 -> 0 | L13: =(Q13+X13+AE13+AL13)-I13 -> 0 | M13: 6 | N13: 6 | O13: =M13*F13/E13 -> 4500 | P13: =O13*8 -> 36000 | Q13: =N13*F13/E13 -> 4500 | R13: =Q13*4 -> 18000 | V13: =T13*F13/E13 -> 0 | W13: =V13*8 -> 0 | X13: =U13*F13/E13 -> 0 | Y13: =X13*4 -> 0 | AA13: 1 | AB13: 1 | AC13: =AA13*F13/E13 -> 750 | AD13: =AC13*8 -> 6000 | AE13: =AB13*F13/E13 -> 750 | AF13: =AE13*4 -> 3000 | AH13: 1 | AI13: 1 | AJ13: =AH13*F13/E13 -> 750 | AK13: =AJ13*8 -> 6000 | AL13: =AI13*F13/E13 -> 750 | AM13: =AL13*4 -> 3000
B14: Twintec | C14: =M14+T14+AA14+AH14 -> 8 | D14: =N14+U14+AB14+AI14 -> 8 | E14: 60 | F14: 155000 | G14: =C14*F14/E14 -> 20666.667 | H14: =G14*8 -> 165333.33 | I14: =D14*F14/E14 -> 20666.667 | J14: =I14*4 -> 82666.667 | K14: =(O14+V14+AC14+AJ14)-G14 -> 0 | L14: =(Q14+X14+AE14+AL14)-I14 -> 0 | M14: 8 | N14: 8 | O14: =M14*F14/E14 -> 20666.667 | P14: =O14*8 -> 165333.33 | Q14: =N14*F14/E14 -> 20666.667 | R14: =Q14*4 -> 82666.667 | V14: =T14*F14/E14 -> 0 | W14: =V14*8 -> 0 | X14: =U14*F14/E14 -> 0 | Y14: =X14*4 -> 0 | AC14: =AA14*F14/E14 -> 0 | AD14: =AC14*8 -> 0 | AE14: =AB14*F14/E14 -> 0 | AF14: =AE14*4 -> 0 | AJ14: =AH14*F14/E14 -> 0 | AK14: =AJ14*8 -> 0 | AL14: =AI14*F14/E14 -> 0 | AM14: =AL14*4 -> 0
B15: Single Disk Machine | C15: =M15+T15+AA15+AH15 -> 27 | D15: =N15+U15+AB15+AI15 -> 27 | E15: 60 | F15: 45000 | G15: =C15*F15/E15 -> 20250 | H15: =G15*8 -> 162000 | I15: =D15*F15/E15 -> 20250 | J15: =I15*4 -> 81000 | K15: =(O15+V15+AC15+AJ15)-G15 -> 0 | L15: =(Q15+X15+AE15+AL15)-I15 -> 0 | M15: 20 | N15: 20 | O15: =M15*F15/E15 -> 15000 | P15: =O15*8 -> 120000 | Q15: =N15*F15/E15 -> 15000 | R15: =Q15*4 -> 60000 | T15: 5 | U15: 5 | V15: =T15*F15/E15 -> 3750 | W15: =V15*8 -> 30000 | X15: =U15*F15/E15 -> 3750 | Y15: =X15*4 -> 15000 | AA15: 1 | AB15: 1 | AC15: =AA15*F15/E15 -> 750 | AD15: =AC15*8 -> 6000 | AE15: =AB15*F15/E15 -> 750 | AF15: =AE15*4 -> 3000 | AH15: 1 | AI15: 1 | AJ15: =AH15*F15/E15 -> 750 | AK15: =AJ15*8 -> 6000 | AL15: =AI15*F15/E15 -> 750 | AM15: =AL15*4 -> 3000
B16: Full Wet/Dry Vacuum Cleaner 3 Motors | C16: =M16+T16+AA16+AH16 -> 27 | D16: =N16+U16+AB16+AI16 -> 27 | E16: 60 | F16: 30000 | G16: =C16*F16/E16 -> 13500 | H16: =G16*8 -> 108000 | I16: =D16*F16/E16 -> 13500 | J16: =I16*4 -> 54000 | K16: =(O16+V16+AC16+AJ16)-G16 -> 0 | L16: =(Q16+X16+AE16+AL16)-I16 -> 0 | M16: 20 | N16: 20 | O16: =M16*F16/E16 -> 10000 | P16: =O16*8 -> 80000 | Q16: =N16*F16/E16 -> 10000 | R16: =Q16*4 -> 40000 | T16: 5 | U16: 5 | V16: =T16*F16/E16 -> 2500 | W16: =V16*8 -> 20000 | X16: =U16*F16/E16 -> 2500 | Y16: =X16*4 -> 10000 | AA16: 1 | AB16: 1 | AC16: =AA16*F16/E16 -> 500 | AD16: =AC16*8 -> 4000 | AE16: =AB16*F16/E16 -> 500 | AF16: =AE16*4 -> 2000 | AH16: 1 | AI16: 1 | AJ16: =AH16*F16/E16 -> 500 | AK16: =AJ16*8 -> 4000 | AL16: =AI16*F16/E16 -> 500 | AM16: =AL16*4 -> 2000
B17: Full Vacuum Cleaner 1 Motor | C17: =M17+T17+AA17+AH17 -> 27 | D17: =N17+U17+AB17+AI17 -> 27 | E17: 60 | F17: 22000 | G17: =C17*F17/E17 -> 9900 | H17: =G17*8 -> 79200 | I17: =D17*F17/E17 -> 9900 | J17: =I17*4 -> 39600 | K17: =(O17+V17+AC17+AJ17)-G17 -> 0 | L17: =(Q17+X17+AE17+AL17)-I17 -> 0 | M17: 20 | N17: 20 | O17: =M17*F17/E17 -> 7333.3333 | P17: =O17*8 -> 58666.667 | Q17: =N17*F17/E17 -> 7333.3333 | R17: =Q17*4 -> 29333.333 | T17: 5 | U17: 5 | V17: =T17*F17/E17 -> 1833.3333 | W17: =V17*8 -> 14666.667 | X17: =U17*F17/E17 -> 1833.3333 | Y17: =X17*4 -> 7333.3333 | AA17: 1 | AB17: 1 | AC17: =AA17*F17/E17 -> 366.66667 | AD17: =AC17*8 -> 2933.3333 | AE17: =AB17*F17/E17 -> 366.66667 | AF17: =AE17*4 -> 1466.6667 | AH17: 1 | AI17: 1 | AJ17: =AH17*F17/E17 -> 366.66667 | AK17: =AJ17*8 -> 2933.3333 | AL17: =AI17*F17/E17 -> 366.66667 | AM17: =AL17*4 -> 1466.6667
B18: Water High Pressure | C18: =M18+T18+AA18+AH18 -> 6 | D18: =N18+U18+AB18+AI18 -> 6 | E18: 60 | F18: 75000 | G18: =C18*F18/E18 -> 7500 | H18: =G18*8 -> 60000 | I18: =D18*F18/E18 -> 7500 | J18: =I18*4 -> 30000 | K18: =(O18+V18+AC18+AJ18)-G18 -> 0 | L18: =(Q18+X18+AE18+AL18)-I18 -> 0 | M18: 3 | N18: 3 | O18: =M18*F18/E18 -> 3750 | P18: =O18*8 -> 30000 | Q18: =N18*F18/E18 -> 3750 | R18: =Q18*4 -> 15000 | T18: 3 | U18: 3 | V18: =T18*F18/E18 -> 3750 | W18: =V18*8 -> 30000 | X18: =U18*F18/E18 -> 3750 | Y18: =X18*4 -> 15000 | AC18: =AA18*F18/E18 -> 0 | AD18: =AC18*8 -> 0 | AE18: =AB18*F18/E18 -> 0 | AF18: =AE18*4 -> 0 | AJ18: =AH18*F18/E18 -> 0 | AK18: =AJ18*8 -> 0 | AL18: =AI18*F18/E18 -> 0 | AM18: =AL18*4 -> 0
B19: Maintenance | C19: =M19+T19+AA19+AH19 -> 2.07 | D19: =N19+U19+AB19+AI19 -> 2.07 | E19: 1 | F19: 15000 | G19: =C19*F19/E19 -> 31050 | H19: =G19*8 -> 248400 | I19: =D19*F19/E19 -> 31050 | J19: =I19*4 -> 124200 | K19: =(O19+V19+AC19+AJ19)-G19 -> 0 | L19: =(Q19+X19+AE19+AL19)-I19 -> 0 | M19: 1 | N19: 1 | O19: =M19*F19/E19 -> 15000 | P19: =O19*8 -> 120000 | Q19: =N19*F19/E19 -> 15000 | R19: =Q19*4 -> 60000 | T19: 1 | U19: 1 | V19: =T19*F19/E19 -> 15000 | W19: =V19*8 -> 120000 | X19: =U19*F19/E19 -> 15000 | Y19: =X19*4 -> 60000 | AA19: 0.07 | AB19: 0.07 | AC19: =AA19*F19/E19 -> 1050 | AD19: =AC19*8 -> 8400 | AE19: =AB19*F19/E19 -> 1050 | AF19: =AE19*4 -> 4200 | AJ19: =AH19*F19/E19 -> 0 | AK19: =AJ19*8 -> 0 | AL19: =AI19*F19/E19 -> 0 | AM19: =AL19*4 -> 0
G20: =SUM(G6:G19) -> 465866.67 | H20: =G20*8 -> 3726933.3 | I20: =SUM(I6:I19) -> 335866.67 | J20: =I20*4 -> 1343466.7 | K20: =(O20+V20+AC20+AJ20)-G20 -> 0 | L20: =(Q20+X20+AE20+AL20)-I20 -> 0 | O20: =SUM(O6:O19) -> 288666.67 | P20: =O20*8 -> 2309333.3 | Q20: =SUM(Q6:Q19) -> 203666.67 | R20: =Q20*4 -> 814666.67 | V20: =SUM(V6:V19) -> 171416.67 | W20: =V20*8 -> 1371333.3 | X20: =SUM(X6:X19) -> 126416.67 | Y20: =X20*4 -> 505666.67 | AC20: =SUM(AC6:AC19) -> 3416.6667 | AD20: =AC20*8 -> 27333.333 | AE20: =SUM(AE6:AE19) -> 3416.6667 | AF20: =AE20*4 -> 13666.667 | AJ20: =SUM(AJ6:AJ19) -> 2366.6667 | AK20: =AJ20*8 -> 18933.333 | AL20: =SUM(AL6:AL19) -> 2366.6667 | AM20: =AL20*4 -> 9466.6667

Sheet AUC Total Tools
M3: INNER CAMPUS Budget | T3: OUTER CAMPUS Budget | AA3: NEW CAIRO OFF CAMPUS HOUSING Budget | AH3: Maadi Buildings Budget
B4: HK Budget | C4: High | D4: Low | E4: Deprecation / Moth | F4: Price | G4: High Season | I4: Low Season | M4: High | N4: Low | O4: High Season | Q4: Low Season | T4: High | U4: Low | V4: High Season | X4: Low Season | AA4: High | AB4: Low | AC4: High Season | AE4: Low Season | AH4: High | AI4: Low | AJ4: High Season | AL4: Low Season
C5: QTY. | D5: QTY. | G5: Monthly | H5: Annually "8"Months | I5: Monthly | J5: Annually "4"Months | M5: QTY. | N5: QTY. | O5: Monthly | P5: Annually "8"Months | Q5: Monthly | R5: Annually "4"Months | T5: QTY. | U5: QTY. | V5: Monthly | W5: Annually "8"Months | X5: Monthly | Y5: Annually "4"Months | AA5: QTY. | AB5: QTY. | AC5: Monthly | AD5: Annually "8"Months | AE5: Monthly | AF5: Annually "4"Months | AH5: QTY. | AI5: QTY. | AJ5: Monthly | AK5: Annually "8"Months | AL5: Monthly | AM5: Annually "4"Months
B6: Ladders 1.5 Meter | C6: =M6+T6+AA6+AH6 -> 27 | D6: =N6+U6+AB6+AI6 -> 27 | E6: 36 | F6: 2800 | G6: =C6*F6/E6 -> 2100 | H6: =G6*8 -> 16800 | I6: =D6*F6/E6 -> 2100 | J6: =I6*4 -> 8400 | K6: =(O6+V6+AC6+AJ6)-G6 -> 0 | L6: =(Q6+X6+AE6+AL6)-I6 -> 0 | M6: 20 | N6: 20 | O6: =M6*F6/E6 -> 1555.5556 | P6: =O6*8 -> 12444.444 | Q6: =N6*F6/E6 -> 1555.5556 | R6: =Q6*4 -> 6222.2222 | T6: 6 | U6: 6 | V6: =T6*F6/E6 -> 466.66667 | W6: =V6*8 -> 3733.3333 | X6: =U6*F6/E6 -> 466.66667 | Y6: =X6*4 -> 1866.6667 | AA6: 0.5 | AB6: 0.5 | AC6: =AA6*F6/E6 -> 38.888889 | AD6: =AC6*8 -> 311.11111 | AE6: =AB6*F6/E6 -> 38.888889 | AF6: =AE6*4 -> 155.55556 | AH6: 0.5 | AI6: 0.5 | AJ6: =AH6*F6/E6 -> 38.888889 | AK6: =AJ6*8 -> 311.11111 | AL6: =AI6*F6/E6 -> 38.888889 | AM6: =AL6*4 -> 155.55556
B7: Ladders 3 Meter | C7: =M7+T7+AA7+AH7 -> 14 | D7: =N7+U7+AB7+AI7 -> 14 | E7: 36 | F7: 4000 | G7: =C7*F7/E7 -> 1555.5556 | H7: =G7*8 -> 12444.444 | I7: =D7*F7/E7 -> 1555.5556 | J7: =I7*4 -> 6222.2222 | K7: =(O7+V7+AC7+AJ7)-G7 -> 0 | L7: =(Q7+X7+AE7+AL7)-I7 -> 0 | M7: 10 | N7: 10 | O7: =M7*F7/E7 -> 1111.1111 | P7: =O7*8 -> 8888.8889 | Q7: =N7*F7/E7 -> 1111.1111 | R7: =Q7*4 -> 4444.4444 | T7: 3 | U7: 3 | V7: =T7*F7/E7 -> 333.33333 | W7: =V7*8 -> 2666.6667 | X7: =U7*F7/E7 -> 333.33333 | Y7: =X7*4 -> 1333.3333 | AA7: 0.5 | AB7: 0.5 | AC7: =AA7*F7/E7 -> 55.555556 | AD7: =AC7*8 -> 444.44444 | AE7: =AB7*F7/E7 -> 55.555556 | AF7: =AE7*4 -> 222.22222 | AH7: 0.5 | AI7: 0.5 | AJ7: =AH7*F7/E7 -> 55.555556 | AK7: =AJ7*8 -> 444.44444 | AL7: =AI7*F7/E7 -> 55.555556 | AM7: =AL7*4 -> 222.22222
B8: Ladders 6 Meter | C8: =M8+T8+AA8+AH8 -> 6 | D8: =N8+U8+AB8+AI8 -> 6 | E8: 36 | F8: 6500 | G8: =C8*F8/E8 -> 1083.3333 | H8: =G8*8 -> 8666.6667 | I8: =D8*F8/E8 -> 1083.3333 | J8: =I8*4 -> 4333.3333 | K8: =(O8+V8+AC8+AJ8)-G8 -> 0 | L8: =(Q8+X8+AE8+AL8)-I8 -> 0 | M8: 4 | N8: 4 | O8: =M8*F8/E8 -> 722.22222 | P8: =O8*8 -> 5777.7778 | Q8: =N8*F8/E8 -> 722.22222 | R8: =Q8*4 -> 2888.8889 | T8: 2 | U8: 2 | V8: =T8*F8/E8 -> 361.11111 | W8: =V8*8 -> 2888.8889 | X8: =U8*F8/E8 -> 361.11111 | Y8: =X8*4 -> 1444.4444 | AC8: =AA8*F8/E8 -> 0 | AD8: =AC8*8 -> 0 | AE8: =AB8*F8/E8 -> 0 | AF8: =AE8*4 -> 0 | AJ8: =AH8*F8/E8 -> 0 | AK8: =AJ8*8 -> 0 | AL8: =AI8*F8/E8 -> 0 | AM8: =AL8*4 -> 0
B9: Blower 3000 cfm | C9: =M9+T9+AA9+AH9 -> 21 | D9: =N9+U9+AB9+AI9 -> 21 | E9: 12 | F9: 1500 | G9: =C9*F9/E9 -> 2625 | H9: =G9*8 -> 21000 | I9: =D9*F9/E9 -> 2625 | J9: =I9*4 -> 10500 | K9: =(O9+V9+AC9+AJ9)-G9 -> 0 | L9: =(Q9+X9+AE9+AL9)-I9 -> 0 | M9: 15 | N9: 15 | O9: =M9*F9/E9 -> 1875 | P9: =O9*8 -> 15000 | Q9: =N9*F9/E9 -> 1875 | R9: =Q9*4 -> 7500 | T9: 5 | U9: 5 | V9: =T9*F9/E9 -> 625 | W9: =V9*8 -> 5000 | X9: =U9*F9/E9 -> 625 | Y9: =X9*4 -> 2500 | AA9: 0.5 | AB9: 0.5 | AC9: =AA9*F9/E9 -> 62.5 | AD9: =AC9*8 -> 500 | AE9: =AB9*F9/E9 -> 62.5 | AF9: =AE9*4 -> 250 | AH9: 0.5 | AI9: 0.5 | AJ9: =AH9*F9/E9 -> 62.5 | AK9: =AJ9*8 -> 500 | AL9: =AI9*F9/E9 -> 62.5 | AM9: =AL9*4 -> 250
B10: H.K trolly Public Area | C10: =M10+T10+AA10+AH10 -> 41.5 | D10: =N10+U10+AB10+AI10 -> 41.5 | E10: 36 | F10: 4500 | G10: =C10*F10/E10 -> 5187.5 | H10: =G10*8 -> 41500 | I10: =D10*F10/E10 -> 5187.5 | J10: =I10*4 -> 20750 | K10: =(O10+V10+AC10+AJ10)-G10 -> 0 | L10: =(Q10+X10+AE10+AL10)-I10 -> 0 | M10: 40 | N10: 40 | O10: =M10*F10/E10 -> 5000 | P10: =O10*8 -> 40000 | Q10: =N10*F10/E10 -> 5000 | R10: =Q10*4 -> 20000 | V10: =T10*F10/E10 -> 0 | W10: =V10*8 -> 0 | X10: =U10*F10/E10 -> 0 | Y10: =X10*4 -> 0 | AA10: 1 | AB10: 1 | AC10: =AA10*F10/E10 -> 125 | AD10: =AC10*8 -> 1000 | AE10: =AB10*F10/E10 -> 125 | AF10: =AE10*4 -> 500 | AH10: 0.5 | AI10: 0.5 | AJ10: =AH10*F10/E10 -> 62.5 | AK10: =AJ10*8 -> 500 | AL10: =AI10*F10/E10 -> 62.5 | AM10: =AL10*4 -> 250
B11: Garbage Trolley Maclin 400 L | C11: =M11+T11+AA11+AH11 -> 40 | D11: =N11+U11+AB11+AI11 -> 40 | E11: 36 | F11: 8500 | G11: =C11*F11/E11 -> 9444.4444 | H11: =G11*8 -> 75555.556 | I11: =D11*F11/E11 -> 9444.4444 | J11: =I11*4 -> 37777.778 | K11: =(O11+V11+AC11+AJ11)-G11 -> 0 | L11: =(Q11+X11+AE11+AL11)-I11 -> 0 | M11: 25 | N11: 25 | O11: =M11*F11/E11 -> 5902.7778 | P11: =O11*8 -> 47222.222 | Q11: =N11*F11/E11 -> 5902.7778 | R11: =Q11*4 -> 23611.111 | T11: 15 | U11: 15 | V11: =T11*F11/E11 -> 3541.6667 | W11: =V11*8 -> 28333.333 | X11: =U11*F11/E11 -> 3541.6667 | Y11: =X11*4 -> 14166.667 | AC11: =AA11*F11/E11 -> 0 | AD11: =AC11*8 -> 0 | AE11: =AB11*F11/E11 -> 0 | AF11: =AE11*4 -> 0 | AJ11: =AH11*F11/E11 -> 0 | AK11: =AJ11*8 -> 0 | AL11: =AI11*F11/E11 -> 0 | AM11: =AL11*4 -> 0
B12: Carry Caddy | C12: =M12+T12+AA12+AH12 -> 153 | D12: =N12+U12+AB12+AI12 -> 153 | E12: 12 | F12: 160 | G12: =C12*F12/E12 -> 2040 | H12: =G12*8 -> 16320 | I12: =D12*F12/E12 -> 2040 | J12: =I12*4 -> 8160 | K12: =(O12+V12+AC12+AJ12)-G12 -> 0 | L12: =(Q12+X12+AE12+AL12)-I12 -> 0 | M12: 100 | N12: 100 | O12: =M12*F12/E12 -> 1333.3333 | P12: =O12*8 -> 10666.667 | Q12: =N12*F12/E12 -> 1333.3333 | R12: =Q12*4 -> 5333.3333 | T12: 50 | U12: 50 | V12: =T12*F12/E12 -> 666.66667 | W12: =V12*8 -> 5333.3333 | X12: =U12*F12/E12 -> 666.66667 | Y12: =X12*4 -> 2666.6667 | AA12: 2 | AB12: 2 | AC12: =AA12*F12/E12 -> 26.666667 | AD12: =AC12*8 -> 213.33333 | AE12: =AB12*F12/E12 -> 26.666667 | AF12: =AE12*4 -> 106.66667 | AH12: 1 | AI12: 1 | AJ12: =AH12*F12/E12 -> 13.333333 | AK12: =AJ12*8 -> 106.66667 | AL12: =AI12*F12/E12 -> 13.333333 | AM12: =AL12*4 -> 53.333333
B13: Telescope 9 M | C13: =M13+T13+AA13+AH13 -> 20 | D13: =N13+U13+AB13+AI13 -> 20 | E13: 12 | F13: 1200 | G13: =C13*F13/E13 -> 2000 | H13: =G13*8 -> 16000 | I13: =D13*F13/E13 -> 2000 | J13: =I13*4 -> 8000 | K13: =(O13+V13+AC13+AJ13)-G13 -> 0 | L13: =(Q13+X13+AE13+AL13)-I13 -> 0 | M13: 15 | N13: 15 | O13: =M13*F13/E13 -> 1500 | P13: =O13*8 -> 12000 | Q13: =N13*F13/E13 -> 1500 | R13: =Q13*4 -> 6000 | T13: 5 | U13: 5 | V13: =T13*F13/E13 -> 500 | W13: =V13*8 -> 4000 | X13: =U13*F13/E13 -> 500 | Y13: =X13*4 -> 2000 | AC13: =AA13*F13/E13 -> 0 | AD13: =AC13*8 -> 0 | AE13: =AB13*F13/E13 -> 0 | AF13: =AE13*4 -> 0 | AJ13: =AH13*F13/E13 -> 0 | AK13: =AJ13*8 -> 0 | AL13: =AI13*F13/E13 -> 0 | AM13: =AL13*4 -> 0
B14: Caution Wet Floor sign | C14: =M14+T14+AA14+AH14 -> 163 | D14: =N14+U14+AB14+AI14 -> 163 | E14: 12 | F14: 150 | G14: =C14*F14/E14 -> 2037.5 | H14: =G14*8 -> 16300 | I14: =D14*F14/E14 -> 2037.5 | J14: =I14*4 -> 8150 | K14: =(O14+V14+AC14+AJ14)-G14 -> 0 | L14: =(Q14+X14+AE14+AL14)-I14 -> 0 | M14: 100 | N14: 100 | O14: =M14*F14/E14 -> 1250 | P14: =O14*8 -> 10000 | Q14: =N14*F14/E14 -> 1250 | R14: =Q14*4 -> 5000 | T14: 60 | U14: 60 | V14: =T14*F14/E14 -> 750 | W14: =V14*8 -> 6000 | X14: =U14*F14/E14 -> 750 | Y14: =X14*4 -> 3000 | AA14: 2 | AB14: 2 | AC14: =AA14*F14/E14 -> 25 | AD14: =AC14*8 -> 200 | AE14: =AB14*F14/E14 -> 25 | AF14: =AE14*4 -> 100 | AH14: 1 | AI14: 1 | AJ14: =AH14*F14/E14 -> 12.5 | AK14: =AJ14*8 -> 100 | AL14: =AI14*F14/E14 -> 12.5 | AM14: =AL14*4 -> 50
B15: Microfiber Flat Mop with Bucket | C15: =M15+T15+AA15+AH15 -> 73 | D15: =N15+U15+AB15+AI15 -> 73 | E15: 24 | F15: 1750 | G15: =C15*F15/E15 -> 5322.9167 | H15: =G15*8 -> 42583.333 | I15: =D15*F15/E15 -> 5322.9167 | J15: =I15*4 -> 21291.667 | K15: =(O15+V15+AC15+AJ15)-G15 -> 0 | L15: =(Q15+X15+AE15+AL15)-I15 -> 0 | M15: 60 | N15: 60 | O15: =M15*F15/E15 -> 4375 | P15: =O15*8 -> 35000 | Q15: =N15*F15/E15 -> 4375 | R15: =Q15*4 -> 17500 | T15: 10 | U15: 10 | V15: =T15*F15/E15 -> 729.16667 | W15: =V15*8 -> 5833.3333 | X15: =U15*F15/E15 -> 729.16667 | Y15: =X15*4 -> 2916.6667 | AA15: 2 | AB15: 2 | AC15: =AA15*F15/E15 -> 145.83333 | AD15: =AC15*8 -> 1166.6667 | AE15: =AB15*F15/E15 -> 145.83333 | AF15: =AE15*4 -> 583.33333 | AH15: 1 | AI15: 1 | AJ15: =AH15*F15/E15 -> 72.916667 | AK15: =AJ15*8 -> 583.33333 | AL15: =AI15*F15/E15 -> 72.916667 | AM15: =AL15*4 -> 291.66667
B16: Microfiber Flat Mop pads | C16: =M16+T16+AA16+AH16 -> 73 | D16: =N16+U16+AB16+AI16 -> 53 | E16: 1 | F16: 145 | G16: =C16*F16/E16 -> 10585 | H16: =G16*8 -> 84680 | I16: =D16*F16/E16 -> 7685 | J16: =I16*4 -> 30740 | K16: =(O16+V16+AC16+AJ16)-G16 -> 0 | L16: =(Q16+X16+AE16+AL16)-I16 -> 0 | M16: 60 | N16: 40 | O16: =M16*F16/E16 -> 8700 | P16: =O16*8 -> 69600 | Q16: =N16*F16/E16 -> 5800 | R16: =Q16*4 -> 23200 | T16: 10 | U16: 10 | V16: =T16*F16/E16 -> 1450 | W16: =V16*8 -> 11600 | X16: =U16*F16/E16 -> 1450 | Y16: =X16*4 -> 5800 | AA16: 2 | AB16: 2 | AC16: =AA16*F16/E16 -> 290 | AD16: =AC16*8 -> 2320 | AE16: =AB16*F16/E16 -> 290 | AF16: =AE16*4 -> 1160 | AH16: 1 | AI16: 1 | AJ16: =AH16*F16/E16 -> 145 | AK16: =AJ16*8 -> 1160 | AL16: =AI16*F16/E16 -> 145 | AM16: =AL16*4 -> 580
B17: Dry Mop 60 cm | C17: =M17+T17+AA17+AH17 -> 73 | D17: =N17+U17+AB17+AI17 -> 73 | E17: 24 | F17: 245 | G17: =C17*F17/E17 -> 745.20833 | H17: =G17*8 -> 5961.6667 | I17: =D17*F17/E17 -> 745.20833 | J17: =I17*4 -> 2980.8333 | K17: =(O17+V17+AC17+AJ17)-G17 -> 0 | L17: =(Q17+X17+AE17+AL17)-I17 -> 0 | M17: 60 | N17: 60 | O17: =M17*F17/E17 -> 612.5 | P17: =O17*8 -> 4900 | Q17: =N17*F17/E17 -> 612.5 | R17: =Q17*4 -> 2450 | T17: 10 | U17: 10 | V17: =T17*F17/E17 -> 102.08333 | W17: =V17*8 -> 816.66667 | X17: =U17*F17/E17 -> 102.08333 | Y17: =X17*4 -> 408.33333 | AA17: 2 | AB17: 2 | AC17: =AA17*F17/E17 -> 20.416667 | AD17: =AC17*8 -> 163.33333 | AE17: =AB17*F17/E17 -> 20.416667 | AF17: =AE17*4 -> 81.666667 | AH17: 1 | AI17: 1 | AJ17: =AH17*F17/E17 -> 10.208333 | AK17: =AJ17*8 -> 81.666667 | AL17: =AI17*F17/E17 -> 10.208333 | AM17: =AL17*4 -> 40.833333
B18: Dry Mop Pads 60 cm | C18: =M18+T18+AA18+AH18 -> 75 | D18: =N18+U18+AB18+AI18 -> 55 | E18: 1 | F18: 125 | G18: =C18*F18/E18 -> 9375 | H18: =G18*8 -> 75000 | I18: =D18*F18/E18 -> 6875 | J18: =I18*4 -> 27500 | K18: =(O18+V18+AC18+AJ18)-G18 -> 0 | L18: =(Q18+X18+AE18+AL18)-I18 -> 0 | M18: 60 | N18: 40 | O18: =M18*F18/E18 -> 7500 | P18: =O18*8 -> 60000 | Q18: =N18*F18/E18 -> 5000 | R18: =Q18*4 -> 20000 | T18: 10 | U18: 10 | V18: =T18*F18/E18 -> 1250 | W18: =V18*8 -> 10000 | X18: =U18*F18/E18 -> 1250 | Y18: =X18*4 -> 5000 | AA18: 4 | AB18: 4 | AC18: =AA18*F18/E18 -> 500 | AD18: =AC18*8 -> 4000 | AE18: =AB18*F18/E18 -> 500 | AF18: =AE18*4 -> 2000 | AH18: 1 | AI18: 1 | AJ18: =AH18*F18/E18 -> 125 | AK18: =AJ18*8 -> 1000 | AL18: =AI18*F18/E18 -> 125 | AM18: =AL18*4 -> 500
B19: Dry Mop 100 cm | C19: =M19+T19+AA19+AH19 -> 20 | D19: =N19+U19+AB19+AI19 -> 20 | E19: 6 | F19: 400 | G19: =C19*F19/E19 -> 1333.3333 | H19: =G19*8 -> 10666.667 | I19: =D19*F19/E19 -> 1333.3333 | J19: =I19*4 -> 5333.3333 | K19: =(O19+V19+AC19+AJ19)-G19 -> 0 | L19: =(Q19+X19+AE19+AL19)-I19 -> 0 | M19: 20 | N19: 20 | O19: =M19*F19/E19 -> 1333.3333 | P19: =O19*8 -> 10666.667 | Q19: =N19*F19/E19 -> 1333.3333 | R19: =Q19*4 -> 5333.3333 | V19: =T19*F19/E19 -> 0 | W19: =V19*8 -> 0 | X19: =U19*F19/E19 -> 0 | Y19: =X19*4 -> 0 | AC19: =AA19*F19/E19 -> 0 | AD19: =AC19*8 -> 0 | AE19: =AB19*F19/E19 -> 0 | AF19: =AE19*4 -> 0 | AJ19: =AH19*F19/E19 -> 0 | AK19: =AJ19*8 -> 0 | AL19: =AI19*F19/E19 -> 0 | AM19: =AL19*4 -> 0
B20: Dry Mop Pads 100 cm | C20: =M20+T20+AA20+AH20 -> 20 | D20: =N20+U20+AB20+AI20 -> 10 | E20: 1 | F20: 150 | G20: =C20*F20/E20 -> 3000 | H20: =G20*8 -> 24000 | I20: =D20*F20/E20 -> 1500 | J20: =I20*4 -> 6000 | K20: =(O20+V20+AC20+AJ20)-G20 -> 0 | L20: =(Q20+X20+AE20+AL20)-I20 -> 0 | M20: 20 | N20: 10 | O20: =M20*F20/E20 -> 3000 | P20: =O20*8 -> 24000 | Q20: =N20*F20/E20 -> 1500 | R20: =Q20*4 -> 6000 | V20: =T20*F20/E20 -> 0 | W20: =V20*8 -> 0 | X20: =U20*F20/E20 -> 0 | Y20: =X20*4 -> 0 | AC20: =AA20*F20/E20 -> 0 | AD20: =AC20*8 -> 0 | AE20: =AB20*F20/E20 -> 0 | AF20: =AE20*4 -> 0 | AJ20: =AH20*F20/E20 -> 0 | AK20: =AJ20*8 -> 0 | AL20: =AI20*F20/E20 -> 0 | AM20: =AL20*4 -> 0
B21: Mop No Dust 40 cm | C21: =M21+T21+AA21+AH21 -> 34 | D21: =N21+U21+AB21+AI21 -> 19 | E21: 6 | F21: 750 | G21: =C21*F21/E21 -> 4250 | H21: =G21*8 -> 34000 | I21: =D21*F21/E21 -> 2375 | J21: =I21*4 -> 9500 | K21: =(O21+V21+AC21+AJ21)-G21 -> 0 | L21: =(Q21+X21+AE21+AL21)-I21 -> 0 | M21: 30 | N21: 15 | O21: =M21*F21/E21 -> 3750 | P21: =O21*8 -> 30000 | Q21: =N21*F21/E21 -> 1875 | R21: =Q21*4 -> 7500 | V21: =T21*F21/E21 -> 0 | W21: =V21*8 -> 0 | X21: =U21*F21/E21 -> 0 | Y21: =X21*4 -> 0 | AA21: 3 | AB21: 3 | AC21: =AA21*F21/E21 -> 375 | AD21: =AC21*8 -> 3000 | AE21: =AB21*F21/E21 -> 375 | AF21: =AE21*4 -> 1500 | AH21: 1 | AI21: 1 | AJ21: =AH21*F21/E21 -> 125 | AK21: =AJ21*8 -> 1000 | AL21: =AI21*F21/E21 -> 125 | AM21: =AL21*4 -> 500
B22: Mop No Dust Pads 40 cm | C22: =M22+T22+AA22+AH22 -> 50 | D22: =N22+U22+AB22+AI22 -> 20 | E22: 1 | F22: 150 | G22: =C22*F22/E22 -> 7500 | H22: =G22*8 -> 60000 | I22: =D22*F22/E22 -> 3000 | J22: =I22*4 -> 12000 | K22: =(O22+V22+AC22+AJ22)-G22 -> 0 | L22: =(Q22+X22+AE22+AL22)-I22 -> 0 | M22: 45 | N22: 15 | O22: =M22*F22/E22 -> 6750 | P22: =O22*8 -> 54000 | Q22: =N22*F22/E22 -> 2250 | R22: =Q22*4 -> 9000 | V22: =T22*F22/E22 -> 0 | W22: =V22*8 -> 0 | X22: =U22*F22/E22 -> 0 | Y22: =X22*4 -> 0 | AA22: 3 | AB22: 3 | AC22: =AA22*F22/E22 -> 450 | AD22: =AC22*8 -> 3600 | AE22: =AB22*F22/E22 -> 450 | AF22: =AE22*4 -> 1800 | AH22: 2 | AI22: 2 | AJ22: =AH22*F22/E22 -> 300 | AK22: =AJ22*8 -> 2400 | AL22: =AI22*F22/E22 -> 300 | AM22: =AL22*4 -> 1200
B23: Gloves No Dust 40 cm | C23: =M23+T23+AA23+AH23 -> 24 | D23: =N23+U23+AB23+AI23 -> 14 | E23: 1 | F23: 150 | G23: =C23*F23/E23 -> 3600 | H23: =G23*8 -> 28800 | I23: =D23*F23/E23 -> 2100 | J23: =I23*4 -> 8400 | K23: =(O23+V23+AC23+AJ23)-G23 -> 0 | L23: =(Q23+X23+AE23+AL23)-I23 -> 0 | M23: 20 | N23: 10 | O23: =M23*F23/E23 -> 3000 | P23: =O23*8 -> 24000 | Q23: =N23*F23/E23 -> 1500 | R23: =Q23*4 -> 6000 | V23: =T23*F23/E23 -> 0 | W23: =V23*8 -> 0 | X23: =U23*F23/E23 -> 0 | Y23: =X23*4 -> 0 | AA23: 3 | AB23: 3 | AC23: =AA23*F23/E23 -> 450 | AD23: =AC23*8 -> 3600 | AE23: =AB23*F23/E23 -> 450 | AF23: =AE23*4 -> 1800 | AH23: 1 | AI23: 1 | AJ23: =AH23*F23/E23 -> 150 | AK23: =AJ23*8 -> 1200 | AL23: =AI23*F23/E23 -> 150 | AM23: =AL23*4 -> 600
B24: Liter Pickers | C24: =M24+T24+AA24+AH24 -> 80 | D24: =N24+U24+AB24+AI24 -> 60 | E24: 6 | F24: 550 | G24: =C24*F24/E24 -> 7333.3333 | H24: =G24*8 -> 58666.667 | I24: =D24*F24/E24 -> 5500 | J24: =I24*4 -> 22000 | K24: =(O24+V24+AC24+AJ24)-G24 -> 0 | L24: =(Q24+X24+AE24+AL24)-I24 -> 0 | M24: 60 | N24: 40 | O24: =M24*F24/E24 -> 5500 | P24: =O24*8 -> 44000 | Q24: =N24*F24/E24 -> 3666.6667 | R24: =Q24*4 -> 14666.667 | T24: 20 | U24: 20 | V24: =T24*F24/E24 -> 1833.3333 | W24: =V24*8 -> 14666.667 | X24: =U24*F24/E24 -> 1833.3333 | Y24: =X24*4 -> 7333.3333 | AC24: =AA24*F24/E24 -> 0 | AD24: =AC24*8 -> 0 | AE24: =AB24*F24/E24 -> 0 | AF24: =AE24*4 -> 0 | AJ24: =AH24*F24/E24 -> 0 | AK24: =AJ24*8 -> 0 | AL24: =AI24*F24/E24 -> 0 | AM24: =AL24*4 -> 0
B25: Hard Floor Brooms W/ Hand 60cm | C25: =M25+T25+AA25+AH25 -> 20 | D25: =N25+U25+AB25+AI25 -> 20 | E25: 4 | F25: 180 | G25: =C25*F25/E25 -> 900 | H25: =G25*8 -> 7200 | I25: =D25*F25/E25 -> 900 | J25: =I25*4 -> 3600 | K25: =(O25+V25+AC25+AJ25)-G25 -> 0 | L25: =(Q25+X25+AE25+AL25)-I25 -> 0 | O25: =M25*F25/E25 -> 0 | P25: =O25*8 -> 0 | Q25: =N25*F25/E25 -> 0 | R25: =Q25*4 -> 0 | T25: 20 | U25: 20 | V25: =T25*F25/E25 -> 900 | W25: =V25*8 -> 7200 | X25: =U25*F25/E25 -> 900 | Y25: =X25*4 -> 3600 | AC25: =AA25*F25/E25 -> 0 | AD25: =AC25*8 -> 0 | AE25: =AB25*F25/E25 -> 0 | AF25: =AE25*4 -> 0 | AJ25: =AH25*F25/E25 -> 0 | AK25: =AJ25*8 -> 0 | AL25: =AI25*F25/E25 -> 0 | AM25: =AL25*4 -> 0
B26: Hard Floor Brooms W/ Hand 30cm | C26: =M26+T26+AA26+AH26 -> 190 | D26: =N26+U26+AB26+AI26 -> 110 | E26: 1 | F26: 38 | G26: =C26*F26/E26 -> 7220 | H26: =G26*8 -> 57760 | I26: =D26*F26/E26 -> 4180 | J26: =I26*4 -> 16720 | K26: =(O26+V26+AC26+AJ26)-G26 -> 0 | L26: =(Q26+X26+AE26+AL26)-I26 -> 0 | M26: 150 | N26: 80 | O26: =M26*F26/E26 -> 5700 | P26: =O26*8 -> 45600 | Q26: =N26*F26/E26 -> 3040 | R26: =Q26*4 -> 12160 | T26: 40 | U26: 30 | V26: =T26*F26/E26 -> 1520 | W26: =V26*8 -> 12160 | X26: =U26*F26/E26 -> 1140 | Y26: =X26*4 -> 4560 | AC26: =AA26*F26/E26 -> 0 | AD26: =AC26*8 -> 0 | AE26: =AB26*F26/E26 -> 0 | AF26: =AE26*4 -> 0 | AJ26: =AH26*F26/E26 -> 0 | AK26: =AJ26*8 -> 0 | AL26: =AI26*F26/E26 -> 0 | AM26: =AL26*4 -> 0
B27: Soft Floor Brooms W/ Hand 30cm | C27: =M27+T27+AA27+AH27 -> 197 | D27: =N27+U27+AB27+AI27 -> 117 | E27: 1 | F27: 38 | G27: =C27*F27/E27 -> 7486 | H27: =G27*8 -> 59888 | I27: =D27*F27/E27 -> 4446 | J27: =I27*4 -> 17784 | K27: =(O27+V27+AC27+AJ27)-G27 -> 0 | L27: =(Q27+X27+AE27+AL27)-I27 -> 0 | M27: 150 | N27: 80 | O27: =M27*F27/E27 -> 5700 | P27: =O27*8 -> 45600 | Q27: =N27*F27/E27 -> 3040 | R27: =Q27*4 -> 12160 | T27: 40 | U27: 30 | V27: =T27*F27/E27 -> 1520 | W27: =V27*8 -> 12160 | X27: =U27*F27/E27 -> 1140 | Y27: =X27*4 -> 4560 | AA27: 4 | AB27: 4 | AC27: =AA27*F27/E27 -> 152 | AD27: =AC27*8 -> 1216 | AE27: =AB27*F27/E27 -> 152 | AF27: =AE27*4 -> 608 | AH27: 3 | AI27: 3 | AJ27: =AH27*F27/E27 -> 114 | AK27: =AJ27*8 -> 912 | AL27: =AI27*F27/E27 -> 114 | AM27: =AL27*4 -> 456
B28: Floor Squeezer W/ Hand 30 cm | C28: =M28+T28+AA28+AH28 -> 187 | D28: =N28+U28+AB28+AI28 -> 107 | E28: 1 | F28: 38 | G28: =C28*F28/E28 -> 7106 | H28: =G28*8 -> 56848 | I28: =D28*F28/E28 -> 4066 | J28: =I28*4 -> 16264 | K28: =(O28+V28+AC28+AJ28)-G28 -> 0 | L28: =(Q28+X28+AE28+AL28)-I28 -> 0 | M28: 150 | N28: 80 | O28: =M28*F28/E28 -> 5700 | P28: =O28*8 -> 45600 | Q28: =N28*F28/E28 -> 3040 | R28: =Q28*4 -> 12160 | T28: 30 | U28: 20 | V28: =T28*F28/E28 -> 1140 | W28: =V28*8 -> 9120 | X28: =U28*F28/E28 -> 760 | Y28: =X28*4 -> 3040 | AA28: 4 | AB28: 4 | AC28: =AA28*F28/E28 -> 152 | AD28: =AC28*8 -> 1216 | AE28: =AB28*F28/E28 -> 152 | AF28: =AE28*4 -> 608 | AH28: 3 | AI28: 3 | AJ28: =AH28*F28/E28 -> 114 | AK28: =AJ28*8 -> 912 | AL28: =AI28*F28/E28 -> 114 | AM28: =AL28*4 -> 456
B29: Floor Squeezer W/ Hand 80 cm | C29: =M29+T29+AA29+AH29 -> 110 | D29: =N29+U29+AB29+AI29 -> 70 | E29: 3 | F29: 135 | G29: =C29*F29/E29 -> 4950 | H29: =G29*8 -> 39600 | I29: =D29*F29/E29 -> 3150 | J29: =I29*4 -> 12600 | K29: =(O29+V29+AC29+AJ29)-G29 -> 0 | L29: =(Q29+X29+AE29+AL29)-I29 -> 0 | M29: 80 | N29: 50 | O29: =M29*F29/E29 -> 3600 | P29: =O29*8 -> 28800 | Q29: =N29*F29/E29 -> 2250 | R29: =Q29*4 -> 9000 | T29: 30 | U29: 20 | V29: =T29*F29/E29 -> 1350 | W29: =V29*8 -> 10800 | X29: =U29*F29/E29 -> 900 | Y29: =X29*4 -> 3600 | AC29: =AA29*F29/E29 -> 0 | AD29: =AC29*8 -> 0 | AE29: =AB29*F29/E29 -> 0 | AF29: =AE29*4 -> 0 | AJ29: =AH29*F29/E29 -> 0 | AK29: =AJ29*8 -> 0 | AL29: =AI29*F29/E29 -> 0 | AM29: =AL29*4 -> 0
B30: Ceiling Duster | C30: =M30+T30+AA30+AH30 -> 74 | D30: =N30+U30+AB30+AI30 -> 39 | E30: 1 | F30: 45 | G30: =C30*F30/E30 -> 3330 | H30: =G30*8 -> 26640 | I30: =D30*F30/E30 -> 1755 | J30: =I30*4 -> 7020 | K30: =(O30+V30+AC30+AJ30)-G30 -> 0 | L30: =(Q30+X30+AE30+AL30)-I30 -> 0 | M30: 60 | N30: 30 | O30: =M30*F30/E30 -> 2700 | P30: =O30*8 -> 21600 | Q30: =N30*F30/E30 -> 1350 | R30: =Q30*4 -> 5400 | T30: 10 | U30: 5 | V30: =T30*F30/E30 -> 450 | W30: =V30*8 -> 3600 | X30: =U30*F30/E30 -> 225 | Y30: =X30*4 -> 900 | AA30: 3 | AB30: 3 | AC30: =AA30*F30/E30 -> 135 | AD30: =AC30*8 -> 1080 | AE30: =AB30*F30/E30 -> 135 | AF30: =AE30*4 -> 540 | AH30: 1 | AI30: 1 | AJ30: =AH30*F30/E30 -> 45 | AK30: =AJ30*8 -> 360 | AL30: =AI30*F30/E30 -> 45 | AM30: =AL30*4 -> 180
B31: Plastic Sprayer | C31: =M31+T31+AA31+AH31 -> 212 | D31: =N31+U31+AB31+AI31 -> 122 | E31: 1 | F31: 25 | G31: =C31*F31/E31 -> 5300 | H31: =G31*8 -> 42400 | I31: =D31*F31/E31 -> 3050 | J31: =I31*4 -> 12200 | K31: =(O31+V31+AC31+AJ31)-G31 -> 0 | L31: =(Q31+X31+AE31+AL31)-I31 -> 0 | M31: 150 | N31: 80 | O31: =M31*F31/E31 -> 3750 | P31: =O31*8 -> 30000 | Q31: =N31*F31/E31 -> 2000 | R31: =Q31*4 -> 8000 | T31: 50 | U31: 30 | V31: =T31*F31/E31 -> 1250 | W31: =V31*8 -> 10000 | X31: =U31*F31/E31 -> 750 | Y31: =X31*4 -> 3000 | AA31: 10 | AB31: 10 | AC31: =AA31*F31/E31 -> 250 | AD31: =AC31*8 -> 2000 | AE31: =AB31*F31/E31 -> 250 | AF31: =AE31*4 -> 1000 | AH31: 2 | AI31: 2 | AJ31: =AH31*F31/E31 -> 50 | AK31: =AJ31*8 -> 400 | AL31: =AI31*F31/E31 -> 50 | AM31: =AL31*4 -> 200
B32: Floor Brush | C32: =M32+T32+AA32+AH32 -> 88 | D32: =N32+U32+AB32+AI32 -> 58 | E32: 2 | F32: 30 | G32: =C32*F32/E32 -> 1320 | H32: =G32*8 -> 10560 | I32: =D32*F32/E32 -> 870 | J32: =I32*4 -> 3480 | K32: =(O32+V32+AC32+AJ32)-G32 -> 0 | L32: =(Q32+X32+AE32+AL32)-I32 -> 0 | M32: 60 | N32: 40 | O32: =M32*F32/E32 -> 900 | P32: =O32*8 -> 7200 | Q32: =N32*F32/E32 -> 600 | R32: =Q32*4 -> 2400 | T32: 20 | U32: 10 | V32: =T32*F32/E32 -> 300 | W32: =V32*8 -> 2400 | X32: =U32*F32/E32 -> 150 | Y32: =X32*4 -> 600 | AA32: 6 | AB32: 6 | AC32: =AA32*F32/E32 -> 90 | AD32: =AC32*8 -> 720 | AE32: =AB32*F32/E32 -> 90 | AF32: =AE32*4 -> 360 | AH32: 2 | AI32: 2 | AJ32: =AH32*F32/E32 -> 30 | AK32: =AJ32*8 -> 240 | AL32: =AI32*F32/E32 -> 30 | AM32: =AL32*4 -> 120
B33: Toilet Bowl Cleaners Broom | C33: =M33+T33+AA33+AH33 -> 80 | D33: =N33+U33+AB33+AI33 -> 60 | E33: 3 | F33: 33 | G33: =C33*F33/E33 -> 880 | H33: =G33*8 -> 7040 | I33: =D33*F33/E33 -> 660 | J33: =I33*4 -> 2640 | K33: =(O33+V33+AC33+AJ33)-G33 -> 0 | L33: =(Q33+X33+AE33+AL33)-I33 -> 0 | M33: 60 | N33: 40 | O33: =M33*F33/E33 -> 660 | P33: =O33*8 -> 5280 | Q33: =N33*F33/E33 -> 440 | R33: =Q33*4 -> 1760 | T33: 15 | U33: 15 | V33: =T33*F33/E33 -> 165 | W33: =V33*8 -> 1320 | X33: =U33*F33/E33 -> 165 | Y33: =X33*4 -> 660 | AA33: 3 | AB33: 3 | AC33: =AA33*F33/E33 -> 33 | AD33: =AC33*8 -> 264 | AE33: =AB33*F33/E33 -> 33 | AF33: =AE33*4 -> 132 | AH33: 2 | AI33: 2 | AJ33: =AH33*F33/E33 -> 22 | AK33: =AJ33*8 -> 176 | AL33: =AI33*F33/E33 -> 22 | AM33: =AL33*4 -> 88
B34: Dust Pans W/ Hand | C34: =M34+T34+AA34+AH34 -> 175 | D34: =N34+U34+AB34+AI34 -> 105 | E34: 3 | F34: 48 | G34: =C34*F34/E34 -> 2800 | H34: =G34*8 -> 22400 | I34: =D34*F34/E34 -> 1680 | J34: =I34*4 -> 6720 | K34: =(O34+V34+AC34+AJ34)-G34 -> 0 | L34: =(Q34+X34+AE34+AL34)-I34 -> 0 | M34: 100 | N34: 60 | O34: =M34*F34/E34 -> 1600 | P34: =O34*8 -> 12800 | Q34: =N34*F34/E34 -> 960 | R34: =Q34*4 -> 3840 | T34: 70 | U34: 40 | V34: =T34*F34/E34 -> 1120 | W34: =V34*8 -> 8960 | X34: =U34*F34/E34 -> 640 | Y34: =X34*4 -> 2560 | AA34: 3 | AB34: 3 | AC34: =AA34*F34/E34 -> 48 | AD34: =AC34*8 -> 384 | AE34: =AB34*F34/E34 -> 48 | AF34: =AE34*4 -> 192 | AH34: 2 | AI34: 2 | AJ34: =AH34*F34/E34 -> 32 | AK34: =AJ34*8 -> 256 | AL34: =AI34*F34/E34 -> 32 | AM34: =AL34*4 -> 128
B35: Dust Pans w / cover | C35: =M35+T35+AA35+AH35 -> 125 | D35: =N35+U35+AB35+AI35 -> 90 | E35: 6 | F35: 650 | G35: =C35*F35/E35 -> 13541.667 | H35: =G35*8 -> 108333.33 | I35: =D35*F35/E35 -> 9750 | J35: =I35*4 -> 39000 | K35: =(O35+V35+AC35+AJ35)-G35 -> 0 | L35: =(Q35+X35+AE35+AL35)-I35 -> 0 | M35: 80 | N35: 60 | O35: =M35*F35/E35 -> 8666.6667 | P35: =O35*8 -> 69333.333 | Q35: =N35*F35/E35 -> 6500 | R35: =Q35*4 -> 26000 | T35: 40 | U35: 25 | V35: =T35*F35/E35 -> 4333.3333 | W35: =V35*8 -> 34666.667 | X35: =U35*F35/E35 -> 2708.3333 | Y35: =X35*4 -> 10833.333 | AA35: 3 | AB35: 3 | AC35: =AA35*F35/E35 -> 325 | AD35: =AC35*8 -> 2600 | AE35: =AB35*F35/E35 -> 325 | AF35: =AE35*4 -> 1300 | AH35: 2 | AI35: 2 | AJ35: =AH35*F35/E35 -> 216.66667 | AK35: =AJ35*8 -> 1733.3333 | AL35: =AI35*F35/E35 -> 216.66667 | AM35: =AL35*4 -> 866.66667
B36: Water Bucket 20 L | C36: =M36+T36+AA36+AH36 -> 125 | D36: =N36+U36+AB36+AI36 -> 90 | E36: 3 | F36: 60 | G36: =C36*F36/E36 -> 2500 | H36: =G36*8 -> 20000 | I36: =D36*F36/E36 -> 1800 | J36: =I36*4 -> 7200 | K36: =(O36+V36+AC36+AJ36)-G36 -> 0 | L36: =(Q36+X36+AE36+AL36)-I36 -> 0 | M36: 100 | N36: 70 | O36: =M36*F36/E36 -> 2000 | P36: =O36*8 -> 16000 | Q36: =N36*F36/E36 -> 1400 | R36: =Q36*4 -> 5600 | T36: 20 | U36: 15 | V36: =T36*F36/E36 -> 400 | W36: =V36*8 -> 3200 | X36: =U36*F36/E36 -> 300 | Y36: =X36*4 -> 1200 | AA36: 3 | AB36: 3 | AC36: =AA36*F36/E36 -> 60 | AD36: =AC36*8 -> 480 | AE36: =AB36*F36/E36 -> 60 | AF36: =AE36*4 -> 240 | AH36: 2 | AI36: 2 | AJ36: =AH36*F36/E36 -> 40 | AK36: =AJ36*8 -> 320 | AL36: =AI36*F36/E36 -> 40 | AM36: =AL36*4 -> 160
B37: Floor Scraper | C37: =M37+T37+AA37+AH37 -> 65 | D37: =N37+U37+AB37+AI37 -> 50 | E37: 1 | F37: 28 | G37: =C37*F37/E37 -> 1820 | H37: =G37*8 -> 14560 | I37: =D37*F37/E37 -> 1400 | J37: =I37*4 -> 5600 | K37: =(O37+V37+AC37+AJ37)-G37 -> 0 | L37: =(Q37+X37+AE37+AL37)-I37 -> 0 | M37: 40 | N37: 30 | O37: =M37*F37/E37 -> 1120 | P37: =O37*8 -> 8960 | Q37: =N37*F37/E37 -> 840 | R37: =Q37*4 -> 3360 | T37: 20 | U37: 15 | V37: =T37*F37/E37 -> 560 | W37: =V37*8 -> 4480 | X37: =U37*F37/E37 -> 420 | Y37: =X37*4 -> 1680 | AA37: 3 | AB37: 3 | AC37: =AA37*F37/E37 -> 84 | AD37: =AC37*8 -> 672 | AE37: =AB37*F37/E37 -> 84 | AF37: =AE37*4 -> 336 | AH37: 2 | AI37: 2 | AJ37: =AH37*F37/E37 -> 56 | AK37: =AJ37*8 -> 448 | AL37: =AI37*F37/E37 -> 56 | AM37: =AL37*4 -> 224
B38: Glass Scraper | C38: =M38+T38+AA38+AH38 -> 85 | D38: =N38+U38+AB38+AI38 -> 50 | E38: 1 | F38: 37 | G38: =C38*F38/E38 -> 3145 | H38: =G38*8 -> 25160 | I38: =D38*F38/E38 -> 1850 | J38: =I38*4 -> 7400 | K38: =(O38+V38+AC38+AJ38)-G38 -> 0 | L38: =(Q38+X38+AE38+AL38)-I38 -> 0 | M38: 60 | N38: 30 | O38: =M38*F38/E38 -> 2220 | P38: =O38*8 -> 17760 | Q38: =N38*F38/E38 -> 1110 | R38: =Q38*4 -> 4440 | T38: 20 | U38: 15 | V38: =T38*F38/E38 -> 740 | W38: =V38*8 -> 5920 | X38: =U38*F38/E38 -> 555 | Y38: =X38*4 -> 2220 | AA38: 3 | AB38: 3 | AC38: =AA38*F38/E38 -> 111 | AD38: =AC38*8 -> 888 | AE38: =AB38*F38/E38 -> 111 | AF38: =AE38*4 -> 444 | AH38: 2 | AI38: 2 | AJ38: =AH38*F38/E38 -> 74 | AK38: =AJ38*8 -> 592 | AL38: =AI38*F38/E38 -> 74 | AM38: =AL38*4 -> 296
B39: Spare Glass Scraper | C39: =M39+T39+AA39+AH39 -> 17 | D39: =N39+U39+AB39+AI39 -> 17 | E39: 1 | F39: 33 | G39: =C39*F39/E39 -> 561 | H39: =G39*8 -> 4488 | I39: =D39*F39/E39 -> 561 | J39: =I39*4 -> 2244 | K39: =(O39+V39+AC39+AJ39)-G39 -> 0 | L39: =(Q39+X39+AE39+AL39)-I39 -> 0 | M39: 10 | N39: 10 | O39: =M39*F39/E39 -> 330 | P39: =O39*8 -> 2640 | Q39: =N39*F39/E39 -> 330 | R39: =Q39*4 -> 1320 | T39: 5 | U39: 5 | V39: =T39*F39/E39 -> 165 | W39: =V39*8 -> 1320 | X39: =U39*F39/E39 -> 165 | Y39: =X39*4 -> 660 | AA39: 1 | AB39: 1 | AC39: =AA39*F39/E39 -> 33 | AD39: =AC39*8 -> 264 | AE39: =AB39*F39/E39 -> 33 | AF39: =AE39*4 -> 132 | AH39: 1 | AI39: 1 | AJ39: =AH39*F39/E39 -> 33 | AK39: =AJ39*8 -> 264 | AL39: =AI39*F39/E39 -> 33 | AM39: =AL39*4 -> 132
B40: Glass Squeezer 35cm | C40: =M40+T40+AA40+AH40 -> 85 | D40: =N40+U40+AB40+AI40 -> 50 | E40: 3 | F40: 125 | G40: =C40*F40/E40 -> 3541.6667 | H40: =G40*8 -> 28333.333 | I40: =D40*F40/E40 -> 2083.3333 | J40: =I40*4 -> 8333.3333 | K40: =(O40+V40+AC40+AJ40)-G40 -> 0 | L40: =(Q40+X40+AE40+AL40)-I40 -> 0 | M40: 60 | N40: 30 | O40: =M40*F40/E40 -> 2500 | P40: =O40*8 -> 20000 | Q40: =N40*F40/E40 -> 1250 | R40: =Q40*4 -> 5000 | T40: 20 | U40: 15 | V40: =T40*F40/E40 -> 833.33333 | W40: =V40*8 -> 6666.6667 | X40: =U40*F40/E40 -> 625 | Y40: =X40*4 -> 2500 | AA40: 3 | AB40: 3 | AC40: =AA40*F40/E40 -> 125 | AD40: =AC40*8 -> 1000 | AE40: =AB40*F40/E40 -> 125 | AF40: =AE40*4 -> 500 | AH40: 2 | AI40: 2 | AJ40: =AH40*F40/E40 -> 83.333333 | AK40: =AJ40*8 -> 666.66667 | AL40: =AI40*F40/E40 -> 83.333333 | AM40: =AL40*4 -> 333.33333
B41: Window Washer 35cm | C41: =M41+T41+AA41+AH41 -> 85 | D41: =N41+U41+AB41+AI41 -> 50 | E41: 3 | F41: 145 | G41: =C41*F41/E41 -> 4108.3333 | H41: =G41*8 -> 32866.667 | I41: =D41*F41/E41 -> 2416.6667 | J41: =I41*4 -> 9666.6667 | K41: =(O41+V41+AC41+AJ41)-G41 -> 0 | L41: =(Q41+X41+AE41+AL41)-I41 -> 0 | M41: 60 | N41: 30 | O41: =M41*F41/E41 -> 2900 | P41: =O41*8 -> 23200 | Q41: =N41*F41/E41 -> 1450 | R41: =Q41*4 -> 5800 | T41: 20 | U41: 15 | V41: =T41*F41/E41 -> 966.66667 | W41: =V41*8 -> 7733.3333 | X41: =U41*F41/E41 -> 725 | Y41: =X41*4 -> 2900 | AA41: 3 | AB41: 3 | AC41: =AA41*F41/E41 -> 145 | AD41: =AC41*8 -> 1160 | AE41: =AB41*F41/E41 -> 145 | AF41: =AE41*4 -> 580 | AH41: 2 | AI41: 2 | AJ41: =AH41*F41/E41 -> 96.666667 | AK41: =AJ41*8 -> 773.33333 | AL41: =AI41*F41/E41 -> 96.666667 | AM41: =AL41*4 -> 386.66667
... B45: White Pads 17mm | C45: =M45+T45+AA45+AH45 -> 38 | D45: =N45+U45+AB45+AI45 -> 27 | E45: 1 | F45: 450 | G45: =C45*F45/E45 -> 17100 | H45: =G45*8 -> 136800 | I45: =D45*F45/E45 -> 12150 | J45: =I45*4 -> 48600 | K45: =(O45+V45+AC45+AJ45)-G45 -> 0 | L45: =(Q45+X45+AE45+AL45)-I45 -> 0 | M45: 30 | N45: 20 | O45: =M45*F45/E45 -> 13500 | P45: =O45*8 -> 108000 | Q45: =N45*F45/E45 -> 9000 | R45: =Q45*4 -> 36000 | T45: 5 | U45: 4 | V45: =T45*F45/E45 -> 2250 | W45: =V45*8 -> 18000 | X45: =U45*F45/E45 -> 1800 | Y45: =X45*4 -> 7200 | AA45: 3 | AB45: 3 | AC45: =AA45*F45/E45 -> 1350 | AD45: =AC45*8 -> 10800 | AE45: =AB45*F45/E45 -> 1350 | AF45: =AE45*4 -> 5400 | AH45: 0 | AI45: 0 | AJ45: =AH45*F45/E45 -> 0 | AK45: =AJ45*8 -> 0 | AL45: =AI45*F45/E45 -> 0 | AM45: =AL45*4 -> 0
B46: Black Pads 17mm | C46: =M46+T46+AA46+AH46 -> 35 | D46: =N46+U46+AB46+AI46 -> 24 | E46: 1 | F46: 450 | G46: =C46*F46/E46 -> 15750 | H46: =G46*8 -> 126000 | I46: =D46*F46/E46 -> 10800 | J46: =I46*4 -> 43200 | K46: =(O46+V46+AC46+AJ46)-G46 -> 0 | L46: =(Q46+X46+AE46+AL46)-I46 -> 0 | M46: 30 | N46: 20 | O46: =M46*F46/E46 -> 13500 | P46: =O46*8 -> 108000 | Q46: =N46*F46/E46 -> 9000 | R46: =Q46*4 -> 36000 | T46: 5 | U46: 4 | V46: =T46*F46/E46 -> 2250 | W46: =V46*8 -> 18000 | X46: =U46*F46/E46 -> 1800 | Y46: =X46*4 -> 7200 | AC46: =AA46*F46/E46 -> 0 | AD46: =AC46*8 -> 0 | AE46: =AB46*F46/E46 -> 0 | AF46: =AE46*4 -> 0 | AJ46: =AH46*F46/E46 -> 0 | AK46: =AJ46*8 -> 0 | AL46: =AI46*F46/E46 -> 0 | AM46: =AL46*4 -> 0
B47: Electric Cable | C47: =M47+T47+AA47+AH47 -> 25 | D47: =N47+U47+AB47+AI47 -> 25 | E47: 12 | F47: 1850 | G47: =C47*F47/E47 -> 3854.1667 | H47: =G47*8 -> 30833.333 | I47: =D47*F47/E47 -> 3854.1667 | J47: =I47*4 -> 15416.667 | K47: =(O47+V47+AC47+AJ47)-G47 -> 0 | L47: =(Q47+X47+AE47+AL47)-I47 -> 0 | M47: 20 | N47: 20 | O47: =M47*F47/E47 -> 3083.3333 | P47: =O47*8 -> 24666.667 | Q47: =N47*F47/E47 -> 3083.3333 | R47: =Q47*4 -> 12333.333 | T47: 5 | U47: 5 | V47: =T47*F47/E47 -> 770.83333 | W47: =V47*8 -> 6166.6667 | X47: =U47*F47/E47 -> 770.83333 | Y47: =X47*4 -> 3083.3333 | AA47: 0 | AB47: 0 | AC47: =AA47*F47/E47 -> 0 | AD47: =AC47*8 -> 0 | AE47: =AB47*F47/E47 -> 0 | AF47: =AE47*4 -> 0 | AH47: 0 | AI47: 0 | AJ47: =AH47*F47/E47 -> 0 | AK47: =AJ47*8 -> 0 | AL47: =AI47*F47/E47 -> 0 | AM47: =AL47*4 -> 0
B48: Hose 50 m | C48: =M48+T48+AA48+AH48 -> 5 | D48: =N48+U48+AB48+AI48 -> 5 | E48: 6 | F48: 1200 | G48: =C48*F48/E48 -> 1000 | H48: =G48*8 -> 8000 | I48: =D48*F48/E48 -> 1000 | J48: =I48*4 -> 4000 | K48: =(O48+V48+AC48+AJ48)-G48 -> 0 | L48: =(Q48+X48+AE48+AL48)-I48 -> 0 | O48: =M48*F48/E48 -> 0 | P48: =O48*8 -> 0 | Q48: =N48*F48/E48 -> 0 | R48: =Q48*4 -> 0 | T48: 5 | U48: 5 | V48: =T48*F48/E48 -> 1000 | W48: =V48*8 -> 8000 | X48: =U48*F48/E48 -> 1000 | Y48: =X48*4 -> 4000 | AC48: =AA48*F48/E48 -> 0 | AD48: =AC48*8 -> 0 | AE48: =AB48*F48/E48 -> 0 | AF48: =AE48*4 -> 0 | AJ48: =AH48*F48/E48 -> 0 | AK48: =AJ48*8 -> 0 | AL48: =AI48*F48/E48 -> 0 | AM48: =AL48*4 -> 0
G49: =SUM(G6:G48) -> 213231.96 | H49: =G49*8 -> 1705855.7 | I49: =SUM(I6:I48) -> 153081.96 | J49: =I49*4 -> 612327.83 | K49: =(O49+V49+AC49+AJ49)-G49 -> 0 | L49: =(Q49+X49+AE49+AL49)-I49 -> 0 | O49: =SUM(O6:O48) -> 163200.83 | P49: =O49*8 -> 1305606.7 | Q49: =SUM(Q6:Q48) -> 110245.83 | R49: =Q49*4 -> 440983.33 | V49: =SUM(V6:V48) -> 40443.194 | W49: =V49*8 -> 323545.56 | X49: =SUM(X6:X48) -> 33248.194 | Y49: =X49*4 -> 132992.78 | AC49: =SUM(AC6:AC48) -> 7247.8611 | AD49: =AC49*8 -> 57982.889 | AE49: =SUM(AE6:AE48) -> 7247.8611 | AF49: =AE49*4 -> 28991.444 | AJ49: =SUM(AJ6:AJ48) -> 2340.0694 | AK49: =AJ49*8 -> 18720.556 | AL49: =SUM(AL6:AL48) -> 2340.0694 | AM49: =AL49*4 -> 9360.2778

Sheet AUC Total Consumables
M3: INNER CAMPUS Budget | T3: OUTER CAMPUS Budget | AA3: NEW CAIRO OFF CAMPUS HOUSING Budget | AH3: Maadi Buildings Budget
B4: HK Budget | C4: High | D4: Low | E4: Deprecation / Moth | F4: Price | G4: High Season | I4: Low Season | M4: High | N4: Low | O4: High Season | Q4: Low Season | T4: High | U4: Low | V4: High Season | X4: Low Season | AA4: High | AB4: Low | AC4: High Season | AE4: Low Season | AH4: High | AI4: Low | AJ4: High Season | AL4: Low Season
C5: QTY. | D5: QTY. | G5: Monthly | H5: Annually "8"Months | I5: Monthly | J5: Annually "4"Months | M5: QTY. | N5: QTY. | O5: Monthly | P5: Annually "8"Months | Q5: Monthly | R5: Annually "4"Months | T5: QTY. | U5: QTY. | V5: Monthly | W5: Annually "8"Months | X5: Monthly | Y5: Annually "4"Months | AA5: QTY. | AB5: QTY. | AC5: Monthly | AD5: Annually "8"Months | AE5: Monthly | AF5: Annually "4"Months | AH5: QTY. | AI5: QTY. | AJ5: Monthly | AK5: Annually "8"Months | AL5: Monthly | AM5: Annually "4"Months
B6: TASKI Jontec ProStrip F 1b | C6: =M6+T6+AA6+AH6 -> 240 | D6: =N6+U6+AB6+AI6 -> 125 | E6: 1 | F6: 22.65 | G6: =C6*F6/E6 -> 5436 | H6: =G6*8 -> 43488 | I6: =D6*F6/E6 -> 2831.25 | J6: =I6*4 -> 11325 | K6: =(O6+V6+AC6+AJ6)-G6 -> 0 | L6: =(Q6+X6+AE6+AL6)-I6 -> 0 | M6: 150 | N6: 50 | O6: =M6*F6/E6 -> 3397.5 | P6: =O6*8 -> 27180 | Q6: =N6*F6/E6 -> 1132.5 | R6: =Q6*4 -> 4530 | T6: 50 | U6: 35 | V6: =T6*F6/E6 -> 1132.5 | W6: =V6*8 -> 9060 | X6: =U6*F6/E6 -> 792.75 | Y6: =X6*4 -> 3171 | AA6: 30 | AB6: 30 | AC6: =AA6*F6/E6 -> 679.5 | AD6: =AC6*8 -> 5436 | AE6: =AB6*F6/E6 -> 679.5 | AF6: =AE6*4 -> 2718 | AH6: 10 | AI6: 10 | AJ6: =AH6*F6/E6 -> 226.5 | AK6: =AJ6*8 -> 1812 | AL6: =AI6*F6/E6 -> 226.5 | AM6: =AL6*4 -> 906
B7: Oxivir Excel | C7: =M7+T7+AA7+AH7 -> 290 | D7: =N7+U7+AB7+AI7 -> 155 | E7: 1 | F7: 14.99 | G7: =C7*F7/E7 -> 4347.1 | H7: =G7*8 -> 34776.8 | I7: =D7*F7/E7 -> 2323.45 | J7: =I7*4 -> 9293.8 | K7: =(O7+V7+AC7+AJ7)-G7 -> 0 | L7: =(Q7+X7+AE7+AL7)-I7 -> 0 | M7: 200 | N7: 80 | O7: =M7*F7/E7 -> 2998 | P7: =O7*8 -> 23984 | Q7: =N7*F7/E7 -> 1199.2 | R7: =Q7*4 -> 4796.8 | T7: 50 | U7: 35 | V7: =T7*F7/E7 -> 749.5 | W7: =V7*8 -> 5996 | X7: =U7*F7/E7 -> 524.65 | Y7: =X7*4 -> 2098.6 | AA7: 30 | AB7: 30 | AC7: =AA7*F7/E7 -> 449.7 | AD7: =AC7*8 -> 3597.6 | AE7: =AB7*F7/E7 -> 449.7 | AF7: =AE7*4 -> 1798.8 | AH7: 10 | AI7: 10 | AJ7: =AH7*F7/E7 -> 149.9 | AK7: =AJ7*8 -> 1199.2 | AL7: =AI7*F7/E7 -> 149.9 | AM7: =AL7*4 -> 599.6
B8: Room Care R1 Conc | C8: =M8+T8+AA8+AH8 -> 285 | D8: =N8+U8+AB8+AI8 -> 150 | E8: 1 | F8: 36 | G8: =C8*F8/E8 -> 10260 | H8: =G8*8 -> 82080 | I8: =D8*F8/E8 -> 5400 | J8: =I8*4 -> 21600 | K8: =(O8+V8+AC8+AJ8)-G8 -> 0 | L8: =(Q8+X8+AE8+AL8)-I8 -> 0 | M8: 200 | N8: 80 | O8: =M8*F8/E8 -> 7200 | P8: =O8*8 -> 57600 | Q8: =N8*F8/E8 -> 2880 | R8: =Q8*4 -> 11520 | T8: 50 | U8: 35 | V8: =T8*F8/E8 -> 1800 | W8: =V8*8 -> 14400 | X8: =U8*F8/E8 -> 1260 | Y8: =X8*4 -> 5040 | AA8: 20 | AB8: 20 | AC8: =AA8*F8/E8 -> 720 | AD8: =AC8*8 -> 5760 | AE8: =AB8*F8/E8 -> 720 | AF8: =AE8*4 -> 2880 | AH8: 15 | AI8: 15 | AJ8: =AH8*F8/E8 -> 540 | AK8: =AJ8*8 -> 4320 | AL8: =AI8*F8/E8 -> 540 | AM8: =AL8*4 -> 2160
B9: TASKI Calcacid W3 | C9: =M9+T9+AA9+AH9 -> 255 | D9: =N9+U9+AB9+AI9 -> 170 | E9: 1 | F9: 9.567 | G9: =C9*F9/E9 -> 2439.585 | H9: =G9*8 -> 19516.68 | I9: =D9*F9/E9 -> 1626.39 | J9: =I9*4 -> 6505.56 | K9: =(O9+V9+AC9+AJ9)-G9 -> 0 | L9: =(Q9+X9+AE9+AL9)-I9 -> 0 | M9: 150 | N9: 80 | O9: =M9*F9/E9 -> 1435.05 | P9: =O9*8 -> 11480.4 | Q9: =N9*F9/E9 -> 765.36 | R9: =Q9*4 -> 3061.44 | T9: 50 | U9: 35 | V9: =T9*F9/E9 -> 478.35 | W9: =V9*8 -> 3826.8 | X9: =U9*F9/E9 -> 334.845 | Y9: =X9*4 -> 1339.38 | AA9: 40 | AB9: 40 | AC9: =AA9*F9/E9 -> 382.68 | AD9: =AC9*8 -> 3061.44 | AE9: =AB9*F9/E9 -> 382.68 | AF9: =AE9*4 -> 1530.72 | AH9: 15 | AI9: 15 | AJ9: =AH9*F9/E9 -> 143.505 | AK9: =AJ9*8 -> 1148.04 | AL9: =AI9*F9/E9 -> 143.505 | AM9: =AL9*4 -> 574.02
B10: Suma Inox Classic D7 | C10: =M10+T10+AA10+AH10 -> 33 | D10: =N10+U10+AB10+AI10 -> 13 | E10: 1 | F10: 563 | G10: =C10*F10/E10 -> 18579 | H10: =G10*8 -> 148632 | I10: =D10*F10/E10 -> 7319 | J10: =I10*4 -> 29276 | K10: =(O10+V10+AC10+AJ10)-G10 -> 0 | L10: =(Q10+X10+AE10+AL10)-I10 -> 0 | M10: 30 | N10: 10 | O10: =M10*F10/E10 -> 16890 | P10: =O10*8 -> 135120 | Q10: =N10*F10/E10 -> 5630 | R10: =Q10*4 -> 22520 | V10: =T10*F10/E10 -> 0 | W10: =V10*8 -> 0 | X10: =U10*F10/E10 -> 0 | Y10: =X10*4 -> 0 | AA10: 2 | AB10: 2 | AC10: =AA10*F10/E10 -> 1126 | AD10: =AC10*8 -> 9008 | AE10: =AB10*F10/E10 -> 1126 | AF10: =AE10*4 -> 4504 | AH10: 1 | AI10: 1 | AJ10: =AH10*F10/E10 -> 563 | AK10: =AJ10*8 -> 4504 | AL10: =AI10*F10/E10 -> 563 | AM10: =AL10*4 -> 2252
B11: Room Care R3 Conc. | C11: =M11+T11+AA11+AH11 -> 260 | D11: =N11+U11+AB11+AI11 -> 170 | E11: 1 | F11: 43.27 | G11: =C11*F11/E11 -> 11250.2 | H11: =G11*8 -> 90001.6 | I11: =D11*F11/E11 -> 7355.9 | J11: =I11*4 -> 29423.6 | K11: =(O11+V11+AC11+AJ11)-G11 -> 0 | L11: =(Q11+X11+AE11+AL11)-I11 -> 0 | M11: 150 | N11: 80 | O11: =M11*F11/E11 -> 6490.5 | P11: =O11*8 -> 51924 | Q11: =N11*F11/E11 -> 3461.6 | R11: =Q11*4 -> 13846.4 | T11: 80 | U11: 60 | V11: =T11*F11/E11 -> 3461.6 | W11: =V11*8 -> 27692.8 | X11: =U11*F11/E11 -> 2596.2 | Y11: =X11*4 -> 10384.8 | AA11: 20 | AB11: 20 | AC11: =AA11*F11/E11 -> 865.4 | AD11: =AC11*8 -> 6923.2 | AE11: =AB11*F11/E11 -> 865.4 | AF11: =AE11*4 -> 3461.6 | AH11: 10 | AI11: 10 | AJ11: =AH11*F11/E11 -> 432.7 | AK11: =AJ11*8 -> 3461.6 | AL11: =AI11*F11/E11 -> 432.7 | AM11: =AL11*4 -> 1730.8
B12: Room Care R5 Conc. | C12: =M12+T12+AA12+AH12 -> 0 | D12: =N12+U12+AB12+AI12 -> 0 | E12: 1 | F12: 14.38 | G12: =C12*F12/E12 -> 0 | H12: =G12*8 -> 0 | I12: =D12*F12/E12 -> 0 | J12: =I12*4 -> 0 | K12: =(O12+V12+AC12+AJ12)-G12 -> 0 | L12: =(Q12+X12+AE12+AL12)-I12 -> 0 | O12: =M12*F12/E12 -> 0 | P12: =O12*8 -> 0 | Q12: =N12*F12/E12 -> 0 | R12: =Q12*4 -> 0 | V12: =T12*F12/E12 -> 0 | W12: =V12*8 -> 0 | X12: =U12*F12/E12 -> 0 | Y12: =X12*4 -> 0 | AC12: =AA12*F12/E12 -> 0 | AD12: =AC12*8 -> 0 | AE12: =AB12*F12/E12 -> 0 | AF12: =AE12*4 -> 0 | AJ12: =AH12*F12/E12 -> 0 | AK12: =AJ12*8 -> 0 | AL12: =AI12*F12/E12 -> 0 | AM12: =AL12*4 -> 0
B13: TASKI Tapi Extract C1b | C13: =M13+T13+AA13+AH13 -> 250 | D13: =N13+U13+AB13+AI13 -> 130 | E13: 1 | F13: 4.87 | G13: =C13*F13/E13 -> 1217.5 | H13: =G13*8 -> 9740 | I13: =D13*F13/E13 -> 633.1 | J13: =I13*4 -> 2532.4 | K13: =(O13+V13+AC13+AJ13)-G13 -> 0 | L13: =(Q13+X13+AE13+AL13)-I13 -> 0 | M13: 200 | N13: 80 | O13: =M13*F13/E13 -> 974 | P13: =O13*8 -> 7792 | Q13: =N13*F13/E13 -> 389.6 | R13: =Q13*4 -> 1558.4 | V13: =T13*F13/E13 -> 0 | W13: =V13*8 -> 0 | X13: =U13*F13/E13 -> 0 | Y13: =X13*4 -> 0 | AA13: 40 | AB13: 40 | AC13: =AA13*F13/E13 -> 194.8 | AD13: =AC13*8 -> 1558.4 | AE13: =AB13*F13/E13 -> 194.8 | AF13: =AE13*4 -> 779.2 | AH13: 10 | AI13: 10 | AJ13: =AH13*F13/E13 -> 48.7 | AK13: =AJ13*8 -> 389.6 | AL13: =AI13*F13/E13 -> 48.7 | AM13: =AL13*4 -> 194.8
B14: TASKI Tapi Spotx 1 | C14: =M14+T14+AA14+AH14 -> 0 | D14: =N14+U14+AB14+AI14 -> 0 | E14: 1 | F14: 404 | G14: =C14*F14/E14 -> 0 | H14: =G14*8 -> 0 | I14: =D14*F14/E14 -> 0 | J14: =I14*4 -> 0 | K14: =(O14+V14+AC14+AJ14)-G14 -> 0 | L14: =(Q14+X14+AE14+AL14)-I14 -> 0 | O14: =M14*F14/E14 -> 0 | P14: =O14*8 -> 0 | Q14: =N14*F14/E14 -> 0 | R14: =Q14*4 -> 0 | V14: =T14*F14/E14 -> 0 | W14: =V14*8 -> 0 | X14: =U14*F14/E14 -> 0 | Y14: =X14*4 -> 0 | AC14: =AA14*F14/E14 -> 0 | AD14: =AC14*8 -> 0 | AE14: =AB14*F14/E14 -> 0 | AF14: =AE14*4 -> 0 | AJ14: =AH14*F14/E14 -> 0 | AK14: =AJ14*8 -> 0 | AL14: =AI14*F14/E14 -> 0 | AM14: =AL14*4 -> 0
B15: TASKI Tapi Spotx2 | C15: =M15+T15+AA15+AH15 -> 0 | D15: =N15+U15+AB15+AI15 -> 0 | E15: 1 | F15: 198 | G15: =C15*F15/E15 -> 0 | H15: =G15*8 -> 0 | I15: =D15*F15/E15 -> 0 | J15: =I15*4 -> 0 | K15: =(O15+V15+AC15+AJ15)-G15 -> 0 | L15: =(Q15+X15+AE15+AL15)-I15 -> 0 | O15: =M15*F15/E15 -> 0 | P15: =O15*8 -> 0 | Q15: =N15*F15/E15 -> 0 | R15: =Q15*4 -> 0 | V15: =T15*F15/E15 -> 0 | W15: =V15*8 -> 0 | X15: =U15*F15/E15 -> 0 | Y15: =X15*4 -> 0 | AC15: =AA15*F15/E15 -> 0 | AD15: =AC15*8 -> 0 | AE15: =AB15*F15/E15 -> 0 | AF15: =AE15*4 -> 0 | AJ15: =AH15*F15/E15 -> 0 | AK15: =AJ15*8 -> 0 | AL15: =AI15*F15/E15 -> 0 | AM15: =AL15*4 -> 0
B16: Soft Care Plus H41 | C16: =M16+T16+AA16+AH16 -> 0 | D16: =N16+U16+AB16+AI16 -> 0 | E16: 1 | F16: 149 | G16: =C16*F16/E16 -> 0 | H16: =G16*8 -> 0 | I16: =D16*F16/E16 -> 0 | J16: =I16*4 -> 0 | K16: =(O16+V16+AC16+AJ16)-G16 -> 0 | L16: =(Q16+X16+AE16+AL16)-I16 -> 0 | O16: =M16*F16/E16 -> 0 | P16: =O16*8 -> 0 | Q16: =N16*F16/E16 -> 0 | R16: =Q16*4 -> 0 | V16: =T16*F16/E16 -> 0 | W16: =V16*8 -> 0 | X16: =U16*F16/E16 -> 0 | Y16: =X16*4 -> 0 | AC16: =AA16*F16/E16 -> 0 | AD16: =AC16*8 -> 0 | AE16: =AB16*F16/E16 -> 0 | AF16: =AE16*4 -> 0 | AJ16: =AH16*F16/E16 -> 0 | AK16: =AJ16*8 -> 0 | AL16: =AI16*F16/E16 -> 0 | AM16: =AL16*4 -> 0
B17: Oxivir Excel | C17: =M17+T17+AA17+AH17 -> 0 | D17: =N17+U17+AB17+AI17 -> 0 | E17: 1 | F17: 15 | G17: =C17*F17/E17 -> 0 | H17: =G17*8 -> 0 | I17: =D17*F17/E17 -> 0 | J17: =I17*4 -> 0 | K17: =(O17+V17+AC17+AJ17)-G17 -> 0 | L17: =(Q17+X17+AE17+AL17)-I17 -> 0 | O17: =M17*F17/E17 -> 0 | P17: =O17*8 -> 0 | Q17: =N17*F17/E17 -> 0 | R17: =Q17*4 -> 0 | V17: =T17*F17/E17 -> 0 | W17: =V17*8 -> 0 | X17: =U17*F17/E17 -> 0 | Y17: =X17*4 -> 0 | AC17: =AA17*F17/E17 -> 0 | AD17: =AC17*8 -> 0 | AE17: =AB17*F17/E17 -> 0 | AF17: =AE17*4 -> 0 | AJ17: =AH17*F17/E17 -> 0 | AK17: =AJ17*8 -> 0 | AL17: =AI17*F17/E17 -> 0 | AM17: =AL17*4 -> 0
B18: Room Care R1 Conc | C18: =M18+T18+AA18+AH18 -> 0 | D18: =N18+U18+AB18+AI18 -> 0 | E18: 1 | F18: 63 | G18: =C18*F18/E18 -> 0 | H18: =G18*8 -> 0 | I18: =D18*F18/E18 -> 0 | J18: =I18*4 -> 0 | K18: =(O18+V18+AC18+AJ18)-G18 -> 0 | L18: =(Q18+X18+AE18+AL18)-I18 -> 0 | O18: =M18*F18/E18 -> 0 | P18: =O18*8 -> 0 | Q18: =N18*F18/E18 -> 0 | R18: =Q18*4 -> 0 | V18: =T18*F18/E18 -> 0 | W18: =V18*8 -> 0 | X18: =U18*F18/E18 -> 0 | Y18: =X18*4 -> 0 | AC18: =AA18*F18/E18 -> 0 | AD18: =AC18*8 -> 0 | AE18: =AB18*F18/E18 -> 0 | AF18: =AE18*4 -> 0 | AJ18: =AH18*F18/E18 -> 0 | AK18: =AJ18*8 -> 0 | AL18: =AI18*F18/E18 -> 0 | AM18: =AL18*4 -> 0
B19: Room Care R4 | C19: =M19+T19+AA19+AH19 -> 105 | D19: =N19+U19+AB19+AI19 -> 60 | E19: 1 | F19: 229 | G19: =C19*F19/E19 -> 24045 | H19: =G19*8 -> 192360 | I19: =D19*F19/E19 -> 13740 | J19: =I19*4 -> 54960 | K19: =(O19+V19+AC19+AJ19)-G19 -> 0 | L19: =(Q19+X19+AE19+AL19)-I19 -> 0 | M19: 60 | N19: 20 | O19: =M19*F19/E19 -> 13740 | P19: =O19*8 -> 109920 | Q19: =N19*F19/E19 -> 4580 | R19: =Q19*4 -> 18320 | T19: 30 | U19: 25 | V19: =T19*F19/E19 -> 6870 | W19: =V19*8 -> 54960 | X19: =U19*F19/E19 -> 5725 | Y19: =X19*4 -> 22900 | AA19: 10 | AB19: 10 | AC19: =AA19*F19/E19 -> 2290 | AD19: =AC19*8 -> 18320 | AE19: =AB19*F19/E19 -> 2290 | AF19: =AE19*4 -> 9160 | AH19: 5 | AI19: 5 | AJ19: =AH19*F19/E19 -> 1145 | AK19: =AJ19*8 -> 9160 | AL19: =AI19*F19/E19 -> 1145 | AM19: =AL19*4 -> 4580
B20: TASKI Jontec Liquid Wax | C20: =M20+T20+AA20+AH20 -> 40 | D20: =N20+U20+AB20+AI20 -> 20 | E20: 1 | F20: 706 | G20: =C20*F20/E20 -> 28240 | H20: =G20*8 -> 225920 | I20: =D20*F20/E20 -> 14120 | J20: =I20*4 -> 56480 | K20: =(O20+V20+AC20+AJ20)-G20 -> 0 | L20: =(Q20+X20+AE20+AL20)-I20 -> 0 | M20: 30 | N20: 10 | O20: =M20*F20/E20 -> 21180 | P20: =O20*8 -> 169440 | Q20: =N20*F20/E20 -> 7060 | R20: =Q20*4 -> 28240 | V20: =T20*F20/E20 -> 0 | W20: =V20*8 -> 0 | X20: =U20*F20/E20 -> 0 | Y20: =X20*4 -> 0 | AA20: 5 | AB20: 5 | AC20: =AA20*F20/E20 -> 3530 | AD20: =AC20*8 -> 28240 | AE20: =AB20*F20/E20 -> 3530 | AF20: =AE20*4 -> 14120 | AH20: 5 | AI20: 5 | AJ20: =AH20*F20/E20 -> 3530 | AK20: =AJ20*8 -> 28240 | AL20: =AI20*F20/E20 -> 3530 | AM20: =AL20*4 -> 14120
B21: Soft Care Elegant | C21: =M21+T21+AA21+AH21 -> 0 | D21: =N21+U21+AB21+AI21 -> 0 | E21: 1 | F21: 149 | G21: =C21*F21/E21 -> 0 | H21: =G21*8 -> 0 | I21: =D21*F21/E21 -> 0 | J21: =I21*4 -> 0 | K21: =(O21+V21+AC21+AJ21)-G21 -> 0 | L21: =(Q21+X21+AE21+AL21)-I21 -> 0 | O21: =M21*F21/E21 -> 0 | P21: =O21*8 -> 0 | Q21: =N21*F21/E21 -> 0 | R21: =Q21*4 -> 0 | V21: =T21*F21/E21 -> 0 | W21: =V21*8 -> 0 | X21: =U21*F21/E21 -> 0 | Y21: =X21*4 -> 0 | AC21: =AA21*F21/E21 -> 0 | AD21: =AC21*8 -> 0 | AE21: =AB21*F21/E21 -> 0 | AF21: =AE21*4 -> 0 | AJ21: =AH21*F21/E21 -> 0 | AK21: =AJ21*8 -> 0 | AL21: =AI21*F21/E21 -> 0 | AM21: =AL21*4 -> 0
B22: TASKI Sprint Flower | C22: =M22+T22+AA22+AH22 -> 850 | D22: =N22+U22+AB22+AI22 -> 410 | E22: 1 | F22: 7.9 | G22: =C22*F22/E22 -> 6715 | H22: =G22*8 -> 53720 | I22: =D22*F22/E22 -> 3239 | J22: =I22*4 -> 12956 | K22: =(O22+V22+AC22+AJ22)-G22 -> 0 | L22: =(Q22+X22+AE22+AL22)-I22 -> 0 | M22: 500 | N22: 100 | O22: =M22*F22/E22 -> 3950 | P22: =O22*8 -> 31600 | Q22: =N22*F22/E22 -> 790 | R22: =Q22*4 -> 3160 | T22: 200 | U22: 160 | V22: =T22*F22/E22 -> 1580 | W22: =V22*8 -> 12640 | X22: =U22*F22/E22 -> 1264 | Y22: =X22*4 -> 5056 | AA22: 100 | AB22: 100 | AC22: =AA22*F22/E22 -> 790 | AD22: =AC22*8 -> 6320 | AE22: =AB22*F22/E22 -> 790 | AF22: =AE22*4 -> 3160 | AH22: 50 | AI22: 50 | AJ22: =AH22*F22/E22 -> 395 | AK22: =AJ22*8 -> 3160 | AL22: =AI22*F22/E22 -> 395 | AM22: =AL22*4 -> 1580
B23: Room Care R5 Conc. | C23: =M23+T23+AA23+AH23 -> 0 | D23: =N23+U23+AB23+AI23 -> 0 | E23: 1 | F23: 14.4 | G23: =C23*F23/E23 -> 0 | H23: =G23*8 -> 0 | I23: =D23*F23/E23 -> 0 | J23: =I23*4 -> 0 | K23: =(O23+V23+AC23+AJ23)-G23 -> 0 | L23: =(Q23+X23+AE23+AL23)-I23 -> 0 | O23: =M23*F23/E23 -> 0 | P23: =O23*8 -> 0 | Q23: =N23*F23/E23 -> 0 | R23: =Q23*4 -> 0 | V23: =T23*F23/E23 -> 0 | W23: =V23*8 -> 0 | X23: =U23*F23/E23 -> 0 | Y23: =X23*4 -> 0 | AC23: =AA23*F23/E23 -> 0 | AD23: =AC23*8 -> 0 | AE23: =AB23*F23/E23 -> 0 | AF23: =AE23*4 -> 0 | AJ23: =AH23*F23/E23 -> 0 | AK23: =AJ23*8 -> 0 | AL23: =AI23*F23/E23 -> 0 | AM23: =AL23*4 -> 0
B24: Domestos Prof Urinal Blocks | C24: =M24+T24+AA24+AH24 -> 0 | D24: =N24+U24+AB24+AI24 -> 0 | E24: 1 | F24: 2375 | G24: =C24*F24/E24 -> 0 | H24: =G24*8 -> 0 | I24: =D24*F24/E24 -> 0 | J24: =I24*4 -> 0 | K24: =(O24+V24+AC24+AJ24)-G24 -> 0 | L24: =(Q24+X24+AE24+AL24)-I24 -> 0 | O24: =M24*F24/E24 -> 0 | P24: =O24*8 -> 0 | Q24: =N24*F24/E24 -> 0 | R24: =Q24*4 -> 0 | V24: =T24*F24/E24 -> 0 | W24: =V24*8 -> 0 | X24: =U24*F24/E24 -> 0 | Y24: =X24*4 -> 0 | AC24: =AA24*F24/E24 -> 0 | AD24: =AC24*8 -> 0 | AE24: =AB24*F24/E24 -> 0 | AF24: =AE24*4 -> 0 | AJ24: =AH24*F24/E24 -> 0 | AK24: =AJ24*8 -> 0 | AL24: =AI24*F24/E24 -> 0 | AM24: =AL24*4 -> 0
B25: Domestos Prof Urinal Blocks | C25: =M25+T25+AA25+AH25 -> 0 | D25: =N25+U25+AB25+AI25 -> 0 | E25: 1 | F25: 2375 | G25: =C25*F25/E25 -> 0 | H25: =G25*8 -> 0 | I25: =D25*F25/E25 -> 0 | J25: =I25*4 -> 0 | K25: =(O25+V25+AC25+AJ25)-G25 -> 0 | L25: =(Q25+X25+AE25+AL25)-I25 -> 0 | O25: =M25*F25/E25 -> 0 | P25: =O25*8 -> 0 | Q25: =N25*F25/E25 -> 0 | R25: =Q25*4 -> 0 | V25: =T25*F25/E25 -> 0 | W25: =V25*8 -> 0 | X25: =U25*F25/E25 -> 0 | Y25: =X25*4 -> 0 | AC25: =AA25*F25/E25 -> 0 | AD25: =AC25*8 -> 0 | AE25: =AB25*F25/E25 -> 0 | AF25: =AE25*4 -> 0 | AJ25: =AH25*F25/E25 -> 0 | AK25: =AJ25*8 -> 0 | AL25: =AI25*F25/E25 -> 0 | AM25: =AL25*4 -> 0
B26: LAPE O.L.T. SHAMPOO & BODY WASH 2X5L | C26: =M26+T26+AA26+AH26 -> 0 | D26: =N26+U26+AB26+AI26 -> 0 | E26: 1 | F26: 1980 | G26: =C26*F26/E26 -> 0 | H26: =G26*8 -> 0 | I26: =D26*F26/E26 -> 0 | J26: =I26*4 -> 0 | K26: =(O26+V26+AC26+AJ26)-G26 -> 0 | L26: =(Q26+X26+AE26+AL26)-I26 -> 0 | O26: =M26*F26/E26 -> 0 | P26: =O26*8 -> 0 | Q26: =N26*F26/E26 -> 0 | R26: =Q26*4 -> 0 | V26: =T26*F26/E26 -> 0 | W26: =V26*8 -> 0 | X26: =U26*F26/E26 -> 0 | Y26: =X26*4 -> 0 | AC26: =AA26*F26/E26 -> 0 | AD26: =AC26*8 -> 0 | AE26: =AB26*F26/E26 -> 0 | AF26: =AE26*4 -> 0 | AJ26: =AH26*F26/E26 -> 0 | AK26: =AJ26*8 -> 0 | AL26: =AI26*F26/E26 -> 0 | AM26: =AL26*4 -> 0
B27: Blue Towels 50*100 | C27: =M27+T27+AA27+AH27 -> 490 | D27: =N27+U27+AB27+AI27 -> 270 | E27: 1 | F27: 16 | G27: =C27*F27/E27 -> 7840 | H27: =G27*8 -> 62720 | I27: =D27*F27/E27 -> 4320 | J27: =I27*4 -> 17280 | K27: =(O27+V27+AC27+AJ27)-G27 -> 0 | L27: =(Q27+X27+AE27+AL27)-I27 -> 0 | M27: 300 | N27: 100 | O27: =M27*F27/E27 -> 4800 | P27: =O27*8 -> 38400 | Q27: =N27*F27/E27 -> 1600 | R27: =Q27*4 -> 6400 | T27: 100 | U27: 80 | V27: =T27*F27/E27 -> 1600 | W27: =V27*8 -> 12800 | X27: =U27*F27/E27 -> 1280 | Y27: =X27*4 -> 5120 | AA27: 60 | AB27: 60 | AC27: =AA27*F27/E27 -> 960 | AD27: =AC27*8 -> 7680 | AE27: =AB27*F27/E27 -> 960 | AF27: =AE27*4 -> 3840 | AH27: 30 | AI27: 30 | AJ27: =AH27*F27/E27 -> 480 | AK27: =AJ27*8 -> 3840 | AL27: =AI27*F27/E27 -> 480 | AM27: =AL27*4 -> 1920
B28: Yellow Towels 30*30 | C28: =M28+T28+AA28+AH28 -> 300 | D28: =N28+U28+AB28+AI28 -> 180 | E28: 1 | F28: 12 | G28: =C28*F28/E28 -> 3600 | H28: =G28*8 -> 28800 | I28: =D28*F28/E28 -> 2160 | J28: =I28*4 -> 8640 | K28: =(O28+V28+AC28+AJ28)-G28 -> 0 | L28: =(Q28+X28+AE28+AL28)-I28 -> 0 | M28: 150 | N28: 50 | O28: =M28*F28/E28 -> 1800 | P28: =O28*8 -> 14400 | Q28: =N28*F28/E28 -> 600 | R28: =Q28*4 -> 2400 | T28: 100 | U28: 80 | V28: =T28*F28/E28 -> 1200 | W28: =V28*8 -> 9600 | X28: =U28*F28/E28 -> 960 | Y28: =X28*4 -> 3840 | AA28: 30 | AB28: 30 | AC28: =AA28*F28/E28 -> 360 | AD28: =AC28*8 -> 2880 | AE28: =AB28*F28/E28 -> 360 | AF28: =AE28*4 -> 1440 | AH28: 20 | AI28: 20 | AJ28: =AH28*F28/E28 -> 240 | AK28: =AJ28*8 -> 1920 | AL28: =AI28*F28/E28 -> 240 | AM28: =AL28*4 -> 960
B29: White Towels 30*30 | C29: =M29+T29+AA29+AH29 -> 300 | D29: =N29+U29+AB29+AI29 -> 180 | E29: 1 | F29: 14 | G29: =C29*F29/E29 -> 4200 | H29: =G29*8 -> 33600 | I29: =D29*F29/E29 -> 2520 | J29: =I29*4 -> 10080 | K29: =(O29+V29+AC29+AJ29)-G29 -> 0 | L29: =(Q29+X29+AE29+AL29)-I29 -> 0 | M29: 150 | N29: 50 | O29: =M29*F29/E29 -> 2100 | P29: =O29*8 -> 16800 | Q29: =N29*F29/E29 -> 700 | R29: =Q29*4 -> 2800 | T29: 100 | U29: 80 | V29: =T29*F29/E29 -> 1400 | W29: =V29*8 -> 11200 | X29: =U29*F29/E29 -> 1120 | Y29: =X29*4 -> 4480 | AA29: 30 | AB29: 30 | AC29: =AA29*F29/E29 -> 420 | AD29: =AC29*8 -> 3360 | AE29: =AB29*F29/E29 -> 420 | AF29: =AE29*4 -> 1680 | AH29: 20 | AI29: 20 | AJ29: =AH29*F29/E29 -> 280 | AK29: =AJ29*8 -> 2240 | AL29: =AI29*F29/E29 -> 280 | AM29: =AL29*4 -> 1120
B30: Microfiber red color | C30: =M30+T30+AA30+AH30 -> 300 | D30: =N30+U30+AB30+AI30 -> 180 | E30: 1 | F30: 30 | G30: =C30*F30/E30 -> 9000 | H30: =G30*8 -> 72000 | I30: =D30*F30/E30 -> 5400 | J30: =I30*4 -> 21600 | K30: =(O30+V30+AC30+AJ30)-G30 -> 0 | L30: =(Q30+X30+AE30+AL30)-I30 -> 0 | M30: 150 | N30: 50 | O30: =M30*F30/E30 -> 4500 | P30: =O30*8 -> 36000 | Q30: =N30*F30/E30 -> 1500 | R30: =Q30*4 -> 6000 | T30: 100 | U30: 80 | V30: =T30*F30/E30 -> 3000 | W30: =V30*8 -> 24000 | X30: =U30*F30/E30 -> 2400 | Y30: =X30*4 -> 9600 | AA30: 30 | AB30: 30 | AC30: =AA30*F30/E30 -> 900 | AD30: =AC30*8 -> 7200 | AE30: =AB30*F30/E30 -> 900 | AF30: =AE30*4 -> 3600 | AH30: 20 | AI30: 20 | AJ30: =AH30*F30/E30 -> 600 | AK30: =AJ30*8 -> 4800 | AL30: =AI30*F30/E30 -> 600 | AM30: =AL30*4 -> 2400
B31: Microfiber blue color | C31: =M31+T31+AA31+AH31 -> 300 | D31: =N31+U31+AB31+AI31 -> 180 | E31: 1 | F31: 30 | G31: =C31*F31/E31 -> 9000 | H31: =G31*8 -> 72000 | I31: =D31*F31/E31 -> 5400 | J31: =I31*4 -> 21600 | K31: =(O31+V31+AC31+AJ31)-G31 -> 0 | L31: =(Q31+X31+AE31+AL31)-I31 -> 0 | M31: 150 | N31: 50 | O31: =M31*F31/E31 -> 4500 | P31: =O31*8 -> 36000 | Q31: =N31*F31/E31 -> 1500 | R31: =Q31*4 -> 6000 | T31: 100 | U31: 80 | V31: =T31*F31/E31 -> 3000 | W31: =V31*8 -> 24000 | X31: =U31*F31/E31 -> 2400 | Y31: =X31*4 -> 9600 | AA31: 30 | AB31: 30 | AC31: =AA31*F31/E31 -> 900 | AD31: =AC31*8 -> 7200 | AE31: =AB31*F31/E31 -> 900 | AF31: =AE31*4 -> 3600 | AH31: 20 | AI31: 20 | AJ31: =AH31*F31/E31 -> 600 | AK31: =AJ31*8 -> 4800 | AL31: =AI31*F31/E31 -> 600 | AM31: =AL31*4 -> 2400
B32: Microfiber green color | C32: =M32+T32+AA32+AH32 -> 300 | D32: =N32+U32+AB32+AI32 -> 180 | E32: 1 | F32: 30 | G32: =C32*F32/E32 -> 9000 | H32: =G32*8 -> 72000 | I32: =D32*F32/E32 -> 5400 | J32: =I32*4 -> 21600 | K32: =(O32+V32+AC32+AJ32)-G32 -> 0 | L32: =(Q32+X32+AE32+AL32)-I32 -> 0 | M32: 150 | N32: 50 | O32: =M32*F32/E32 -> 4500 | P32: =O32*8 -> 36000 | Q32: =N32*F32/E32 -> 1500 | R32: =Q32*4 -> 6000 | T32: 100 | U32: 80 | V32: =T32*F32/E32 -> 3000 | W32: =V32*8 -> 24000 | X32: =U32*F32/E32 -> 2400 | Y32: =X32*4 -> 9600 | AA32: 30 | AB32: 30 | AC32: =AA32*F32/E32 -> 900 | AD32: =AC32*8 -> 7200 | AE32: =AB32*F32/E32 -> 900 | AF32: =AE32*4 -> 3600 | AH32: 20 | AI32: 20 | AJ32: =AH32*F32/E32 -> 600 | AK32: =AJ32*8 -> 4800 | AL32: =AI32*F32/E32 -> 600 | AM32: =AL32*4 -> 2400
B33: Hard Sponges | C33: =M33+T33+AA33+AH33 -> 350 | D33: =N33+U33+AB33+AI33 -> 180 | E33: 1 | F33: 9 | G33: =C33*F33/E33 -> 3150 | H33: =G33*8 -> 25200 | I33: =D33*F33/E33 -> 1620 | J33: =I33*4 -> 6480 | K33: =(O33+V33+AC33+AJ33)-G33 -> 0 | L33: =(Q33+X33+AE33+AL33)-I33 -> 0 | M33: 200 | N33: 50 | O33: =M33*F33/E33 -> 1800 | P33: =O33*8 -> 14400 | Q33: =N33*F33/E33 -> 450 | R33: =Q33*4 -> 1800 | T33: 100 | U33: 80 | V33: =T33*F33/E33 -> 900 | W33: =V33*8 -> 7200 | X33: =U33*F33/E33 -> 720 | Y33: =X33*4 -> 2880 | AA33: 30 | AB33: 30 | AC33: =AA33*F33/E33 -> 270 | AD33: =AC33*8 -> 2160 | AE33: =AB33*F33/E33 -> 270 | AF33: =AE33*4 -> 1080 | AH33: 20 | AI33: 20 | AJ33: =AH33*F33/E33 -> 180 | AK33: =AJ33*8 -> 1440 | AL33: =AI33*F33/E33 -> 180 | AM33: =AL33*4 -> 720
B34: Soft Sponges | C34: =M34+T34+AA34+AH34 -> 350 | D34: =N34+U34+AB34+AI34 -> 180 | E34: 1 | F34: 8 | G34: =C34*F34/E34 -> 2800 | H34: =G34*8 -> 22400 | I34: =D34*F34/E34 -> 1440 | J34: =I34*4 -> 5760 | K34: =(O34+V34+AC34+AJ34)-G34 -> 0 | L34: =(Q34+X34+AE34+AL34)-I34 -> 0 | M34: 200 | N34: 50 | O34: =M34*F34/E34 -> 1600 | P34: =O34*8 -> 12800 | Q34: =N34*F34/E34 -> 400 | R34: =Q34*4 -> 1600 | T34: 100 | U34: 80 | V34: =T34*F34/E34 -> 800 | W34: =V34*8 -> 6400 | X34: =U34*F34/E34 -> 640 | Y34: =X34*4 -> 2560 | AA34: 30 | AB34: 30 | AC34: =AA34*F34/E34 -> 240 | AD34: =AC34*8 -> 1920 | AE34: =AB34*F34/E34 -> 240 | AF34: =AE34*4 -> 960 | AH34: 20 | AI34: 20 | AJ34: =AH34*F34/E34 -> 160 | AK34: =AJ34*8 -> 1280 | AL34: =AI34*F34/E34 -> 160 | AM34: =AL34*4 -> 640
B35: Aluminum mesh | C35: =M35+T35+AA35+AH35 -> 160 | D35: =N35+U35+AB35+AI35 -> 60 | E35: 1 | F35: 150 | G35: =C35*F35/E35 -> 24000 | H35: =G35*8 -> 192000 | I35: =D35*F35/E35 -> 9000 | J35: =I35*4 -> 36000 | K35: =(O35+V35+AC35+AJ35)-G35 -> 0 | L35: =(Q35+X35+AE35+AL35)-I35 -> 0 | M35: 100 | N35: 15 | O35: =M35*F35/E35 -> 15000 | P35: =O35*8 -> 120000 | Q35: =N35*F35/E35 -> 2250 | R35: =Q35*4 -> 9000 | T35: 50 | U35: 35 | V35: =T35*F35/E35 -> 7500 | W35: =V35*8 -> 60000 | X35: =U35*F35/E35 -> 5250 | Y35: =X35*4 -> 21000 | AA35: 5 | AB35: 5 | AC35: =AA35*F35/E35 -> 750 | AD35: =AC35*8 -> 6000 | AE35: =AB35*F35/E35 -> 750 | AF35: =AE35*4 -> 3000 | AH35: 5 | AI35: 5 | AJ35: =AH35*F35/E35 -> 750 | AK35: =AJ35*8 -> 6000 | AL35: =AI35*F35/E35 -> 750 | AM35: =AL35*4 -> 3000
B36: Garbage Bags 120 L | C36: =M36+T36+AA36+AH36 -> 10520 | D36: =N36+U36+AB36+AI36 -> 2020 | E36: 1 | F36: 37 | G36: =C36*F36/E36 -> 389240 | H36: =G36*8 -> 3113920 | I36: =D36*F36/E36 -> 74740 | J36: =I36*4 -> 298960 | K36: =(O36+V36+AC36+AJ36)-G36 -> 0 | L36: =(Q36+X36+AE36+AL36)-I36 -> 0 | M36: 8000 | N36: 1000 | O36: =M36*F36/E36 -> 296000 | P36: =O36*8 -> 2368000 | Q36: =N36*F36/E36 -> 37000 | R36: =Q36*4 -> 148000 | T36: 2500 | U36: 1000 | V36: =T36*F36/E36 -> 92500 | W36: =V36*8 -> 740000 | X36: =U36*F36/E36 -> 37000 | Y36: =X36*4 -> 148000 | AA36: 10 | AB36: 10 | AC36: =AA36*F36/E36 -> 370 | AD36: =AC36*8 -> 2960 | AE36: =AB36*F36/E36 -> 370 | AF36: =AE36*4 -> 1480 | AH36: 10 | AI36: 10 | AJ36: =AH36*F36/E36 -> 370 | AK36: =AJ36*8 -> 2960 | AL36: =AI36*F36/E36 -> 370 | AM36: =AL36*4 -> 1480
B37: Garbage Bags 60 L | C37: =M37+T37+AA37+AH37 -> 3520 | D37: =N37+U37+AB37+AI37 -> 1320 | E37: 1 | F37: 37 | G37: =C37*F37/E37 -> 130240 | H37: =G37*8 -> 1041920 | I37: =D37*F37/E37 -> 48840 | J37: =I37*4 -> 195360 | K37: =(O37+V37+AC37+AJ37)-G37 -> 0 | L37: =(Q37+X37+AE37+AL37)-I37 -> 0 | M37: 3000 | N37: 1000 | O37: =M37*F37/E37 -> 111000 | P37: =O37*8 -> 888000 | Q37: =N37*F37/E37 -> 37000 | R37: =Q37*4 -> 148000 | T37: 500 | U37: 300 | V37: =T37*F37/E37 -> 18500 | W37: =V37*8 -> 148000 | X37: =U37*F37/E37 -> 11100 | Y37: =X37*4 -> 44400 | AA37: 10 | AB37: 10 | AC37: =AA37*F37/E37 -> 370 | AD37: =AC37*8 -> 2960 | AE37: =AB37*F37/E37 -> 370 | AF37: =AE37*4 -> 1480 | AH37: 10 | AI37: 10 | AJ37: =AH37*F37/E37 -> 370 | AK37: =AJ37*8 -> 2960 | AL37: =AI37*F37/E37 -> 370 | AM37: =AL37*4 -> 1480
B38: Garbage Bags 20 L | C38: =M38+T38+AA38+AH38 -> 3020 | D38: =N38+U38+AB38+AI38 -> 1020 | E38: 1 | F38: 37 | G38: =C38*F38/E38 -> 111740 | H38: =G38*8 -> 893920 | I38: =D38*F38/E38 -> 37740 | J38: =I38*4 -> 150960 | K38: =(O38+V38+AC38+AJ38)-G38 -> 0 | L38: =(Q38+X38+AE38+AL38)-I38 -> 0 | M38: 3000 | N38: 1000 | O38: =M38*F38/E38 -> 111000 | P38: =O38*8 -> 888000 | Q38: =N38*F38/E38 -> 37000 | R38: =Q38*4 -> 148000 | V38: =T38*F38/E38 -> 0 | W38: =V38*8 -> 0 | X38: =U38*F38/E38 -> 0 | Y38: =X38*4 -> 0 | AA38: 10 | AB38: 10 | AC38: =AA38*F38/E38 -> 370 | AD38: =AC38*8 -> 2960 | AE38: =AB38*F38/E38 -> 370 | AF38: =AE38*4 -> 1480 | AH38: 10 | AI38: 10 | AJ38: =AH38*F38/E38 -> 370 | AK38: =AJ38*8 -> 2960 | AL38: =AI38*F38/E38 -> 370 | AM38: =AL38*4 -> 1480
G39: =SUM(G6:G38) -> 816339.39 | H39: =G39*8 -> 6530715.1 | I39: =SUM(I6:I38) -> 257168.09 | J39: =I39*4 -> 1028672.4 | K39: =(O39+V39+AC39+AJ39)-G39 -> 0 | L39: =(Q39+X39+AE39+AL39)-I39 -> 0 | O39: =SUM(O6:O38) -> 636855.05 | P39: =O39*8 -> 5094840.4 | Q39: =SUM(Q6:Q38) -> 149388.26 | R39: =Q39*4 -> 597553.04 | V39: =SUM(V6:V38) -> 149471.95 | W39: =V39*8 -> 1195775.6 | X39: =SUM(X6:X38) -> 77767.445 | Y39: =X39*4 -> 311069.78 | AC39: =SUM(AC6:AC38) -> 17838.08 | AD39: =AC39*8 -> 142704.64 | AE39: =SUM(AE6:AE38) -> 17838.08 | AF39: =AE39*4 -> 71352.32 | AJ39: =SUM(AJ6:AJ38) -> 12174.305 | AK39: =AJ39*8 -> 97394.44 | AL39: =SUM(AL6:AL38) -> 12174.305 | AM39: =AL39*4 -> 48697.22

Sheet AUC Total Transportation
B2: Transportation & Vehicles
M3: INNER CAMPUS Budget | T3: OUTER CAMPUS Budget | AA3: NEW CAIRO OFF CAMPUS HOUSING Budget | AH3: Maadi Buildings Budget
B4: HK Budget | C4: High | D4: Low | E4: Deprecation / Moth | F4: Price | G4: High Season | I4: Low Season | M4: High | N4: Low | O4: High Season | Q4: Low Season | T4: High | U4: Low | V4: High Season | X4: Low Season | AA4: High | AB4: Low | AC4: High Season | AE4: Low Season | AH4: High | AI4: Low | AJ4: High Season | AL4: Low Season
C5: QTY. | D5: QTY. | G5: Monthly | H5: Annually "8"Months | I5: Monthly | J5: Annually "4"Months | M5: QTY. | N5: QTY. | O5: Monthly | P5: Annually "8"Months | Q5: Monthly | R5: Annually "4"Months | T5: QTY. | U5: QTY. | V5: Monthly | W5: Annually "8"Months | X5: Monthly | Y5: Annually "4"Months | AA5: QTY. | AB5: QTY. | AC5: Monthly | AD5: Annually "8"Months | AE5: Monthly | AF5: Annually "4"Months | AH5: QTY. | AI5: QTY. | AJ5: Monthly | AK5: Annually "8"Months | AL5: Monthly | AM5: Annually "4"Months
B6: Bus | C6: =M6+T6+AA6+AH6 -> 10 | D6: =N6+U6+AB6+AI6 -> 5 | E6: 1 | F6: 36000 | G6: =C6*F6/E6 -> 360000 | H6: =G6*8 -> 2880000 | I6: =D6*F6/E6 -> 180000 | J6: =I6*4 -> 720000 | K6: =(O6+V6+AC6+AJ6)-G6 -> 0 | L6: =(Q6+X6+AE6+AL6)-I6 -> 0 | M6: 8 | N6: 3 | O6: =M6*F6/E6 -> 288000 | P6: =O6*8 -> 2304000 | Q6: =N6*F6/E6 -> 108000 | R6: =Q6*4 -> 432000 | T6: 2 | U6: 2 | V6: =T6*F6/E6 -> 72000 | W6: =V6*8 -> 576000 | X6: =U6*F6/E6 -> 72000 | Y6: =X6*4 -> 288000 | AC6: =AA6*F6/E6 -> 0 | AD6: =AC6*8 -> 0 | AE6: =AB6*F6/E6 -> 0 | AF6: =AE6*4 -> 0 | AJ6: =AH6*F6/E6 -> 0 | AK6: =AJ6*8 -> 0 | AL6: =AI6*F6/E6 -> 0 | AM6: =AL6*4 -> 0
B7: Microbus | C7: =M7+T7+AA7+AH7 -> 0 | D7: =N7+U7+AB7+AI7 -> 0 | E7: 1 | F7: 21000 | G7: =C7*F7/E7 -> 0 | H7: =G7*8 -> 0 | I7: =D7*F7/E7 -> 0 | J7: =I7*4 -> 0 | K7: =(O7+V7+AC7+AJ7)-G7 -> 0 | L7: =(Q7+X7+AE7+AL7)-I7 -> 0 | O7: =M7*F7/E7 -> 0 | P7: =O7*8 -> 0 | Q7: =N7*F7/E7 -> 0 | R7: =Q7*4 -> 0 | V7: =T7*F7/E7 -> 0 | W7: =V7*8 -> 0 | X7: =U7*F7/E7 -> 0 | Y7: =X7*4 -> 0 | AC7: =AA7*F7/E7 -> 0 | AD7: =AC7*8 -> 0 | AE7: =AB7*F7/E7 -> 0 | AF7: =AE7*4 -> 0 | AJ7: =AH7*F7/E7 -> 0 | AK7: =AJ7*8 -> 0 | AL7: =AI7*F7/E7 -> 0 | AM7: =AL7*4 -> 0
B8: Sidan Car | C8: =M8+T8+AA8+AH8 -> 1 | D8: =N8+U8+AB8+AI8 -> 1 | E8: 1 | F8: 13000 | G8: =C8*F8/E8 -> 13000 | H8: =G8*8 -> 104000 | I8: =D8*F8/E8 -> 13000 | J8: =I8*4 -> 52000 | K8: =(O8+V8+AC8+AJ8)-G8 -> 0 | L8: =(Q8+X8+AE8+AL8)-I8 -> 0 | M8: 0.75 | N8: 0.75 | O8: =M8*F8/E8 -> 9750 | P8: =O8*8 -> 78000 | Q8: =N8*F8/E8 -> 9750 | R8: =Q8*4 -> 39000 | T8: 0.25 | U8: 0.25 | V8: =T8*F8/E8 -> 3250 | W8: =V8*8 -> 26000 | X8: =U8*F8/E8 -> 3250 | Y8: =X8*4 -> 13000 | AC8: =AA8*F8/E8 -> 0 | AD8: =AC8*8 -> 0 | AE8: =AB8*F8/E8 -> 0 | AF8: =AE8*4 -> 0 | AJ8: =AH8*F8/E8 -> 0 | AK8: =AJ8*8 -> 0 | AL8: =AI8*F8/E8 -> 0 | AM8: =AL8*4 -> 0
B9: Minivan | C9: =M9+T9+AA9+AH9 -> 5 | D9: =N9+U9+AB9+AI9 -> 5 | E9: 1 | F9: 18000 | G9: =C9*F9/E9 -> 90000 | H9: =G9*8 -> 720000 | I9: =D9*F9/E9 -> 90000 | J9: =I9*4 -> 360000 | K9: =(O9+V9+AC9+AJ9)-G9 -> 0 | L9: =(Q9+X9+AE9+AL9)-I9 -> 0 | M9: 3 | N9: 3 | O9: =M9*F9/E9 -> 54000 | P9: =O9*8 -> 432000 | Q9: =N9*F9/E9 -> 54000 | R9: =Q9*4 -> 216000 | T9: 2 | U9: 2 | V9: =T9*F9/E9 -> 36000 | W9: =V9*8 -> 288000 | X9: =U9*F9/E9 -> 36000 | Y9: =X9*4 -> 144000 | AC9: =AA9*F9/E9 -> 0 | AD9: =AC9*8 -> 0 | AE9: =AB9*F9/E9 -> 0 | AF9: =AE9*4 -> 0 | AJ9: =AH9*F9/E9 -> 0 | AK9: =AJ9*8 -> 0 | AL9: =AI9*F9/E9 -> 0 | AM9: =AL9*4 -> 0
B10: Pick up Car | C10: =M10+T10+AA10+AH10 -> 5 | D10: =N10+U10+AB10+AI10 -> 4 | E10: 1 | F10: 20000 | G10: =C10*F10/E10 -> 100000 | H10: =G10*8 -> 800000 | I10: =D10*F10/E10 -> 80000 | J10: =I10*4 -> 320000 | K10: =(O10+V10+AC10+AJ10)-G10 -> 0 | L10: =(Q10+X10+AE10+AL10)-I10 -> 0 | M10: 3 | N10: 2 | O10: =M10*F10/E10 -> 60000 | P10: =O10*8 -> 480000 | Q10: =N10*F10/E10 -> 40000 | R10: =Q10*4 -> 160000 | T10: 2 | U10: 2 | V10: =T10*F10/E10 -> 40000 | W10: =V10*8 -> 320000 | X10: =U10*F10/E10 -> 40000 | Y10: =X10*4 -> 160000 | AC10: =AA10*F10/E10 -> 0 | AD10: =AC10*8 -> 0 | AE10: =AB10*F10/E10 -> 0 | AF10: =AE10*4 -> 0 | AJ10: =AH10*F10/E10 -> 0 | AK10: =AJ10*8 -> 0 | AL10: =AI10*F10/E10 -> 0 | AM10: =AL10*4 -> 0
B11: Fule | C11: =M11+T11+AA11+AH11 -> 1 | D11: =N11+U11+AB11+AI11 -> 1 | E11: 1 | F11: 12000 | G11: =C11*F11/E11 -> 12000 | H11: =G11*8 -> 96000 | I11: =D11*F11/E11 -> 12000 | J11: =I11*4 -> 48000 | K11: =(O11+V11+AC11+AJ11)-G11 -> 0 | L11: =(Q11+X11+AE11+AL11)-I11 -> 0 | M11: 0.75 | N11: 0.5 | O11: =M11*F11/E11 -> 9000 | P11: =O11*8 -> 72000 | Q11: =N11*F11/E11 -> 6000 | R11: =Q11*4 -> 24000 | T11: 0.25 | U11: 0.5 | V11: =T11*F11/E11 -> 3000 | W11: =V11*8 -> 24000 | X11: =U11*F11/E11 -> 6000 | Y11: =X11*4 -> 24000 | AC11: =AA11*F11/E11 -> 0 | AD11: =AC11*8 -> 0 | AE11: =AB11*F11/E11 -> 0 | AF11: =AE11*4 -> 0 | AJ11: =AH11*F11/E11 -> 0 | AK11: =AJ11*8 -> 0 | AL11: =AI11*F11/E11 -> 0 | AM11: =AL11*4 -> 0
G12: =SUM(G6:G11) -> 575000 | H12: =G12*8 -> 4600000 | I12: =SUM(I6:I11) -> 375000 | J12: =I12*4 -> 1500000 | K12: =(O12+V12+AC12+AJ12)-G12 -> 0 | L12: =(Q12+X12+AE12+AL12)-I12 -> 0 | O12: =SUM(O6:O11) -> 420750 | P12: =O12*8 -> 3366000 | Q12: =SUM(Q6:Q11) -> 217750 | R12: =Q12*4 -> 871000 | V12: =SUM(V6:V11) -> 154250 | W12: =V12*8 -> 1234000 | X12: =SUM(X6:X11) -> 157250 | Y12: =X12*4 -> 629000 | AC12: =SUM(AC6:AC11) -> 0 | AD12: =AC12*8 -> 0 | AE12: =SUM(AE6:AE11) -> 0 | AF12: =AE12*4 -> 0 | AJ12: =SUM(AJ6:AJ11) -> 0 | AK12: =AJ12*8 -> 0 | AL12: =SUM(AL6:AL11) -> 0 | AM12: =AL12*4 -> 0

Sheet AUC Total IT & Communication
B2: IT and Communications
M3: INNER CAMPUS Budget | T3: OUTER CAMPUS Budget | AA3: NEW CAIRO OFF CAMPUS HOUSING Budget | AH3: Maadi Buildings Budget
B4: HK Budget | C4: High | D4: Low | E4: Deprecation / Moth | F4: Price | G4: High Season | I4: Low Season | M4: High | N4: Low | O4: High Season | Q4: Low Season | T4: High | U4: Low | V4: High Season | X4: Low Season | AA4: High | AB4: Low | AC4: High Season | AE4: Low Season | AH4: High | AI4: Low | AJ4: High Season | AL4: Low Season
C5: QTY. | D5: QTY. | G5: Monthly | H5: Annually "8"Months | I5: Monthly | J5: Annually "4"Months | M5: QTY. | N5: QTY. | O5: Monthly | P5: Annually "8"Months | Q5: Monthly | R5: Annually "4"Months | T5: QTY. | U5: QTY. | V5: Monthly | W5: Annually "8"Months | X5: Monthly | Y5: Annually "4"Months | AA5: QTY. | AB5: QTY. | AC5: Monthly | AD5: Annually "8"Months | AE5: Monthly | AF5: Annually "4"Months | AH5: QTY. | AI5: QTY. | AJ5: Monthly | AK5: Annually "8"Months | AL5: Monthly | AM5: Annually "4"Months
B6: Laptop | C6: =M6+T6+AA6+AH6 -> 10 | D6: =N6+U6+AB6+AI6 -> 10 | E6: 36 | G6: =C6*F6/E6 -> 0 | H6: =G6*8 -> 0 | I6: =D6*F6/E6 -> 0 | J6: =I6*4 -> 0 | K6: =(O6+V6+AC6+AJ6)-G6 -> 0 | L6: =(Q6+X6+AE6+AL6)-I6 -> 0 | M6: ='AUC Total Manning'!F5+'AUC Total Manning'!F6+'AUC Total Manning'!F14+'AUC Total Manning'!F15+'AUC Total Manning'!F17 -> 6.5 | N6: ='AUC Total Manning'!G5+'AUC Total Manning'!G6+'AUC Total Manning'!G14+'AUC Total Manning'!G15+'AUC Total Manning'!G17 -> 6.5 | O6: =M6*F6/E6 -> 0 | P6: =O6*8 -> 0 | Q6: =N6*F6/E6 -> 0 | R6: =Q6*4 -> 0 | T6: ='AUC Total Manning'!I5+'AUC Total Manning'!I6+'AUC Total Manning'!I14+'AUC Total Manning'!I17 -> 3.5 | U6: ='AUC Total Manning'!J5+'AUC Total Manning'!J6+'AUC Total Manning'!J14+'AUC Total Manning'!J17 -> 3.5 | V6: =T6*F6/E6 -> 0 | W6: =V6*8 -> 0 | X6: =U6*F6/E6 -> 0 | Y6: =X6*4 -> 0 | AC6: =AA6*F6/E6 -> 0 | AD6: =AC6*8 -> 0 | AE6: =AB6*F6/E6 -> 0 | AF6: =AE6*4 -> 0 | AJ6: =AH6*F6/E6 -> 0 | AK6: =AJ6*8 -> 0 | AL6: =AI6*F6/E6 -> 0 | AM6: =AL6*4 -> 0
B7: Mobile Phone | C7: =M7+T7+AA7+AH7 -> 10 | D7: =N7+U7+AB7+AI7 -> 10 | E7: 24 | G7: =C7*F7/E7 -> 0 | H7: =G7*8 -> 0 | I7: =D7*F7/E7 -> 0 | J7: =I7*4 -> 0 | K7: =(O7+V7+AC7+AJ7)-G7 -> 0 | L7: =(Q7+X7+AE7+AL7)-I7 -> 0 | M7: =M6 -> 6.5 | N7: =N6 -> 6.5 | O7: =M7*F7/E7 -> 0 | P7: =O7*8 -> 0 | Q7: =N7*F7/E7 -> 0 | R7: =Q7*4 -> 0 | T7: =T6 -> 3.5 | U7: =U6 -> 3.5 | V7: =T7*F7/E7 -> 0 | W7: =V7*8 -> 0 | X7: =U7*F7/E7 -> 0 | Y7: =X7*4 -> 0 | AC7: =AA7*F7/E7 -> 0 | AD7: =AC7*8 -> 0 | AE7: =AB7*F7/E7 -> 0 | AF7: =AE7*4 -> 0 | AJ7: =AH7*F7/E7 -> 0 | AK7: =AJ7*8 -> 0 | AL7: =AI7*F7/E7 -> 0 | AM7: =AL7*4 -> 0
B8: Printers | C8: =M8+T8+AA8+AH8 -> 3 | D8: =N8+U8+AB8+AI8 -> 3 | E8: 36 | G8: =C8*F8/E8 -> 0 | H8: =G8*8 -> 0 | I8: =D8*F8/E8 -> 0 | J8: =I8*4 -> 0 | K8: =(O8+V8+AC8+AJ8)-G8 -> 0 | L8: =(Q8+X8+AE8+AL8)-I8 -> 0 | M8: 2 | N8: 2 | O8: =M8*F8/E8 -> 0 | P8: =O8*8 -> 0 | Q8: =N8*F8/E8 -> 0 | R8: =Q8*4 -> 0 | T8: 1 | U8: 1 | V8: =T8*F8/E8 -> 0 | W8: =V8*8 -> 0 | X8: =U8*F8/E8 -> 0 | Y8: =X8*4 -> 0 | AC8: =AA8*F8/E8 -> 0 | AD8: =AC8*8 -> 0 | AE8: =AB8*F8/E8 -> 0 | AF8: =AE8*4 -> 0 | AJ8: =AH8*F8/E8 -> 0 | AK8: =AJ8*8 -> 0 | AL8: =AI8*F8/E8 -> 0 | AM8: =AL8*4 -> 0
B9: SIM Cards Calls | C9: =M9+T9+AA9+AH9 -> 35.75 | D9: =N9+U9+AB9+AI9 -> 30.75 | E9: 1 | G9: =C9*F9/E9 -> 0 | H9: =G9*8 -> 0 | I9: =D9*F9/E9 -> 0 | J9: =I9*4 -> 0 | K9: =(O9+V9+AC9+AJ9)-G9 -> 0 | L9: =(Q9+X9+AE9+AL9)-I9 -> 0 | M9: ='AUC Total Manning'!F5+'AUC Total Manning'!F6+'AUC Total Manning'!F7+'AUC Total Manning'!F10+'AUC Total Manning'!F12+'AUC Total Manning'!F14+'AUC Total Manning'!F15+'AUC Total Manning'!F16+'AUC Total Manning'!F17+'AUC Total Manning'!F18 -> 18.25 | N9: ='AUC Total Manning'!G5+'AUC Total Manning'!G6+'AUC Total Manning'!G7+'AUC Total Manning'!G10+'AUC Total Manning'!G12+'AUC Total Manning'!G14+'AUC Total Manning'!G15+'AUC Total Manning'!G16+'AUC Total Manning'!G17+'AUC Total Manning'!G18 -> 17.25 | O9: =M9*F9/E9 -> 0 | P9: =O9*8 -> 0 | Q9: =N9*F9/E9 -> 0 | R9: =Q9*4 -> 0 | T9: ='AUC Total Manning'!I5+'AUC Total Manning'!I6+'AUC Total Manning'!I7+'AUC Total Manning'!I8+'AUC Total Manning'!I10+'AUC Total Manning'!I11+'AUC Total Manning'!I14+'AUC Total Manning'!I15+'AUC Total Manning'!I16+'AUC Total Manning'!I18 -> 17.5 | U9: ='AUC Total Manning'!J5+'AUC Total Manning'!J6+'AUC Total Manning'!J7+'AUC Total Manning'!J8+'AUC Total Manning'!J10+'AUC Total Manning'!J11+'AUC Total Manning'!J14+'AUC Total Manning'!J15+'AUC Total Manning'!J16+'AUC Total Manning'!J18 -> 13.5 | V9: =T9*F9/E9 -> 0 | W9: =V9*8 -> 0 | X9: =U9*F9/E9 -> 0 | Y9: =X9*4 -> 0 | AC9: =AA9*F9/E9 -> 0 | AD9: =AC9*8 -> 0 | AE9: =AB9*F9/E9 -> 0 | AF9: =AE9*4 -> 0 | AJ9: =AH9*F9/E9 -> 0 | AK9: =AJ9*8 -> 0 | AL9: =AI9*F9/E9 -> 0 | AM9: =AL9*4 -> 0
B10: SIM Cards Data | C10: =M10+T10+AA10+AH10 -> 10 | D10: =N10+U10+AB10+AI10 -> 10 | E10: 1 | G10: =C10*F10/E10 -> 0 | H10: =G10*8 -> 0 | I10: =D10*F10/E10 -> 0 | J10: =I10*4 -> 0 | K10: =(O10+V10+AC10+AJ10)-G10 -> 0 | L10: =(Q10+X10+AE10+AL10)-I10 -> 0 | M10: =M6 -> 6.5 | N10: =N6 -> 6.5 | O10: =M10*F10/E10 -> 0 | P10: =O10*8 -> 0 | Q10: =N10*F10/E10 -> 0 | R10: =Q10*4 -> 0 | T10: =T6 -> 3.5 | U10: =U6 -> 3.5 | V10: =T10*F10/E10 -> 0 | W10: =V10*8 -> 0 | X10: =U10*F10/E10 -> 0 | Y10: =X10*4 -> 0 | AC10: =AA10*F10/E10 -> 0 | AD10: =AC10*8 -> 0 | AE10: =AB10*F10/E10 -> 0 | AF10: =AE10*4 -> 0 | AJ10: =AH10*F10/E10 -> 0 | AK10: =AJ10*8 -> 0 | AL10: =AI10*F10/E10 -> 0 | AM10: =AL10*4 -> 0
B11: MIFI | C11: =M11+T11+AA11+AH11 -> 10 | D11: =N11+U11+AB11+AI11 -> 10 | E11: 12 | G11: =C11*F11/E11 -> 0 | H11: =G11*8 -> 0 | I11: =D11*F11/E11 -> 0 | J11: =I11*4 -> 0 | M11: =M6 -> 6.5 | N11: =N6 -> 6.5 | O11: =M11*F11/E11 -> 0 | P11: =O11*8 -> 0 | Q11: =N11*F11/E11 -> 0 | R11: =Q11*4 -> 0 | T11: =T6 -> 3.5 | U11: =U6 -> 3.5 | V11: =T11*F11/E11 -> 0 | W11: =V11*8 -> 0 | X11: =U11*F11/E11 -> 0 | Y11: =X11*4 -> 0 | AC11: =AA11*F11/E11 -> 0 | AD11: =AC11*8 -> 0 | AE11: =AB11*F11/E11 -> 0 | AF11: =AE11*4 -> 0 | AJ11: =AH11*F11/E11 -> 0 | AK11: =AJ11*8 -> 0 | AL11: =AI11*F11/E11 -> 0 | AM11: =AL11*4 -> 0
B12: Fingerprints Machine | C12: =M12+T12+AA12+AH12 -> 2 | D12: =N12+U12+AB12+AI12 -> 2 | E12: 36 | G12: =C12*F12/E12 -> 0 | H12: =G12*8 -> 0 | I12: =D12*F12/E12 -> 0 | J12: =I12*4 -> 0 | K12: =(O12+V12+AC12+AJ12)-G12 -> 0 | L12: =(Q12+X12+AE12+AL12)-I12 -> 0 | M12: 1 | N12: 1 | O12: =M12*F12/E12 -> 0 | P12: =O12*8 -> 0 | Q12: =N12*F12/E12 -> 0 | R12: =Q12*4 -> 0 | T12: 1 | U12: 1 | V12: =T12*F12/E12 -> 0 | W12: =V12*8 -> 0 | X12: =U12*F12/E12 -> 0 | Y12: =X12*4 -> 0 | AC12: =AA12*F12/E12 -> 0 | AD12: =AC12*8 -> 0 | AE12: =AB12*F12/E12 -> 0 | AF12: =AE12*4 -> 0 | AJ12: =AH12*F12/E12 -> 0 | AK12: =AJ12*8 -> 0 | AL12: =AI12*F12/E12 -> 0 | AM12: =AL12*4 -> 0
G13: =SUM(G6:G12) -> 0 | H13: =G13*8 -> 0 | I13: =SUM(I6:I12) -> 0 | J13: =I13*4 -> 0 | K13: =(O13+V13+AC13+AJ13)-G13 -> 0 | L13: =(Q13+X13+AE13+AL13)-I13 -> 0 | O13: =SUM(O6:O12) -> 0 | P13: =O13*8 -> 0 | Q13: =SUM(Q6:Q12) -> 0 | R13: =Q13*4 -> 0 | V13: =SUM(V6:V12) -> 0 | W13: =V13*8 -> 0 | X13: =SUM(X6:X12) -> 0 | Y13: =X13*4 -> 0 | AC13: =SUM(AC6:AC12) -> 0 | AD13: =AC13*8 -> 0 | AE13: =SUM(AE6:AE12) -> 0 | AF13: =AE13*4 -> 0 | AJ13: =SUM(AJ6:AJ12) -> 0 | AK13: =AJ13*8 -> 0 | AL13: =SUM(AL6:AL12) -> 0 | AM13: =AL13*4 -> 0
