Workbook
Name \a: #N/A
Name \B: #REF!
Name \C: #REF!
Name \D: #REF!
Name \E: #REF!
Name \F: #REF!
Name \G: #REF!
Name \H: #REF!
Name \I: #REF!
Name \J: #REF!
Name \K: #REF!
Name \T: #REF!
Name \Z: #REF!
Name ___end1: [1]DATA!$V$71
Name __2_4THCOL: [3]DATA!$T$35:$T$35
Name __4_4THPMV: [3]DATA!$S$35:$S$35
Name __6_4THSPEND: [3]DATA!$U$35:$U$35
Name __end1: [3]DATA!$V$71
Name __new1: #REF!
Name _1_4THCOL: [1]DATA!$T$35:$T$35
Name _2_4THCOL: [4]DATA!$T$35:$T$35
Name _2_4THPMV: [1]DATA!$S$35:$S$35
Name _3_4THSPEND: [1]DATA!$U$35:$U$35
Name _4_4THPMV: [4]DATA!$S$35:$S$35
Name _6_4THSPEND: [4]DATA!$U$35:$U$35
Name _acr2: '[5]Apr-05'!#REF!
Name _CON1: #REF!
Name _CON10: #REF!
Name _CON11: #REF!
Name _CON12: #REF!
Name _CON13: #REF!
Name _CON14: #REF!
Name _CON15: #REF!
Name _CON16: #REF!
Name _CON2: #REF!
Name _CON3: #REF!
Name _CON4: #REF!
Name _CON5: #REF!
Name _CON6: #REF!
Name _CON7: #REF!
Name _CON8: #REF!
Name _CON9: #REF!
Name _end1: [4]DATA!$V$71
Name _ETB1: #REF!
Name _ETB2: #REF!
Name _ETB3: #REF!
Name _ETB4: #REF!
Name _ETB5: #REF!
Name _ETB6: #REF!
Name _fim: #REF!
Name _new1: [7]Original!$V$8
Name _OH1: #REF!
Name _OH2: #REF!
Name _OH3: #REF!
Name _OH4: #REF!
Name _OH5: #REF!
Name _OH6: #REF!
Name a: '[9]Manpower Master'!$O$57:$O$66
Name aa: #REF!
Name AB: #REF!

Sheet Pricing Notes
H6: Appendix A – Price Framework – FM Fees
H7: Pricing Notes
B9: · Accepted Fees: The amount accepted in the Letter of Acceptance for the completion of the FM Services.
B10: · Total FM Fees: The amount payable to the FM Service Provider for the Services and
B11: includes Variations and Reimbursable Expenses (Provisional Sum) as applicable in
B12: accordance with the Agreement.
B13: · Rates are per Person (EGP/Shift) including all required\proposed tools & equipment & consumables related to the Services
B14: · Service Provider shall be responsible for the consumables related to the Services
B15: · The Tenderer’s fee proposal for the Services shall be made on a total Man/Month basis with the total sum as the ceiling for the Contract Sum inclusive of all required\proposed tools & equipment, salaries, social insurance, overheads, direct and indirect expenses, all expected reimbursable, VAT, withholding tax and any other costs or expenditures required in the Arab Republic of Egypt for proper completion of the Scope of Services.
B16: · Monthly payment will be based on the actual attendance for each position at the rates stated in the Manning Schedule accepted by the Service Provider
B17: · Within the stated scope of services and the total Contract duration as stated, the Service Provider to ensure that the staff as per the manning schedule are sufficient to perform and complete the Scope of Services.
B18: · Should the Service Provider fail to cover the required Scope of Services in full satisfactory performance, the Employer reserve the right to instruct The Service Provider’s Representative to increase the staffing to recover such default without any extra cost whatsoever to the Employer.
B19: · A biometric attendance system must be used for daily attendance.
B20: · The Employer has the full right to extract the daily attendance at any time.
... B55: The Service Provider shall submit all the documentary evidence and substantiation to the Employer prior to the payment of Reimbursable / Provisional expenses in all cases.

Sheet FM Fees Summary
D2: Facility Management Services for Zone 2D, Zone 3D & Civic Park
D3: The Price Framework, Schedule 1 - Appendix A- Rev 03
D4: FM Fees Summary
D7: Zone | E7: Zone 2D | F7: Zone | G7: Zone 2D - 3D & Civic Park
D8: Contractual Year | E8: Year 1 | F8: Contractual Year | G8: Year 2
D9: Contractual Month | E9: Total amount/ Year1 | F9: Contractual Month | G9: Total amount/ Year2
D10: Mobilization | E10: ='Manning Schedule'!B12 -> 1579876 | F10: Mobilization (Not Applicable) / year 2 | G10: ='Manning Schedule'!T12 -> 0
D11: Total amount for MEP Services /year 1 | E11: ='Manning Schedule'!B31 -> 7322040 | F11: Total amount for MEP Services /year 2 | G11: ='Manning Schedule'!T31 -> 11566440
D12: Total amount for Housekeeping /year 1 | E12: ='Manning Schedule'!B37 -> 7147080 | F12: Total amount for Housekeeping /year 2 | G12: ='Manning Schedule'!T37 -> 12538440
D13: Total amount for Pest Control /year 1 | E13: ='Manning Schedule'!B41 -> 1008000 | F13: Total amount for Pest Control /year 2 | G13: ='Manning Schedule'!T41 -> 2130120
D14: Total amount for Landscape /year 1 | E14: ='Manning Schedule'!B46 -> 5643360 | F14: Total amount for Landscape /year 2 | G14: ='Manning Schedule'!T46 -> 16568280
D15: Total amount for Security Services /year 1 | E15: ='Manning Schedule'!B53 -> 12167280 | F15: Total amount for Security Services /year 2 | G15: ='Manning Schedule'!T53 -> 36174240
D16: Total amount for Transportation /year 1 | E16: ='Manning Schedule'!B58 -> 3469680 | F16: Total amount for Transportation /year 2 | G16: ='Manning Schedule'!T58 -> 3898080
D17: FM Fees/ year 1 | E17: =SUM(E10:E16) -> 38337316 | F17: FM Fees/ year 2 | G17: =SUM(G10:G16) -> 82875600
D18: Provisional Sum / reimbursable items / year 1 | E18: 10000000 | F18: Provisional Sum / reimbursable items / year 2 | G18: 10000000
D19: Total FM Fees amount including Provisional Sum/ year 1 | E19: =E18+E17 -> 48337316 | F19: Total FM Fees amount including Provisional Sum / year 2 | G19: =G18+G17 -> 92875600
D20: Total FM Fees Excluding VAT | E20: =E19+G19 -> 141212916
D21: VAT 14% | E21: =E20*0.14 -> 19769808
D22: Total FM Fees Including VAT | E22: =E20+E21 -> 1.6098272e+08

Sheet Manning Schedule
A2: Facility Management Services for Zone 2D, Zone 3D & Civic Park
A3: RFP Manning Schedule and Rates -Rev 03
A6: Zone | B6: Zone 2D | S6: Zone | T6: Zone 2D - 3D & Civic Park
A7: Contractual Year | B7: Year 1 | S7: Contractual Year | T7: Year 2
A8: Contractual Month | B8: Rate/ Shift/ Day | C8: No. of Manning/ Shift/ Day | O8: No. of Shifts/Day | P8: No. of Shifts /Month | Q8: Total Rate /Month | R8: Total Rate /Year 1 | T8: Rate/ Shift/ Day | U8: No. of Manning/ Shift/ Day | AG8: No. of Shifts/Day | AH8: No. of Shifts /Month | AI8: Total Rate /Month | AJ8: Total Rate /Year 2
C9: M1 | D9: M2 | E9: M3 | F9: M4 | G9: M5 | H9: M6 | I9: M7 | J9: M8 | K9: M9 | L9: M10 | M9: M11 | N9: M12 | S9: Contractual Month | U9: M1 | V9: M2 | W9: M3 | X9: M4 | Y9: M5 | Z9: M6 | AA9: M7 | AB9: M8 | AC9: M9 | AD9: M10 | AE9: M11 | AF9: M12
B10: Mobilization | T10: Mobilization
A11: Mobilization (Lumpsum item) | B11: =ROUNDUP('Mobilization Budget'!E105,0) -> 1579876 | C11: 1 | O11: 1 | P11: 1 | Q11: =B11*C11*P11 -> 1579876 | R11: =B11*SUM(C11:N11)*P11 -> 1579876 | S11: Mobilization (Not Applicable) | T11: 0
A12: Total amount for Mobilization /year 1 | B12: =R11 -> 1579876 | S12: Total amount for Mobilization /year 2 | T12: =AJ11 -> 0
J13: MEP Services | T13: MEP Services
A14: FM Manager | B14: ='MEP Budget-Y1'!N7 -> 2419 | C14: 1 | D14: 1 | E14: 1 | F14: 1 | G14: 1 | H14: 1 | I14: 1 | J14: 1 | K14: 1 | L14: 1 | M14: 1 | N14: 1 | O14: 1 | P14: =O14*30 -> 30 | Q14: =B14*C14*P14 -> 72570 | R14: =B14*SUM(C14:N14)*P14 -> 870840 | S14: FM Manager | T14: ='MEP Budget-Y2'!N7 -> 2760 | U14: 1 | V14: 1 | W14: 1 | X14: 1 | Y14: 1 | Z14: 1 | AA14: 1 | AB14: 1 | AC14: 1 | AD14: 1 | AE14: 1 | AF14: 1 | AG14: 1 | AH14: =AG14*30 -> 30 | AI14: =T14*U14*AH14 -> 82800 | AJ14: =T14*SUM(U14:AF14)*AH14 -> 993600
A15: Senior Engineer MEP | B15: ='MEP Budget-Y1'!N8 -> 1573 | C15: 1 | D15: 1 | E15: 1 | F15: 1 | G15: 1 | H15: 1 | I15: 1 | J15: 1 | K15: 1 | L15: 1 | M15: 1 | N15: 1 | O15: 1 | P15: =O15*30 -> 30 | Q15: =B15*C15*P15 -> 47190 | R15: =B15*SUM(C15:N15)*P15 -> 566280 | S15: Senior Engineer MEP | T15: ='MEP Budget-Y2'!N8 -> 1794 | U15: 2 | V15: 2 | W15: 2 | X15: 2 | Y15: 2 | Z15: 2 | AA15: 2 | AB15: 2 | AC15: 2 | AD15: 2 | AE15: 2 | AF15: 2 | AG15: 1 | AH15: =AG15*30 -> 30 | AI15: =T15*U15*AH15 -> 107640 | AJ15: =T15*SUM(U15:AF15)*AH15 -> 1291680
A16: Supervisor - Electrical | B16: ='MEP Budget-Y1'!N9 -> 883 | C16: 1 | D16: 1 | E16: 1 | F16: 1 | G16: 1 | H16: 1 | I16: 1 | J16: 1 | K16: 1 | L16: 1 | M16: 1 | N16: 1 | O16: 1 | P16: =O16*30 -> 30 | Q16: =B16*C16*P16 -> 26490 | R16: =B16*SUM(C16:N16)*P16 -> 317880 | S16: Supervisor - Electrical | T16: ='MEP Budget-Y2'!N9 -> 1008 | U16: 2 | V16: 2 | W16: 2 | X16: 2 | Y16: 2 | Z16: 2 | AA16: 2 | AB16: 2 | AC16: 2 | AD16: 2 | AE16: 2 | AF16: 2 | AG16: 1 | AH16: =AG16*30 -> 30 | AI16: =T16*U16*AH16 -> 60480 | AJ16: =T16*SUM(U16:AF16)*AH16 -> 725760
A17: Supervisor - Mechanical | B17: ='MEP Budget-Y1'!N10 -> 883 | C17: 1 | D17: 1 | E17: 1 | F17: 1 | G17: 1 | H17: 1 | I17: 1 | J17: 1 | K17: 1 | L17: 1 | M17: 1 | N17: 1 | O17: 1 | P17: =O17*30 -> 30 | Q17: =B17*C17*P17 -> 26490 | R17: =B17*SUM(C17:N17)*P17 -> 317880 | S17: Supervisor - Mechanical | T17: ='MEP Budget-Y2'!N10 -> 1008 | U17: 2 | V17: 2 | W17: 2 | X17: 2 | Y17: 2 | Z17: 2 | AA17: 2 | AB17: 2 | AC17: 2 | AD17: 2 | AE17: 2 | AF17: 2 | AG17: 1 | AH17: =AG17*30 -> 30 | AI17: =T17*U17*AH17 -> 60480 | AJ17: =T17*SUM(U17:AF17)*AH17 -> 725760
A18: Supervisor - Light Current | B18: ='MEP Budget-Y1'!N11 -> 883 | C18: 1 | D18: 1 | E18: 1 | F18: 1 | G18: 1 | H18: 1 | I18: 1 | J18: 1 | K18: 1 | L18: 1 | M18: 1 | N18: 1 | O18: 1 | P18: =O18*30 -> 30 | Q18: =B18*C18*P18 -> 26490 | R18: =B18*SUM(C18:N18)*P18 -> 317880 | S18: Supervisor - Light Current | T18: ='MEP Budget-Y2'!N11 -> 1008 | U18: 1 | V18: 1 | W18: 1 | X18: 1 | Y18: 1 | Z18: 1 | AA18: 1 | AB18: 1 | AC18: 1 | AD18: 1 | AE18: 1 | AF18: 1 | AG18: 1 | AH18: =AG18*30 -> 30 | AI18: =T18*U18*AH18 -> 30240 | AJ18: =T18*SUM(U18:AF18)*AH18 -> 362880
A19: Technician - Electrical | B19: ='MEP Budget-Y1'!N12 -> 500 | C19: 3 | D19: 3 | E19: 3 | F19: 3 | G19: 3 | H19: 3 | I19: 3 | J19: 3 | K19: 3 | L19: 3 | M19: 3 | N19: 3 | O19: 1 | P19: =O19*30 -> 30 | Q19: =B19*C19*P19 -> 45000 | R19: =B19*SUM(C19:N19)*P19 -> 540000 | S19: Technician - Electrical | T19: ='MEP Budget-Y2'!N12 -> 577 | U19: 5 | V19: 5 | W19: 5 | X19: 5 | Y19: 5 | Z19: 5 | AA19: 5 | AB19: 5 | AC19: 5 | AD19: 5 | AE19: 5 | AF19: 5 | AG19: 1 | AH19: =AG19*30 -> 30 | AI19: =T19*U19*AH19 -> 86550 | AJ19: =T19*SUM(U19:AF19)*AH19 -> 1038600
A20: Technician - Mechanical | B20: ='MEP Budget-Y1'!N13 -> 530 | C20: 1 | D20: 1 | E20: 1 | F20: 1 | G20: 1 | H20: 1 | I20: 1 | J20: 1 | K20: 1 | L20: 1 | M20: 1 | N20: 1 | O20: 1 | P20: =O20*30 -> 30 | Q20: =B20*C20*P20 -> 15900 | R20: =B20*SUM(C20:N20)*P20 -> 190800 | S20: Technician - Mechanical | T20: ='MEP Budget-Y2'!N13 -> 604 | U20: 2 | V20: 2 | W20: 2 | X20: 2 | Y20: 2 | Z20: 2 | AA20: 2 | AB20: 2 | AC20: 2 | AD20: 2 | AE20: 2 | AF20: 2 | AG20: 1 | AH20: =AG20*30 -> 30 | AI20: =T20*U20*AH20 -> 36240 | AJ20: =T20*SUM(U20:AF20)*AH20 -> 434880
A21: Technician - Pluming | B21: ='MEP Budget-Y1'!N14 -> 491 | C21: 3 | D21: 3 | E21: 3 | F21: 3 | G21: 3 | H21: 3 | I21: 3 | J21: 3 | K21: 3 | L21: 3 | M21: 3 | N21: 3 | O21: 1 | P21: =O21*30 -> 30 | Q21: =B21*C21*P21 -> 44190 | R21: =B21*SUM(C21:N21)*P21 -> 530280 | S21: Technician - Pluming | T21: ='MEP Budget-Y2'!N14 -> 567 | U21: 5 | V21: 5 | W21: 5 | X21: 5 | Y21: 5 | Z21: 5 | AA21: 5 | AB21: 5 | AC21: 5 | AD21: 5 | AE21: 5 | AF21: 5 | AG21: 1 | AH21: =AG21*30 -> 30 | AI21: =T21*U21*AH21 -> 85050 | AJ21: =T21*SUM(U21:AF21)*AH21 -> 1020600
A22: Technician - light Current | B22: ='MEP Budget-Y1'!N15 -> 545 | C22: 1 | D22: 1 | E22: 1 | F22: 1 | G22: 1 | H22: 1 | I22: 1 | J22: 1 | K22: 1 | L22: 1 | M22: 1 | N22: 1 | O22: 1 | P22: =O22*30 -> 30 | Q22: =B22*C22*P22 -> 16350 | R22: =B22*SUM(C22:N22)*P22 -> 196200 | S22: Technician - light Current | T22: ='MEP Budget-Y2'!N15 -> 621 | U22: 1 | V22: 1 | W22: 1 | X22: 1 | Y22: 1 | Z22: 1 | AA22: 1 | AB22: 1 | AC22: 1 | AD22: 1 | AE22: 1 | AF22: 1 | AG22: 1 | AH22: =AG22*30 -> 30 | AI22: =T22*U22*AH22 -> 18630 | AJ22: =T22*SUM(U22:AF22)*AH22 -> 223560
A23: CAFM - Coordinator | B23: ='MEP Budget-Y1'!N16 -> 744 | C23: 1 | D23: 1 | E23: 1 | F23: 1 | G23: 1 | H23: 1 | I23: 1 | J23: 1 | K23: 1 | L23: 1 | M23: 1 | N23: 1 | O23: 1 | P23: =O23*30 -> 30 | Q23: =B23*C23*P23 -> 22320 | R23: =B23*SUM(C23:N23)*P23 -> 267840 | S23: CAFM - Coordinator | T23: ='MEP Budget-Y2'!N16 -> 849 | U23: 1 | V23: 1 | W23: 1 | X23: 1 | Y23: 1 | Z23: 1 | AA23: 1 | AB23: 1 | AC23: 1 | AD23: 1 | AE23: 1 | AF23: 1 | AG23: 1 | AH23: =AG23*30 -> 30 | AI23: =T23*U23*AH23 -> 25470 | AJ23: =T23*SUM(U23:AF23)*AH23 -> 305640
A24: Painter | B24: ='MEP Budget-Y1'!N17 -> 514 | C24: 1 | D24: 1 | E24: 1 | F24: 1 | G24: 1 | H24: 1 | I24: 1 | J24: 1 | K24: 1 | L24: 1 | M24: 1 | N24: 1 | O24: 1 | P24: =O24*30 -> 30 | Q24: =B24*C24*P24 -> 15420 | R24: =B24*SUM(C24:N24)*P24 -> 185040 | S24: Painter | T24: ='MEP Budget-Y2'!N17 -> 587 | U24: 2 | V24: 2 | W24: 2 | X24: 2 | Y24: 2 | Z24: 2 | AA24: 2 | AB24: 2 | AC24: 2 | AD24: 2 | AE24: 2 | AF24: 2 | AG24: 1 | AH24: =AG24*30 -> 30 | AI24: =T24*U24*AH24 -> 35220 | AJ24: =T24*SUM(U24:AF24)*AH24 -> 422640
A25: Carpenter | B25: ='MEP Budget-Y1'!N18 -> 514 | C25: 1 | D25: 1 | E25: 1 | F25: 1 | G25: 1 | H25: 1 | I25: 1 | J25: 1 | K25: 1 | L25: 1 | M25: 1 | N25: 1 | O25: 1 | P25: =O25*30 -> 30 | Q25: =B25*C25*P25 -> 15420 | R25: =B25*SUM(C25:N25)*P25 -> 185040 | S25: Carpenter | T25: ='MEP Budget-Y2'!N18 -> 587 | U25: 2 | V25: 2 | W25: 2 | X25: 2 | Y25: 2 | Z25: 2 | AA25: 2 | AB25: 2 | AC25: 2 | AD25: 2 | AE25: 2 | AF25: 2 | AG25: 1 | AH25: =AG25*30 -> 30 | AI25: =T25*U25*AH25 -> 35220 | AJ25: =T25*SUM(U25:AF25)*AH25 -> 422640
... A30: Manlift | B30: ='MEP Budget-Y1'!N23 -> 3628 | C30: 1 | D30: 1 | E30: 1 | F30: 1 | G30: 1 | H30: 1 | I30: 1 | J30: 1 | K30: 1 | L30: 1 | M30: 1 | N30: 1 | O30: 1 | P30: =O30*30 -> 30 | Q30: =B30*C30*P30 -> 108840 | R30: =B30*SUM(C30:N30)*P30 -> 1306080 | S30: Manlift | T30: ='MEP Budget-Y2'!N23 -> 4140 | U30: 1 | V30: 1 | W30: 1 | X30: 1 | Y30: 1 | Z30: 1 | AA30: 1 | AB30: 1 | AC30: 1 | AD30: 1 | AE30: 1 | AF30: 1 | AG30: 1 | AH30: =AG30*30 -> 30 | AI30: =T30*U30*AH30 -> 124200 | AJ30: =T30*SUM(U30:AF30)*AH30 -> 1490400
A31: Total amount for MEP Services /year 1 | B31: =SUM(R14:R30) -> 7322040 | S31: Total amount for MEP Services /year 2 | T31: =SUM(AJ14:AJ30) -> 11566440
J32: Housekeeping & Waste Management | AB32: Housekeeping
A33: HK Supervisors | B33: ='HK & Waste Management-Y1'!N7 -> 895 | C33: 2 | D33: 2 | E33: 2 | F33: 2 | G33: 2 | H33: 2 | I33: 2 | J33: 2 | K33: 2 | L33: 2 | M33: 2 | N33: 2 | O33: 1 | P33: =O33*30 -> 30 | Q33: =B33*C33*P33 -> 53700 | R33: =B33*SUM(C33:N33)*P33 -> 644400 | S33: HK Supervisors | T33: ='HK & Waste Management-Y2'!N7 -> 955 | U33: 4 | V33: 4 | W33: 4 | X33: 4 | Y33: 4 | Z33: 4 | AA33: 4 | AB33: 4 | AC33: 4 | AD33: 4 | AE33: 4 | AF33: 4 | AG33: 1 | AH33: =AG33*30 -> 30 | AI33: =T33*U33*AH33 -> 114600 | AJ33: =T33*SUM(U33:AF33)*AH33 -> 1375200
A34: Janitors | B34: ='HK & Waste Management-Y1'!N8 -> 392 | C34: 20 | D34: 20 | E34: 20 | F34: 20 | G34: 20 | H34: 20 | I34: 20 | J34: 20 | K34: 20 | L34: 20 | M34: 20 | N34: 20 | O34: 1 | P34: =O34*30 -> 30 | Q34: =B34*C34*P34 -> 235200 | R34: =B34*SUM(C34:N34)*P34 -> 2822400 | S34: Janitors | T34: ='HK & Waste Management-Y2'!N8 -> 430 | U34: 40 | V34: 40 | W34: 40 | X34: 40 | Y34: 40 | Z34: 40 | AA34: 40 | AB34: 40 | AC34: 40 | AD34: 40 | AE34: 40 | AF34: 40 | AG34: 1 | AH34: =AG34*30 -> 30 | AI34: =T34*U34*AH34 -> 516000 | AJ34: =T34*SUM(U34:AF34)*AH34 -> 6192000
A35: Road Sweeper | B35: ='HK & Waste Management-Y1'!N9 -> 7667 | C35: 1 | D35: 1 | E35: 1 | F35: 1 | G35: 1 | H35: 1 | I35: 1 | J35: 1 | K35: 1 | L35: 1 | M35: 1 | N35: 1 | O35: 1 | P35: =O35*30 -> 30 | Q35: =B35*C35*P35 -> 230010 | R35: =B35*SUM(C35:N35)*P35 -> 2760120 | S35: Road Sweeper | T35: ='HK & Waste Management-Y2'!N9 -> 9095 | U35: 1 | V35: 1 | W35: 1 | X35: 1 | Y35: 1 | Z35: 1 | AA35: 1 | AB35: 1 | AC35: 1 | AD35: 1 | AE35: 1 | AF35: 1 | AG35: 1 | AH35: =AG35*30 -> 30 | AI35: =T35*U35*AH35 -> 272850 | AJ35: =T35*SUM(U35:AF35)*AH35 -> 3274200
A36: Waste Management (Lumpsum item per month) | B36: ='HK & Waste Management-Y1'!N10 -> 2556 | C36: 1 | D36: 1 | E36: 1 | F36: 1 | G36: 1 | H36: 1 | I36: 1 | J36: 1 | K36: 1 | L36: 1 | M36: 1 | N36: 1 | O36: 1 | P36: =O36*30 -> 30 | Q36: =B36*C36*P36 -> 76680 | R36: =B36*SUM(C36:N36)*P36 -> 920160 | S36: Waste Management | T36: ='HK & Waste Management-Y2'!N10 -> 4714 | U36: 1 | V36: 1 | W36: 1 | X36: 1 | Y36: 1 | Z36: 1 | AA36: 1 | AB36: 1 | AC36: 1 | AD36: 1 | AE36: 1 | AF36: 1 | AG36: 1 | AH36: =AG36*30 -> 30 | AI36: =T36*U36*AH36 -> 141420 | AJ36: =T36*SUM(U36:AF36)*AH36 -> 1697040
A37: Total amount for Housekeeping /year 1 | B37: =SUM(R33:R36) -> 7147080 | S37: Total amount for Housekeeping /year 2 | T37: =SUM(AJ33:AJ36) -> 12538440
J38: Pest Control | AB38: Pest Control
A39: Pest Control Supervisor | B39: ='Pest Control Y-1'!N7 -> 850 | C39: 1 | D39: 1 | E39: 1 | F39: 1 | G39: 1 | H39: 1 | I39: 1 | J39: 1 | K39: 1 | L39: 1 | M39: 1 | N39: 1 | O39: 1 | P39: =O39*30 -> 30 | Q39: =B39*C39*P39 -> 25500 | R39: =B39*SUM(C39:N39)*P39 -> 306000 | S39: Pest Control Supervisor | T39: ='Pest Control Y-2'!N7 -> 844 | U39: 1 | V39: 1 | W39: 1 | X39: 1 | Y39: 1 | Z39: 1 | AA39: 1 | AB39: 1 | AC39: 1 | AD39: 1 | AE39: 1 | AF39: 1 | AG39: 1 | AH39: =AG39*30 -> 30 | AI39: =T39*U39*AH39 -> 25320 | AJ39: =T39*SUM(U39:AF39)*AH39 -> 303840
A40: Pest Control Service (Lumpsum item per month) | B40: ='Pest Control Y-1'!N8 -> 1950 | C40: 1 | D40: 1 | E40: 1 | F40: 1 | G40: 1 | H40: 1 | I40: 1 | J40: 1 | K40: 1 | L40: 1 | M40: 1 | N40: 1 | O40: 1 | P40: =O40*30 -> 30 | Q40: =B40*C40*P40 -> 58500 | R40: =B40*SUM(C40:N40)*P40 -> 702000 | S40: Pest Control Service | T40: ='Pest Control Y-2'!N8 -> 5073 | U40: 1 | V40: 1 | W40: 1 | X40: 1 | Y40: 1 | Z40: 1 | AA40: 1 | AB40: 1 | AC40: 1 | AD40: 1 | AE40: 1 | AF40: 1 | AG40: 1 | AH40: =AG40*30 -> 30 | AI40: =T40*U40*AH40 -> 152190 | AJ40: =T40*SUM(U40:AF40)*AH40 -> 1826280
A41: Total amount for Pest Control /year 1 | B41: =SUM(R39:R40) -> 1008000 | C41: =#REF!*SUM(#REF!)*B41 -> #REF! | D41: =#REF!*SUM(#REF!)*C41 -> #REF! | E41: =#REF!*SUM(#REF!)*D41 -> #REF! | F41: =#REF!*SUM(#REF!)*E41 -> #REF! | G41: =#REF!*SUM(#REF!)*F41 -> #REF! | H41: =#REF!*SUM(#REF!)*G41 -> #REF! | I41: =#REF!*SUM(#REF!)*H41 -> #REF! | J41: =#REF!*SUM(#REF!)*I41 -> #REF! | ... M41: =#REF!*SUM(#REF!)*L41 -> #REF! | N41: =#REF!*SUM(A41:K41)*M41 -> #REF! | O41: =#REF!*SUM(A41:L41)*N41 -> #REF! | P41: =A41*SUM(B41:M41)*O41 -> #VALUE! | R41: =B41*SUM(C41:N41)*P41 -> #REF! | S41: Total amount for Pest Control /year 2 | T41: =SUM(AJ39:AJ40) -> 2130120
J42: Landscape (optional) | AB42: Landscape (optional)
A43: Landscape Manager | B43: ='Landscape Y1'!N7 -> 1958 | C43: 1 | D43: 1 | E43: 1 | F43: 1 | G43: 1 | H43: 1 | I43: 1 | J43: 1 | K43: 1 | L43: 1 | M43: 1 | N43: 1 | O43: 1 | P43: =O43*30 -> 30 | Q43: =B43*C43*P43 -> 58740 | R43: =B43*SUM(C43:N43)*P43 -> 704880 | S43: Landscape Manager | T43: ='Landscape Y2'!N7 -> 2179 | U43: 1 | V43: 1 | W43: 1 | X43: 1 | Y43: 1 | Z43: 1 | AA43: 1 | AB43: 1 | AC43: 1 | AD43: 1 | AE43: 1 | AF43: 1 | AG43: 1 | AH43: =AG43*30 -> 30 | AI43: =T43*U43*AH43 -> 65370 | AJ43: =T43*SUM(U43:AF43)*AH43 -> 784440
A44: Landscape Supervisor | B44: ='Landscape Y1'!N8 -> 1599 | C44: 2 | D44: 2 | E44: 2 | F44: 2 | G44: 2 | H44: 2 | I44: 2 | J44: 2 | K44: 2 | L44: 2 | M44: 2 | N44: 2 | O44: 1 | P44: =O44*30 -> 30 | Q44: =B44*C44*P44 -> 95940 | R44: =B44*SUM(C44:N44)*P44 -> 1151280 | S44: Landscape Supervisor | T44: ='Landscape Y2'!N8 -> 1631 | U44: 4 | V44: 4 | W44: 4 | X44: 4 | Y44: 4 | Z44: 4 | AA44: 4 | AB44: 4 | AC44: 4 | AD44: 4 | AE44: 4 | AF44: 4 | AG44: 1 | AH44: =AG44*30 -> 30 | AI44: =T44*U44*AH44 -> 195720 | AJ44: =T44*SUM(U44:AF44)*AH44 -> 2348640
A45: Gardner | B45: ='Landscape Y1'!N9 -> 526 | C45: 20 | D45: 20 | E45: 20 | F45: 20 | G45: 20 | H45: 20 | I45: 20 | J45: 20 | K45: 20 | L45: 20 | M45: 20 | N45: 20 | O45: 1 | P45: =O45*30 -> 30 | Q45: =B45*C45*P45 -> 315600 | R45: =B45*SUM(C45:N45)*P45 -> 3787200 | S45: Gardner | T45: ='Landscape Y2'!N9 -> 622 | U45: 60 | V45: 60 | W45: 60 | X45: 60 | Y45: 60 | Z45: 60 | AA45: 60 | AB45: 60 | AC45: 60 | AD45: 60 | AE45: 60 | AF45: 60 | AG45: 1 | AH45: =AG45*30 -> 30 | AI45: =T45*U45*AH45 -> 1119600 | AJ45: =T45*SUM(U45:AF45)*AH45 -> 13435200
A46: Total amount for Landscape /year 1 | B46: =SUM(R43:R45) -> 5643360 | S46: Total amount for Landscape /year 2 | T46: =SUM(AJ43:AJ45) -> 16568280
J47: Security Services | AB47: Security Services
A48: Security Manger | B48: ='Security Y1'!N7 -> 1374 | C48: 1 | D48: 1 | E48: 1 | F48: 1 | G48: 1 | H48: 1 | I48: 1 | J48: 1 | K48: 1 | L48: 1 | M48: 1 | N48: 1 | O48: 1 | P48: =O48*30 -> 30 | Q48: =B48*C48*P48 -> 41220 | R48: =B48*SUM(C48:N48)*P48 -> 494640 | S48: Security Manger | T48: ='Security Y2'!N7 -> 1456 | U48: 1 | V48: 1 | W48: 1 | X48: 1 | Y48: 1 | Z48: 1 | AA48: 1 | AB48: 1 | AC48: 1 | AD48: 1 | AE48: 1 | AF48: 1 | AG48: 1 | AH48: =AG48*30 -> 30 | AI48: =T48*U48*AH48 -> 43680 | AJ48: =T48*SUM(U48:AF48)*AH48 -> 524160
A49: Safety Supervisor / Agent | B49: ='Security Y1'!N8 -> 916 | C49: 2 | D49: 2 | E49: 2 | F49: 2 | G49: 2 | H49: 2 | I49: 2 | J49: 2 | K49: 2 | L49: 2 | M49: 2 | N49: 2 | O49: 2 | P49: =O49*30 -> 60 | Q49: =B49*C49*P49 -> 109920 | R49: =B49*SUM(C49:N49)*P49 -> 1319040 | S49: Safety Supervisor / Agent | T49: ='Security Y2'!N8 -> 971 | U49: 4 | V49: 4 | W49: 4 | X49: 4 | Y49: 4 | Z49: 4 | AA49: 4 | AB49: 4 | AC49: 4 | AD49: 4 | AE49: 4 | AF49: 4 | AG49: 2 | AH49: =AG49*30 -> 60 | AI49: =T49*U49*AH49 -> 233040 | AJ49: =T49*SUM(U49:AF49)*AH49 -> 2796480
A50: Security Supervisor / per shift | B50: ='Security Y1'!N9 -> 620 | C50: 1 | D50: 1 | E50: 1 | F50: 1 | G50: 1 | H50: 1 | I50: 1 | J50: 1 | K50: 1 | L50: 1 | M50: 1 | N50: 1 | O50: 2 | P50: =O50*30 -> 60 | Q50: =B50*C50*P50 -> 37200 | R50: =B50*SUM(C50:N50)*P50 -> 446400 | S50: Security Supervisor / per shift | T50: ='Security Y2'!N9 -> 656 | U50: 1 | V50: 1 | W50: 1 | X50: 1 | Y50: 1 | Z50: 1 | AA50: 1 | AB50: 1 | AC50: 1 | AD50: 1 | AE50: 1 | AF50: 1 | AG50: 2 | AH50: =AG50*30 -> 60 | AI50: =T50*U50*AH50 -> 39360 | AJ50: =T50*SUM(U50:AF50)*AH50 -> 472320
A51: Security Guards / per shift | B51: ='Security Y1'!N10 -> 344 | C51: 40 | D51: 40 | E51: 40 | F51: 40 | G51: 40 | H51: 40 | I51: 40 | J51: 40 | K51: 40 | L51: 40 | M51: 40 | N51: 40 | O51: 2 | P51: =O51*30 -> 60 | Q51: =B51*C51*P51 -> 825600 | R51: =B51*SUM(C51:N51)*P51 -> 9907200 | S51: Security Guards / per shift | T51: ='Security Y2'!N10 -> 364 | U51: 120 | V51: 120 | W51: 120 | X51: 120 | Y51: 120 | Z51: 120 | AA51: 120 | AB51: 120 | AC51: 120 | AD51: 120 | AE51: 120 | AF51: 120 | AG51: 2 | AH51: =AG51*30 -> 60 | AI51: =T51*U51*AH51 -> 2620800 | AJ51: =T51*SUM(U51:AF51)*AH51 -> 31449600
A52: CCTV Operator | O52: 0 | P52: =O52*30 -> 0 | Q52: =B52*C52*P52 -> 0 | R52: =B52*SUM(C52:N52)*P52 -> 0 | S52: CCTV Operator | T52: ='Security Y2'!N11 -> 647 | U52: 2 | V52: 2 | W52: 2 | X52: 2 | Y52: 2 | Z52: 2 | AA52: 2 | AB52: 2 | AC52: 2 | AD52: 2 | AE52: 2 | AF52: 2 | AG52: 2 | AH52: =AG52*30 -> 60 | AI52: =T52*U52*AH52 -> 77640 | AJ52: =T52*SUM(U52:AF52)*AH52 -> 931680
A53: Total amount for Security Services /year 1 | B53: =SUM(R48:R52) -> 12167280 | S53: Total amount for Security Services /year 2 | T53: =SUM(AJ48:AJ52) -> 36174240
J54: Transportation | AB54: Transportation
A55: Pickup Double Cabinet (1 security + 1 MEP) | B55: ='Transportation Y1'!N7 -> 2002 | C55: 2 | D55: 2 | E55: 2 | F55: 2 | G55: 2 | H55: 2 | I55: 2 | J55: 2 | K55: 2 | L55: 2 | M55: 2 | N55: 2 | O55: 1 | P55: =O55*30 -> 30 | Q55: =B55*C55*P55 -> 120120 | R55: =B55*SUM(C55:N55)*P55 -> 1441440 | S55: Pickup Double Cabinet (1 security + 1 MEP) | T55: ='Transportation Y2'!N7 -> 2249 | U55: 2 | V55: 2 | W55: 2 | X55: 2 | Y55: 2 | Z55: 2 | AA55: 2 | AB55: 2 | AC55: 2 | AD55: 2 | AE55: 2 | AF55: 2 | AG55: 1 | AH55: =AG55*30 -> 30 | AI55: =T55*U55*AH55 -> 134940 | AJ55: =T55*SUM(U55:AF55)*AH55 -> 1619280
A56: Golf Car | B56: ='Transportation Y1'!N8 -> 2310 | C56: 2 | D56: 2 | E56: 2 | F56: 2 | G56: 2 | H56: 2 | I56: 2 | J56: 2 | K56: 2 | L56: 2 | M56: 2 | N56: 2 | O56: 1 | P56: =O56*30 -> 30 | Q56: =B56*C56*P56 -> 138600 | R56: =B56*SUM(C56:N56)*P56 -> 1663200 | S56: Golf Car | T56: ='Transportation Y2'!N8 -> 2595 | U56: 2 | V56: 2 | W56: 2 | X56: 2 | Y56: 2 | Z56: 2 | AA56: 2 | AB56: 2 | AC56: 2 | AD56: 2 | AE56: 2 | AF56: 2 | AG56: 1 | AH56: =AG56*30 -> 30 | AI56: =T56*U56*AH56 -> 155700 | AJ56: =T56*SUM(U56:AF56)*AH56 -> 1868400
A57: Security Patrol Motorcycles / Tricycles | B57: ='Transportation Y1'!N9 -> 507 | C57: 2 | D57: 2 | E57: 2 | F57: 2 | G57: 2 | H57: 2 | I57: 2 | J57: 2 | K57: 2 | L57: 2 | M57: 2 | N57: 2 | O57: 1 | P57: =O57*30 -> 30 | Q57: =B57*C57*P57 -> 30420 | R57: =B57*SUM(C57:N57)*P57 -> 365040 | S57: Security Patrol Motorcycles / Tricycles | T57: ='Transportation Y2'!N9 -> 570 | U57: 2 | V57: 2 | W57: 2 | X57: 2 | Y57: 2 | Z57: 2 | AA57: 2 | AB57: 2 | AC57: 2 | AD57: 2 | AE57: 2 | AF57: 2 | AG57: 1 | AH57: =AG57*30 -> 30 | AI57: =T57*U57*AH57 -> 34200 | AJ57: =T57*SUM(U57:AF57)*AH57 -> 410400
A58: Total amount for Transportation /year 1 | B58: =SUM(R55:R57) -> 3469680 | S58: Total amount for Transportation /year 2 | T58: =SUM(AJ55:AJ57) -> 3898080
A59: FM Fees amount/ year 1 | B59: =B12+B31+B37+B41+B46+B53+B58 -> 38337316 | S59: FM Fees amount/ year 2 | T59: =T12+T31+T37+T41+T46+T53+T58 -> 82875600
A60: FM Fees Year 1 + Year 2 | B60: =B59+T59 -> 121212916

Sheet End User Services Rates
B3: Facility Management Services for Zone 2D, Zone 3D & Civic Park
B4: End User & Days Works Rates
B7: Labor category | C7: Unite | D7: Rate
B10: Maintenance Engineer | C10: Hr | D10: 225
B11: Electrician | C11: Hr | D11: 100
B12: Electrician Helper | C12: Hr | D12: 80
B13: HVAC Technician | C13: Hr | D13: 120
B14: HVAC Helper | C14: Hr | D14: 80
B15: Plumber | C15: Hr | D15: 100
B16: Plumber Helper | C16: Hr | D16: 80
B17: Carpenter | C17: Hr | D17: 100
B18: Planting & Irrigator technician | C18: Hr | D18: 80
B19: Painter | C19: Hr | D19: 100
B20: 24-hour emergency call | C20: Day | D20: 3200
B21: Construction Waste Disposal from Tenants Units to Outside Project Boundary | C21: Trip | D21: 1800
... B24: Sewage Truck | C24: Visit | D24: 10000

Sheet Manning Schedule (2)
A2: Facility Management Services for Zone 2D, Zone 3D & Civic Park
A3: RFP Manning Schedule and Rates -Rev 03
A6: Zone | B6: Zone 2D | S6: Zone | T6: Zone 2D - 3D & Civic Park
A7: Contractual Year | B7: Year 1 | S7: Contractual Year | T7: Year 2
A8: Contractual Month | B8: Rate/ Shift/ Day | C8: No. of Manning/ Shift/ Day | O8: No. of Shifts/Day | P8: No. of Shifts /Month | Q8: Total Rate /Month | R8: Total Rate /Year 1 | T8: Rate/ Shift/ Day | U8: No. of Manning/ Shift/ Day | AG8: No. of Shifts/Day | AH8: No. of Shifts /Month | AI8: Total Rate /Month | AJ8: Total Rate /Year 2
C9: M1 | D9: M2 | E9: M3 | F9: M4 | G9: M5 | H9: M6 | I9: M7 | J9: M8 | K9: M9 | L9: M10 | M9: M11 | N9: M12 | S9: Contractual Month | U9: M1 | V9: M2 | W9: M3 | X9: M4 | Y9: M5 | Z9: M6 | AA9: M7 | AB9: M8 | AC9: M9 | AD9: M10 | AE9: M11 | AF9: M12
B10: Mobilization | T10: Mobilization
A11: Mobilization (Lumpsum item) | B11: =ROUNDUP('Mobilization Budget'!E105,0) -> 1579876 | C11: 1 | O11: 1 | P11: 1 | Q11: =B11*C11*P11 -> 1579876 | R11: =B11*SUM(C11:N11)*P11 -> 1579876 | S11: Mobilization (Not Applicable) | T11: 0
A12: Total amount for Mobilization /year 1 | B12: =R11 -> 1579876 | S12: Total amount for Mobilization /year 2 | T12: =AJ11 -> 0
J13: MEP Services | T13: MEP Services
A14: FM Manager | B14: ='MEP Budget-Y1'!N7 -> 2419 | C14: 1 | D14: 1 | E14: 1 | F14: 1 | G14: 1 | H14: 1 | I14: 1 | J14: 1 | K14: 1 | L14: 1 | M14: 1 | N14: 1 | O14: 1 | P14: =O14*30 -> 30 | Q14: =B14*C14*P14 -> 72570 | R14: =B14*SUM(C14:N14)*P14 -> 870840 | S14: FM Manager | T14: ='MEP Budget-Y2'!N7 -> 2760 | U14: 1 | V14: 1 | W14: 1 | X14: 1 | Y14: 1 | Z14: 1 | AA14: 1 | AB14: 1 | AC14: 1 | AD14: 1 | AE14: 1 | AF14: 1 | AG14: 1 | AH14: =AG14*30 -> 30 | AI14: =T14*U14*AH14 -> 82800 | AJ14: =T14*SUM(U14:AF14)*AH14 -> 993600
A15: Senior Engineer MEP | B15: ='MEP Budget-Y1'!N8 -> 1573 | C15: 1 | D15: 1 | E15: 1 | F15: 1 | G15: 1 | H15: 1 | I15: 1 | J15: 1 | K15: 1 | L15: 1 | M15: 1 | N15: 1 | O15: 1 | P15: =O15*30 -> 30 | Q15: =B15*C15*P15 -> 47190 | R15: =B15*SUM(C15:N15)*P15 -> 566280 | S15: Senior Engineer MEP | T15: ='MEP Budget-Y2'!N8 -> 1794 | U15: 2 | V15: 2 | W15: 2 | X15: 2 | Y15: 2 | Z15: 2 | AA15: 2 | AB15: 2 | AC15: 2 | AD15: 2 | AE15: 2 | AF15: 2 | AG15: 1 | AH15: =AG15*30 -> 30 | AI15: =T15*U15*AH15 -> 107640 | AJ15: =T15*SUM(U15:AF15)*AH15 -> 1291680
A16: Supervisor - Electrical | B16: ='MEP Budget-Y1'!N9 -> 883 | C16: 1 | D16: 1 | E16: 1 | F16: 1 | G16: 1 | H16: 1 | I16: 1 | J16: 1 | K16: 1 | L16: 1 | M16: 1 | N16: 1 | O16: 1 | P16: =O16*30 -> 30 | Q16: =B16*C16*P16 -> 26490 | R16: =B16*SUM(C16:N16)*P16 -> 317880 | S16: Supervisor - Electrical | T16: ='MEP Budget-Y2'!N9 -> 1008 | U16: 2 | V16: 2 | W16: 2 | X16: 2 | Y16: 2 | Z16: 2 | AA16: 2 | AB16: 2 | AC16: 2 | AD16: 2 | AE16: 2 | AF16: 2 | AG16: 1 | AH16: =AG16*30 -> 30 | AI16: =T16*U16*AH16 -> 60480 | AJ16: =T16*SUM(U16:AF16)*AH16 -> 725760
A17: Supervisor - Mechanical | B17: ='MEP Budget-Y1'!N10 -> 883 | C17: 1 | D17: 1 | E17: 1 | F17: 1 | G17: 1 | H17: 1 | I17: 1 | J17: 1 | K17: 1 | L17: 1 | M17: 1 | N17: 1 | O17: 1 | P17: =O17*30 -> 30 | Q17: =B17*C17*P17 -> 26490 | R17: =B17*SUM(C17:N17)*P17 -> 317880 | S17: Supervisor - Mechanical | T17: ='MEP Budget-Y2'!N10 -> 1008 | U17: 2 | V17: 2 | W17: 2 | X17: 2 | Y17: 2 | Z17: 2 | AA17: 2 | AB17: 2 | AC17: 2 | AD17: 2 | AE17: 2 | AF17: 2 | AG17: 1 | AH17: =AG17*30 -> 30 | AI17: =T17*U17*AH17 -> 60480 | AJ17: =T17*SUM(U17:AF17)*AH17 -> 725760
A18: Supervisor - Light Current | B18: ='MEP Budget-Y1'!N11 -> 883 | C18: 1 | D18: 1 | E18: 1 | F18: 1 | G18: 1 | H18: 1 | I18: 1 | J18: 1 | K18: 1 | L18: 1 | M18: 1 | N18: 1 | O18: 1 | P18: =O18*30 -> 30 | Q18: =B18*C18*P18 -> 26490 | R18: =B18*SUM(C18:N18)*P18 -> 317880 | S18: Supervisor - Light Current | T18: ='MEP Budget-Y2'!N11 -> 1008 | U18: 1 | V18: 1 | W18: 1 | X18: 1 | Y18: 1 | Z18: 1 | AA18: 1 | AB18: 1 | AC18: 1 | AD18: 1 | AE18: 1 | AF18: 1 | AG18: 1 | AH18: =AG18*30 -> 30 | AI18: =T18*U18*AH18 -> 30240 | AJ18: =T18*SUM(U18:AF18)*AH18 -> 362880
A19: Technician - Electrical | B19: ='MEP Budget-Y1'!N12 -> 500 | C19: 3 | D19: 3 | E19: 3 | F19: 3 | G19: 3 | H19: 3 | I19: 3 | J19: 3 | K19: 3 | L19: 3 | M19: 3 | N19: 3 | O19: 1 | P19: =O19*30 -> 30 | Q19: =B19*C19*P19 -> 45000 | R19: =B19*SUM(C19:N19)*P19 -> 540000 | S19: Technician - Electrical | T19: ='MEP Budget-Y2'!N12 -> 577 | U19: 5 | V19: 5 | W19: 5 | X19: 5 | Y19: 5 | Z19: 5 | AA19: 5 | AB19: 5 | AC19: 5 | AD19: 5 | AE19: 5 | AF19: 5 | AG19: 1 | AH19: =AG19*30 -> 30 | AI19: =T19*U19*AH19 -> 86550 | AJ19: =T19*SUM(U19:AF19)*AH19 -> 1038600
A20: Technician - Mechanical | B20: ='MEP Budget-Y1'!N13 -> 530 | C20: 1 | D20: 1 | E20: 1 | F20: 1 | G20: 1 | H20: 1 | I20: 1 | J20: 1 | K20: 1 | L20: 1 | M20: 1 | N20: 1 | O20: 1 | P20: =O20*30 -> 30 | Q20: =B20*C20*P20 -> 15900 | R20: =B20*SUM(C20:N20)*P20 -> 190800 | S20: Technician - Mechanical | T20: ='MEP Budget-Y2'!N13 -> 604 | U20: 2 | V20: 2 | W20: 2 | X20: 2 | Y20: 2 | Z20: 2 | AA20: 2 | AB20: 2 | AC20: 2 | AD20: 2 | AE20: 2 | AF20: 2 | AG20: 1 | AH20: =AG20*30 -> 30 | AI20: =T20*U20*AH20 -> 36240 | AJ20: =T20*SUM(U20:AF20)*AH20 -> 434880
A21: Technician - Pluming | B21: ='MEP Budget-Y1'!N14 -> 491 | C21: 3 | D21: 3 | E21: 3 | F21: 3 | G21: 3 | H21: 3 | I21: 3 | J21: 3 | K21: 3 | L21: 3 | M21: 3 | N21: 3 | O21: 1 | P21: =O21*30 -> 30 | Q21: =B21*C21*P21 -> 44190 | R21: =B21*SUM(C21:N21)*P21 -> 530280 | S21: Technician - Pluming | T21: ='MEP Budget-Y2'!N14 -> 567 | U21: 5 | V21: 5 | W21: 5 | X21: 5 | Y21: 5 | Z21: 5 | AA21: 5 | AB21: 5 | AC21: 5 | AD21: 5 | AE21: 5 | AF21: 5 | AG21: 1 | AH21: =AG21*30 -> 30 | AI21: =T21*U21*AH21 -> 85050 | AJ21: =T21*SUM(U21:AF21)*AH21 -> 1020600
A22: Technician - light Current | B22: ='MEP Budget-Y1'!N15 -> 545 | C22: 1 | D22: 1 | E22: 1 | F22: 1 | G22: 1 | H22: 1 | I22: 1 | J22: 1 | K22: 1 | L22: 1 | M22: 1 | N22: 1 | O22: 1 | P22: =O22*30 -> 30 | Q22: =B22*C22*P22 -> 16350 | R22: =B22*SUM(C22:N22)*P22 -> 196200 | S22: Technician - light Current | T22: ='MEP Budget-Y2'!N15 -> 621 | U22: 1 | V22: 1 | W22: 1 | X22: 1 | Y22: 1 | Z22: 1 | AA22: 1 | AB22: 1 | AC22: 1 | AD22: 1 | AE22: 1 | AF22: 1 | AG22: 1 | AH22: =AG22*30 -> 30 | AI22: =T22*U22*AH22 -> 18630 | AJ22: =T22*SUM(U22:AF22)*AH22 -> 223560
A23: CAFM - Coordinator | B23: ='MEP Budget-Y1'!N16 -> 744 | C23: 1 | D23: 1 | E23: 1 | F23: 1 | G23: 1 | H23: 1 | I23: 1 | J23: 1 | K23: 1 | L23: 1 | M23: 1 | N23: 1 | O23: 1 | P23: =O23*30 -> 30 | Q23: =B23*C23*P23 -> 22320 | R23: =B23*SUM(C23:N23)*P23 -> 267840 | S23: CAFM - Coordinator | T23: ='MEP Budget-Y2'!N16 -> 849 | U23: 1 | V23: 1 | W23: 1 | X23: 1 | Y23: 1 | Z23: 1 | AA23: 1 | AB23: 1 | AC23: 1 | AD23: 1 | AE23: 1 | AF23: 1 | AG23: 1 | AH23: =AG23*30 -> 30 | AI23: =T23*U23*AH23 -> 25470 | AJ23: =T23*SUM(U23:AF23)*AH23 -> 305640
A24: Painter | B24: ='MEP Budget-Y1'!N17 -> 514 | C24: 1 | D24: 1 | E24: 1 | F24: 1 | G24: 1 | H24: 1 | I24: 1 | J24: 1 | K24: 1 | L24: 1 | M24: 1 | N24: 1 | O24: 1 | P24: =O24*30 -> 30 | Q24: =B24*C24*P24 -> 15420 | R24: =B24*SUM(C24:N24)*P24 -> 185040 | S24: Painter | T24: ='MEP Budget-Y2'!N17 -> 587 | U24: 2 | V24: 2 | W24: 2 | X24: 2 | Y24: 2 | Z24: 2 | AA24: 2 | AB24: 2 | AC24: 2 | AD24: 2 | AE24: 2 | AF24: 2 | AG24: 1 | AH24: =AG24*30 -> 30 | AI24: =T24*U24*AH24 -> 35220 | AJ24: =T24*SUM(U24:AF24)*AH24 -> 422640
A25: Carpenter | B25: ='MEP Budget-Y1'!N18 -> 514 | C25: 1 | D25: 1 | E25: 1 | F25: 1 | G25: 1 | H25: 1 | I25: 1 | J25: 1 | K25: 1 | L25: 1 | M25: 1 | N25: 1 | O25: 1 | P25: =O25*30 -> 30 | Q25: =B25*C25*P25 -> 15420 | R25: =B25*SUM(C25:N25)*P25 -> 185040 | S25: Carpenter | T25: ='MEP Budget-Y2'!N18 -> 587 | U25: 2 | V25: 2 | W25: 2 | X25: 2 | Y25: 2 | Z25: 2 | AA25: 2 | AB25: 2 | AC25: 2 | AD25: 2 | AE25: 2 | AF25: 2 | AG25: 1 | AH25: =AG25*30 -> 30 | AI25: =T25*U25*AH25 -> 35220 | AJ25: =T25*SUM(U25:AF25)*AH25 -> 422640
... A30: Manlift | B30: ='MEP Budget-Y1'!N23 -> 3628 | C30: 1 | D30: 1 | E30: 1 | F30: 1 | G30: 1 | H30: 1 | I30: 1 | J30: 1 | K30: 1 | L30: 1 | M30: 1 | N30: 1 | O30: 1 | P30: =O30*30 -> 30 | Q30: =B30*C30*P30 -> 108840 | R30: =B30*SUM(C30:N30)*P30 -> 1306080 | S30: Manlift | T30: ='MEP Budget-Y2'!N23 -> 4140 | U30: 1 | V30: 1 | W30: 1 | X30: 1 | Y30: 1 | Z30: 1 | AA30: 1 | AB30: 1 | AC30: 1 | AD30: 1 | AE30: 1 | AF30: 1 | AG30: 1 | AH30: =AG30*30 -> 30 | AI30: =T30*U30*AH30 -> 124200 | AJ30: =T30*SUM(U30:AF30)*AH30 -> 1490400
A31: Total amount for MEP Services /year 1 | B31: =SUM(R14:R30) -> 7322040 | S31: Total amount for MEP Services /year 2 | T31: =SUM(AJ14:AJ30) -> 11566440
J32: Housekeeping & Waste Management | AB32: Housekeeping
A33: HK Supervisors | B33: ='HK & Waste Management-Y1'!N7 -> 895 | C33: 2 | D33: 2 | E33: 2 | F33: 2 | G33: 2 | H33: 2 | I33: 2 | J33: 2 | K33: 2 | L33: 2 | M33: 2 | N33: 2 | O33: 1 | P33: =O33*30 -> 30 | Q33: =B33*C33*P33 -> 53700 | R33: =B33*SUM(C33:N33)*P33 -> 644400 | S33: HK Supervisors | T33: ='HK & Waste Management-Y2'!N7 -> 955 | U33: 4 | V33: 4 | W33: 4 | X33: 4 | Y33: 4 | Z33: 4 | AA33: 4 | AB33: 4 | AC33: 4 | AD33: 4 | AE33: 4 | AF33: 4 | AG33: 1 | AH33: =AG33*30 -> 30 | AI33: =T33*U33*AH33 -> 114600 | AJ33: =T33*SUM(U33:AF33)*AH33 -> 1375200
A34: Janitors | B34: ='HK & Waste Management-Y1'!N8 -> 392 | C34: 20 | D34: 20 | E34: 20 | F34: 20 | G34: 20 | H34: 20 | I34: 20 | J34: 20 | K34: 20 | L34: 20 | M34: 20 | N34: 20 | O34: 1 | P34: =O34*30 -> 30 | Q34: =B34*C34*P34 -> 235200 | R34: =B34*SUM(C34:N34)*P34 -> 2822400 | S34: Janitors | T34: ='HK & Waste Management-Y2'!N8 -> 430 | U34: 40 | V34: 40 | W34: 40 | X34: 40 | Y34: 40 | Z34: 40 | AA34: 40 | AB34: 40 | AC34: 40 | AD34: 40 | AE34: 40 | AF34: 40 | AG34: 1 | AH34: =AG34*30 -> 30 | AI34: =T34*U34*AH34 -> 516000 | AJ34: =T34*SUM(U34:AF34)*AH34 -> 6192000
A35: Road Sweeper | B35: ='HK & Waste Management-Y1'!N9 -> 7667 | C35: 1 | D35: 1 | E35: 1 | F35: 1 | G35: 1 | H35: 1 | I35: 1 | J35: 1 | K35: 1 | L35: 1 | M35: 1 | N35: 1 | O35: 1 | P35: =O35*30 -> 30 | Q35: =B35*C35*P35 -> 230010 | R35: =B35*SUM(C35:N35)*P35 -> 2760120 | S35: Road Sweeper | T35: ='HK & Waste Management-Y2'!N9 -> 9095 | U35: 1 | V35: 1 | W35: 1 | X35: 1 | Y35: 1 | Z35: 1 | AA35: 1 | AB35: 1 | AC35: 1 | AD35: 1 | AE35: 1 | AF35: 1 | AG35: 1 | AH35: =AG35*30 -> 30 | AI35: =T35*U35*AH35 -> 272850 | AJ35: =T35*SUM(U35:AF35)*AH35 -> 3274200
A36: Waste Management (Lumpsum item per month) | B36: ='HK & Waste Management-Y1'!N10 -> 2556 | C36: 1 | D36: 1 | E36: 1 | F36: 1 | G36: 1 | H36: 1 | I36: 1 | J36: 1 | K36: 1 | L36: 1 | M36: 1 | N36: 1 | O36: 1 | P36: =O36*30 -> 30 | Q36: =B36*C36*P36 -> 76680 | R36: =B36*SUM(C36:N36)*P36 -> 920160 | S36: Waste Management | T36: ='HK & Waste Management-Y2'!N10 -> 4714 | U36: 1 | V36: 1 | W36: 1 | X36: 1 | Y36: 1 | Z36: 1 | AA36: 1 | AB36: 1 | AC36: 1 | AD36: 1 | AE36: 1 | AF36: 1 | AG36: 1 | AH36: =AG36*30 -> 30 | AI36: =T36*U36*AH36 -> 141420 | AJ36: =T36*SUM(U36:AF36)*AH36 -> 1697040
A37: Total amount for Housekeeping /year 1 | B37: =SUM(R33:R36) -> 7147080 | S37: Total amount for Housekeeping /year 2 | T37: =SUM(AJ33:AJ36) -> 12538440
J38: Pest Control | AB38: Pest Control
A39: Pest Control Supervisor | B39: ='Pest Control Y-1'!N7 -> 850 | C39: 1 | D39: 1 | E39: 1 | F39: 1 | G39: 1 | H39: 1 | I39: 1 | J39: 1 | K39: 1 | L39: 1 | M39: 1 | N39: 1 | O39: 1 | P39: =O39*30 -> 30 | Q39: =B39*C39*P39 -> 25500 | R39: =B39*SUM(C39:N39)*P39 -> 306000 | S39: Pest Control Supervisor | T39: ='Pest Control Y-2'!N7 -> 844 | U39: 1 | V39: 1 | W39: 1 | X39: 1 | Y39: 1 | Z39: 1 | AA39: 1 | AB39: 1 | AC39: 1 | AD39: 1 | AE39: 1 | AF39: 1 | AG39: 1 | AH39: =AG39*30 -> 30 | AI39: =T39*U39*AH39 -> 25320 | AJ39: =T39*SUM(U39:AF39)*AH39 -> 303840
A40: Pest Control Service (Lumpsum item per month) | B40: ='Pest Control Y-1'!N8 -> 1950 | C40: 1 | D40: 1 | E40: 1 | F40: 1 | G40: 1 | H40: 1 | I40: 1 | J40: 1 | K40: 1 | L40: 1 | M40: 1 | N40: 1 | O40: 1 | P40: =O40*30 -> 30 | Q40: =B40*C40*P40 -> 58500 | R40: =B40*SUM(C40:N40)*P40 -> 702000 | S40: Pest Control Service | T40: ='Pest Control Y-2'!N8 -> 5073 | U40: 1 | V40: 1 | W40: 1 | X40: 1 | Y40: 1 | Z40: 1 | AA40: 1 | AB40: 1 | AC40: 1 | AD40: 1 | AE40: 1 | AF40: 1 | AG40: 1 | AH40: =AG40*30 -> 30 | AI40: =T40*U40*AH40 -> 152190 | AJ40: =T40*SUM(U40:AF40)*AH40 -> 1826280
A41: Total amount for Pest Control /year 1 | B41: =SUM(R39:R40) -> 1008000 | C41: =#REF!*SUM(#REF!)*B41 -> #REF! | D41: =#REF!*SUM(#REF!)*C41 -> #REF! | E41: =#REF!*SUM(#REF!)*D41 -> #REF! | F41: =#REF!*SUM(#REF!)*E41 -> #REF! | G41: =#REF!*SUM(#REF!)*F41 -> #REF! | H41: =#REF!*SUM(#REF!)*G41 -> #REF! | I41: =#REF!*SUM(#REF!)*H41 -> #REF! | J41: =#REF!*SUM(#REF!)*I41 -> #REF! | ... M41: =#REF!*SUM(#REF!)*L41 -> #REF! | N41: =#REF!*SUM(A41:K41)*M41 -> #REF! | O41: =#REF!*SUM(A41:L41)*N41 -> #REF! | P41: =A41*SUM(B41:M41)*O41 -> #VALUE! | R41: =B41*SUM(C41:N41)*P41 -> #REF! | S41: Total amount for Pest Control /year 2 | T41: =SUM(AJ39:AJ40) -> 2130120
J42: Landscape (optional) | AB42: Landscape (optional)
A43: Landscape Manager | B43: ='Landscape Y1'!N7 -> 1958 | C43: 1 | D43: 1 | E43: 1 | F43: 1 | G43: 1 | H43: 1 | I43: 1 | J43: 1 | K43: 1 | L43: 1 | M43: 1 | N43: 1 | O43: 1 | P43: =O43*30 -> 30 | Q43: =B43*C43*P43 -> 58740 | R43: =B43*SUM(C43:N43)*P43 -> 704880 | S43: Landscape Manager | T43: ='Landscape Y2'!N7 -> 2179 | U43: 1 | V43: 1 | W43: 1 | X43: 1 | Y43: 1 | Z43: 1 | AA43: 1 | AB43: 1 | AC43: 1 | AD43: 1 | AE43: 1 | AF43: 1 | AG43: 1 | AH43: =AG43*30 -> 30 | AI43: =T43*U43*AH43 -> 65370 | AJ43: =T43*SUM(U43:AF43)*AH43 -> 784440
A44: Landscape Supervisor | B44: ='Landscape Y1'!N8 -> 1599 | C44: 2 | D44: 2 | E44: 2 | F44: 2 | G44: 2 | H44: 2 | I44: 2 | J44: 2 | K44: 2 | L44: 2 | M44: 2 | N44: 2 | O44: 1 | P44: =O44*30 -> 30 | Q44: =B44*C44*P44 -> 95940 | R44: =B44*SUM(C44:N44)*P44 -> 1151280 | S44: Landscape Supervisor | T44: ='Landscape Y2'!N8 -> 1631 | U44: 4 | V44: 4 | W44: 4 | X44: 4 | Y44: 4 | Z44: 4 | AA44: 4 | AB44: 4 | AC44: 4 | AD44: 4 | AE44: 4 | AF44: 4 | AG44: 1 | AH44: =AG44*30 -> 30 | AI44: =T44*U44*AH44 -> 195720 | AJ44: =T44*SUM(U44:AF44)*AH44 -> 2348640
A45: Gardner | B45: ='Landscape Y1'!N9 -> 526 | C45: 20 | D45: 20 | E45: 20 | F45: 20 | G45: 20 | H45: 20 | I45: 20 | J45: 20 | K45: 20 | L45: 20 | M45: 20 | N45: 20 | O45: 1 | P45: =O45*30 -> 30 | Q45: =B45*C45*P45 -> 315600 | R45: =B45*SUM(C45:N45)*P45 -> 3787200 | S45: Gardner | T45: ='Landscape Y2'!N9 -> 622 | U45: 60 | V45: 60 | W45: 60 | X45: 60 | Y45: 60 | Z45: 60 | AA45: 60 | AB45: 60 | AC45: 60 | AD45: 60 | AE45: 60 | AF45: 60 | AG45: 1 | AH45: =AG45*30 -> 30 | AI45: =T45*U45*AH45 -> 1119600 | AJ45: =T45*SUM(U45:AF45)*AH45 -> 13435200
A46: Total amount for Landscape /year 1 | B46: =SUM(R43:R45) -> 5643360 | S46: Total amount for Landscape /year 2 | T46: =SUM(AJ43:AJ45) -> 16568280
J47: Security Services | AB47: Security Services
A48: Security Manger | B48: ='Security Y1'!N7 -> 1374 | C48: 1 | D48: 1 | E48: 1 | F48: 1 | G48: 1 | H48: 1 | I48: 1 | J48: 1 | K48: 1 | L48: 1 | M48: 1 | N48: 1 | O48: 1 | P48: =O48*30 -> 30 | Q48: =B48*C48*P48 -> 41220 | R48: =B48*SUM(C48:N48)*P48 -> 494640 | S48: Security Manger | T48: ='Security Y2'!N7 -> 1456 | U48: 1 | V48: 1 | W48: 1 | X48: 1 | Y48: 1 | Z48: 1 | AA48: 1 | AB48: 1 | AC48: 1 | AD48: 1 | AE48: 1 | AF48: 1 | AG48: 1 | AH48: =AG48*30 -> 30 | AI48: =T48*U48*AH48 -> 43680 | AJ48: =T48*SUM(U48:AF48)*AH48 -> 524160
A49: Safety Supervisor / Agent | B49: ='Security Y1'!N8 -> 916 | C49: 2 | D49: 2 | E49: 2 | F49: 2 | G49: 2 | H49: 2 | I49: 2 | J49: 2 | K49: 2 | L49: 2 | M49: 2 | N49: 2 | O49: 2 | P49: =O49*30 -> 60 | Q49: =B49*C49*P49 -> 109920 | R49: =B49*SUM(C49:N49)*P49 -> 1319040 | S49: Safety Supervisor / Agent | T49: ='Security Y2'!N8 -> 971 | U49: 4 | V49: 4 | W49: 4 | X49: 4 | Y49: 4 | Z49: 4 | AA49: 4 | AB49: 4 | AC49: 4 | AD49: 4 | AE49: 4 | AF49: 4 | AG49: 2 | AH49: =AG49*30 -> 60 | AI49: =T49*U49*AH49 -> 233040 | AJ49: =T49*SUM(U49:AF49)*AH49 -> 2796480
A50: Security Supervisor / per shift | B50: ='Security Y1'!N9 -> 620 | C50: 1 | D50: 1 | E50: 1 | F50: 1 | G50: 1 | H50: 1 | I50: 1 | J50: 1 | K50: 1 | L50: 1 | M50: 1 | N50: 1 | O50: 2 | P50: =O50*30 -> 60 | Q50: =B50*C50*P50 -> 37200 | R50: =B50*SUM(C50:N50)*P50 -> 446400 | S50: Security Supervisor / per shift | T50: ='Security Y2'!N9 -> 656 | U50: 1 | V50: 1 | W50: 1 | X50: 1 | Y50: 1 | Z50: 1 | AA50: 1 | AB50: 1 | AC50: 1 | AD50: 1 | AE50: 1 | AF50: 1 | AG50: 2 | AH50: =AG50*30 -> 60 | AI50: =T50*U50*AH50 -> 39360 | AJ50: =T50*SUM(U50:AF50)*AH50 -> 472320
A51: Security Guards / per shift | B51: ='Security Y1'!N10 -> 344 | C51: 40 | D51: 40 | E51: 40 | F51: 40 | G51: 40 | H51: 40 | I51: 40 | J51: 40 | K51: 40 | L51: 40 | M51: 40 | N51: 40 | O51: 2 | P51: =O51*30 -> 60 | Q51: =B51*C51*P51 -> 825600 | R51: =B51*SUM(C51:N51)*P51 -> 9907200 | S51: Security Guards / per shift | T51: ='Security Y2'!N10 -> 364 | U51: 120 | V51: 120 | W51: 120 | X51: 120 | Y51: 120 | Z51: 120 | AA51: 120 | AB51: 120 | AC51: 120 | AD51: 120 | AE51: 120 | AF51: 120 | AG51: 2 | AH51: =AG51*30 -> 60 | AI51: =T51*U51*AH51 -> 2620800 | AJ51: =T51*SUM(U51:AF51)*AH51 -> 31449600
A52: CCTV Operator | O52: 0 | P52: =O52*30 -> 0 | Q52: =B52*C52*P52 -> 0 | R52: =B52*SUM(C52:N52)*P52 -> 0 | S52: CCTV Operator | T52: ='Security Y2'!N11 -> 647 | U52: 2 | V52: 2 | W52: 2 | X52: 2 | Y52: 2 | Z52: 2 | AA52: 2 | AB52: 2 | AC52: 2 | AD52: 2 | AE52: 2 | AF52: 2 | AG52: 2 | AH52: =AG52*30 -> 60 | AI52: =T52*U52*AH52 -> 77640 | AJ52: =T52*SUM(U52:AF52)*AH52 -> 931680
A53: Total amount for Security Services /year 1 | B53: =SUM(R48:R52) -> 12167280 | S53: Total amount for Security Services /year 2 | T53: =SUM(AJ48:AJ52) -> 36174240
J54: Transportation | AB54: Transportation
A55: Pickup Double Cabinet (1 security + 1 MEP) | B55: ='Transportation Y1'!N7 -> 2002 | C55: 2 | D55: 2 | E55: 2 | F55: 2 | G55: 2 | H55: 2 | I55: 2 | J55: 2 | K55: 2 | L55: 2 | M55: 2 | N55: 2 | O55: 1 | P55: =O55*30 -> 30 | Q55: =B55*C55*P55 -> 120120 | R55: =B55*SUM(C55:N55)*P55 -> 1441440 | S55: Pickup Double Cabinet (1 security + 1 MEP) | T55: ='Transportation Y2'!N7 -> 2249 | U55: 2 | V55: 2 | W55: 2 | X55: 2 | Y55: 2 | Z55: 2 | AA55: 2 | AB55: 2 | AC55: 2 | AD55: 2 | AE55: 2 | AF55: 2 | AG55: 1 | AH55: =AG55*30 -> 30 | AI55: =T55*U55*AH55 -> 134940 | AJ55: =T55*SUM(U55:AF55)*AH55 -> 1619280
A56: Golf Car | B56: ='Transportation Y1'!N8 -> 2310 | C56: 2 | D56: 2 | E56: 2 | F56: 2 | G56: 2 | H56: 2 | I56: 2 | J56: 2 | K56: 2 | L56: 2 | M56: 2 | N56: 2 | O56: 1 | P56: =O56*30 -> 30 | Q56: =B56*C56*P56 -> 138600 | R56: =B56*SUM(C56:N56)*P56 -> 1663200 | S56: Golf Car | T56: ='Transportation Y2'!N8 -> 2595 | U56: 2 | V56: 2 | W56: 2 | X56: 2 | Y56: 2 | Z56: 2 | AA56: 2 | AB56: 2 | AC56: 2 | AD56: 2 | AE56: 2 | AF56: 2 | AG56: 1 | AH56: =AG56*30 -> 30 | AI56: =T56*U56*AH56 -> 155700 | AJ56: =T56*SUM(U56:AF56)*AH56 -> 1868400
A57: Security Patrol Motorcycles / Tricycles | B57: ='Transportation Y1'!N9 -> 507 | C57: 2 | D57: 2 | E57: 2 | F57: 2 | G57: 2 | H57: 2 | I57: 2 | J57: 2 | K57: 2 | L57: 2 | M57: 2 | N57: 2 | O57: 1 | P57: =O57*30 -> 30 | Q57: =B57*C57*P57 -> 30420 | R57: =B57*SUM(C57:N57)*P57 -> 365040 | S57: Security Patrol Motorcycles / Tricycles | T57: ='Transportation Y2'!N9 -> 570 | U57: 2 | V57: 2 | W57: 2 | X57: 2 | Y57: 2 | Z57: 2 | AA57: 2 | AB57: 2 | AC57: 2 | AD57: 2 | AE57: 2 | AF57: 2 | AG57: 1 | AH57: =AG57*30 -> 30 | AI57: =T57*U57*AH57 -> 34200 | AJ57: =T57*SUM(U57:AF57)*AH57 -> 410400
A58: Total amount for Transportation /year 1 | B58: =SUM(R55:R57) -> 3469680 | S58: Total amount for Transportation /year 2 | T58: =SUM(AJ55:AJ57) -> 3898080
A59: FM Fees amount/ year 1 | B59: =B12+B31+B37+B41+B46+B53+B58 -> 38337316 | S59: FM Fees amount/ year 2 | T59: =T12+T31+T37+T41+T46+T53+T58 -> 82875600
A60: FM Fees Year 1 + Year 2 | B60: =B59+T59 -> 121212916

Sheet Fianl All
B1: 1) Security Budget Scenarios
B2: Security Manpower | D2: Rate | E2: Qty | F2: Shift/Month | G2: Monthly | I2: Rate | J2: Qty | K2: Shift/Month | L2: Monthly | N2: Rate | O2: Qty | P2: Shift/Month | Q2: Monthly
B3: Security Manger | D3: 1374 | E3: 1 | F3: 30 | G3: =F3*E3*D3 -> 41220 | I3: 1456 | J3: 1 | K3: 30 | L3: =I3*F3*E3 -> 43680 | N3: 1456 | O3: 1 | P3: 30 | Q3: =P3*O3*N3 -> 43680
B4: Safety Supervisor / Agent | D4: 916 | E4: 4 | F4: 30 | G4: =F4*E4*D4 -> 109920 | I4: 971 | J4: 4 | K4: 30 | L4: =I4*F4*E4 -> 116520 | N4: 971 | O4: 8 | P4: 30 | Q4: =P4*O4*N4 -> 233040
B5: Security Supervisor / per shift | D5: 620 | E5: 2 | F5: 30 | G5: =F5*E5*D5 -> 37200 | I5: 656 | J5: 2 | K5: 30 | L5: =I5*F5*E5 -> 39360 | N5: 656 | O5: 2 | P5: 30 | Q5: =P5*O5*N5 -> 39360
B6: Security Guards / per shift | D6: 344 | E6: 80 | F6: 30 | G6: =F6*E6*D6 -> 825600 | I6: 364 | J6: 80 | K6: 30 | L6: =I6*F6*E6 -> 873600 | N6: 364 | O6: 240 | P6: 30 | Q6: =P6*O6*N6 -> 2620800
B7: CCTV Operator | D7: 0 | E7: 0 | F7: 0 | G7: =F7*E7*D7 -> 0 | I7: 647 | J7: 0 | K7: 0 | L7: =I7*F7*E7 -> 0 | N7: 647 | O7: 4 | P7: 30 | Q7: =P7*O7*N7 -> 77640
B8: Total | D8: =Table1511[[#Totals],[Monthly]]/Table1511[[#Totals],[Qty]] -> 11654.483 | E8: =SUBTOTAL(109,Table1511[Qty]) -> 87 | G8: =SUBTOTAL(109,Table1511[Monthly]) -> 1013940 | I8: =Table2612[[#Totals],[Monthly]]/Table2612[[#Totals],[Qty]] -> 12335.172 | J8: =SUBTOTAL(109,Table2612[Qty]) -> 87 | L8: =SUBTOTAL(109,Table2612[Monthly]) -> 1073160 | N8: =Table3713[[#Totals],[Monthly]]/Table3713[[#Totals],[Qty]] -> 11821.647 | O8: =SUBTOTAL(109,Table3713[Qty]) -> 255 | Q8: =SUBTOTAL(109,Table3713[Monthly]) -> 3014520
B10: Transportation | D10: Rate | E10: Qty | F10: Shift/Month | G10: Monthly | I10: Rate | J10: Qty | K10: Shift/Month | L10: Monthly | N10: Rate | O10: Qty | P10: Shift/Month | Q10: Monthly
B11: Pickup Double Cabinet (1 security ) | D11: 2002 | E11: 0 | F11: 30 | G11: =D11*E11*F11 -> 0 | I11: 2249 | J11: 0 | K11: 30 | L11: =I11*J11*K11 -> 0 | N11: 2249 | O11: 0 | P11: 30 | Q11: =N11*O11*P11 -> 0
B12: Golf Car | D12: 2310 | E12: 1 | F12: 30 | G12: =D12*E12*F12 -> 69300 | I12: 2595 | J12: 1 | K12: 30 | L12: =I12*J12*K12 -> 77850 | N12: 2595 | O12: 1 | P12: 30 | Q12: =N12*O12*P12 -> 77850
B13: Security Patrol Motorcycles / Tricycles | D13: 507 | E13: 2 | F13: 30 | G13: =D13*E13*F13 -> 30420 | I13: 570 | J13: 2 | K13: 30 | L13: =I13*J13*K13 -> 34200 | N13: 570 | O13: 2 | P13: 30 | Q13: =N13*O13*P13 -> 34200
B14: Total | G14: =SUBTOTAL(109,Table15[Monthly]) -> 99720 | L14: =SUBTOTAL(109,Table16[Monthly]) -> 112050 | Q14: =SUBTOTAL(109,Table17[Monthly]) -> 112050
B16: Total Revenue | D16: =G16/Table1511[[#Totals],[Qty]] -> 12800.69 | G16: =Table15[[#Totals],[Monthly]]+Table1511[[#Totals],[Monthly]] -> 1113660 | I16: =L16/Table2612[[#Totals],[Qty]] -> 13623.103 | L16: =Table16[[#Totals],[Monthly]]+Table2612[[#Totals],[Monthly]] -> 1185210 | N16: =Q16/Table3713[[#Totals],[Qty]] -> 12261.059 | Q16: =Table17[[#Totals],[Monthly]]+Table3713[[#Totals],[Monthly]] -> 3126570
B18: Security Manpower | D18: Rate | E18: Qty | F18: Shift/Month | G18: Monthly | I18: Rate | J18: Qty | K18: Shift/Month | L18: Monthly | N18: Rate | O18: Qty | P18: Shift/Month | Q18: Monthly
B19: Security Manger | D19: 29000 | E19: 1 | F19: 30 | G19: ='Fianl All'!$D19*'Fianl All'!$E19 -> 29000 | I19: 29000 | J19: 1 | K19: 30 | L19: ='Fianl All'!$I19*'Fianl All'!$J19 -> 29000 | N19: 29000 | O19: 1 | P19: 30 | Q19: ='Fianl All'!$N19*'Fianl All'!$O19 -> 29000 | S19: =('Fianl All'!$D19/30)*(16/12) -> 1288.8889 | T19: =S19*'Fianl All'!$E19 -> 1288.8889 | U19: =('Fianl All'!$I19/30)*(16/12) -> 1288.8889 | V19: =U19*'Fianl All'!$J19 -> 1288.8889 | W19: =('Fianl All'!$N19/30)*(16/12) -> 1288.8889 | X19: =W19*'Fianl All'!$O19 -> 1288.8889
B20: Safety Supervisor / Agent | D20: 14000 | E20: 5 | F20: 30 | G20: ='Fianl All'!$D20*'Fianl All'!$E20 -> 70000 | I20: 14000 | J20: 5 | K20: 30 | L20: ='Fianl All'!$I20*'Fianl All'!$J20 -> 70000 | N20: 14000 | O20: 9 | P20: 30 | Q20: ='Fianl All'!$N20*'Fianl All'!$O20 -> 126000 | S20: =('Fianl All'!$D20/30)*(16/12) -> 622.22222 | T20: =S20*'Fianl All'!$E20 -> 3111.1111 | U20: =('Fianl All'!$I20/30)*(16/12) -> 622.22222 | V20: =U20*'Fianl All'!$J20 -> 3111.1111 | W20: =('Fianl All'!$N20/30)*(16/12) -> 622.22222 | X20: =W20*'Fianl All'!$O20 -> 5600
B21: Security Supervisor / per shift | D21: 9000 | E21: 3 | F21: 30 | G21: ='Fianl All'!$D21*'Fianl All'!$E21 -> 27000 | I21: 9500 | J21: 3 | K21: 30 | L21: ='Fianl All'!$I21*'Fianl All'!$J21 -> 28500 | N21: 9500 | O21: 3 | P21: 30 | Q21: ='Fianl All'!$N21*'Fianl All'!$O21 -> 28500 | S21: =('Fianl All'!$D21/30)*(16/12) -> 400 | T21: =S21*'Fianl All'!$E21 -> 1200 | U21: =('Fianl All'!$I21/30)*(16/12) -> 422.22222 | V21: =U21*'Fianl All'!$J21 -> 1266.6667 | W21: =('Fianl All'!$N21/30)*(16/12) -> 422.22222 | X21: =W21*'Fianl All'!$O21 -> 1266.6667
B22: Security Guards / per shift | D22: 7000 | E22: 96 | F22: 30 | G22: ='Fianl All'!$D22*'Fianl All'!$E22 -> 672000 | I22: 8000 | J22: 96 | K22: 30 | L22: ='Fianl All'!$I22*'Fianl All'!$J22 -> 768000 | N22: 8200 | O22: 288 | P22: 30 | Q22: ='Fianl All'!$N22*'Fianl All'!$O22 -> 2361600 | S22: =('Fianl All'!$D22/30)*(16/12) -> 311.11111 | T22: =S22*'Fianl All'!$E22 -> 29866.667 | U22: =('Fianl All'!$I22/30)*(16/12) -> 355.55556 | V22: =U22*'Fianl All'!$J22 -> 34133.333 | W22: =('Fianl All'!$N22/30)*(16/12) -> 364.44444 | X22: =W22*'Fianl All'!$O22 -> 104960
B23: CCTV Operator | D23: 8000 | E23: 0 | F23: 0 | G23: ='Fianl All'!$D23*'Fianl All'!$E23 -> 0 | I23: 9000 | J23: 0 | K23: 0 | L23: ='Fianl All'!$I23*'Fianl All'!$J23 -> 0 | N23: 9000 | O23: 0 | P23: 0 | Q23: ='Fianl All'!$N23*'Fianl All'!$O23 -> 0
B24: Eid Vacation Allowance | D24: =T24 -> 35466.667 | E24: 1 | F24: 30 | G24: ='Fianl All'!$D24*'Fianl All'!$E24 -> 35466.667 | I24: =V24 -> 39800 | J24: 1 | K24: 30 | L24: ='Fianl All'!$I24*'Fianl All'!$J24 -> 39800 | N24: =X24 -> 113115.56 | O24: 1 | P24: 0 | Q24: ='Fianl All'!$N24*'Fianl All'!$O24 -> 113115.56 | S24: =SUM(S19:S23) -> 2622.2222 | T24: =SUM(T19:T23) -> 35466.667 | U24: =SUM(U19:U23) -> 2688.8889 | V24: =SUM(V19:V23) -> 39800 | W24: =SUM(W19:W23) -> 2697.7778 | X24: =SUM(X19:X23) -> 113115.56
B25: Total | D25: ='Fianl All'!$G$25/'Fianl All'!$E$25 -> 8907.619 | E25: =SUBTOTAL(109,'Fianl All'!$E$19:$E$23) -> 105 | F25: ='Fianl All'!$G$25/G16 -> 0.8398434 | G25: =SUBTOTAL(109,'Fianl All'!$L$19:$L$24) -> 935300 | I25: ='Fianl All'!$L$25/'Fianl All'!$J$25 -> 8907.619 | J25: =SUBTOTAL(109,'Fianl All'!$J$19:$J$23) -> 105 | K25: ='Fianl All'!$L$25/L16 -> 0.78914285 | L25: =SUBTOTAL(109,'Fianl All'!$L$19:$L$24) -> 935300 | N25: ='Fianl All'!$Q$25/'Fianl All'!$O$25 -> 8831.2809 | O25: =SUBTOTAL(109,'Fianl All'!$O$19:$O$23) -> 301 | P25: ='Fianl All'!$Q$25/Q16 -> 0.85020184 | Q25: =SUM(Q19:Q24) -> 2658215.6
B27: Security Tools&Consumabls&uniform | D27: Rate | E27: Qty | F27: . | G27: Monthly | I27: Rate | J27: Qty | K27: . | L27: Monthly | N27: Rate | O27: Qty | P27: . | Q27: Monthly
B28: Depreciation tools | D28: 2750 | E28: 1 | G28: =D28*E28 -> 2750 | I28: =Table23[[#This Row],[Rate]] -> 2750 | J28: 1 | K28: 0 | L28: =I28*J28 -> 2750 | N28: =Table23[[#This Row],[Rate]] -> 2750 | O28: 3 | P28: 0 | Q28: =N28*O28 -> 8250
B29: Consumtion documentation | D29: 10000 | E29: 1 | G29: =D29*E29 -> 10000 | I29: =Table23[[#This Row],[Rate]] -> 10000 | J29: 1 | K29: 0 | L29: =I29*J29 -> 10000 | N29: =Table23[[#This Row],[Rate]] -> 10000 | O29: 3 | P29: 0 | Q29: =N29*O29 -> 30000
B30: Depreciation uniform | D30: 600 | E30: ='Fianl All'!$E$25-E19 -> 104 | G30: =D30*E30 -> 62400 | I30: =Table23[[#This Row],[Rate]] -> 600 | J30: ='Fianl All'!$J$25-J19 -> 104 | K30: 0 | L30: =I30*J30 -> 62400 | N30: =Table23[[#This Row],[Rate]] -> 600 | O30: ='Fianl All'!$O$25-O19 -> 300 | P30: 0 | Q30: =N30*O30 -> 180000
B31: Total | F31: =Table23[[#Totals],[Monthly]]/G16 -> 0.0674802 | G31: =SUBTOTAL(109,Table24[Monthly]) -> 75150 | K31: =Table24[[#Totals],[Monthly]]/L16 -> 0.063406485 | L31: =SUBTOTAL(109,Table24[Monthly]) -> 75150 | P31: =Table25[[#Totals],[Monthly]]/Q16 -> 0.06980493 | Q31: =SUBTOTAL(109,Table25[Monthly]) -> 218250
B33: ICT & Others | D33: Rate | E33: Qty | F33: . | G33: Monthly | I33: Rate | J33: Qty | K33: . | L33: Monthly | N33: Rate | O33: Qty | P33: . | Q33: Monthly
B34: Software Account | D34: 8000 | E34: 1 | F34: 0 | G34: =D34*E34 -> 8000 | I34: =D34 -> 8000 | J34: 1 | L34: =I34*J34 -> 8000 | N34: =D34 -> 8000 | O34: 1 | Q34: =N34*O34 -> 8000 | T34: =D19/30 -> 966.66667
B35: Depreciation ICT | D35: 2500 | E35: 1 | F35: 0 | G35: =D35*E35 -> 2500 | I35: =D35 -> 2500 | J35: 1 | L35: =I35*J35 -> 2500 | N35: =D35 -> 2500 | O35: 2 | Q35: =N35*O35 -> 5000 | T35: =T34*16 -> 15466.667
B36: Arab Fees | D36: 16250 | E36: 1 | F36: 0 | G36: =D36*E36 -> 16250 | I36: =D36 -> 16250 | J36: 1 | L36: =I36*J36 -> 16250 | N36: =D36 -> 16250 | O36: 1.5 | Q36: =N36*O36 -> 24375 | T36: =T35/12 -> 1288.8889
B37: Over Head | D37: 30000 | E37: 1 | F37: 0 | G37: =D37*E37 -> 30000 | I37: =D37 -> 30000 | J37: 1 | L37: =I37*J37 -> 30000 | N37: =D37 -> 30000 | O37: 1.5 | Q37: =N37*O37 -> 45000
B38: Meals | D38: =30*30 -> 900 | E38: =Table1511[[#Totals],[Qty]] -> 87 | F38: 0 | G38: =D38*E38 -> 78300 | I38: =D38 -> 900 | J38: =Table2612[[#Totals],[Qty]] -> 87 | L38: =I38*J38 -> 78300 | N38: =D38 -> 900 | O38: =Table3713[[#Totals],[Qty]] -> 255 | Q38: =N38*O38 -> 229500
B39: Ramadan Meals (140-30)=110 Per Meals | D39: =110*30 -> 3300 | E39: =Table1511[[#Totals],[Qty]] -> 87 | G39: =(D39*E39)/12 -> 23925 | I39: =D39 -> 3300 | J39: =Table2612[[#Totals],[Qty]] -> 87 | L39: =(I39*J39)/12 -> 23925 | N39: =D39 -> 3300 | O39: =Table3713[[#Totals],[Qty]] -> 255 | Q39: =(N39*O39)/12 -> 70125
B40: Total | F40: =G40/G16 -> 0.12126681 | G40: =SUM(G34:G38) -> 135050 | K40: =L40/L16 -> 0.11394605 | L40: =SUM(L34:L38) -> 135050 | P40: =Q40/Q16 -> 0.099749886 | Q40: =SUM(Q34:Q38) -> 311875
B42: Accoumedation | D42: Rate | E42: Qty | F42: . | G42: Monthly | I42: Rate | J42: Qty | K42: . | L42: Monthly | N42: Rate | O42: Qty | P42: . | Q42: Monthly
B43: Rent Appartment | D43: 10000 | E43: 5 | F43: 0 | G43: =Table29[[#This Row],[Rate]]*Table29[[#This Row],[Qty]] -> 50000 | I43: =Table29[[#This Row],[Rate]] -> 10000 | J43: 5 | K43: 0 | L43: =Table2931[[#This Row],[Rate]]*Table2931[[#This Row],[Qty]] -> 50000 | N43: =Table29[[#This Row],[Rate]] -> 10000 | O43: 12 | P43: 0 | Q43: =Table2932[[#This Row],[Rate]]*Table2932[[#This Row],[Qty]] -> 120000
B44: Elec,Water,,, | D44: 1000 | E44: 5 | F44: 0 | G44: =Table29[[#This Row],[Rate]]*Table29[[#This Row],[Qty]] -> 5000 | I44: =Table29[[#This Row],[Rate]] -> 1000 | J44: 5 | K44: 0 | L44: =Table2931[[#This Row],[Rate]]*Table2931[[#This Row],[Qty]] -> 5000 | N44: =Table29[[#This Row],[Rate]] -> 1000 | O44: 12 | P44: 0 | Q44: =Table2932[[#This Row],[Rate]]*Table2932[[#This Row],[Qty]] -> 12000
B45: Depreciataion Furniture | D45: 10000 | E45: 1 | F45: 0 | G45: =Table29[[#This Row],[Rate]]*Table29[[#This Row],[Qty]] -> 10000 | I45: =Table29[[#This Row],[Rate]] -> 10000 | J45: 1 | K45: 0 | L45: =Table2931[[#This Row],[Rate]]*Table2931[[#This Row],[Qty]] -> 10000 | N45: =Table29[[#This Row],[Rate]] -> 10000 | O45: 4 | P45: 0 | Q45: =Table2932[[#This Row],[Rate]]*Table2932[[#This Row],[Qty]] -> 40000
B46: Total | F46: =Table29[[#Totals],[Monthly]]/G16 -> 0.058366108 | G46: =SUBTOTAL(109,Table29[Monthly]) -> 65000 | K46: =Table2931[[#Totals],[Monthly]]/L16 -> 0.054842602 | L46: =SUBTOTAL(109,Table2931[Monthly]) -> 65000 | P46: =Table2932[[#Totals],[Monthly]]/Q16 -> 0.055012362 | Q46: =SUBTOTAL(109,Table2932[Monthly]) -> 172000
B48: Transportation | D48: Rate | E48: Qty | F48: . | G48: Monthly | I48: Rate | J48: Qty | K48: . | L48: Monthly | N48: Rate | O48: Qty | P48: . | Q48: Monthly
B49: buss Depreciation | D49: 12000 | E49: 1 | F49: 0 | G49: =Table2934[[#This Row],[Rate]]*Table2934[[#This Row],[Qty]] -> 12000 | I49: =Table2934[[#This Row],[Rate]] -> 12000 | J49: 1 | K49: 0 | L49: =Table293435[[#This Row],[Rate]]*Table293435[[#This Row],[Qty]] -> 12000 | N49: =Table2934[[#This Row],[Rate]] -> 12000 | O49: 1 | P49: 0 | Q49: =Table293436[[#This Row],[Rate]]*Table293436[[#This Row],[Qty]] -> 12000
B50: Driver | D50: 12500 | E50: 1 | F50: 0 | G50: =Table2934[[#This Row],[Rate]]*Table2934[[#This Row],[Qty]] -> 12500 | I50: =Table2934[[#This Row],[Rate]] -> 12500 | J50: 1.1 | K50: 0 | L50: =Table293435[[#This Row],[Rate]]*Table293435[[#This Row],[Qty]] -> 13750 | N50: =Table2934[[#This Row],[Rate]] -> 12500 | O50: 1.15 | P50: 0 | Q50: =Table293436[[#This Row],[Rate]]*Table293436[[#This Row],[Qty]] -> 14375
B51: Jeep | D51: 45000 | E51: 1 | F51: 0 | G51: =Table2934[[#This Row],[Rate]]*Table2934[[#This Row],[Qty]] -> 45000 | I51: =Table2934[[#This Row],[Rate]] -> 45000 | J51: 1 | K51: 0 | L51: =Table293435[[#This Row],[Rate]]*Table293435[[#This Row],[Qty]] -> 45000 | N51: =Table2934[[#This Row],[Rate]] -> 45000 | O51: 1 | P51: 0 | Q51: =Table293436[[#This Row],[Rate]]*Table293436[[#This Row],[Qty]] -> 45000
B52: Scooter | D52: 3000 | E52: 2 | F52: 0 | G52: =Table2934[[#This Row],[Rate]]*Table2934[[#This Row],[Qty]] -> 6000 | I52: =Table2934[[#This Row],[Rate]] -> 3000 | J52: 2 | K52: 0 | L52: =Table293435[[#This Row],[Rate]]*Table293435[[#This Row],[Qty]] -> 6000 | N52: =Table2934[[#This Row],[Rate]] -> 3000 | O52: 2 | P52: 0 | Q52: =Table293436[[#This Row],[Rate]]*Table293436[[#This Row],[Qty]] -> 6000
B53: Gas, Oil , maintenance | D53: 9500 | E53: 1 | F53: 0 | G53: =Table2934[[#This Row],[Rate]]*Table2934[[#This Row],[Qty]] -> 9500 | I53: =Table2934[[#This Row],[Rate]] -> 9500 | J53: 1.25 | K53: 0 | L53: =Table293435[[#This Row],[Rate]]*Table293435[[#This Row],[Qty]] -> 11875 | N53: =Table2934[[#This Row],[Rate]] -> 9500 | O53: 4 | P53: 0 | Q53: =Table293436[[#This Row],[Rate]]*Table293436[[#This Row],[Qty]] -> 38000
B54: Total | F54: =Table2934[[#Totals],[Monthly]]/G16 -> 0.076324911 | G54: =SUBTOTAL(109,Table2934[Monthly]) -> 85000 | K54: =Table293435[[#Totals],[Monthly]]/L16 -> 0.074775778 | L54: =SUBTOTAL(109,Table293435[Monthly]) -> 88625 | P54: =Table293436[[#Totals],[Monthly]]/Q16 -> 0.036901461 | Q54: =SUBTOTAL(109,Table293436[Monthly]) -> 115375
B56: Total Cost | G56: =Table2934[[#Totals],[Monthly]]+Table29[[#Totals],[Monthly]]+G40+Table23[[#Totals],[Monthly]]+'Fianl All'!$G$25 -> 1295500 | L56: =Table293435[[#Totals],[Monthly]]+Table2931[[#Totals],[Monthly]]+L40+Table24[[#Totals],[Monthly]]+'Fianl All'!$L$25 -> 1299125 | Q56: =Table293436[[#Totals],[Monthly]]+Table2932[[#Totals],[Monthly]]+Q40+Table25[[#Totals],[Monthly]]+'Fianl All'!$Q$25 -> 3475715.6
B58: Total Revenue | G58: =Table15[[#Totals],[Monthly]]+Table1511[[#Totals],[Monthly]] -> 1113660 | L58: =Table16[[#Totals],[Monthly]]+Table2612[[#Totals],[Monthly]] -> 1185210 | Q58: =Table17[[#Totals],[Monthly]]+Table3713[[#Totals],[Monthly]] -> 3126570
B60: Contracting Insurance | D60: 0.09 | E60: -1 | G60: =E60*D60*G58 -> -100229.4 | I60: =D60 -> 0.09 | J60: -1 | L60: =J60*I60*L58 -> -106668.9 | N60: 0.09 | O60: -1 | Q60: =O60*N60*Q58 -> -281391.3
B62: GM | G62: =G58-G56+G60 -> -282069.4 | L62: =L58-L56+L60 -> -220583.9 | Q62: =Q58-Q56+Q60 -> -630536.86
B64: GM % | G64: =G62/G58 -> -0.25328143 | L64: =L62/L58 -> -0.18611377 | Q64: =Q62/Q58 -> -0.20167047
B67: 2) Housekeeping Budget Scenarios
B68: Housekeeping Manpower | D68: Rate | E68: Qty | F68: Shift/Month | G68: Monthly | I68: Rate | J68: Qty | K68: Shift/Month | L68: Monthly | N68: Rate | O68: Qty | P68: Shift/Month | Q68: Monthly
B69: HK Supervisors | D69: 895 | E69: 2 | F69: 30 | G69: =F69*E69*D69 -> 53700 | I69: 955 | J69: 2 | K69: 30 | L69: =I69*F69*E69 -> 57300 | N69: 955 | O69: 4 | P69: 30 | Q69: =P69*O69*N69 -> 114600
B70: Janitors | D70: 392 | E70: 20 | F70: 30 | G70: =F70*E70*D70 -> 235200 | I70: 430 | J70: 20 | K70: 30 | L70: =I70*F70*E70 -> 258000 | N70: 430 | O70: 40 | P70: 30 | Q70: =P70*O70*N70 -> 516000
B71: Road Sweeper | D71: 7667 | E71: 0 | F71: 30 | G71: =F71*E71*D71 -> 0 | I71: 9095 | J71: 1 | K71: 30 | L71: =I71*F71*E71 -> 0 | N71: 9095 | O71: 1 | P71: 30 | Q71: =P71*O71*N71 -> 272850
B72: Waste Management (Lumpsum item per month) | D72: 2556 | E72: 1 | F72: 30 | G72: =F72*E72*D72 -> 76680 | I72: 4714 | J72: 1 | K72: 30 | L72: =I72*F72*E72 -> 141420 | N72: 4714 | O72: 1 | P72: 30 | Q72: =P72*O72*N72 -> 141420
B74: Total | D74: =Table15115[[#Totals],[Monthly]]/Table15115[[#Totals],[Qty]] -> 15894.783 | E74: =SUBTOTAL(109,Table15115[Qty]) -> 23 | G74: =SUBTOTAL(109,Table15115[Monthly]) -> 365580 | I74: =Table26126[[#Totals],[Monthly]]/Table26126[[#Totals],[Qty]] -> 19030 | J74: =SUBTOTAL(109,Table26126[Qty]) -> 24 | L74: =SUBTOTAL(109,Table26126[Monthly]) -> 456720 | N74: =Table37137[[#Totals],[Monthly]]/Table37137[[#Totals],[Qty]] -> 22714.565 | O74: =SUBTOTAL(109,Table37137[Qty]) -> 46 | Q74: =SUBTOTAL(109,Table37137[Monthly]) -> 1044870
B76: Transportation | D76: Rate | E76: Qty | F76: Shift/Month | G76: Monthly | I76: Rate | J76: Qty | K76: Shift/Month | L76: Monthly | N76: Rate | O76: Qty | P76: Shift/Month | Q76: Monthly
B77: Pickup Double Cabinet (1 HK ) | D77: 2002 | E77: 1 | F77: 30 | G77: =D77*E77*F77 -> 60060 | I77: 2249 | J77: 1 | K77: 30 | L77: =I77*J77*K77 -> 67470 | N77: 2249 | O77: 1 | P77: 30 | Q77: =N77*O77*P77 -> 67470
B78: Golf Car | D78: 2310 | E78: 0 | F78: 30 | G78: =D78*E78*F78 -> 0 | I78: 2595 | J78: 0 | K78: 30 | L78: =I78*J78*K78 -> 0 | N78: 2595 | O78: 0 | P78: 30 | Q78: =N78*O78*P78 -> 0
B79: Security Patrol Motorcycles / Tricycles | D79: 507 | E79: 0 | F79: 30 | G79: =D79*E79*F79 -> 0 | I79: 570 | J79: 0 | K79: 30 | L79: =I79*J79*K79 -> 0 | N79: 570 | O79: 0 | P79: 30 | Q79: =N79*O79*P79 -> 0
B80: Total | G80: =SUBTOTAL(109,Table1510[Monthly]) -> 60060 | L80: =SUBTOTAL(109,Table1628[Monthly]) -> 67470 | Q80: =SUBTOTAL(109,Table1737[Monthly]) -> 67470
B82: Total Revenue | D82: =G82/Table15115[[#Totals],[Qty]] -> 18506.087 | G82: =Table1510[[#Totals],[Monthly]]+Table15115[[#Totals],[Monthly]] -> 425640 | I82: =L82/Table26126[[#Totals],[Qty]] -> 21841.25 | L82: =Table1628[[#Totals],[Monthly]]+Table26126[[#Totals],[Monthly]] -> 524190 | N82: =Q82/Table37137[[#Totals],[Qty]] -> 24181.304 | Q82: =Table1737[[#Totals],[Monthly]]+Table37137[[#Totals],[Monthly]] -> 1112340
B84: Housekeeping Manpower | D84: Rate | E84: Qty | F84: Shift/Month | G84: Monthly | I84: Rate | J84: Qty | K84: Shift/Month | L84: Monthly | N84: Rate | O84: Qty | P84: Shift/Month | Q84: Monthly
B85: =B69 -> HK Supervisors | D85: 10000 | E85: =E69 -> 2 | F85: 30 | G85: ='Fianl All'!$D85*'Fianl All'!$E85 -> 20000 | I85: 11000 | J85: =J69 -> 2 | K85: 30 | L85: ='Fianl All'!$I85*'Fianl All'!$J85 -> 22000 | N85: 11000 | O85: =O69 -> 4 | P85: 30 | Q85: ='Fianl All'!$N85*'Fianl All'!$O85 -> 44000 | S85: =('Fianl All'!$D85/30)*(16/12) -> 444.44444 | T85: =S85*'Fianl All'!$E85 -> 888.88889 | U85: =('Fianl All'!$I85/30)*(16/12) -> 488.88889 | V85: =U85*'Fianl All'!$J85 -> 977.77778 | W85: =('Fianl All'!$N85/30)*(16/12) -> 488.88889 | X85: =W85*'Fianl All'!$O85 -> 1955.5556
B86: =B70 -> Janitors | D86: 8100 | E86: =E70 -> 20 | F86: 30 | G86: ='Fianl All'!$D86*'Fianl All'!$E86 -> 162000 | I86: 8550 | J86: =J70 -> 20 | K86: 30 | L86: ='Fianl All'!$I86*'Fianl All'!$J86 -> 171000 | N86: 8550 | O86: =O70 -> 40 | P86: 30 | Q86: ='Fianl All'!$N86*'Fianl All'!$O86 -> 342000 | S86: =('Fianl All'!$D86/30)*(16/12) -> 360 | T86: =S86*'Fianl All'!$E86 -> 7200 | U86: =('Fianl All'!$I86/30)*(16/12) -> 380 | V86: =U86*'Fianl All'!$J86 -> 7600 | W86: =('Fianl All'!$N86/30)*(16/12) -> 380 | X86: =W86*'Fianl All'!$O86 -> 15200
B87: =B71 -> Road Sweeper | D87: 0 | E87: =E71 -> 0 | F87: 30 | G87: ='Fianl All'!$D87*'Fianl All'!$E87 -> 0 | J87: =J71 -> 1 | K87: 30 | L87: ='Fianl All'!$I87*'Fianl All'!$J87 -> 0 | N87: 137000 | O87: =O71 -> 1 | P87: 30 | Q87: ='Fianl All'!$N87*'Fianl All'!$O87 -> 137000 | S87: =('Fianl All'!$D87/30)*(16/365) -> 0 | T87: =S87*'Fianl All'!$E87 -> 0 | V87: =U87*'Fianl All'!$J87 -> 0 | X87: =W87*'Fianl All'!$O87 -> 0
B88: =B72 -> Waste Management (Lumpsum item per month) | D88: 0 | E88: =E72 -> 1 | F88: 30 | G88: ='Fianl All'!$D88*'Fianl All'!$E88 -> 0 | J88: =J72 -> 1 | K88: 30 | L88: ='Fianl All'!$I88*'Fianl All'!$J88 -> 0 | N88: 0 | O88: =O72 -> 1 | P88: 30 | Q88: ='Fianl All'!$N88*'Fianl All'!$O88 -> 0 | S88: =('Fianl All'!$D88/30)*(16/365) -> 0 | T88: =S88*'Fianl All'!$E88 -> 0 | V88: =U88*'Fianl All'!$J88 -> 0 | W88: =('Fianl All'!$N88/30)*(16/12) -> 0 | X88: =W88*'Fianl All'!$O88 -> 0
B89: housekeeping specialist | D89: 18000 | E89: 1 | F89: 30 | G89: ='Fianl All'!$D89*'Fianl All'!$E89 -> 18000 | I89: 20000 | J89: 1 | K89: 0 | L89: ='Fianl All'!$I89*'Fianl All'!$J89 -> 20000 | N89: 20000 | O89: 1 | P89: 0 | Q89: ='Fianl All'!$N89*'Fianl All'!$O89 -> 20000 | S89: =('Fianl All'!$D89/30)*(16/12) -> 800 | T89: =S89*'Fianl All'!$E89 -> 800 | V89: =U89*'Fianl All'!$J89 -> 0 | W89: =('Fianl All'!$N89/30)*(16/12) -> 888.88889 | X89: =W89*'Fianl All'!$O89 -> 888.88889
B90: =B74 -> Total | D90: ='Fianl All'!$G$90/'Fianl All'!$E$90 -> 8333.3333 | E90: =SUBTOTAL(109,'Fianl All'!$E$85:$E$89) -> 24 | F90: ='Fianl All'!$G$90/G82 -> 0.46988065 | G90: =SUBTOTAL(109,'Fianl All'!$G$85:$G$89) -> 200000 | I90: ='Fianl All'!$L$90/'Fianl All'!$J$90 -> 8520 | J90: =SUBTOTAL(109,'Fianl All'!$J$85:$J$89) -> 25 | K90: ='Fianl All'!$L$90/L82 -> 0.40634121 | L90: =SUBTOTAL(109,'Fianl All'!$L$85:$L$89) -> 213000 | N90: ='Fianl All'!$Q$90/'Fianl All'!$O$90 -> 11553.191 | O90: =SUBTOTAL(109,'Fianl All'!$O$85:$O$89) -> 47 | P90: ='Fianl All'!$Q$90/Q82 -> 0.48816009 | Q90: =SUBTOTAL(109,'Fianl All'!$Q$85:$Q$89) -> 543000 | S90: =SUM(S84:S89) -> 1604.4444 | T90: =SUM(T84:T89) -> 8888.8889 | U90: =SUM(U84:U89) -> 868.88889 | V90: =SUM(V84:V89) -> 8577.7778 | W90: =SUM(W84:W89) -> 1757.7778 | X90: =SUM(X84:X89) -> 18044.444
B92: HK Tools&Consumabls&uniform | D92: Rate | E92: Qty | F92: . | G92: Monthly | I92: Rate | J92: Qty | K92: . | L92: Monthly | N92: Rate | O92: Qty | P92: . | Q92: Monthly
B93: Depreciation tools and equipment | D93: 18750 | E93: 1 | G93: =D93*E93 -> 18750 | I93: =Table2343[[#This Row],[Rate]] -> 18750 | J93: 1 | K93: 0 | L93: =I93*J93 -> 18750 | N93: 37500 | O93: 1 | P93: 0 | Q93: =N93*O93 -> 37500
B94: Consumables | D94: 6500 | E94: 1 | G94: =D94*E94 -> 6500 | I94: =Table2343[[#This Row],[Rate]] -> 6500 | J94: 1 | K94: 0 | L94: =I94*J94 -> 6500 | N94: 13000 | O94: 1 | P94: 0 | Q94: =N94*O94 -> 13000
B95: Depreciation uniform | D95: 400 | E95: 22 | G95: =D95*E95 -> 8800 | I95: =Table2343[[#This Row],[Rate]] -> 400 | J95: 22 | K95: 0 | L95: =I95*J95 -> 8800 | N95: =Table2343[[#This Row],[Rate]] -> 400 | O95: 44 | P95: 0 | Q95: =N95*O95 -> 17600
B96: Total | F96: =Table2343[[#Totals],[Monthly]]/G82 -> 0.079997181 | G96: =SUBTOTAL(109,Table2343[Monthly]) -> 34050 | K96: =Table2444[[#Totals],[Monthly]]/L82 -> 0.064957363 | L96: =SUBTOTAL(109,Table2444[Monthly]) -> 34050 | P96: =Table2545[[#Totals],[Monthly]]/Q82 -> 0.061222288 | Q96: =SUBTOTAL(109,Table2545[Monthly]) -> 68100
B98: ICT & Others | D98: Rate | E98: Qty | F98: . | G98: Monthly | I98: Rate | J98: Qty | K98: . | L98: Monthly | N98: Rate | O98: Qty | P98: . | Q98: Monthly
B99: Software Account | D99: 4000 | E99: 1 | F99: 0 | G99: =D99*E99 -> 4000 | I99: =D99 -> 4000 | J99: 1 | L99: =I99*J99 -> 4000 | N99: =D99 -> 4000 | O99: 1 | Q99: =N99*O99 -> 4000
B100: ICT Depriciation | D100: 3000 | E100: 1 | F100: 0 | G100: =D100*E100 -> 3000 | I100: =D100 -> 3000 | J100: 1 | L100: =I100*J100 -> 3000 | N100: =D100 -> 3000 | O100: 1 | Q100: =N100*O100 -> 3000
B101: Arab Fees | D101: 8000 | E101: 1 | F101: 0 | G101: =D101*E101 -> 8000 | I101: =D101 -> 8000 | J101: 1 | L101: =I101*J101 -> 8000 | N101: =D101 -> 8000 | O101: 1 | Q101: =N101*O101 -> 8000
B102: Over Head | D102: 0 | E102: 1 | F102: 0 | G102: =D102*E102 -> 0 | I102: =D102 -> 0 | J102: 1 | L102: =I102*J102 -> 0 | N102: 9000 | O102: 1 | Q102: =N102*O102 -> 9000
B103: Meals | D103: 0 | E103: 0 | F103: 0 | G103: =D103*E103 -> 0 | I103: =D103 -> 0 | J103: 0 | L103: =I103*J103 -> 0 | N103: =D103 -> 0 | O103: 0 | Q103: =N103*O103 -> 0
B104: Total | F104: =G104/G82 -> 0.035241049 | G104: =SUM(G99:G103) -> 15000 | K104: =L104/L82 -> 0.028615578 | L104: =SUM(L99:L103) -> 15000 | P104: =Q104/Q82 -> 0.021576137 | Q104: =SUM(Q99:Q103) -> 24000
B106: Accoumedation | D106: Rate | E106: Qty | F106: . | G106: Monthly | I106: Rate | J106: Qty | K106: . | L106: Monthly | N106: Rate | O106: Qty | P106: . | Q106: Monthly
B107: Rent Appartment | D107: 0 | E107: 0 | F107: 0 | G107: =Table2948[[#This Row],[Rate]]*Table2948[[#This Row],[Qty]] -> 0 | I107: =Table2948[[#This Row],[Rate]] -> 0 | J107: 0 | K107: 0 | L107: =Table293149[[#This Row],[Rate]]*Table293149[[#This Row],[Qty]] -> 0 | N107: =Table2948[[#This Row],[Rate]] -> 0 | O107: 0 | P107: 0 | Q107: =Table293250[[#This Row],[Rate]]*Table293250[[#This Row],[Qty]] -> 0
B108: Elec,Water,,, | D108: 0 | E108: 0 | F108: 0 | G108: =Table2948[[#This Row],[Rate]]*Table2948[[#This Row],[Qty]] -> 0 | I108: =Table2948[[#This Row],[Rate]] -> 0 | J108: 0 | K108: 0 | L108: =Table293149[[#This Row],[Rate]]*Table293149[[#This Row],[Qty]] -> 0 | N108: =Table2948[[#This Row],[Rate]] -> 0 | O108: 0 | P108: 0 | Q108: =Table293250[[#This Row],[Rate]]*Table293250[[#This Row],[Qty]] -> 0
B109: Depreciataion Furniture | D109: 0 | E109: 0 | F109: 0 | G109: =Table2948[[#This Row],[Rate]]*Table2948[[#This Row],[Qty]] -> 0 | I109: =Table2948[[#This Row],[Rate]] -> 0 | J109: 0 | K109: 0 | L109: =Table293149[[#This Row],[Rate]]*Table293149[[#This Row],[Qty]] -> 0 | N109: =Table2948[[#This Row],[Rate]] -> 0 | O109: 0 | P109: 0 | Q109: =Table293250[[#This Row],[Rate]]*Table293250[[#This Row],[Qty]] -> 0
B110: Total | F110: =Table2948[[#Totals],[Monthly]]/G82 -> 0 | G110: =SUBTOTAL(109,Table2948[Monthly]) -> 0 | K110: =Table293149[[#Totals],[Monthly]]/L82 -> 0 | L110: =SUBTOTAL(109,Table293149[Monthly]) -> 0 | P110: =Table293250[[#Totals],[Monthly]]/Q82 -> 0 | Q110: =SUBTOTAL(109,Table293250[Monthly]) -> 0
B112: Transportation | D112: Rate | E112: Qty | F112: . | G112: Monthly | I112: Rate | J112: Qty | K112: . | L112: Monthly | N112: Rate | O112: Qty | P112: . | Q112: Monthly
B113: Pickup Double Cabinet (1 HK ) | D113: 45000 | E113: 1 | F113: 0 | G113: =Table293452[[#This Row],[Rate]]*Table293452[[#This Row],[Qty]] -> 45000 | I113: =Table293452[[#This Row],[Rate]] -> 45000 | J113: 1 | K113: 0 | L113: =Table29343553[[#This Row],[Rate]]*Table29343553[[#This Row],[Qty]] -> 45000 | N113: =Table293452[[#This Row],[Rate]] -> 45000 | O113: 1 | P113: 0 | Q113: =Table29343654[[#This Row],[Rate]]*Table29343654[[#This Row],[Qty]] -> 45000
B114: Transportation costs | D114: 60000 | E114: 1 | F114: 0 | G114: =Table293452[[#This Row],[Rate]]*Table293452[[#This Row],[Qty]] -> 60000 | I114: =Table293452[[#This Row],[Rate]] -> 60000 | J114: 1 | K114: 0 | L114: =Table29343553[[#This Row],[Rate]]*Table29343553[[#This Row],[Qty]] -> 60000 | N114: =Table293452[[#This Row],[Rate]] -> 60000 | O114: 1 | P114: 0 | Q114: =Table29343654[[#This Row],[Rate]]*Table29343654[[#This Row],[Qty]] -> 60000
D115: 0 | E115: 0 | F115: 0 | G115: =Table293452[[#This Row],[Rate]]*Table293452[[#This Row],[Qty]] -> 0 | I115: =Table293452[[#This Row],[Rate]] -> 0 | J115: 0 | K115: 0 | L115: =Table29343553[[#This Row],[Rate]]*Table29343553[[#This Row],[Qty]] -> 0 | N115: =Table293452[[#This Row],[Rate]] -> 0 | O115: 0 | P115: 0 | Q115: =Table29343654[[#This Row],[Rate]]*Table29343654[[#This Row],[Qty]] -> 0
D116: 0 | E116: 0 | F116: 0 | G116: =Table293452[[#This Row],[Rate]]*Table293452[[#This Row],[Qty]] -> 0 | I116: =Table293452[[#This Row],[Rate]] -> 0 | J116: 0 | K116: 0 | L116: =Table29343553[[#This Row],[Rate]]*Table29343553[[#This Row],[Qty]] -> 0 | N116: =Table293452[[#This Row],[Rate]] -> 0 | O116: 0 | P116: 0 | Q116: =Table29343654[[#This Row],[Rate]]*Table29343654[[#This Row],[Qty]] -> 0
D117: 0 | E117: 0 | F117: 0 | G117: =Table293452[[#This Row],[Rate]]*Table293452[[#This Row],[Qty]] -> 0 | I117: =Table293452[[#This Row],[Rate]] -> 0 | J117: 0 | K117: 0 | L117: =Table29343553[[#This Row],[Rate]]*Table29343553[[#This Row],[Qty]] -> 0 | N117: =Table293452[[#This Row],[Rate]] -> 0 | O117: 0 | P117: 0 | Q117: =Table29343654[[#This Row],[Rate]]*Table29343654[[#This Row],[Qty]] -> 0
B118: Total | F118: =Table293452[[#Totals],[Monthly]]/G82 -> 0.24668734 | G118: =SUBTOTAL(109,Table293452[Monthly]) -> 105000 | K118: =Table29343553[[#Totals],[Monthly]]/L82 -> 0.20030905 | L118: =SUBTOTAL(109,Table29343553[Monthly]) -> 105000 | P118: =Table29343654[[#Totals],[Monthly]]/Q82 -> 0.094395598 | Q118: =SUBTOTAL(109,Table29343654[Monthly]) -> 105000
B120: Total Cost | G120: =Table293452[[#Totals],[Monthly]]+Table2948[[#Totals],[Monthly]]+G104+Table2343[[#Totals],[Monthly]]+'Fianl All'!$G$90 -> 354050 | L120: =Table29343553[[#Totals],[Monthly]]+Table293149[[#Totals],[Monthly]]+L104+Table2444[[#Totals],[Monthly]]+'Fianl All'!$L$90 -> 367050 | Q120: =Table29343654[[#Totals],[Monthly]]+Table293250[[#Totals],[Monthly]]+Q104+Table2545[[#Totals],[Monthly]]+'Fianl All'!$Q$90 -> 740100
B122: Total Revenue | G122: =Table1510[[#Totals],[Monthly]]+Table15115[[#Totals],[Monthly]] -> 425640 | L122: =Table1628[[#Totals],[Monthly]]+Table26126[[#Totals],[Monthly]] -> 524190 | Q122: =Table1737[[#Totals],[Monthly]]+Table37137[[#Totals],[Monthly]] -> 1112340
B124: Contracting Insurance | D124: 0.0827 | E124: -1 | G124: =E124*D124*G122 -> -35200.428 | I124: 0.0827 | J124: -1 | L124: =J124*I124*L122 -> -43350.513 | N124: 0.0827 | O124: -1 | Q124: =O124*N124*Q122 -> -91990.518
B126: GM | G126: =G122-G120+G124 -> 36389.572 | L126: =L122-L120+L124 -> 113789.49 | Q126: =Q122-Q120+Q124 -> 280249.48
...

Sheet MEP
B2: MEP Manpower | D2: Rate | E2: Qty | F2: Shift/Month | G2: Monthly | I2: Rate | J2: Qty | K2: Shift/Month | L2: Monthly | N2: Rate | O2: Qty | P2: Shift/Month | Q2: Monthly
B3: FM Manager | D3: 2419 | E3: 1 | F3: 30 | G3: =F3*E3*D3 -> 72570 | I3: 2760 | J3: 1 | K3: 30 | L3: =I3*F3*E3 -> 82800 | N3: 2760 | O3: 1 | P3: 30 | Q3: =P3*O3*N3 -> 82800
B4: Senior Engineer MEP | D4: 1573 | E4: 1 | F4: 30 | G4: =F4*E4*D4 -> 47190 | I4: 1794 | J4: 1 | K4: 30 | L4: =I4*F4*E4 -> 53820 | N4: 1794 | O4: 2 | P4: 30 | Q4: =P4*O4*N4 -> 107640
B5: Supervisor - Electrical | D5: 883 | E5: 1 | F5: 30 | G5: =F5*E5*D5 -> 26490 | I5: 1008 | J5: 1 | K5: 30 | L5: =I5*F5*E5 -> 30240 | N5: 1008 | O5: 2 | P5: 30 | Q5: =P5*O5*N5 -> 60480
B6: Supervisor - Mechanical | D6: 883 | E6: 1 | F6: 30 | G6: =F6*E6*D6 -> 26490 | I6: 1008 | J6: 1 | K6: 30 | L6: =I6*F6*E6 -> 30240 | N6: 1008 | O6: 2 | P6: 30 | Q6: =P6*O6*N6 -> 60480
B7: Supervisor - Light Current | D7: 883 | E7: 1 | F7: 30 | G7: =F7*E7*D7 -> 26490 | I7: 1008 | J7: 1 | K7: 30 | L7: =I7*F7*E7 -> 30240 | N7: 1008 | O7: 1 | P7: 30 | Q7: =P7*O7*N7 -> 30240
B8: Technician - Electrical | D8: 500 | E8: 3 | F8: 30 | G8: =F8*E8*D8 -> 45000 | I8: 577 | J8: 3 | K8: 30 | L8: =I8*F8*E8 -> 51930 | N8: 577 | O8: 5 | P8: 30 | Q8: =P8*O8*N8 -> 86550
B9: Technician - Mechanical | D9: 530 | E9: 1 | F9: 30 | G9: =F9*E9*D9 -> 15900 | I9: 604 | J9: 1 | K9: 30 | L9: =I9*F9*E9 -> 18120 | N9: 604 | O9: 2 | P9: 30 | Q9: =P9*O9*N9 -> 36240
B10: Technician - Pluming | D10: 491 | E10: 3 | F10: 30 | G10: =F10*E10*D10 -> 44190 | I10: 567 | J10: 3 | K10: 30 | L10: =I10*F10*E10 -> 51030 | N10: 567 | O10: 5 | P10: 30 | Q10: =P10*O10*N10 -> 85050
B11: Technician - light Current | D11: 545 | E11: 1 | F11: 30 | G11: =F11*E11*D11 -> 16350 | I11: 621 | J11: 1 | K11: 30 | L11: =I11*F11*E11 -> 18630 | N11: 621 | O11: 1 | P11: 30 | Q11: =P11*O11*N11 -> 18630
B12: CAFM - Coordinator | D12: 744 | E12: 1 | F12: 30 | G12: =F12*E12*D12 -> 22320 | I12: 849 | J12: 1 | K12: 30 | L12: =I12*F12*E12 -> 25470 | N12: 849 | O12: 1 | P12: 30 | Q12: =P12*O12*N12 -> 25470
B13: Painter | D13: 514 | E13: 1 | F13: 30 | G13: =F13*E13*D13 -> 15420 | I13: 587 | J13: 1 | K13: 30 | L13: =I13*F13*E13 -> 17610 | N13: 587 | O13: 2 | P13: 30 | Q13: =P13*O13*N13 -> 35220
B14: Carpenter | D14: 514 | E14: 1 | F14: 30 | G14: =F14*E14*D14 -> 15420 | I14: 587 | J14: 1 | K14: 30 | L14: =I14*F14*E14 -> 17610 | N14: 587 | O14: 2 | P14: 30 | Q14: =P14*O14*N14 -> 35220
... B19: Manlift | D19: 3628 | E19: 0 | F19: 30 | G19: =F19*E19*D19 -> 0 | I19: 4140 | J19: 0 | K19: 30 | L19: =I19*F19*E19 -> 0 | N19: 4140 | O19: 0 | P19: 30 | Q19: =P19*O19*N19 -> 0
B20: Total | E20: =SUBTOTAL(109,Table1[Qty]) -> 23 | G20: =SUBTOTAL(109,Table1[Monthly]) -> 501330 | J20: =SUBTOTAL(109,Table2[Qty]) -> 23 | L20: =SUBTOTAL(109,Table2[Monthly]) -> 572790 | O20: =SUBTOTAL(109,Table3[Qty]) -> 35 | Q20: =SUBTOTAL(109,Table3[Monthly]) -> 839670

Sheet Mobilization Budget
A2: City Gate - FMPLus Mobilization Area
A4: 1 | B4: Mobilization Area
B6: A | C6: Caravans
B8: # | C8: Caravan For | D8: Dimensions | E8: Cost | F8: Dep. Period | G8: Monthly Cost
B9: 1 | C9: Head Of Operations | D9: 3*6 M | E9: 50000 | F9: 24 | G9: =E9/F9 -> 2083.3333
B10: 2 | C10: Engineering Team | D10: 3*9 M | E10: 65000 | F10: 24 | G10: =E10/F10 -> 2708.3333
B11: 3 | C11: Helpdesk & admins | D11: 3*9 M | E11: 65000 | F11: 24 | G11: =E11/F11 -> 2708.3333
B12: 4 | C12: Quality Team | D12: 3*6 M | E12: 40000 | F12: 24 | G12: =E12/F12 -> 1666.6667
B13: 5 | C13: Meeting Room | D13: 3*6 M | E13: 40000 | F13: 24 | G13: =E13/F13 -> 1666.6667
B14: 6 | C14: Houskeeping Team | D14: 3*6 M | E14: 40000 | F14: 24 | G14: =E14/F14 -> 1666.6667
B15: 7 | C15: LS Team | D15: 3*6 M | E15: 40000 | F15: 24 | G15: =E15/F15 -> 1666.6667
B16: 8 | C16: Centralized Kitchen | D16: 3*6 M | E16: 40000 | F16: 24 | G16: =E16/F16 -> 1666.6667
B17: 9 | C17: Maintenance Team (Lockers Caravan) | D17: 3*12 M | E17: 105000 | F17: 24 | G17: =E17/F17 -> 4375
B18: 10 | C18: HK Team (Lockers Caravan) - Male | D18: 3*12 M | E18: 105000 | F18: 24 | G18: =E18/F18 -> 4375
B19: 11 | C19: HK Team (Lockers Caravan) - Female | D19: 3*3 M | E19: 50000 | F19: 24 | G19: =E19/F19 -> 2083.3333
B20: 12 | C20: LS Team (Lockers Caravan) | D20: 3*12 M | E20: 85000 | F20: 24 | G20: =E20/F20 -> 3541.6667
B21: 13 | C21: Security Management Team | D21: 3*9 M | E21: 85000 | F21: 24 | G21: =E21/F21 -> 3541.6667
B22: 14 | C22: Public Toilets Male | D22: 12 | E22: 12000 | F22: 24 | G22: =D22*E22/F22 -> 6000
B23: 15 | C23: Public Toilets Female | D23: 2 | E23: 15000 | F23: 24 | G23: =D23*E23/F23 -> 1250
B24: TOTAL | G24: =SUM(G9:G23) -> 41000
B26: B | C26: Containers / Stores
B28: # | C28: Container For | D28: Dimensions | E28: Cost | F28: Dep. Period | G28: Monthly Cost
B29: 1 | C29: MEP | D29: 3*12 M | E29: 60000 | F29: 24 | G29: =E29/F29 -> 2500
B30: 2 | C30: HK & Security | D30: 3*12 M | E30: 60000 | F30: 24 | G30: =E30/F30 -> 2500
B31: 3 | C31: Landscape | D31: 3*12 M | E31: 60000 | F31: 24 | G31: =E31/F31 -> 2500
B32: 4 | C32: Pest Control | D32: 3*6 M | E32: 60000 | F32: 24 | G32: =E32/F32 -> 2500
B33: 5 | C33: Uniform | D33: 3*12 M | E33: 60000 | F33: 24 | G33: =E33/F33 -> 2500
B34: TOTAL | G34: =SUM(G29:G33) -> 12500
B36: C | C36: Outdoor Area
B38: # | C38: Container For | D38: Dimensions | E38: Cost | F38: Dep. Period | G38: Monthly Cost
B39: 1 | C39: Car Parking Shade | D39: 3*16 M | E39: 123000 | F39: 24 | G39: =E39/F39 -> 5125
B40: 2 | C40: Outdoor Electrical Sockets | D40: LUM | E40: 20000 | F40: 24 | G40: =E40/F40 -> 833.33333
B41: 3 | C41: Outdoor Lighting | D41: LUM | E41: 20000 | F41: 24 | G41: =E41/F41 -> 833.33333
B42: 4 | C42: Outdoor Interlock & Landscape | D42: LUM | E42: 50000 | F42: 24 | G42: =E42/F42 -> 2083.3333
B43: 5 | C43: Concerete Base & Installation | D43: LUM | E43: 120000 | F43: 24 | G43: =E43/F43 -> 5000
B44: TOTAL | G44: =SUM(G39:G43) -> 13875
B46: D | C46: Furniture
B48: # | C48: Container For | D48: QTY | E48: Cost | F48: Dep. Period | G48: Monthly Cost
B49: 1 | C49: Office | D49: 6 | E49: 5000 | F49: 12 | G49: =(D49*E49)/F49 -> 2500
B50: 2 | C50: WorkSpace | D50: 10 | E50: 14000 | F50: 12 | G50: =(D50*E50)/F50 -> 11666.667
B51: 3 | C51: Chair | D51: 65 | E51: 2800 | F51: 12 | G51: =(D51*E51)/F51 -> 15166.667
B52: 4 | C52: AC's | D52: 15 | E52: 30000 | F52: 12 | G52: =(D52*E52)/F52 -> 37500
B53: 5 | C53: Kitchen Eq | D53: LUM | E53: 23000 | F53: 12 | G53: =E53/24 -> 958.33333
B54: 6 | C54: Meeting Room Fur. | D54: LUm | E54: 24500 | F54: 12 | G54: =E54/24 -> 1020.8333
B55: 7 | C55: Ex. Fans | D55: 8 | E55: 2000 | F55: 12 | G55: =(D55*E55)/F55 -> 1333.3333
B56: TOTAL | G56: =SUM(G49:G55) -> 70145.833
B58: E | C58: IT Equipment & Data Center
B60: # | C60: Container For | D60: QTY | E60: Cost | F60: Dep. Period | G60: Monthly Cost
B61: 1 | C61: finger print | D61: 2 | E61: 3000 | F61: 24 | G61: =(D61*E61)/F61 -> 250
B62: 2 | C62: laptop | D62: 22 | E62: 8000 | F62: 24 | G62: =(D62*E62)/F62 -> 7333.3333
B63: 3 | C63: Camera | D63: 10 | E63: 2500 | F63: 24 | G63: =(D63*E63)/F63 -> 1041.6667
B64: 4 | C64: Routers & Data Networks - Data Center | D64: 6 | E64: 8000 | F64: 24 | G64: =(D64*E64)/F64 -> 2000
B65: 5 | C65: Access Cards &Panel | D65: LUM | E65: 20000 | F65: 24 | G65: =E65/24 -> 833.33333
B66: 6 | C66: TV Screen | D66: 2 | E66: 16000 | F66: 24 | G66: =E66/24 -> 666.66667
B67: 7 | C67: 3cX Phones | D67: 15 | E67: 3400 | F67: 24 | G67: =(D67*E67)/F67 -> 2125
B68: TOTAL | G68: =SUM(G61:G67) -> 14250
B70: F | C70: Fire Alarm & Fire Fighting - Emergency Power
B72: # | C72: Container For | D72: QTY | E72: Cost | F72: Dep. Period | G72: Monthly Cost
B73: 1 | C73: Fire Alarm Panel | D73: 1 | E73: 110000 | F73: 24 | G73: =(D73*E73)/F73 -> 4583.3333
B74: 2 | C74: Fire alarm sensors & networks | D74: 30 | E74: 1500 | F74: 24 | G74: =(D74*E74)/F74 -> 1875
B75: 3 | C75: FF Extigusher | D75: 12 | E75: 5600 | F75: 24 | G75: =(D75*E75)/F75 -> 2800
B76: 4 | C76: FF Fire Search | D76: 3 | E76: 8000 | F76: 24 | G76: =(D76*E76)/F76 -> 1000
B77: 5 | C77: Gen & ATS | D77: 0 | E77: 430000 | F77: 24 | G77: =(D77*E77)/F77 -> 0
B78: TOTAL | G78: =SUM(G73:G77) -> 10258.333
B80: G | C80: Monthly Consumption & Office Supplies
B82: # | C82: Container For | D82: QTY | E82: Cost | F82: Dep. Period | G82: Monthly Cost
B83: 1 | C83: Potable Water | D83: 1 | E83: 2000 | F83: 1 | G83: =(D83*E83)/F83 -> 2000
B84: 2 | C84: Electricity | D84: 1 | E84: 2500 | F84: 1 | G84: =(D84*E84)/F84 -> 2500
B85: 3 | C85: Internet | D85: 1 | E85: 1900 | F85: 1 | G85: =(D85*E85)/F85 -> 1900
B86: 4 | C86: Maintenance 10% - Spare Parts | D86: 1 | E86: =(E83+E84+E85+E90)*0.05 -> 370 | F86: 1 | G86: =(D86*E86)/F86 -> 370
B87: 5 | C87: Pantry | D87: 1 | E87: 5000 | F87: 1 | G87: =(D87*E87)/F87 -> 5000
B88: 6 | C88: Paper | D88: 1 | E88: 2000 | F88: 1 | G88: =(D88*E88)/F88 -> 2000
B89: 7 | C89: Printers & Ink | D89: 1 | E89: 2000 | F89: 1 | G89: =(D89*E89)/F89 -> 2000
B90: 8 | C90: Fuel For Generator | D90: 0 | E90: 1000 | F90: 1 | G90: =(D90*E90)/F90 -> 0
B91: TOTAL | G91: =SUM(G83:G90) -> 15770
B93: Mobilization Summary
B95: # | C95: Item | D95: Monthly Cost | E95: Annual Cost
B96: A | C96: =C6 -> Caravans | D96: =G24 -> 41000 | E96: =D96*12 -> 492000
B97: B | C97: =C26 -> Containers / Stores | D97: =G34 -> 12500 | E97: =D97*12 -> 150000
B98: C | C98: =C36 -> Outdoor Area | D98: =G44 -> 13875 | E98: =D98*12 -> 166500
B99: D | C99: =C46 -> Furniture | D99: =G68 -> 14250 | E99: =D99*12 -> 171000
B100: E | C100: =C58 -> IT Equipment & Data Center | D100: =G68 -> 14250 | E100: =D100*12 -> 171000
B101: F | C101: =C70 -> Fire Alarm & Fire Fighting - Emergency Power | D101: =G78 -> 10258.333 | E101: =D101*12 -> 123100
B102: G | C102: =C80 -> Monthly Consumption & Office Supplies | D102: =G91 -> 15770 | E102: =D102*12 -> 189240
B103: Total | D103: =ROUNDUP(SUM(D96:D102),0) -> 121904 | E103: =D103*12 -> 1462848
E104: 0.08
E105: =E103+(E103*E104) -> 1579875.8
E107: Total Mobilization Costs | F107: =(G24*24)+(G34*24)+(G44*24)+(G56*12)+(G68*24)+(G78*24)+(G91*12) -> 3236190
E108: Rest | F108: =F107-E105 -> 1656314.2 | H108: Value / Month - Y2
D109: MEP | E109: 0.22 | F109: =F$108*E109 -> 364389.12 | G109: =F109/12 -> 30365.76 | H109: =ROUNDUP(G109,0) -> 30366
D110: HK | E110: 0.18 | F110: =F$108*E110 -> 298136.55 | G110: =F110/12 -> 24844.712 | H110: =ROUNDUP(G110,0) -> 24845
D111: Pest | E111: 0.05 | F111: =F$108*E111 -> 82815.708 | G111: =F111/12 -> 6901.309 | H111: =ROUNDUP(G111,0) -> 6902
D112: Lands | E112: 0.33 | F112: =F$108*E112 -> 546583.67 | G112: =F112/12 -> 45548.639 | H112: =ROUNDUP(G112,0) -> 45549
D113: Security | E113: 0.2 | F113: =F$108*E113 -> 331262.83 | G113: =F113/12 -> 27605.236 | H113: =ROUNDUP(G113,0) -> 27606
D114: Transp | E114: 0.02 | F114: =F$108*E114 -> 33126.283 | G114: =F114/12 -> 2760.5236 | H114: =ROUNDUP(G114,0) -> 2761

Sheet MEP Budget-Y1
B2: City Gate - MEP Budget (Year 1)
D4: Head Count | F4: Head Cost / CTC | H4: Monthly | J4: Annualy
B6: Direct Costs - As per Pricing Sheet | D6: Sheet HC | E6: Budget HC | L6: FMPlus Rate | N6: Rate / Shift
A7: 1 | B7: FM Manager | D7: 1 | E7: =ROUNDUP(D7+(D7/6),1) -> 1.2 | F7: 40000 | H7: =F7*E7 -> 48000 | J7: =H7*12 -> 576000 | L7: =H7/(1-D$68) -> 72558.647 | N7: =ROUNDUP(L7/D7/30,0) -> 2419
A8: 2 | B8: Senior Engineer MEP | D8: 1 | E8: =ROUNDUP(D8+(D8/6),1) -> 1.2 | F8: 26000 | H8: =F8*E8 -> 31200 | J8: =H8*12 -> 374400 | L8: =H8/(1-D$68) -> 47163.12 | N8: =ROUNDUP(L8/D8/30,0) -> 1573
A9: 3 | B9: Supervisor - Electrical | D9: 1 | E9: =ROUNDUP(D9+(D9/6),1) -> 1.2 | F9: 14600 | H9: =F9*E9 -> 17520 | J9: =H9*12 -> 210240 | L9: =H9/(1-D$68) -> 26483.906 | N9: =ROUNDUP(L9/D9/30,0) -> 883
A10: 4 | B10: Supervisor - Mechanical | D10: 1 | E10: =ROUNDUP(D10+(D10/6),1) -> 1.2 | F10: 14600 | H10: =F10*E10 -> 17520 | J10: =H10*12 -> 210240 | L10: =H10/(1-D$68) -> 26483.906 | N10: =ROUNDUP(L10/D10/30,0) -> 883
A11: 5 | B11: Supervisor - Light Current | D11: 1 | E11: =ROUNDUP(D11+(D11/6),1) -> 1.2 | F11: 14600 | H11: =F11*E11 -> 17520 | J11: =H11*12 -> 210240 | L11: =H11/(1-D$68) -> 26483.906 | N11: =ROUNDUP(L11/D11/30,0) -> 883
A12: 6 | B12: Technician - Electrical | D12: 3 | E12: =ROUNDUP(D12+(D12/6),1) -> 3.5 | F12: 8500 | H12: =F12*E12 -> 29750 | J12: =H12*12 -> 357000 | L12: =H12/(1-D$68) -> 44971.245 | N12: =ROUNDUP(L12/D12/30,0) -> 500
A13: 7 | B13: Technician - Mechanical | D13: 1 | E13: =ROUNDUP(D13+(D13/6),1) -> 1.2 | F13: 8750 | H13: =F13*E13 -> 10500 | J13: =H13*12 -> 126000 | L13: =H13/(1-D$68) -> 15872.204 | N13: =ROUNDUP(L13/D13/30,0) -> 530
A14: 8 | B14: Technician - Pluming | D14: 3 | E14: =ROUNDUP(D14+(D14/6),1) -> 3.5 | F14: 8350 | H14: =F14*E14 -> 29225 | J14: =H14*12 -> 350700 | L14: =H14/(1-D$68) -> 44177.634 | N14: =ROUNDUP(L14/D14/30,0) -> 491
A15: 9 | B15: Technician - light Current | D15: 1 | E15: =ROUNDUP(D15+(D15/6),1) -> 1.2 | F15: 9000 | H15: =F15*E15 -> 10800 | J15: =H15*12 -> 129600 | L15: =H15/(1-D$68) -> 16325.696 | N15: =ROUNDUP(L15/D15/30,0) -> 545
A16: 10 | B16: CAFM - Coordinator | D16: 1 | E16: =ROUNDUP(D16+(D16/6),1) -> 1.2 | F16: 12300 | H16: =F16*E16 -> 14760 | J16: =H16*12 -> 177120 | L16: =H16/(1-D$68) -> 22311.784 | N16: =ROUNDUP(L16/D16/30,0) -> 744
A17: 11 | B17: Painter | D17: 1 | E17: =ROUNDUP(D17+(D17/6),1) -> 1.2 | F17: 8500 | H17: =F17*E17 -> 10200 | J17: =H17*12 -> 122400 | L17: =H17/(1-D$68) -> 15418.712 | N17: =ROUNDUP(L17/D17/30,0) -> 514
A18: 12 | B18: Carpenter | D18: 1 | E18: =ROUNDUP(D18+(D18/6),1) -> 1.2 | F18: 8500 | H18: =F18*E18 -> 10200 | J18: =H18*12 -> 122400 | L18: =H18/(1-D$68) -> 15418.712 | N18: =ROUNDUP(L18/D18/30,0) -> 514
... A23: 17 | B23: Manlift | D23: 1 | E23: =ROUNDUP(D23+(D23/6),1) -> 1.2 | F23: 60000 | H23: =F23*E23 -> 72000 | J23: =H23*12 -> 864000 | L23: =H23/(1-D$68) -> 108837.97 | N23: =ROUNDUP(L23/D23/30,0) -> 3628
B24: Total Direct Manpower - As Per Pricing Sheet | D24: =SUM(D7:D23) -> 24 | E24: =SUM(E7:E23) -> 28.5 | H24: =SUM(H7:H23) -> 403515 | J24: =SUM(J7:J23) -> 4842180 | L24: =SUM(L7:L23) -> 609968.8 | N24: Should Be Same
B26: Indirect Costs
A27: A | B27: MEP - Tools + Equipment
A28: 1 | B28: Electrical Tools | E28: 1 | F28: 2000 | H28: =E28*F28 -> 2000 | J28: =H28*12 -> 24000
A29: 2 | B29: Carpentry Tools | E29: 1 | F29: 1500 | H29: =E29*F29 -> 1500 | J29: =H29*12 -> 18000
A30: 3 | B30: Plumbing Tools | E30: 1 | F30: 1500 | H30: =E30*F30 -> 1500 | J30: =H30*12 -> 18000
A31: 4 | B31: Light Current Tools | E31: 1 | F31: 1500 | H31: =E31*F31 -> 1500 | J31: =H31*12 -> 18000
A32: 5 | B32: Mechanical Tools | E32: 1 | F32: 3300 | H32: =E32*F32 -> 3300 | J32: =H32*12 -> 39600
A33: 6 | B33: Water features Tools | E33: 1 | F33: 3300 | H33: =E33*F33 -> 3300 | J33: =H33*12 -> 39600
A34: 7 | B34: MEP Shared Equipment | E34: 1 | F34: 9000 | H34: =E34*F34 -> 9000 | J34: =H34*12 -> 108000
A35: B | B35: MEP - Consumables
A36: 1 | B36: Electrical | E36: 1 | F36: 2000 | H36: =F36*E36 -> 2000 | J36: =H36*12 -> 24000
A37: 2 | B37: Plumbing | E37: 1 | F37: 2000 | H37: =F37*E37 -> 2000 | J37: =H37*12 -> 24000
A38: 3 | B38: Civil | E38: 1 | F38: 1000 | H38: =F38*E38 -> 1000 | J38: =H38*12 -> 12000
A39: 4 | B39: LC | E39: 1 | F39: 1500 | H39: =F39*E39 -> 1500 | J39: =H39*12 -> 18000
A40: 5 | B40: Mechanical Including Oil Filters …etc | E40: 1 | F40: 7500 | H40: =F40*E40 -> 7500 | J40: =H40*12 -> 90000
A41: C | B41: Chemicals - Consumables
A42: 1 | B42: Chlorine | E42: 1 | F42: 5600 | H42: =F42*E42 -> 5600 | J42: =H42*12 -> 67200
A43: 2 | B43: Aliga Cide | E43: 1 | F43: 2300 | H43: =F43*E43 -> 2300 | J43: =H43*12 -> 27600
A44: 3 | B44: PH Modifier | E44: 1 | F44: 3000 | H44: =F44*E44 -> 3000 | J44: =H44*12 -> 36000
A45: 4 | B45: Water Softner | E45: 1 | F45: 1000 | H45: =F45*E45 -> 1000 | J45: =H45*12 -> 12000
A46: 5 | B46: Others | E46: 1 | F46: 2000 | H46: =F46*E46 -> 2000 | J46: =H46*12 -> 24000
A47: D | B47: Water Tanks - Cleaning & Disinfection
A48: 1 | B48: Zone 2D | E48: 1 | F48: 13000 | H48: =F48*E48 -> 13000 | J48: =H48*12 -> 156000
A49: 2 | B49: Zone 3D | E49: 0 | F49: 28000 | H49: =F49*E49 -> 0 | J49: =H49*12 -> 0
A50: E | B50: CAFM
A51: 1 | B51: Software Accounts - Users | E51: 1 | F51: 8000 | H51: =F51*E51 -> 8000 | J51: =H51*12 -> 96000
A52: 2 | B52: IT Support | E52: 1 | F52: 3000 | H52: =F52*E52 -> 3000 | J52: =H52*12 -> 36000
A53: F | B53: Transportation Outside Site
A54: 1 | B54: Managers Transportation Allowance | E54: =E7+E8 -> 2.4 | F54: 1500 | H54: =F54*E54 -> 3600 | J54: =H54*12 -> 43200
A55: 2 | B55: Supervisors & Technicians Transportation Allowance | E55: =SUM(E9:E23) -> 26.1 | F55: 1000 | H55: =F55*E55 -> 26100 | J55: =H55*12 -> 313200
A56: G | B56: Others
A57: 1 | B57: Arab Fees | E57: 1 | F57: 8000 | H57: =F57*E57 -> 8000 | J57: =H57*12 -> 96000
A58: 2 | B58: Sub-Contractors Management | E58: 1 | F58: 9000 | H58: =F58*E58 -> 9000 | J58: =H58*12 -> 108000
A59: 3 | B59: Uniform | E59: =E24 -> 28.5 | F59: 400 | H59: =F59*E59 -> 11400 | J59: =H59*12 -> 136800
A60: 4 | B60: HSE | E60: 0.5 | F60: 18000 | H60: =F60*E60 -> 9000 | J60: =H60*12 -> 108000
B61: Total Of Indirect Costs | H61: =SUM(H28:H34)+SUM(H36:H40)+SUM(H42:H46)+SUM(H48:H49)+SUM(H51:H52)+SUM(H54:H55)+SUM(H57:H60) -> 141100 | J61: =SUM(J28:J34)+SUM(J36:J40)+SUM(J42:J46)+SUM(J48:J49)+SUM(J51:J52)+SUM(J54:J55)+SUM(J57:J60) -> 1693200
B63: Costing Sheet Summary
B64: Direct Costs | D64: =H24 -> 403515
B65: In-Direct Costs | D65: =H61 -> 141100 | E65: Monthly | F65: Annualy
A66: 0.12 | B66: FMPlus GP | D66: =(D64+D65)*A66 -> 65353.8 | E66: =SUM(D64+D65+D66) -> 609968.8 | F66: =E66*12 -> 7319625.6
B68: In-Direct % | D68: =(D66+D65)/(D64+D65+D66) -> 0.33846616
F74: 0 | H74: 0 | J74: 0
F90: 0

Sheet MEP Budget-Y2
B2: City Gate - MEP Budget (Year 2)
D4: Head Count | F4: Head Cost / CTC | H4: Monthly | J4: Annualy
B6: Direct Costs - As per Pricing Sheet | D6: Sheet HC | E6: Budget HC | L6: FMPlus Rate | N6: Rate / Shift
A7: 1 | B7: FM Manager | D7: 1 | E7: =ROUNDUP(D7+(D7/6),1) -> 1.2 | F7: ='MEP Budget-Y1'!F7*1.1 -> 44000 | H7: =F7*E7 -> 52800 | J7: =H7*12 -> 633600 | L7: =H7/(1-D$69) -> 82788.457 | N7: =ROUNDUP(L7/D7/30,0) -> 2760
A8: 2 | B8: Senior Engineer MEP | D8: 2 | E8: =ROUNDUP(D8+(D8/6),1) -> 2.4 | F8: ='MEP Budget-Y1'!F8*1.1 -> 28600 | H8: =F8*E8 -> 68640 | J8: =H8*12 -> 823680 | L8: =H8/(1-D$69) -> 107624.99 | N8: =ROUNDUP(L8/D8/30,0) -> 1794
A9: 3 | B9: Supervisor - Electrical | D9: 2 | E9: =ROUNDUP(D9+(D9/6),1) -> 2.4 | F9: ='MEP Budget-Y1'!F9*1.1 -> 16060 | H9: =F9*E9 -> 38544 | J9: =H9*12 -> 462528 | L9: =H9/(1-D$69) -> 60435.574 | N9: =ROUNDUP(L9/D9/30,0) -> 1008
A10: 4 | B10: Supervisor - Mechanical | D10: 2 | E10: =ROUNDUP(D10+(D10/6),1) -> 2.4 | F10: ='MEP Budget-Y1'!F10*1.1 -> 16060 | H10: =F10*E10 -> 38544 | J10: =H10*12 -> 462528 | L10: =H10/(1-D$69) -> 60435.574 | N10: =ROUNDUP(L10/D10/30,0) -> 1008
A11: 5 | B11: Supervisor - Light Current | D11: 1 | E11: =ROUNDUP(D11+(D11/6),1) -> 1.2 | F11: ='MEP Budget-Y1'!F11*1.1 -> 16060 | H11: =F11*E11 -> 19272 | J11: =H11*12 -> 231264 | L11: =H11/(1-D$69) -> 30217.787 | N11: =ROUNDUP(L11/D11/30,0) -> 1008
A12: 6 | B12: Technician - Electrical | D12: 5 | E12: =ROUNDUP(D12+(D12/6),1) -> 5.9 | F12: ='MEP Budget-Y1'!F12*1.1 -> 9350 | H12: =F12*E12 -> 55165 | J12: =H12*12 -> 661980 | L12: =H12/(1-D$69) -> 86496.69 | N12: =ROUNDUP(L12/D12/30,0) -> 577
A13: 7 | B13: Technician - Mechanical | D13: 2 | E13: =ROUNDUP(D13+(D13/6),1) -> 2.4 | F13: ='MEP Budget-Y1'!F13*1.1 -> 9625 | H13: =F13*E13 -> 23100 | J13: =H13*12 -> 277200 | L13: =H13/(1-D$69) -> 36219.95 | N13: =ROUNDUP(L13/D13/30,0) -> 604
A14: 8 | B14: Technician - Pluming | D14: 5 | E14: =ROUNDUP(D14+(D14/6),1) -> 5.9 | F14: ='MEP Budget-Y1'!F14*1.1 -> 9185 | H14: =F14*E14 -> 54191.5 | J14: =H14*12 -> 650298 | L14: =H14/(1-D$69) -> 84970.278 | N14: =ROUNDUP(L14/D14/30,0) -> 567
A15: 9 | B15: Technician - light Current | D15: 1 | E15: =ROUNDUP(D15+(D15/6),1) -> 1.2 | F15: ='MEP Budget-Y1'!F15*1.1 -> 9900 | H15: =F15*E15 -> 11880 | J15: =H15*12 -> 142560 | L15: =H15/(1-D$69) -> 18627.403 | N15: =ROUNDUP(L15/D15/30,0) -> 621
A16: 10 | B16: CAFM - Coordinator | D16: 1 | E16: =ROUNDUP(D16+(D16/6),1) -> 1.2 | F16: ='MEP Budget-Y1'!F16*1.1 -> 13530 | H16: =F16*E16 -> 16236 | J16: =H16*12 -> 194832 | L16: =H16/(1-D$69) -> 25457.451 | N16: =ROUNDUP(L16/D16/30,0) -> 849
A17: 11 | B17: Painter | D17: 2 | E17: =ROUNDUP(D17+(D17/6),1) -> 2.4 | F17: ='MEP Budget-Y1'!F17*1.1 -> 9350 | H17: =F17*E17 -> 22440 | J17: =H17*12 -> 269280 | L17: =H17/(1-D$69) -> 35185.094 | N17: =ROUNDUP(L17/D17/30,0) -> 587
A18: 12 | B18: Carpenter | D18: 2 | E18: =ROUNDUP(D18+(D18/6),1) -> 2.4 | F18: ='MEP Budget-Y1'!F18*1.1 -> 9350 | H18: =F18*E18 -> 22440 | J18: =H18*12 -> 269280 | L18: =H18/(1-D$69) -> 35185.094 | N18: =ROUNDUP(L18/D18/30,0) -> 587
... A23: 17 | B23: Manlift | D23: 1 | E23: =ROUNDUP(D23+(D23/6),1) -> 1.2 | F23: ='MEP Budget-Y1'!F23*1.1 -> 66000 | H23: =F23*E23 -> 79200 | J23: =H23*12 -> 950400 | L23: =H23/(1-D$69) -> 124182.69 | N23: =ROUNDUP(L23/D23/30,0) -> 4140
B24: Total Direct Manpower - As Per Pricing Sheet | D24: =SUM(D7:D23) -> 36 | E24: =SUM(E7:E23) -> 42.8 | H24: =SUM(H7:H23) -> 614432.5 | J24: =SUM(J7:J23) -> 7373190 | L24: =SUM(L7:L23) -> 963407.55 | N24: Should Be Same
B26: Indirect Costs
A27: A | B27: MEP - Tools + Equipment
A28: 1 | B28: Electrical Tools | E28: 1 | F28: ='MEP Budget-Y1'!F28*1.05 -> 2100 | H28: =E28*F28 -> 2100 | J28: =H28*12 -> 25200
A29: 2 | B29: Carpentry Tools | E29: 1 | F29: ='MEP Budget-Y1'!F29*1.05 -> 1575 | H29: =E29*F29 -> 1575 | J29: =H29*12 -> 18900
A30: 3 | B30: Plumbing Tools | E30: 1 | F30: ='MEP Budget-Y1'!F30*1.05 -> 1575 | H30: =E30*F30 -> 1575 | J30: =H30*12 -> 18900
A31: 4 | B31: Light Current Tools | E31: 1 | F31: ='MEP Budget-Y1'!F31*1.05 -> 1575 | H31: =E31*F31 -> 1575 | J31: =H31*12 -> 18900
A32: 5 | B32: Mechanical Tools | E32: 1 | F32: ='MEP Budget-Y1'!F32*1.05 -> 3465 | H32: =E32*F32 -> 3465 | J32: =H32*12 -> 41580
A33: 6 | B33: Water features Tools | E33: 1 | F33: ='MEP Budget-Y1'!F33*1.05 -> 3465 | H33: =E33*F33 -> 3465 | J33: =H33*12 -> 41580
A34: 7 | B34: MEP Shared Equipment | E34: 1 | F34: ='MEP Budget-Y1'!F34*1.05 -> 9450 | H34: =E34*F34 -> 9450 | J34: =H34*12 -> 113400
A35: B | B35: MEP - Consumables
A36: 1 | B36: Electrical | E36: 1 | F36: ='MEP Budget-Y1'!F36*1.05 -> 2100 | H36: =F36*E36 -> 2100 | J36: =H36*12 -> 25200
A37: 2 | B37: Plumbing | E37: 1 | F37: ='MEP Budget-Y1'!F37*1.05 -> 2100 | H37: =F37*E37 -> 2100 | J37: =H37*12 -> 25200
A38: 3 | B38: Civil | E38: 1 | F38: ='MEP Budget-Y1'!F38*1.05 -> 1050 | H38: =F38*E38 -> 1050 | J38: =H38*12 -> 12600
A39: 4 | B39: LC | E39: 1 | F39: ='MEP Budget-Y1'!F39*1.05 -> 1575 | H39: =F39*E39 -> 1575 | J39: =H39*12 -> 18900
A40: 5 | B40: Mechanical Including Oil Filters …etc | E40: 1 | F40: ='MEP Budget-Y1'!F40*1.05 -> 7875 | H40: =F40*E40 -> 7875 | J40: =H40*12 -> 94500
A41: C | B41: Chemicals - Consumables
A42: 1 | B42: Chlorine | E42: 1 | F42: ='MEP Budget-Y1'!F42*1.1 -> 6160 | H42: =F42*E42 -> 6160 | J42: =H42*12 -> 73920
A43: 2 | B43: Aliga Cide | E43: 1 | F43: ='MEP Budget-Y1'!F43*1.1 -> 2530 | H43: =F43*E43 -> 2530 | J43: =H43*12 -> 30360
A44: 3 | B44: PH Modifier | E44: 1 | F44: ='MEP Budget-Y1'!F44*1.1 -> 3300 | H44: =F44*E44 -> 3300 | J44: =H44*12 -> 39600
A45: 4 | B45: Water Softner | E45: 1 | F45: ='MEP Budget-Y1'!F45*1.1 -> 1100 | H45: =F45*E45 -> 1100 | J45: =H45*12 -> 13200
A46: 5 | B46: Others | E46: 1 | F46: ='MEP Budget-Y1'!F46*1.1 -> 2200 | H46: =F46*E46 -> 2200 | J46: =H46*12 -> 26400
A47: D | B47: Water Tanks - Cleaning & Disinfection
A48: 1 | B48: Zone 2D | E48: 1 | F48: ='MEP Budget-Y1'!F48*1.1 -> 14300 | H48: =F48*E48 -> 14300 | J48: =H48*12 -> 171600
A49: 2 | B49: Zone 3D | E49: 1 | F49: ='MEP Budget-Y1'!F49*1.1 -> 30800 | H49: =F49*E49 -> 30800 | J49: =H49*12 -> 369600
A50: E | B50: CAFM
A51: 1 | B51: Software Accounts - Users | E51: 1 | F51: 8000 | H51: =F51*E51 -> 8000 | J51: =H51*12 -> 96000
A52: 2 | B52: IT Support | E52: 1 | F52: 3000 | H52: =F52*E52 -> 3000 | J52: =H52*12 -> 36000
A53: F | B53: Transportation Outside Site
A54: 1 | B54: Managers Transportation Allowance | E54: =E7+E8 -> 3.6 | F54: ='MEP Budget-Y1'!F54*1.1 -> 1650 | H54: =F54*E54 -> 5940 | J54: =H54*12 -> 71280
A55: 2 | B55: Supervisors & Technicians Transportation Allowance | E55: =SUM(E9:E23) -> 39.2 | F55: ='MEP Budget-Y1'!F55*1.1 -> 1100 | H55: =F55*E55 -> 43120 | J55: =H55*12 -> 517440
A56: G | B56: Others
A57: 1 | B57: Arab Fees | E57: 1 | F57: ='MEP Budget-Y1'!F57*1.15 -> 9200 | H57: =F57*E57 -> 9200 | J57: =H57*12 -> 110400
A58: 2 | B58: Sub-Contractors Management | E58: 1 | F58: ='MEP Budget-Y1'!F58*1.15 -> 10350 | H58: =F58*E58 -> 10350 | J58: =H58*12 -> 124200
A59: 3 | B59: Uniform | E59: =E24 -> 42.8 | F59: 400 | H59: =F59*E59 -> 17120 | J59: =H59*12 -> 205440
A60: 4 | B60: HSE | E60: 0.5 | F60: 18000 | H60: =F60*E60 -> 9000 | J60: =H60*12 -> 108000
B61: Total Of Indirect Costs | H61: =SUM(H28:H34)+SUM(H36:H40)+SUM(H42:H46)+SUM(H48:H49)+SUM(H51:H52)+SUM(H54:H55)+SUM(H57:H60) -> 204025 | J61: =SUM(J28:J34)+SUM(J36:J40)+SUM(J42:J46)+SUM(J48:J49)+SUM(J51:J52)+SUM(J54:J55)+SUM(J57:J60) -> 2448300
B63: Costing Sheet Summary
B64: Direct Costs | D64: =H24 -> 614432.5
B65: In-Direct Costs | D65: =H61 -> 204025 | E65: Monthly | F65: Annualy
A66: 0.14 | B66: FMPlus GP | D66: =(D64+D65)*A66 -> 114584.05 | E66: =SUM(D64+D65+D66+D67) -> 963407.55 | F66: =E66*12 -> 11560891
B67: Mobilization Rate For Y-2 | D67: ='Mobilization Budget'!H109 -> 30366
B69: In-Direct % | D69: =(D66+D67+D65)/(D64+D65+D66+D67) -> 0.36222993
F75: 0 | H75: 0 | J75: 0
F91: 0

Sheet HK & Waste Management-Y1
B2: City Gate - HK & Waste Management Budget (Year 1)
D4: Head Count | F4: Head Cost / CTC | H4: Monthly | J4: Annualy
B6: Direct Costs - As per Pricing Sheet | D6: Sheet HC | E6: Budget HC | L6: FMPlus Rate | N6: Rate / Shift
A7: 1 | B7: HK Supervisors | D7: 2 | E7: 2.8 | F7: 10000 | H7: =F7*E7 -> 28000 | J7: =H7*12 -> 336000 | L7: =H7/(1-D$68) -> 53666.504 | N7: =ROUNDUP(L7/D7/30,0) -> 895
A8: 2 | B8: Janitors | D8: 20 | E8: =ROUNDUP(D8+(D8/6),0)+1 -> 25 | F8: 4900 | H8: =F8*E8 -> 122500 | J8: =H8*12 -> 1470000 | L8: =H8/(1-D$68) -> 234790.96 | N8: =ROUNDUP(L8/D8/30,0) -> 392
A9: 3 | B9: Road Sweeper | D9: 1 | E9: 1 | F9: 120000 | H9: =F9*E9 -> 120000 | J9: =H9*12 -> 1440000 | L9: =H9/(1-D$68) -> 229999.3 | N9: =ROUNDUP(L9/D9/30,0) -> 7667
A10: 4 | B10: Waste Management (Lumpsum item per month) | D10: 1 | E10: 1 | F10: 40000 | H10: =F10*E10 -> 40000 | J10: =H10*12 -> 480000 | L10: =H10/(1-D$68) -> 76666.435 | N10: =ROUNDUP(L10/D10/30,0) -> 2556
A11: 5
A12: 6
A13: 7
A14: 8
A15: 9
A16: 10
A17: 11
A18: 12
A19: 13
A20: 14
A21: 15
A22: 16
A23: 17
B24: Total Direct Manpower - As Per Pricing Sheet | D24: =SUM(D7:D23) -> 24 | E24: =SUM(E7:E23) -> 29.8 | H24: =SUM(H7:H23) -> 310500 | J24: =SUM(J7:J23) -> 3726000 | L24: =SUM(L7:L23) -> 595123.2 | N24: Should Be Same
B26: Indirect Costs
A27: A | B27: HK - Tools + Equipment
A28: 1 | B28: HK - Tools | E28: =E8 -> 25 | F28: 500 | H28: =E28*F28 -> 12500 | J28: =H28*12 -> 150000
A29: 2 | B29: HK - Equipment | E29: =E28 -> 25 | F29: 800 | H29: =E29*F29 -> 20000 | J29: =H29*12 -> 240000
A30: 3
A31: 4
A32: 5
A33: 6
A34: 7
A35: B | B35: HK - Consumables
A36: 1 | B36: HK - Public Consumables | E36: =E29 -> 25 | F36: 300 | H36: =F36*E36 -> 7500 | J36: =H36*12 -> 90000
A37: 2 | B37: HK - Garbage Bags | E37: 2 | F37: 38000 | H37: =F37*E37 -> 76000 | J37: =H37*12 -> 912000
A38: 3
A39: 4
A40: 5
A41: C
A42: 1
A43: 2
A44: 3
A45: 4
A46: 5
A47: D | B47: Management Manpower
A48: 1 | B48: HK Specialist | E48: 1 | F48: 20000 | H48: =F48*E48 -> 20000 | J48: =H48*12 -> 240000
A49: 2
A50: E | B50: CAFM
A51: 1 | B51: Software Accounts - Users | E51: 0.5 | F51: 8000 | H51: =F51*E51 -> 4000 | J51: =H51*12 -> 48000
A52: 2 | B52: IT Support | E52: 1 | F52: 3000 | H52: =F52*E52 -> 3000 | J52: =H52*12 -> 36000
A53: F | B53: Transportation Outside Site
A54: 1 | B54: Managers Transportation Allowance | E54: =E7 -> 2.8 | F54: 2300 | H54: =F54*E54 -> 6440 | J54: =H54*12 -> 77280
A55: 2 | B55: Supervisors & Technicians Transportation Allowance | E55: =E8 -> 25 | F55: 1700 | H55: =F55*E55 -> 42500 | J55: =H55*12 -> 510000
A56: G | B56: Others
A57: 1 | B57: Arab Fees | E57: 1 | F57: 8000 | H57: =F57*E57 -> 8000 | J57: =H57*12 -> 96000
A58: 2 | B58: Sub-Contractors Management | E58: 0 | F58: 9000 | H58: =F58*E58 -> 0 | J58: =H58*12 -> 0
A59: 3 | B59: Uniform | E59: =E24 -> 29.8 | F59: 400 | H59: =F59*E59 -> 11920 | J59: =H59*12 -> 143040
A60: 4 | B60: HSE | E60: 0.5 | F60: 18000 | H60: =F60*E60 -> 9000 | J60: =H60*12 -> 108000
B61: Total Of Indirect Costs | H61: =SUM(H28:H34)+SUM(H36:H40)+SUM(H42:H46)+SUM(H48:H49)+SUM(H51:H52)+SUM(H54:H55)+SUM(H57:H60) -> 220860 | J61: =SUM(J28:J34)+SUM(J36:J40)+SUM(J42:J46)+SUM(J48:J49)+SUM(J51:J52)+SUM(J54:J55)+SUM(J57:J60) -> 2650320
B63: Costing Sheet Summary
B64: Direct Costs | D64: =H24 -> 310500
B65: In-Direct Costs | D65: =H61 -> 220860 | E65: Monthly | F65: Annualy
A66: 0.12 | B66: FMPlus GP | D66: =(D64+D65)*A66 -> 63763.2 | E66: =SUM(D64+D65+D66) -> 595123.2 | F66: =E66*12 -> 7141478.4
B68: In-Direct % | D68: =(D66+D65)/(D64+D65+D66) -> 0.47825929
F74: 0 | H74: 0 | J74: 0
F90: 0

Sheet HK & Waste Management-Y2
B2: City Gate - HK & Waste Management Budget (Year 2)
D4: Head Count | F4: Head Cost / CTC | H4: Monthly | J4: Annualy
B6: Direct Costs - As per Pricing Sheet | D6: Sheet HC | E6: Budget HC | L6: FMPlus Rate | N6: Rate / Shift
A7: 1 | B7: HK Supervisors | D7: 4 | E7: =ROUNDUP(D7+(D7/6),0) -> 5 | F7: ='HK & Waste Management-Y1'!F7*1.15 -> 11500 | H7: =F7*E7 -> 57500 | J7: =H7*12 -> 690000 | L7: =H7/(1-D$69) -> 114514.79 | N7: =ROUNDUP(L7/D7/30,0) -> 955
A8: 2 | B8: Janitors | D8: 40 | E8: =ROUNDUP(D8+(D8/6),0)+1 -> 48 | F8: ='HK & Waste Management-Y1'!F8*1.1 -> 5390 | H8: =F8*E8 -> 258720 | J8: =H8*12 -> 3104640 | L8: =H8/(1-D$69) -> 515256.81 | N8: =ROUNDUP(L8/D8/30,0) -> 430
A9: 3 | B9: Road Sweeper | D9: 1 | E9: 1 | F9: ='HK & Waste Management-Y1'!F9*1.1 + 5000 -> 137000 | H9: =F9*E9 -> 137000 | J9: =H9*12 -> 1644000 | L9: =H9/(1-D$69) -> 272843.93 | N9: =ROUNDUP(L9/D9/30,0) -> 9095
A10: 4 | B10: Waste Management (Lumpsum item per month) | D10: 1 | E10: 1 | F10: ='HK & Waste Management-Y1'!F10*1.1 +27000 -> 71000 | H10: =F10*E10 -> 71000 | J10: =H10*12 -> 852000 | L10: =H10/(1-D$69) -> 141400.87 | N10: =ROUNDUP(L10/D10/30,0) -> 4714
A11: 5
A12: 6
A13: 7
A14: 8
A15: 9
A16: 10
A17: 11
A18: 12
A19: 13
A20: 14
A21: 15
A22: 16
A23: 17
B24: Total Direct Manpower - As Per Pricing Sheet | D24: =SUM(D7:D23) -> 46 | E24: =SUM(E7:E23) -> 55 | H24: =SUM(H7:H23) -> 524220 | J24: =SUM(J7:J23) -> 6290640 | L24: =SUM(L7:L23) -> 1044016.4 | N24: Should Be Same
B26: Indirect Costs
A27: A | B27: HK - Tools + Equipment
A28: 1 | B28: HK - Tools | E28: =E8 -> 48 | F28: 500 | H28: =E28*F28 -> 24000 | J28: =H28*12 -> 288000
A29: 2 | B29: HK - Equipment | E29: =E28 -> 48 | F29: 800 | H29: =E29*F29 -> 38400 | J29: =H29*12 -> 460800
A30: 3
A31: 4
A32: 5
A33: 6
A34: 7
A35: B | B35: HK - Consumables
A36: 1 | B36: HK - Public Consumables | E36: =E29 -> 48 | F36: 300 | H36: =F36*E36 -> 14400 | J36: =H36*12 -> 172800
A37: 2 | B37: HK - Garbage Bags | E37: 3 | F37: =38000 -> 38000 | H37: =F37*E37 -> 114000 | J37: =H37*12 -> 1368000
A38: 3
A39: 4
A40: 5
A41: C
A42: 1
A43: 2
A44: 3
A45: 4
A46: 5
A47: D | B47: Management Manpower
A48: 1 | B48: HK Specialist | E48: 1 | F48: =23000*1.1 -> 25300 | H48: =F48*E48 -> 25300 | J48: =H48*12 -> 303600
A49: 2
A50: E | B50: CAFM
A51: 1 | B51: Software Accounts - Users | E51: 0.5 | F51: 8000 | H51: =F51*E51 -> 4000 | J51: =H51*12 -> 48000
A52: 2 | B52: IT Support | E52: 1 | F52: 3000 | H52: =F52*E52 -> 3000 | J52: =H52*12 -> 36000
A53: F | B53: Transportation Outside Site
A54: 1 | B54: Managers Transportation Allowance | E54: =E7 -> 5 | F54: =2300*1.1 -> 2530 | H54: =F54*E54 -> 12650 | J54: =H54*12 -> 151800
A55: 2 | B55: Supervisors & Technicians Transportation Allowance | E55: =E8 -> 48 | F55: =1800*1.1 -> 1980 | H55: =F55*E55 -> 95040 | J55: =H55*12 -> 1140480
A56: G | B56: Others
A57: 1 | B57: Arab Fees | E57: 1 | F57: 8000 | H57: =F57*E57 -> 8000 | J57: =H57*12 -> 96000
A58: 2 | B58: Sub-Contractors Management | E58: 0 | F58: 9000 | H58: =F58*E58 -> 0 | J58: =H58*12 -> 0
A59: 3 | B59: Uniform | E59: =E24 -> 55 | F59: 400 | H59: =F59*E59 -> 22000 | J59: =H59*12 -> 264000
A60: 4 | B60: HSE | E60: 0.5 | F60: 18000 | H60: =F60*E60 -> 9000 | J60: =H60*12 -> 108000
B61: Total Of Indirect Costs | H61: =SUM(H28:H34)+SUM(H36:H40)+SUM(H42:H46)+SUM(H48:H49)+SUM(H51:H52)+SUM(H54:H55)+SUM(H57:H60) -> 369790 | J61: =SUM(J28:J34)+SUM(J36:J40)+SUM(J42:J46)+SUM(J48:J49)+SUM(J51:J52)+SUM(J54:J55)+SUM(J57:J60) -> 4437480
B63: Costing Sheet Summary
B64: Direct Costs | D64: =H24 -> 524220
B65: In-Direct Costs | D65: =H61 -> 369790 | E65: Monthly | F65: Annualy
A66: 0.14 | B66: FMPlus GP | D66: =(D64+D65)*A66 -> 125161.4 | E66: =SUM(D64+D65+D66+D67) -> 1044016.4 | F66: =E66*12 -> 12528197
B67: Mobilization Rate For Y-2 | D67: ='Mobilization Budget'!H110 -> 24845
B69: In-Direct % | D69: =(D66+D65+D67)/(D64+D65+D66+D67) -> 0.49788145
F75: 0 | H75: 0 | J75: 0
F91: 0

Sheet Pest Control Y-1
B2: City Gate - Pest Control Budget (Year 1)
D4: Head Count | F4: Head Cost / CTC | H4: Monthly | J4: Annualy
B6: Direct Costs - As per Pricing Sheet | D6: Sheet HC | E6: Budget HC | L6: FMPlus Rate | N6: Rate / Shift
A7: 1 | B7: ='[46]Manning Schedule'!B39 -> Pest Control Supervisor | D7: ='[46]Manning Schedule'!D39 -> 1 | E7: =2 -> 2 | F7: 9000 | H7: =F7*E7 -> 18000 | J7: =H7*12 -> 216000 | L7: =H7/(1-D$68) -> 25474.248 | N7: =ROUNDUP(L7/D7/30,0) -> 850
A8: 2 | B8: ='[46]Manning Schedule'!B40 -> Pest Control Service (Lumpsum item per month) | D8: ='[46]Manning Schedule'!D40 -> 1 | E8: 1 | F8: 41320 | H8: =F8*E8 -> 41320 | J8: =H8*12 -> 495840 | L8: =H8/(1-D$68) -> 58477.552 | N8: =ROUNDUP(L8/D8/30,0) -> 1950
A9: 3 | L9: =H9/(1-D$68) -> 0 | N9: =ROUNDUP(L9/D9/30,0) -> #DIV/0!
A10: 4 | L10: =H10/(1-D$68) -> 0 | N10: =ROUNDUP(L10/D10/30,0) -> #DIV/0!
A11: 5
A12: 6
A13: 7
A14: 8
A15: 9
A16: 10
A17: 11
A18: 12
A19: 13
A20: 14
A21: 15
A22: 16
A23: 17
B24: Total Direct Manpower - As Per Pricing Sheet | D24: =SUM(D7:D23) -> 2 | E24: =SUM(E7:E23) -> 3 | H24: =SUM(H7:H23) -> 59320 | J24: =SUM(J7:J23) -> 711840 | L24: =SUM(L7:L23) -> 83951.8 | N24: Should Be Same
B26: Indirect Costs
A27: A
A28: 1
A29: 2
A30: 3
A31: 4
A32: 5
A33: 6
A34: 7
A35: B
A36: 1
A37: 2
A38: 3
A39: 4
A40: 5
A41: C
A42: 1
A43: 2
A44: 3
A45: 4
A46: 5
A47: D
A48: 1
A49: 2
A50: E | B50: CAFM
A51: 1 | B51: Software Accounts - Users | E51: 0.5 | F51: 8000 | H51: =F51*E51 -> 4000 | J51: =H51*12 -> 48000
A52: 2 | B52: IT Support | E52: 0.5 | F52: 3000 | H52: =F52*E52 -> 1500 | J52: =H52*12 -> 18000
A53: F | B53: Transportation Outside Site
A54: 1 | B54: Managers Transportation Allowance | E54: =E7 -> 2 | F54: 2300 | H54: =F54*E54 -> 4600 | J54: =H54*12 -> 55200
A55: 2
A56: G | B56: Others
A57: 1 | B57: Arab Fees | E57: 0.25 | F57: 8000 | H57: =F57*E57 -> 2000 | J57: =H57*12 -> 24000
A58: 2 | B58: Sub-Contractors Management | E58: 0 | F58: 9000 | H58: =F58*E58 -> 0 | J58: =H58*12 -> 0
A59: 3 | B59: Uniform | E59: 5 | F59: 400 | H59: =F59*E59 -> 2000 | J59: =H59*12 -> 24000
A60: 4 | B60: HSE | E60: 0.2 | F60: 18000 | H60: =F60*E60 -> 3600 | J60: =H60*12 -> 43200
B61: Total Of Indirect Costs | H61: =SUM(H28:H34)+SUM(H36:H40)+SUM(H42:H46)+SUM(H48:H49)+SUM(H51:H52)+SUM(H54:H55)+SUM(H57:H60) -> 17700 | J61: =SUM(J28:J34)+SUM(J36:J40)+SUM(J42:J46)+SUM(J48:J49)+SUM(J51:J52)+SUM(J54:J55)+SUM(J57:J60) -> 212400
B63: Costing Sheet Summary
B64: Direct Costs | D64: =H24 -> 59320
B65: In-Direct Costs | D65: =H61 -> 17700 | E65: Monthly | F65: Annualy
A66: 0.09 | B66: FMPlus GP | D66: =(D64+D65)*A66 -> 6931.8 | E66: =SUM(D64+D65+D66) -> 83951.8 | F66: =E66*12 -> 1007421.6
B68: In-Direct % | D68: =(D66+D65)/(D64+D65+D66) -> 0.29340407
F74: 0 | H74: 0 | J74: 0
F90: 0

Sheet Pest Control Y-2
B2: City Gate - Pest Control Budget (Year 2)
D4: Head Count | F4: Head Cost / CTC | H4: Monthly | J4: Annualy
B6: Direct Costs - As per Pricing Sheet | D6: Sheet HC | E6: Budget HC | L6: FMPlus Rate | N6: Rate / Shift
A7: 1 | B7: ='[46]Manning Schedule'!B39 -> Pest Control Supervisor | D7: ='[46]Manning Schedule'!D39 -> 1 | E7: =2 -> 2 | F7: 9900 | H7: =F7*E7 -> 19800 | J7: =H7*12 -> 237600 | L7: =H7/(1-D$69) -> 25318.751 | N7: =ROUNDUP(L7/D7/30,0) -> 844
A8: 2 | B8: ='[46]Manning Schedule'!B40 -> Pest Control Service (Lumpsum item per month) | D8: ='[46]Manning Schedule'!D40 -> 1 | E8: 1 | F8: 119000 | H8: =F8*E8 -> 119000 | J8: =H8*12 -> 1428000 | L8: =H8/(1-D$69) -> 152168.25 | N8: =ROUNDUP(L8/D8/30,0) -> 5073
A9: 3 | L9: =H9/(1-D$69) -> 0 | N9: =ROUNDUP(L9/D9/30,0) -> #DIV/0!
A10: 4 | L10: =H10/(1-D$69) -> 0 | N10: =ROUNDUP(L10/D10/30,0) -> #DIV/0!
A11: 5
A12: 6
A13: 7
A14: 8
A15: 9
A16: 10
A17: 11
A18: 12
A19: 13
A20: 14
A21: 15
A22: 16
A23: 17
B24: Total Direct Manpower - As Per Pricing Sheet | D24: =SUM(D7:D23) -> 2 | E24: =SUM(E7:E23) -> 3 | H24: =SUM(H7:H23) -> 138800 | J24: =SUM(J7:J23) -> 1665600 | L24: =SUM(L7:L23) -> 177487 | N24: Should Be Same
B26: Indirect Costs
A27: A
A28: 1
A29: 2
A30: 3
A31: 4
A32: 5
A33: 6
A34: 7
A35: B
A36: 1
A37: 2
A38: 3
A39: 4
A40: 5
A41: C
A42: 1
A43: 2
A44: 3
A45: 4
A46: 5
A47: D
A48: 1
A49: 2
A50: E | B50: CAFM
A51: 1 | B51: Software Accounts - Users | E51: 0.5 | F51: 8000 | H51: =F51*E51 -> 4000 | J51: =H51*12 -> 48000
A52: 2 | B52: IT Support | E52: 0.5 | F52: 3000 | H52: =F52*E52 -> 1500 | J52: =H52*12 -> 18000
A53: F | B53: Transportation Outside Site
A54: 1 | B54: Managers Transportation Allowance | E54: =E7 -> 2 | F54: 2300 | H54: =F54*E54 -> 4600 | J54: =H54*12 -> 55200
A55: 2
A56: G | B56: Others
A57: 1 | B57: Arab Fees | E57: 0.25 | F57: 8000 | H57: =F57*E57 -> 2000 | J57: =H57*12 -> 24000
A58: 2 | B58: Sub-Contractors Management | E58: 0 | F58: 9000 | H58: =F58*E58 -> 0 | J58: =H58*12 -> 0
A59: 3 | B59: Uniform | E59: 5 | F59: 400 | H59: =F59*E59 -> 2000 | J59: =H59*12 -> 24000
A60: 4 | B60: HSE | E60: 0.2 | F60: 18000 | H60: =F60*E60 -> 3600 | J60: =H60*12 -> 43200
B61: Total Of Indirect Costs | H61: =SUM(H28:H34)+SUM(H36:H40)+SUM(H42:H46)+SUM(H48:H49)+SUM(H51:H52)+SUM(H54:H55)+SUM(H57:H60) -> 17700 | J61: =SUM(J28:J34)+SUM(J36:J40)+SUM(J42:J46)+SUM(J48:J49)+SUM(J51:J52)+SUM(J54:J55)+SUM(J57:J60) -> 212400
B63: Costing Sheet Summary
B64: Direct Costs | D64: =H24 -> 138800
B65: In-Direct Costs | D65: =H61 -> 17700 | E65: Monthly | F65: Annualy
A66: 0.09 | B66: FMPlus GP | D66: =(D64+D65)*A66 -> 14085 | E66: =SUM(D64+D65+D66+D67) -> 177487 | F66: =E66*12 -> 2129844
B67: Mobilization Rate For Y-2 | D67: ='Mobilization Budget'!H111 -> 6902
B69: In-Direct % | D69: =(D66+D65+D67)/(D64+D65+D66+D67) -> 0.21797089
F75: 0 | H75: 0 | J75: 0
F91: 0

Sheet Landscape Y1
B2: City Gate - Landscape Year 1
D4: Head Count | F4: Head Cost / CTC | H4: Monthly | J4: Annualy
B6: Direct Costs - As per Pricing Sheet | D6: Sheet HC | E6: Budget HC | L6: FMPlus Rate | N6: Rate / Shift
A7: 1 | B7: ='[46]Manning Schedule'!B43 -> Landscape Manager | D7: ='[46]Manning Schedule'!D43 -> 1 | E7: 1 | F7: 24000 | H7: =F7*E7 -> 24000 | J7: =H7*12 -> 288000 | L7: =H7/(1-D$68) -> 58723 | N7: =ROUNDUP(L7/D7/30,0) -> 1958
A8: 2 | B8: ='[46]Manning Schedule'!B44 -> Landscape Supervisor | D8: ='[46]Manning Schedule'!D44 -> 2 | E8: =ROUNDUP(D8+(D8/6),0)+1 -> 4 | F8: 9800 | H8: =F8*E8 -> 39200 | J8: =H8*12 -> 470400 | L8: =H8/(1-D$68) -> 95914.233 | N8: =ROUNDUP(L8/D8/30,0) -> 1599
A9: 3 | B9: ='[46]Manning Schedule'!B45 -> Gardner | D9: ='[46]Manning Schedule'!D45 -> 20 | E9: 28 | F9: 4600 | H9: =F9*E9 -> 128800 | J9: =H9*12 -> 1545600 | L9: =H9/(1-D$68) -> 315146.77 | N9: =ROUNDUP(L9/D9/30,0) -> 526
A10: 4
A11: 5
A12: 6
A13: 7
A14: 8
A15: 9
A16: 10
A17: 11
A18: 12
A19: 13
A20: 14
A21: 15
... A23: 17
B24: Total Direct Manpower - As Per Pricing Sheet | D24: =SUM(D7:D23) -> 23 | E24: =SUM(E7:E23) -> 33 | H24: =SUM(H7:H23) -> 192000 | J24: =SUM(J7:J23) -> 2304000 | L24: =SUM(L7:L23) -> 469784 | N24: Should Be Same
L25: =L24/D35 -> 10.48625
B26: Indirect Costs
A27: A | B27: LS - Tools + Equipment
A28: 1 | B28: LS - Tools | E28: =E9 -> 28 | F28: 400 | H28: =E28*F28 -> 11200 | J28: =H28*12 -> 134400
A29: 2 | B29: LS - Equipment | E29: =E28 -> 28 | F29: 600 | H29: =E29*F29 -> 16800 | J29: =H29*12 -> 201600
A30: 3
A31: 4
A32: 5
A33: 6
A34: 7
A35: B | B35: LS - Consumables | D35: 44800
A36: 1 | B36: LS - Fertilizers | E36: =D35 -> 44800 | F36: 0.9 | H36: =F36*E36 -> 40320 | J36: =H36*12 -> 483840
A37: 2 | B37: LS- Chemicals | E37: =D35 -> 44800 | F37: 1.1 | H37: =F37*E37 -> 49280 | J37: =H37*12 -> 591360
A38: 3 | B38: LS- Petsidies | E38: =D35 -> 44800 | F38: 0.5 | H38: =F38*E38 -> 22400 | J38: =H38*12 -> 268800
A39: 4
A40: 5
A41: C
A42: 1
A43: 2
A44: 3
A45: 4
A46: 5
A47: D | B47: Landscape Wastes
A48: 1 | B48: Waste Collection | E48: 1 | F48: 22000 | H48: =F48*E48 -> 22000 | J48: =H48*12 -> 264000
A49: 2 | B49: Waste Bags | E49: 25 | F49: 150 | H49: =F49*E49 -> 3750 | J49: =H49*12 -> 45000
A50: E | B50: CAFM
A51: 1 | B51: Software Accounts - Users | E51: 0.25 | F51: 8000 | H51: =F51*E51 -> 2000 | J51: =H51*12 -> 24000
A52: 2 | B52: IT Support | E52: 1 | F52: 3000 | H52: =F52*E52 -> 3000 | J52: =H52*12 -> 36000
A53: F | B53: Transportation Outside Site
A54: 1 | B54: Managers Transportation Allowance | E54: =E8+E7 -> 5 | F54: 1200 | H54: =F54*E54 -> 6000 | J54: =H54*12 -> 72000
A55: 2 | B55: Supervisors & Technicians Transportation Allowance | E55: =E9 -> 28 | F55: 1000 | H55: =F55*E55 -> 28000 | J55: =H55*12 -> 336000
A56: G | B56: Others
A57: 1 | B57: Arab Fees | E57: 1 | F57: 5000 | H57: =F57*E57 -> 5000 | J57: =H57*12 -> 60000
A58: 2 | B58: Sub-Contractors Management | E58: 0 | F58: 9000 | H58: =F58*E58 -> 0 | J58: =H58*12 -> 0
A59: 3 | B59: Uniform | E59: =E24 -> 33 | F59: 400 | H59: =F59*E59 -> 13200 | J59: =H59*12 -> 158400
A60: 4 | B60: HSE | E60: 0.25 | F60: 18000 | H60: =F60*E60 -> 4500 | J60: =H60*12 -> 54000
B61: Total Of Indirect Costs | H61: =SUM(H28:H34)+SUM(H36:H40)+SUM(H42:H46)+SUM(H48:H49)+SUM(H51:H52)+SUM(H54:H55)+SUM(H57:H60) -> 227450 | J61: =SUM(J28:J34)+SUM(J36:J40)+SUM(J42:J46)+SUM(J48:J49)+SUM(J51:J52)+SUM(J54:J55)+SUM(J57:J60) -> 2729400
B63: Costing Sheet Summary
B64: Direct Costs | D64: =H24 -> 192000
B65: In-Direct Costs | D65: =H61 -> 227450 | E65: Monthly | F65: Annualy
A66: 0.12 | B66: FMPlus GP | D66: =(D64+D65)*A66 -> 50334 | E66: =SUM(D64+D65+D66) -> 469784 | F66: =E66*12 -> 5637408
B68: In-Direct % | D68: =(D66+D65)/(D64+D65+D66) -> 0.59130153
F74: 0 | H74: 0 | J74: 0
F90: 0

Sheet Landscape Y2
B2: City Gate - Landscape Year 2
D4: Head Count | F4: Head Cost / CTC | H4: Monthly | J4: Annualy
B6: Direct Costs - As per Pricing Sheet | D6: Sheet HC | E6: Budget HC | L6: FMPlus Rate | N6: Rate / Shift
A7: 1 | B7: ='[46]Manning Schedule'!B43 -> Landscape Manager | D7: ='[46]Manning Schedule'!V43 -> 1 | E7: 0.6 | F7: ='Landscape Y1'!F7*1.25 -> 30000 | H7: =F7*E7 -> 18000 | J7: =H7*12 -> 216000 | L7: =H7/(1-D$69) -> 65360.469 | N7: =ROUNDUP(L7/D7/30,0) -> 2179
A8: 2 | B8: ='[46]Manning Schedule'!B44 -> Landscape Supervisor | D8: ='[46]Manning Schedule'!V44 -> 4 | E8: 5 | F8: ='Landscape Y1'!F8*1.1 -> 10780 | H8: =F8*E8 -> 53900 | J8: =H8*12 -> 646800 | L8: =H8/(1-D$69) -> 195718.29 | N8: =ROUNDUP(L8/D8/30,0) -> 1631
A9: 3 | B9: ='[46]Manning Schedule'!B45 -> Gardner | D9: ='[46]Manning Schedule'!V45 -> 60 | E9: 70 | F9: 4400 | H9: =F9*E9 -> 308000 | J9: =H9*12 -> 3696000 | L9: =H9/(1-D$69) -> 1118390.3 | N9: =ROUNDUP(L9/D9/30,0) -> 622
A10: 4
A11: 5
A12: 6
A13: 7
A14: 8
A15: 9
A16: 10
A17: 11
A18: 12
A19: 13
A20: 14
A21: 15
... A23: 17
B24: Total Direct Manpower - As Per Pricing Sheet | D24: =SUM(D7:D23) -> 65 | E24: =SUM(E7:E23) -> 75.6 | H24: =SUM(H7:H23) -> 379900 | J24: =SUM(J7:J23) -> 4558800 | L24: =SUM(L7:L23) -> 1379469 | N24: Should Be Same
L25: =L24/D35 -> 5.6846407
B26: Indirect Costs
A27: A | B27: LS - Tools + Equipment
A28: 1 | B28: LS - Tools | E28: =E9 -> 70 | F28: ='Landscape Y1'!F28*1.1 -> 440 | H28: =E28*F28 -> 30800 | J28: =H28*12 -> 369600
A29: 2 | B29: LS - Equipment | E29: =E28 -> 70 | F29: ='Landscape Y1'!F29*1.1 -> 660 | H29: =E29*F29 -> 46200 | J29: =H29*12 -> 554400
A30: 3
A31: 4
A32: 5
A33: 6
A34: 7
A35: B | B35: LS - Consumables | D35: 242666
A36: 1 | B36: LS - Fertilizers | E36: =D35 -> 242666 | F36: 0.76 | H36: =F36*E36 -> 184426.16 | J36: =H36*12 -> 2213113.9
A37: 2 | B37: LS- Chemicals | E37: =D35 -> 242666 | F37: 0.87 | H37: =F37*E37 -> 211119.42 | J37: =H37*12 -> 2533433
A38: 3 | B38: LS- Petsidies | E38: =D35 -> 242666 | F38: 0.45 | H38: =F38*E38 -> 109199.7 | J38: =H38*12 -> 1310396.4
A39: 4
A40: 5
A41: C
A42: 1
A43: 2
A44: 3
A45: 4
A46: 5
A47: D | B47: Landscape Wastes
A48: 1 | B48: Waste Collection | E48: 1 | F48: 67000 | H48: =F48*E48 -> 67000 | J48: =H48*12 -> 804000
A49: 2 | B49: Waste Bags | E49: 100 | F49: 150 | H49: =F49*E49 -> 15000 | J49: =H49*12 -> 180000
A50: E | B50: CAFM
A51: 1 | B51: Software Accounts - Users | E51: 0.25 | F51: 8000 | H51: =F51*E51 -> 2000 | J51: =H51*12 -> 24000
A52: 2 | B52: IT Support | E52: 1 | F52: 3000 | H52: =F52*E52 -> 3000 | J52: =H52*12 -> 36000
A53: F | B53: Transportation Outside Site
A54: 1 | B54: Managers Transportation Allowance | E54: =E8+E7 -> 5.6 | F54: 1200 | H54: =F54*E54 -> 6720 | J54: =H54*12 -> 80640
A55: 2 | B55: Supervisors & Technicians Transportation Allowance | E55: =E9 -> 70 | F55: 1000 | H55: =F55*E55 -> 70000 | J55: =H55*12 -> 840000
A56: G | B56: Others
A57: 1 | B57: Arab Fees | E57: 1 | F57: 10000 | H57: =F57*E57 -> 10000 | J57: =H57*12 -> 120000
A58: 2 | B58: Sub-Contractors Management | E58: 0 | F58: 9000 | H58: =F58*E58 -> 0 | J58: =H58*12 -> 0
A59: 3 | B59: Uniform | E59: =E24 -> 75.6 | F59: 400 | H59: =F59*E59 -> 30240 | J59: =H59*12 -> 362880
A60: 4 | B60: HSE | E60: 0.25 | F60: 18000 | H60: =F60*E60 -> 4500 | J60: =H60*12 -> 54000
B61: Total Of Indirect Costs | H61: =SUM(H28:H34)+SUM(H36:H40)+SUM(H42:H46)+SUM(H48:H49)+SUM(H51:H52)+SUM(H54:H55)+SUM(H57:H60) -> 790205.28 | J61: =SUM(J28:J34)+SUM(J36:J40)+SUM(J42:J46)+SUM(J48:J49)+SUM(J51:J52)+SUM(J54:J55)+SUM(J57:J60) -> 9482463.4
B63: Costing Sheet Summary
B64: Direct Costs | D64: =H24 -> 379900
B65: In-Direct Costs | D65: =H61 -> 790205.28 | E65: Monthly | F65: Annualy
A66: 0.14 | B66: FMPlus GP | D66: =(D64+D65)*A66 -> 163814.74 | E66: =SUM(D64+D65+D66+D67) -> 1379469 | F66: =E66*12 -> 16553628
B67: Mobilization Rate For Y-2 | D67: ='Mobilization Budget'!H112 -> 45549
B69: In-Direct % | D69: =(D66+D65+D67)/(D64+D65+D66+D67) -> 0.72460418
F75: 0 | H75: 0 | J75: 0
F91: 0

Sheet Security Y1
B2: City Gate - Security Y1
D4: Head Count | F4: Head Cost / CTC | H4: Monthly | J4: Annualy
B6: Direct Costs - As per Pricing Sheet | D6: Sheet HC | E6: Budget HC | L6: FMPlus Rate | N6: Rate / Shift
A7: 1 | B7: ='[46]Manning Schedule'!B48 -> Security Manger | D7: ='[46]Manning Schedule'!D48 -> 1 | E7: =D7+(D7/5) -> 1.2 | F7: 18000 | H7: =F7*E7 -> 21600 | J7: =H7*12 -> 259200 | L7: =H7/(1-D$68) -> 41217.757 | N7: =ROUNDUP(L7/D7/30,0) -> 1374
A8: 2 | B8: ='[46]Manning Schedule'!B49 -> Safety Supervisor / Agent | D8: ='[46]Manning Schedule'!D49 -> 2 | E8: =D8+(D8/5) -> 2.4 | F8: 12000 | H8: =F8*E8 -> 28800 | J8: =H8*12 -> 345600 | L8: =H8/(1-D$68) -> 54957.009 | N8: =ROUNDUP(L8/D8/30,0) -> 916
A9: 3 | B9: ='[46]Manning Schedule'!B50 -> Security Supervisor / per shift | D9: ='[46]Manning Schedule'!D50*2 -> 2 | E9: =D9+(D9/5) -> 2.4 | F9: 8110 | H9: =F9*E9 -> 19464 | J9: =H9*12 -> 233568 | L9: =H9/(1-D$68) -> 37141.779 | N9: =ROUNDUP(L9/D9/30,0) -> 620
A10: 4 | B10: ='[46]Manning Schedule'!B51 -> Security Guards / per shift | D10: ='[46]Manning Schedule'!D51*2 -> 80 | E10: =D10+(D10/5) -> 96 | F10: 4500 | H10: =F10*E10 -> 432000 | J10: =H10*12 -> 5184000 | L10: =H10/(1-D$68) -> 824355.14 | N10: =ROUNDUP(L10/D10/30,0) -> 344
A11: 5 | B11: ='[46]Manning Schedule'!B52 -> CCTV Operator | D11: ='[46]Manning Schedule'!D52 -> 0 | E11: =D11+(D11/5) -> 0 | F11: 8000 | H11: =F11*E11 -> 0 | J11: =H11*12 -> 0 | L11: =H11/(1-D$68) -> 0 | N11: =ROUNDUP(L11/D11/30,0) -> #DIV/0!
A12: 6
A13: 7
A14: 8
A15: 9
A16: 10
A17: 11
A18: 12
A19: 13
A20: 14
A21: 15
A22: 16
A23: 17
B24: Total Direct Manpower - As Per Pricing Sheet | D24: =SUM(D7:D23) -> 85 | E24: =SUM(E7:E23) -> 102 | H24: =SUM(H7:H23) -> 501864 | J24: =SUM(J7:J23) -> 6022368 | L24: =SUM(L7:L23) -> 957671.68 | N24: Should Be Same
B26: Indirect Costs
A27: A | B27: Security Tools & Equipment
A28: 1 | B28: Security - عصا | E28: 20 | F28: 90 | H28: =E28*F28 -> 1800 | J28: =H28*12 -> 21600
A29: 2 | B29: Security Lighting | E29: 40 | F29: 75 | H29: =E29*F29 -> 3000 | J29: =H29*12 -> 36000
A30: 3 | B30: Secuirty Walkie Takie | E30: 22 | F30: 850 | H30: =E30*F30 -> 18700 | J30: =H30*12 -> 224400
A31: 4
A32: 5
A33: 6
A34: 7
A35: B | B35: Secuirty Consumables
A36: 1 | B36: Documentation | E36: 1 | F36: 3000 | H36: =F36*E36 -> 3000 | J36: =H36*12 -> 36000
A37: 2 | B37: Visitors ID | E37: 1 | F37: 2000 | H37: =F37*E37 -> 2000 | J37: =H37*12 -> 24000
A38: 3 | B38: Fuel for Scooters | E38: 4 | F38: 2000 | H38: =F38*E38 -> 8000 | J38: =H38*12 -> 96000
A39: 4 | B39: Fuel For Cars | E39: 1 | F39: 5000 | H39: =F39*E39 -> 5000 | J39: =H39*12 -> 60000
A40: 5
A41: C
A42: 1
A43: 2
A44: 3
A45: 4
A46: 5
A47: D | B47: Accommodation
A48: 1 | B48: Apartments for guards & Supervisors | E48: =(E10+E9+E8)/8 -> 12.6 | F48: 12000 | H48: =F48*E48 -> 151200 | J48: =H48*12 -> 1814400
A49: 2
A50: E | B50: CAFM
A51: 1 | B51: Software Accounts - Users | E51: 0.5 | F51: 8000 | H51: =F51*E51 -> 4000 | J51: =H51*12 -> 48000
A52: 2 | B52: IT Support | E52: 1 | F52: 3000 | H52: =F52*E52 -> 3000 | J52: =H52*12 -> 36000
A53: F | B53: Transportation Outside Site
A54: 1 | B54: Managers Transportation Allowance | E54: =E7+E8+E9 -> 6 | F54: 1200 | H54: =F54*E54 -> 7200 | J54: =H54*12 -> 86400
A55: 2 | B55: Supervisors & Technicians Transportation Allowance | E55: =E10 -> 96 | F55: 1000 | H55: =F55*E55 -> 96000 | J55: =H55*12 -> 1152000
A56: G | B56: Others
A57: 1 | B57: Arab Fees | E57: 1 | F57: 5000 | H57: =F57*E57 -> 5000 | J57: =H57*12 -> 60000
A58: 2 | B58: Sub-Contractors Management | E58: 0 | F58: 9000 | H58: =F58*E58 -> 0 | J58: =H58*12 -> 0
A59: 3 | B59: Uniform | E59: =E24 -> 102 | F59: 400 | H59: =F59*E59 -> 40800 | J59: =H59*12 -> 489600
A60: 4 | B60: HSE | E60: 0.25 | F60: 18000 | H60: =F60*E60 -> 4500 | J60: =H60*12 -> 54000
B61: Total Of Indirect Costs | H61: =SUM(H28:H34)+SUM(H36:H40)+SUM(H42:H46)+SUM(H48:H49)+SUM(H51:H52)+SUM(H54:H55)+SUM(H57:H60) -> 353200 | J61: =SUM(J28:J34)+SUM(J36:J40)+SUM(J42:J46)+SUM(J48:J49)+SUM(J51:J52)+SUM(J54:J55)+SUM(J57:J60) -> 4238400
B63: Costing Sheet Summary
B64: Direct Costs | D64: =H24 -> 501864
B65: In-Direct Costs | D65: =H61 -> 353200 | E65: Monthly | F65: Annualy
A66: 0.12 | B66: FMPlus GP | D66: =(D64+D65)*A66 -> 102607.68 | E66: =SUM(D64+D65+D66) -> 957671.68 | F66: =E66*12 -> 11492060
B68: In-Direct % | D68: =(D66+D65)/(D64+D65+D66) -> 0.47595401
F74: 0 | H74: 0 | J74: 0
F90: 0

Sheet Security Y2
B2: City Gate - Security Y2
D4: Head Count | F4: Head Cost / CTC | H4: Monthly | J4: Annualy
B6: Direct Costs - As per Pricing Sheet | D6: Sheet HC | E6: Budget HC | L6: FMPlus Rate | N6: Rate / Shift
A7: 1 | B7: ='[46]Manning Schedule'!B48 -> Security Manger | D7: ='[46]Manning Schedule'!V48 -> 1 | E7: =D7+(D7/5) -> 1.2 | F7: ='Security Y1'!F7*1.08 -> 19440 | H7: =F7*E7 -> 23328 | J7: =H7*12 -> 279936 | L7: =H7/(1-D$69) -> 43653.267 | N7: =ROUNDUP(L7/D7/30,0) -> 1456
A8: 2 | B8: ='[46]Manning Schedule'!B49 -> Safety Supervisor / Agent | D8: ='[46]Manning Schedule'!V49 -> 4 | E8: =D8+(D8/5) -> 4.8 | F8: ='Security Y1'!F8*1.08 -> 12960 | H8: =F8*E8 -> 62208 | J8: =H8*12 -> 746496 | L8: =H8/(1-D$69) -> 116408.71 | N8: =ROUNDUP(L8/D8/30,0) -> 971
A9: 3 | B9: ='[46]Manning Schedule'!B50 -> Security Supervisor / per shift | D9: ='[46]Manning Schedule'!V50*2 -> 2 | E9: =D9+(D9/5) -> 2.4 | F9: ='Security Y1'!F9*1.08 -> 8758.8 | H9: =F9*E9 -> 21021.12 | J9: =H9*12 -> 252253.44 | L9: =H9/(1-D$69) -> 39336.444 | N9: =ROUNDUP(L9/D9/30,0) -> 656
A10: 4 | B10: ='[46]Manning Schedule'!B51 -> Security Guards / per shift | D10: ='[46]Manning Schedule'!V51*2 -> 240 | E10: =D10+(D10/5) -> 288 | F10: ='Security Y1'!F10*1.08 -> 4860 | H10: =F10*E10 -> 1399680 | J10: =H10*12 -> 16796160 | L10: =H10/(1-D$69) -> 2619196 | N10: =ROUNDUP(L10/D10/30,0) -> 364
A11: 5 | B11: ='[46]Manning Schedule'!B52 -> CCTV Operator | D11: ='[46]Manning Schedule'!V52 -> 2 | E11: =D11+(D11/5) -> 2.4 | F11: ='Security Y1'!F11*1.08 -> 8640 | H11: =F11*E11 -> 20736 | J11: =H11*12 -> 248832 | L11: =H11/(1-D$69) -> 38802.904 | N11: =ROUNDUP(L11/D11/30,0) -> 647
A12: 6
A13: 7
A14: 8
A15: 9
A16: 10
A17: 11
A18: 12
A19: 13
A20: 14
A21: 15
A22: 16
A23: 17
B24: Total Direct Manpower - As Per Pricing Sheet | D24: =SUM(D7:D23) -> 249 | E24: =SUM(E7:E23) -> 298.8 | H24: =SUM(H7:H23) -> 1526973.1 | J24: =SUM(J7:J23) -> 18323677 | L24: =SUM(L7:L23) -> 2857397.4 | N24: Should Be Same
B26: Indirect Costs
A27: A | B27: Security Tools & Equipment
A28: 1 | B28: Security - عصا | E28: 20 | F28: 90 | H28: =E28*F28 -> 1800 | J28: =H28*12 -> 21600
A29: 2 | B29: Security Lighting | E29: 40 | F29: 75 | H29: =E29*F29 -> 3000 | J29: =H29*12 -> 36000
A30: 3 | B30: Secuirty Walkie Takie | E30: 22 | F30: 850 | H30: =E30*F30 -> 18700 | J30: =H30*12 -> 224400
A31: 4
A32: 5
A33: 6
A34: 7
A35: B | B35: Secuirty Consumables
A36: 1 | B36: Documentation | E36: 1 | F36: 3000 | H36: =F36*E36 -> 3000 | J36: =H36*12 -> 36000
A37: 2 | B37: Visitors ID | E37: 1 | F37: 2000 | H37: =F37*E37 -> 2000 | J37: =H37*12 -> 24000
A38: 3 | B38: Fuel for Scooters | E38: 4 | F38: 2000 | H38: =F38*E38 -> 8000 | J38: =H38*12 -> 96000
A39: 4 | B39: Fuel For Cars | E39: 1 | F39: 5000 | H39: =F39*E39 -> 5000 | J39: =H39*12 -> 60000
A40: 5
A41: C
A42: 1
A43: 2
A44: 3
A45: 4
A46: 5
A47: D | B47: Accommodation
A48: 1 | B48: Apartments for guards & Supervisors | E48: =(E10+E9+E8)/8 -> 36.9 | F48: 13000 | H48: =F48*E48 -> 479700 | J48: =H48*12 -> 5756400
A49: 2
A50: E | B50: CAFM
A51: 1 | B51: Software Accounts - Users | E51: 0.5 | F51: 8000 | H51: =F51*E51 -> 4000 | J51: =H51*12 -> 48000
A52: 2 | B52: IT Support | E52: 1 | F52: 3000 | H52: =F52*E52 -> 3000 | J52: =H52*12 -> 36000
A53: F | B53: Transportation Outside Site
A54: 1 | B54: Managers Transportation Allowance | E54: =E7+E8+E9 -> 8.4 | F54: 1200 | H54: =F54*E54 -> 10080 | J54: =H54*12 -> 120960
A55: 2 | B55: Supervisors & Technicians Transportation Allowance | E55: =E10 -> 288 | F55: 1000 | H55: =F55*E55 -> 288000 | J55: =H55*12 -> 3456000
A56: G | B56: Others
A57: 1 | B57: Arab Fees | E57: 1 | F57: 5000 | H57: =F57*E57 -> 5000 | J57: =H57*12 -> 60000
A58: 2 | B58: Sub-Contractors Management | E58: 0 | F58: 9000 | H58: =F58*E58 -> 0 | J58: =H58*12 -> 0
A59: 3 | B59: Uniform | E59: =E24 -> 298.8 | F59: 400 | H59: =F59*E59 -> 119520 | J59: =H59*12 -> 1434240
A60: 4 | B60: HSE | E60: 0.25 | F60: 18000 | H60: =F60*E60 -> 4500 | J60: =H60*12 -> 54000
B61: Total Of Indirect Costs | H61: =SUM(H28:H34)+SUM(H36:H40)+SUM(H42:H46)+SUM(H48:H49)+SUM(H51:H52)+SUM(H54:H55)+SUM(H57:H60) -> 955300 | J61: =SUM(J28:J34)+SUM(J36:J40)+SUM(J42:J46)+SUM(J48:J49)+SUM(J51:J52)+SUM(J54:J55)+SUM(J57:J60) -> 11463600
B63: Costing Sheet Summary
B64: Direct Costs | D64: =H24 -> 1526973.1
B65: In-Direct Costs | D65: =H61 -> 955300 | E65: Monthly | F65: Annualy
A66: 0.14 | B66: FMPlus GP | D66: =(D64+D65)*A66 -> 347518.24 | E66: =SUM(D64+D65+D67+D66) -> 2857397.4 | F66: =E66*12 -> 34288768
B67: Mobilization Rate For Y-2 | D67: ='Mobilization Budget'!H113 -> 27606
B69: In-Direct % | D69: =(D66+D65+D67)/(D64+D65+D66+D67) -> 0.46560701
F75: 0 | H75: 0 | J75: 0
F91: 0

Sheet Transportation Y1
B2: City Gate - TR Y1
D4: Head Count | F4: Head Cost / CTC | H4: Monthly | J4: Annualy
B6: Direct Costs - As per Pricing Sheet | D6: Sheet HC | E6: Budget HC | L6: FMPlus Rate | N6: Rate / Shift
A7: 1 | B7: ='[46]Manning Schedule'!B55 -> Pickup Double Cabinet (1 security + 1 MEP) | D7: ='[46]Manning Schedule'!D55 -> 2 | E7: =D7 -> 2 | F7: 39000 | H7: =F7*E7 -> 78000 | J7: =H7*12 -> 936000 | L7: =H7/(1-D$68) -> 120118.84 | N7: =ROUNDUP(L7/D7/30,0) -> 2002
A8: 2 | B8: ='[46]Manning Schedule'!B56 -> Golf Car | D8: ='[46]Manning Schedule'!D56 -> 2 | E8: =D8 -> 2 | F8: 45000 | H8: =F8*E8 -> 90000 | J8: =H8*12 -> 1080000 | L8: =H8/(1-D$68) -> 138598.66 | N8: =ROUNDUP(L8/D8/30,0) -> 2310
A9: 3 | B9: ='[46]Manning Schedule'!B57 -> Security Patrol Motorcycles / Tricycles | D9: ='[46]Manning Schedule'!D57 -> 2 | E9: =D9 -> 2 | F9: 9870 | H9: =F9*E9 -> 19740 | J9: =H9*12 -> 236880 | L9: =H9/(1-D$68) -> 30399.306 | N9: =ROUNDUP(L9/D9/30,0) -> 507
A10: 4
A11: 5
A12: 6
A13: 7
A14: 8
A15: 9
A16: 10
A17: 11
A18: 12
A19: 13
A20: 14
A21: 15
... A23: 17
B24: Total Direct Manpower - As Per Pricing Sheet | D24: =SUM(D7:D23) -> 6 | E24: =SUM(E7:E23) -> 6 | H24: =SUM(H7:H23) -> 187740 | J24: =SUM(J7:J23) -> 2252880 | L24: =SUM(L7:L23) -> 289116.8 | N24: Should Be Same
B26: Indirect Costs
A27: A | B27: Drivers
A28: 1 | B28: Driver 12 HRs | E28: =E24 -> 6 | F28: 9000 | H28: =E28*F28 -> 54000 | J28: =H28*12 -> 648000
A29: 2
A30: 3
A31: 4
A32: 5
A33: 6
A34: 7
A35: B | B35: Secuirty Consumables
A36: 1
A37: 2
A38: 3
A39: 4
A40: 5
A41: C
A42: 1
A43: 2
A44: 3
A45: 4
A46: 5
A47: D | B47: Accommodation
A48: 1 | B48: Apartments for Drivers | E48: 6 | F48: 1500 | H48: =F48*E48 -> 9000 | J48: =H48*12 -> 108000
A49: 2
A50: E | B50: CAFM
A51: 1
A52: 2
A53: F | B53: Transportation Outside Site
A54: 1
A55: 2
A56: G | B56: Others
A57: 1 | B57: Arab Fees | E57: 1 | F57: 5000 | H57: =F57*E57 -> 5000 | J57: =H57*12 -> 60000
A58: 2 | B58: Sub-Contractors Management | E58: 0 | F58: 9000 | H58: =F58*E58 -> 0 | J58: =H58*12 -> 0
A59: 3 | B59: Uniform | E59: =E24 -> 6 | F59: 400 | H59: =F59*E59 -> 2400 | J59: =H59*12 -> 28800
A60: 4 | B60: HSE | E60: 0 | F60: 18000 | H60: =F60*E60 -> 0 | J60: =H60*12 -> 0
B61: Total Of Indirect Costs | H61: =SUM(H28:H34)+SUM(H36:H40)+SUM(H42:H46)+SUM(H48:H49)+SUM(H51:H52)+SUM(H54:H55)+SUM(H57:H60) -> 70400 | J61: =SUM(J28:J34)+SUM(J36:J40)+SUM(J42:J46)+SUM(J48:J49)+SUM(J51:J52)+SUM(J54:J55)+SUM(J57:J60) -> 844800
B63: Costing Sheet Summary
B64: Direct Costs | D64: =H24 -> 187740
B65: In-Direct Costs | D65: =H61 -> 70400 | E65: Monthly | F65: Annualy
A66: 0.12 | B66: FMPlus GP | D66: =(D64+D65)*A66 -> 30976.8 | E66: =SUM(D64+D65+D66) -> 289116.8 | F66: =E66*12 -> 3469401.6
B68: In-Direct % | D68: =(D66+D65)/(D64+D65+D66) -> 0.35064306
F74: 0 | H74: 0 | J74: 0
F90: 0

Sheet Transportation Y2
B2: City Gate - TR Y2
D4: Head Count | F4: Head Cost / CTC | H4: Monthly | J4: Annualy
B6: Direct Costs - As per Pricing Sheet | D6: Sheet HC | E6: Budget HC | L6: FMPlus Rate | N6: Rate / Shift
A7: 1 | B7: ='[46]Manning Schedule'!B55 -> Pickup Double Cabinet (1 security + 1 MEP) | D7: ='[46]Manning Schedule'!D55 -> 2 | E7: =D7 -> 2 | F7: ='Transportation Y1'!F7*1.12 -> 43680 | H7: =F7*E7 -> 87360 | J7: =H7*12 -> 1048320 | L7: =H7/(1-D$69) -> 134933.86 | N7: =ROUNDUP(L7/D7/30,0) -> 2249
A8: 2 | B8: ='[46]Manning Schedule'!B56 -> Golf Car | D8: ='[46]Manning Schedule'!D56 -> 2 | E8: =D8 -> 2 | F8: ='Transportation Y1'!F8*1.12 -> 50400 | H8: =F8*E8 -> 100800 | J8: =H8*12 -> 1209600 | L8: =H8/(1-D$69) -> 155692.92 | N8: =ROUNDUP(L8/D8/30,0) -> 2595
A9: 3 | B9: ='[46]Manning Schedule'!B57 -> Security Patrol Motorcycles / Tricycles | D9: ='[46]Manning Schedule'!D57 -> 2 | E9: =D9 -> 2 | F9: ='Transportation Y1'!F9*1.12 -> 11054.4 | H9: =F9*E9 -> 22108.8 | J9: =H9*12 -> 265305.6 | L9: =H9/(1-D$69) -> 34148.647 | N9: =ROUNDUP(L9/D9/30,0) -> 570
A10: 4
A11: 5
A12: 6
A13: 7
A14: 8
A15: 9
A16: 10
A17: 11
A18: 12
A19: 13
A20: 14
A21: 15
... A23: 17
B24: Total Direct Manpower - As Per Pricing Sheet | D24: =SUM(D7:D23) -> 6 | E24: =SUM(E7:E23) -> 6 | H24: =SUM(H7:H23) -> 210268.8 | J24: =SUM(J7:J23) -> 2523225.6 | L24: =SUM(L7:L23) -> 324775.43 | N24: Should Be Same
B26: Indirect Costs
A27: A | B27: Drivers
A28: 1 | B28: Driver 12 HRs | E28: =E24 -> 6 | F28: 9000 | H28: =E28*F28 -> 54000 | J28: =H28*12 -> 648000
A29: 2
A30: 3
A31: 4
A32: 5
A33: 6
A34: 7
A35: B | B35: Secuirty Consumables
A36: 1
A37: 2
A38: 3
A39: 4
A40: 5
A41: C
A42: 1
A43: 2
A44: 3
A45: 4
A46: 5
A47: D | B47: Accommodation
A48: 1 | B48: Apartments for Drivers | E48: 6 | F48: 1800 | H48: =F48*E48 -> 10800 | J48: =H48*12 -> 129600
A49: 2
A50: E | B50: CAFM
A51: 1
A52: 2
A53: F | B53: Transportation Outside Site
A54: 1
A55: 2
A56: G | B56: Others
A57: 1 | B57: Arab Fees | E57: 1 | F57: 5000 | H57: =F57*E57 -> 5000 | J57: =H57*12 -> 60000
A58: 2 | B58: Sub-Contractors Management | E58: 0 | F58: 9000 | H58: =F58*E58 -> 0 | J58: =H58*12 -> 0
A59: 3 | B59: Uniform | E59: =E24 -> 6 | F59: 400 | H59: =F59*E59 -> 2400 | J59: =H59*12 -> 28800
A60: 4 | B60: HSE | E60: 0 | F60: 18000 | H60: =F60*E60 -> 0 | J60: =H60*12 -> 0
B61: Total Of Indirect Costs | H61: =SUM(H28:H34)+SUM(H36:H40)+SUM(H42:H46)+SUM(H48:H49)+SUM(H51:H52)+SUM(H54:H55)+SUM(H57:H60) -> 72200 | J61: =SUM(J28:J34)+SUM(J36:J40)+SUM(J42:J46)+SUM(J48:J49)+SUM(J51:J52)+SUM(J54:J55)+SUM(J57:J60) -> 866400
B63: Costing Sheet Summary
B64: Direct Costs | D64: =H24 -> 210268.8
B65: In-Direct Costs | D65: =H61 -> 72200 | E65: Monthly | F65: Annualy
A66: 0.14 | B66: FMPlus GP | D66: =(D64+D65)*A66 -> 39545.632 | E66: =SUM(D64+D65+D66+D67) -> 324775.43 | F66: =E66*12 -> 3897305.2
B67: Mobilization Rate For Y-2 | D67: ='Mobilization Budget'!H114 -> 2761
B69: In-Direct % | D69: =(D66+D65+D67)/(D64+D65+D66+D67) -> 0.35257172
F75: 0 | H75: 0 | J75: 0
F91: 0
