Workbook
Name Datew: '[1]12%'!$A$6:$A$101

Sheet HK Budget (2)
B3: UTC HK Budget
B4: Items | D4: Total Amount/ Month | I4: Sierras | J4: Alto | K4: Aurora | L4: Fourteen | M4: Reyna | N4: Eleva | O4: Isadore | P4: Alba's Aliyah | Q4: Alba's Spendia | R4: Commercial Area "UTC-Golf club house | S4: Public Roads | T4: Crossing gates | U4: Mobilization areas " water station " | V4: Managament"sales center"
B6: Head Count Cost | D6: ='Manpower Cost'!F16 -> 1251640 | F6: =D6-(I6+J6+K6+L6+M6+N6+O6+P6+Q6+R6+S6+T6+U6+V6) -> 0 | I6: ='Manpower Cost'!L16 -> 209286.45 | J6: ='Manpower Cost'!N16 -> 105385.54 | K6: ='Manpower Cost'!P16 -> 110169.34 | L6: ='Manpower Cost'!R16 -> 204832.57 | M6: ='Manpower Cost'!T16 -> 49635.278 | N6: ='Manpower Cost'!V16 -> 37223.651 | O6: ='Manpower Cost'!X16 -> 27917.738 | P6: ='Manpower Cost'!Z16 -> 36447.222 | Q6: ='Manpower Cost'!AB16 -> 36447.222 | R6: ='Manpower Cost'!AD16 -> 99270.556 | S6: ='Manpower Cost'!AF16 -> 9111.8056 | T6: ='Manpower Cost'!AH16 -> 54670.833 | U6: ='Manpower Cost'!AJ16 -> 9111.8056 | V6: ='Manpower Cost'!AL16 -> 262130
B7: Equipment & Tools Cost | D7: ='Equipment & Tools Cost'!G52 -> 448150.28 | F7: =D7-(I7+J7+K7+L7+M7+N7+O7+P7+Q7+R7+S7+T7+U7+V7) -> 0 | I7: ='Equipment & Tools Cost'!M52 -> 75883.604 | J7: ='Equipment & Tools Cost'!O52 -> 40131.834 | K7: ='Equipment & Tools Cost'!Q52 -> 41549.942 | L7: ='Equipment & Tools Cost'!S52 -> 73702.856 | M7: ='Equipment & Tools Cost'!U52 -> 16526.184 | N7: ='Equipment & Tools Cost'!W52 -> 13030.725 | O7: ='Equipment & Tools Cost'!Y52 -> 10375.266 | P7: ='Equipment & Tools Cost'!AA52 -> 12655.725 | Q7: ='Equipment & Tools Cost'!AC52 -> 11905.725 | R7: ='Equipment & Tools Cost'!AE52 -> 35356.256 | S7: ='Equipment & Tools Cost'!AG52 -> 4262.6812 | T7: ='Equipment & Tools Cost'!AI52 -> 15687.754 | U7: ='Equipment & Tools Cost'!AK52 -> 3044.6256 | V7: ='Equipment & Tools Cost'!AM52 -> 94037.101
B8: Consumables Cost | D8: ='Consumables Cost '!G33 -> 71385 | F8: =D8-(I8+J8+K8+L8+M8+N8+O8+P8+Q8+R8+S8+T8+U8+V8) -> 0 | I8: ='Consumables Cost '!M33 -> 10000 | J8: ='Consumables Cost '!O33 -> 5150 | K8: ='Consumables Cost '!Q33 -> 5850 | L8: ='Consumables Cost '!S33 -> 10150 | M8: ='Consumables Cost '!U33 -> 2175 | N8: ='Consumables Cost '!W33 -> 1750 | O8: ='Consumables Cost '!Y33 -> 1750 | P8: ='Consumables Cost '!AA33 -> 1750 | Q8: ='Consumables Cost '!AC33 -> 2125 | R8: ='Consumables Cost '!AE33 -> 12725 | S8: ='Consumables Cost '!AG33 -> 870 | T8: ='Consumables Cost '!AI33 -> 2225 | U8: ='Consumables Cost '!AK33 -> 340 | V8: ='Consumables Cost '!AM33 -> 14525
B9: Transportation Cost | D9: ='Transportation Cost'!G14 -> 369000 | F9: =D9-(I9+J9+K9+L9+M9+N9+O9+P9+Q9+R9+S9+T9+U9+V9) -> 0 | I9: ='Transportation Cost'!M14 -> 62182.701 | J9: ='Transportation Cost'!O14 -> 31347.364 | K9: ='Transportation Cost'!Q14 -> 32997.225 | L9: ='Transportation Cost'!S14 -> 60646.623 | M9: ='Transportation Cost'!U14 -> 13369.565 | N9: ='Transportation Cost'!W14 -> 10695.652 | O9: ='Transportation Cost'!Y14 -> 8021.7391 | P9: ='Transportation Cost'!AA14 -> 10695.652 | Q9: ='Transportation Cost'!AC14 -> 10695.652 | R9: ='Transportation Cost'!AE14 -> 26739.13 | S9: ='Transportation Cost'!AG14 -> 2673.913 | T9: ='Transportation Cost'!AI14 -> 16043.478 | U9: ='Transportation Cost'!AK14 -> 2673.913 | V9: ='Transportation Cost'!AM14 -> 80217.391
B10: Mobilization & Over Head Cost | D10: ='Mobilization & Over Head Cost'!G14 -> 34444.444 | F10: =D10-(I10+J10+K10+L10+M10+N10+O10+P10+Q10+R10+S10+T10+U10+V10) -> 0 | I10: ='Mobilization & Over Head Cost'!M14 -> 5804.4677 | J10: ='Mobilization & Over Head Cost'!O14 -> 2926.1315 | K10: ='Mobilization & Over Head Cost'!Q14 -> 3080.1384 | L10: ='Mobilization & Over Head Cost'!S14 -> 5661.082 | M10: ='Mobilization & Over Head Cost'!U14 -> 1247.9871 | N10: ='Mobilization & Over Head Cost'!W14 -> 998.38969 | O10: ='Mobilization & Over Head Cost'!Y14 -> 748.79227 | P10: ='Mobilization & Over Head Cost'!AA14 -> 998.38969 | Q10: ='Mobilization & Over Head Cost'!AC14 -> 998.38969 | R10: ='Mobilization & Over Head Cost'!AE14 -> 2495.9742 | S10: ='Mobilization & Over Head Cost'!AG14 -> 249.59742 | T10: ='Mobilization & Over Head Cost'!AI14 -> 1497.5845 | U10: ='Mobilization & Over Head Cost'!AK14 -> 249.59742 | V10: ='Mobilization & Over Head Cost'!AM14 -> 7487.9227
B11: Others Cost | D11: ='Others Cost '!G12 -> 37500 | F11: =D11-(I11+J11+K11+L11+M11+N11+O11+P11+Q11+R11+S11+T11+U11+V11) -> 0 | I11: ='Others Cost '!M12 -> 6319.3802 | J11: ='Others Cost '!O12 -> 3185.7077 | K11: ='Others Cost '!Q12 -> 3353.3765 | L11: ='Others Cost '!S12 -> 6163.2747 | M11: ='Others Cost '!U12 -> 1358.6957 | N11: ='Others Cost '!W12 -> 1086.9565 | O11: ='Others Cost '!Y12 -> 815.21739 | P11: ='Others Cost '!AA12 -> 1086.9565 | Q11: ='Others Cost '!AC12 -> 1086.9565 | R11: ='Others Cost '!AE12 -> 2717.3913 | S11: ='Others Cost '!AG12 -> 271.73913 | T11: ='Others Cost '!AI12 -> 1630.4348 | U11: ='Others Cost '!AK12 -> 271.73913 | V11: ='Others Cost '!AM12 -> 8152.1739
B12: Facades Cleaning | D12: ='Facades Cleaning Cost'!G14 -> 134750 | F12: =D12-(I12+J12+K12+L12+M12+N12+O12+P12+Q12+R12+S12+T12+U12+V12) -> 0 | I12: ='Facades Cleaning Cost'!M14 -> 63250 | J12: ='Facades Cleaning Cost'!O14 -> 14625 | K12: ='Facades Cleaning Cost'!Q14 -> 11375 | L12: ='Facades Cleaning Cost'!S14 -> 45500
B13: Total Cost | D13: =SUM(D6:D12) -> 2346869.7 | F13: =D13-(I13+J13+K13+L13+M13+N13+O13+P13+Q13+R13+S13+T13+U13+V13) -> 0 | I13: =SUM(I6:I12) -> 432726.6 | J13: =SUM(J6:J12) -> 202751.57 | K13: =SUM(K6:K12) -> 208375.02 | L13: =SUM(L6:L12) -> 406656.4 | M13: =SUM(M6:M12) -> 84312.709 | N13: =SUM(N6:N12) -> 64785.374 | O13: =SUM(O6:O12) -> 49628.753 | P13: =SUM(P6:P12) -> 63633.945 | ... V13: =SUM(V6:V12) -> 466549.59
B14: Gross Margin & Contingency 2% | C14: 0.08 | D14: =D13*$C$14 -> 187749.58 | F14: =D14-(I14+J14+K14+L14+M14+N14+O14+P14+Q14+R14+S14+T14+U14+V14) -> -14752.18 | I14: =I13*$C$14 -> 34618.128 | J14: =J13*$C$14 -> 16220.126 | K14: =K13*$C$14 -> 16670.002 | L14: =L13*$C$14 -> 32532.512 | M14: =M13*$C$14 -> 6745.0167 | N14: =N13*$C$14 -> 5182.8299 | O14: =O13*$C$14 -> 3970.3002 | P14: =P13*$C$14 -> 5090.7156 | Q14: =Q13*$C$14 -> 5060.7156 | R14: =R13*10% -> 17930.431 | S14: =S13*$C$14 -> 1395.1789 | T14: =T13*10% -> 9175.5085 | U14: =U13*$C$14 -> 1255.3345 | V14: =V13*10% -> 46654.959
B15: Total | D15: =SUM(D13:D14) -> 2534619.3 | F15: =D15-(I15+J15+K15+L15+M15+N15+O15+P15+Q15+R15+S15+T15+U15+V15) -> -14752.18 | I15: =SUM(I13:I14) -> 467344.73 | J15: =SUM(J13:J14) -> 218971.7 | K15: =SUM(K13:K14) -> 225045.02 | L15: =SUM(L13:L14) -> 439188.91 | M15: =SUM(M13:M14) -> 91057.726 | N15: =SUM(N13:N14) -> 69968.204 | O15: =SUM(O13:O14) -> 53599.053 | P15: =SUM(P13:P14) -> 68724.661 | ... V15: =SUM(V13:V14) -> 513204.55
B16: Insurance | C16: 0.014 | D16: =D15*$C$16 -> 35484.67 | E16: =D16*36 -> 1277448.1 | F16: =D16-(I16+J16+K16+L16+M16+N16+O16+P16+Q16+R16+S16+T16+U16+V16) -> -206.53051 | I16: =I15*$C$16 -> 6542.8262 | J16: =J15*$C$16 -> 3065.6038 | K16: =K15*$C$16 -> 3150.6303 | L16: =L15*$C$16 -> 6148.6448 | M16: =M15*$C$16 -> 1274.8082 | N16: =N15*$C$16 -> 979.55485 | O16: =O15*$C$16 -> 750.38674 | P16: =P15*$C$16 -> 962.14525 | ... V16: =V15*$C$16 -> 7184.8637
B17: Total Revenue | D17: =SUM(D15:D16) -> 2570104 | F17: =D17-(I17+J17+K17+L17+M17+N17+O17+P17+Q17+R17+S17+T17+U17+V17) -> -14958.71 | I17: =SUM(I15:I16) -> 473887.56 | J17: =SUM(J15:J16) -> 222037.3 | K17: =SUM(K15:K16) -> 228195.65 | L17: =SUM(L15:L16) -> 445337.56 | M17: =SUM(M15:M16) -> 92332.534 | N17: =SUM(N15:N16) -> 70947.759 | O17: =SUM(O15:O16) -> 54349.44 | P17: =SUM(P15:P16) -> 69686.806 | ... V17: =SUM(V15:V16) -> 520389.41
B18: VAT | C18: 0.14 | D18: =D17*$C$18 -> 359814.56 | F18: =D18-(I18+J18+K18+L18+M18+N18+O18+P18+Q18+R18+S18+T18+U18+V18) -> -2094.2194 | I18: =I17*$C$18 -> 66344.258 | J18: =J17*$C$18 -> 31085.223 | K18: =K17*$C$18 -> 31947.391 | L18: =L17*$C$18 -> 62347.258 | M18: =M17*$C$18 -> 12926.555 | N18: =N17*$C$18 -> 9932.6862 | O18: =O17*$C$18 -> 7608.9215 | P18: =P17*$C$18 -> 9756.1529 | ... V18: =V17*$C$18 -> 72854.518
B19: Total W VAT | D19: =D17+D18 -> 2929918.5 | E19: =D19-2999479.74459467 -> -69561.219 | F19: =D19-(I19+J19+K19+L19+M19+N19+O19+P19+Q19+R19+S19+T19+U19+V19) -> -17052.93 | I19: =I17+I18 -> 540231.81 | J19: =J17+J18 -> 253122.53 | K19: =K17+K18 -> 260143.04 | L19: =L17+L18 -> 507684.82 | M19: =M17+M18 -> 105259.09 | N19: =N17+N18 -> 80880.445 | O19: =O17+O18 -> 61958.361 | P19: =P17+P18 -> 79442.959 | ... V19: =V17+V18 -> 593243.93
D20: =3000000 -> 3000000 | E20: =D20*36*0.02 -> 2160000
D21: =D19-D20 -> -70081.474
C22: =C23+C49+C43+F36+F37+F38+F39 -> 2929918.5 | D22: =D21/D19 -> -0.023919257
C23: =C24+C36+C31 -> 1586411.5
B24: Direct Cost | C24: =C25+C26+C27+C28+C29+C30+C32+C33+C34 -> 1447462.5 | J24: Unit Rate
B25: Labors Morning Shift | C25: ='Manpower Cost'!AS6 -> 741671.33 | D25: =C25/$C$24 -> 0.51239417 | F25: =(D25*$C$36)+(D25*$F$36)+(D25*$F$37)+(D25*$F$38)+(D25*$F$39) -> 79840.281 | H25: ='Manpower Cost'!C6 -> 94 | I25: =C25+F25 -> 821511.62 | J25: =I25/H25 -> 8739.4853
B26: Labors Noon Shift | C26: ='Manpower Cost'!AS7 -> 110461.69 | D26: =C26/$C$24 -> 0.076314025 | F26: =(D26*$C$36)+(D26*$F$36)+(D26*$F$37)+(D26*$F$38)+(D26*$F$39) -> 11891.106 | H26: ='Manpower Cost'!C7 -> 14 | I26: =C26+F26 -> 122352.79 | J26: =I26/H26 -> 8739.4853
B27: Supervisor Morning Shift | C27: ='Manpower Cost'!AS8 -> 149275.59 | D27: =C27/$C$24 -> 0.10312916 | F27: =(D27*$C$36)+(D27*$F$36)+(D27*$F$37)+(D27*$F$38)+(D27*$F$39) -> 16069.389 | H27: ='Manpower Cost'!C8 -> 11 | I27: =C27+F27 -> 165344.98 | J27: =I27/H27 -> 15031.362
B28: Supervisor Noon Shift | C28: ='Manpower Cost'!AS9 -> 40711.524 | D28: =C28/$C$24 -> 0.028126134 | F28: =(D28*$C$36)+(D28*$F$36)+(D28*$F$37)+(D28*$F$38)+(D28*$F$39) -> 4382.5605 | H28: ='Manpower Cost'!C9 -> 3 | I28: =C28+F28 -> 45094.085 | J28: =I28/H28 -> 15031.362
B29: Site Admin | C29: ='Manpower Cost'!AS10-10000 -> 32247.101 | D29: =C29/$C$24 -> 0.022278368 | F29: =(D29*$C$36)+(D29*$F$36)+(D29*$F$37)+(D29*$F$38)+(D29*$F$39) -> 3471.3727 | H29: ='Manpower Cost'!C10 -> 2 | I29: =C29+F29 -> 35718.474 | J29: =I29/H29 -> 17859.237
B30: Site Assistant | C30: ='Manpower Cost'!AS11-30000 -> 55842.514 | D30: =C30/$C$24 -> 0.038579593 | F30: =(D30*$C$36)+(D30*$F$36)+(D30*$F$37)+(D30*$F$38)+(D30*$F$39) -> 6011.3986 | H30: ='Manpower Cost'!C11 -> 3 | I30: =C30+F30 -> 61853.913 | J30: =I30/H30 -> 20617.971
B31: Site Manager | C31: =('Manpower Cost'!AS12-16000) -> 49130.948 | F31: =(D31*$C$36)+(D31*$F$36)+(D31*$F$37)+(D31*$F$38)+(D31*$F$39) -> 0 | H31: ='Manpower Cost'!C12 -> 1 | I31: =C31+F31 -> 49130.948 | J31: =I31/H31 -> 49130.948
B32: Sales Center Labor | C32: ='Manpower Cost'!AS13 -> 255430.17 | D32: =C32/$C$24 -> 0.17646756 | F32: =(D32*$C$36)+(D32*$F$36)+(D32*$F$37)+(D32*$F$38)+(D32*$F$39) -> 27496.838 | H32: ='Manpower Cost'!C13 -> 30 | I32: =C32+F32 -> 282927.01 | J32: =I32/H32 -> 9430.9002
B33: Sales Center supervisor | C33: ='Manpower Cost'!AS14 -> 42584.179 | D33: =C33/$C$24 -> 0.029419885 | F33: =(D33*$C$36)+(D33*$F$36)+(D33*$F$37)+(D33*$F$38)+(D33*$F$39) -> 4584.1503 | H33: ='Manpower Cost'!C14 -> 3 | I33: =C33+F33 -> 47168.33 | J33: =I33/H33 -> 15722.777
B34: Sales Center Assistant Manager | C34: ='Manpower Cost'!AS15-10000 -> 19238.39 | D34: =C34/$C$24 -> 0.013291115 | F34: =(D34*$C$36)+(D34*$F$36)+(D34*$F$37)+(D34*$F$38)+(D34*$F$39) -> 2070.9961 | H34: ='Manpower Cost'!C15 -> 1 | I34: =C34+F34 -> 21309.386 | J34: =I34/H34 -> 21309.386
B36: Indirect Cost | C36: =C37+C38+C39+C40 -> 89818.092 | F36: 16000 | I36: =SUM(I25:I35) -> 1652411.5
C37: =D10+D11 -> 71944.444 | F37: 30000
C38: =C37*C14 -> 5755.5556 | F38: 10000 | I38: =I39+I40+I41+I42 -> 2281311.6
C39: =(C37+C38)*C16 -> 1087.8 | F39: 10000 | I39: =D6+D9+D10+D11+D12 -> 1827334.4
C40: =(C37+C38+C39)*C18 -> 11030.292 | I40: =I39*C14 -> 146186.76
I41: =(I39+I40)*C16 -> 27629.297
I42: =(I39+I40+I41)*C18 -> 280161.07
B43: Equipmet, Tools & Consumables | C43: =SUM(C44:C47) -> 816833.82 | D43: =C43-V43 -> 681300.9 | E43: ='BOQ Basic -Residential'!D20+'BOQ Basic -Residential'!D21+'BOQ Basic -Residential'!D22+'BOQ Basic -Residential'!D23+'BOQ Basic -Residential'!D24+'BOQ Basic -Residential'!D25+'BOQ Basic -Residential'!D26+'BOQ Basic -Residential'!D27+'BOQ Basic -Residential'!D28+'BOQ Basic -Residential'!D29+'BOQ Basic -Residential'!D30+'BOQ Basic -Residential'!D31+'BOQ Basic -Residential'!D32+'BOQ Basic -Residential'!D33 -> 590228.86 | V43: =V44+V45+V46+V47 -> 135532.92 | W43: ='BOQ Basic -Residential'!D35+'BOQ Basic -Residential'!D36+'BOQ Basic -Residential'!D37+'BOQ Basic -Residential'!D38+'BOQ Basic -Residential'!D39+'BOQ Basic -Residential'!D40+'BOQ Basic -Residential'!D41+'BOQ Basic -Residential'!D42+'BOQ Basic -Residential'!D43+'BOQ Basic -Residential'!D44+'BOQ Basic -Residential'!D45+'BOQ Basic -Residential'!D46 -> 13123
C44: =D7+D8+D12 -> 654285.28 | V44: =V7+V8 -> 108562.1
C45: =C44*C14 -> 52342.822 | V45: =V44*C14 -> 8684.9681
C46: =(C44+C45)*C16 -> 9892.7934 | V46: =(V44+V45)*C16 -> 1641.459
C47: =(C44+C46+C45)*C18 -> 100312.93 | V47: =(V44+V45+V46)*C18 -> 16644.394
B49: Transportation | C49: =C50+C51+C52+C53 -> 460673.18
C50: =D9 -> 369000
C51: =C50*C14 -> 29520
C52: =(C50+C51)*C16 -> 5579.28
C53: =(C50+C51+C52)*C18 -> 56573.899

Sheet BOQ Basic -Residential (2)
A4: Basic Scope Residential | B4: All Season | C4: Unit Rate | D4: Monthly Fee
A5: Item | B5: QTY
A6: Labors | B6: 94 | C6: 8739.4853 | D6: =C6*$B6 -> 821511.62 | E6: 8894.1264 | F6: 836047.89 | G6: =E6-C6 -> 154.64118 | H6: =F6-D6 -> 14536.271
A7: Supervisor | B7: 11 | C7: 15031.362 | D7: =C7*$B7 -> 165344.98 | E7: 15297.335 | F7: 168270.68 | H7: =F7-D7 -> 2925.7034
A8: Labors Night Shift | B8: 14 | C8: 8739.4853 | D8: =C8*$B8 -> 122352.79 | E8: 8894.1264 | F8: 124517.77 | H8: =F8-D8 -> 2164.9765
A9: Supervisor Night Shift | B9: 3 | C9: 15031.362 | D9: =C9*$B9 -> 45094.085 | E9: 15297.335 | F9: 45892.004 | H9: =F9-D9 -> 797.91911
A10: Site Manager | B10: 1 | C10: 49130.948 | D10: =C10*$B10 -> 49130.948 | E10: 50337.077 | F10: 50337.077 | H10: =F10-D10 -> 1206.1287
A11: Site Assistant | B11: 3 | C11: 20617.971 | D11: =C11*$B11 -> 61853.913 | E11: 21187.751 | F11: 63563.252 | H11: =F11-D11 -> 1709.3394
A12: Site Admin | B12: 2 | C12: 17859.237 | D12: =C12*$B12 -> 35718.474 | E12: 18277.725 | F12: 36555.45 | H12: =F12-D12 -> 836.97626
A13: Sales Center Labor- Morning Shift | B13: 19 | C13: 9597.7757 | D13: =C13*$B13 -> 182357.74 | E13: 9597.7757 | F13: 182357.74 | H13: =F13-D13 -> 0 | I13: In House team Mandatory
A14: Sales Center Labor- Night Shift | B14: 11 | C14: 9597.7757 | D14: =C14*$B14 -> 105575.53 | E14: 9597.7757 | F14: 105575.53 | H14: =F14-D14 -> 0
A15: Sales Center supervisor- Morning Shift | B15: 2 | C15: 16000.984 | D15: =C15*$B15 -> 32001.968 | E15: 16000.984 | F15: 32001.968 | H15: =F15-D15 -> 0
A16: Sales Center supervisor- Night Shift | B16: 1 | C16: 16000.984 | D16: =C16*$B16 -> 16000.984 | E16: 16000.984 | F16: 16000.984 | H16: =F16-D16 -> 0
A17: Sales Center Assistant Manager | B17: 1 | C17: 21891.4 | D17: =C17*$B17 -> 21891.4 | E17: 21891.4 | F17: 21891.4 | H17: =F17-D17 -> 0
A18: Transportation | B18: LS | C18: 469204.16 | D18: =C18 -> 469204.16 | E18: 469204.16 | F18: 469204.16 | H18: =F18-D18 -> 0
A19: Manpower | D19: =SUM(D6:D18) -> 2128038.6 | F19: 2152215.9 | H19: =F19-D19 -> 24177.314
A20: Façade Cleaning service " as per site need max. 168 buildings per year" | B20: 14 | C20: 12238.727 | D20: =C20*$B20 -> 171342.17 | E20: 12238.727 | F20: 171342.17 | H20: =F20-D20 -> 0 | I20: Total Buildings 56 & 3 times per year
A21: Single disk | B21: 5 | C21: 1249 | D21: =C21*$B21 -> 6245 | E21: 1272 | F21: 6360 | H21: =F21-D21 -> 115
A22: Vacuum | B22: 6 | C22: 729 | D22: =C22*$B22 -> 4374 | E22: 742 | F22: 4452 | H22: =F22-D22 -> 78
A23: Manual sweeper | B23: 10 | C23: 937 | D23: =C23*$B23 -> 9370 | E23: 954 | F23: 9540 | H23: =F23-D23 -> 170
A24: McClean Trolley | B24: 14 | C24: 387 | D24: =C24*$B24 -> 5418 | E24: 394 | F24: 5516 | H24: =F24-D24 -> 98
A25: Black Broom and Closed Ban | B25: 23 | C25: 94 | D25: =C25*$B25 -> 2162 | E25: 96 | F25: 2208 | H25: =F25-D25 -> 46
A26: Litter Picking Steak | B26: 12 | C26: 105 | D26: =C26*$B26 -> 1260 | E26: 106 | F26: 1272 | H26: =F26-D26 -> 12
A27: Mob Bucket with Cotton Cloth | B27: 25 | C27: 63 | D27: =C27*$B27 -> 1575 | E27: 64 | F27: 1600 | H27: =F27-D27 -> 25
A28: Water Fed Telescope (20 Meter) | B28: 2 | C28: 7907 | D28: =C28*$B28 -> 15814 | E28: 8054 | F28: 16108 | H28: =F28-D28 -> 294
A29: High Pressure Set One Car, Driver, 1K Liter tank" -30 days" | B29: 2 | C29: 64999 | D29: =C29*$B29 -> 129998 | E29: 64999 | F29: 129998 | H29: =F29-D29 -> 0
A30: Man Lift 15M" *30 days" | B30: 2 | C30: 68970 | D30: =C30*$B30 -> 137940 | E30: 68970 | F30: 137940 | H30: =F30-D30 -> 0
A31: Pick up Car with driver | B31: 2 | C31: 53406 | D31: =C31*$B31 -> 106812 | E31: 53406 | F31: 106812 | H31: =F31-D31 -> 0
A32: Public trolly for Building | B32: 25 | C32: 278 | D32: =C32*$B32 -> 6950 | E32: 283 | F32: 7075 | H32: =F32-D32 -> 125
... A47: Sales Center - Consumables & tools & Chemical Rates | B47: 1 | C47: 64044.588 | D47: =C47*$B47 -> 64044.588 | E47: 65244.96 | F47: 65244.96 | H47: =F47-D47 -> 1200.372
A48: Equipment | D48: =SUM(D20:D47) -> 826761.13 | F48: 831960.37 | H48: =F48-D48 -> 5199.24
A49: Grand Total | D49: =D48+D19 -> 2954799.7 | F49: 2984176.3 | H49: =F49-D49 -> 29376.554 | I49: =H49/F49 -> 0.0098441082
A50: First Year | D50: =D49*12 -> 35457597 | F50: 35810115 | H50: =F50-D50 -> 352518.65 | I50: =H50/F50 -> 0.0098441082
A51: Second Year | D51: =D50*1.1 -> 39003356
A52: Third Year | D52: =D51*1.1 -> 42903692 | G52: =D49-'BOQ A (2)'!G17 -> 0
A53: Grand Total | D53: =SUM(D50:D52) -> 1.1736464e+08

Sheet BOQ A (2)
B2: Scope | C2: # | D2: UPTWON CAIRO-ZONE A | E2: Description (Housekeeping) | F2: Duration | G2: Monthly Rate | H2: Amount
B3: Basic Scope | C3: 1 | D3: Sierras | E3: Sierras Building, Entrance,Furniture, Corridors, Stairs, Handrails, Walls, Elevators, Ceiling, Roofs and Roads, Parking, Asphalt, Walk Ways, as well as Littering in public landscape. | F3: 12 | G3: 542381.07 | H3: =G3*F3 -> 6508572.8 | I3: =G3*$Q$42 -> 0 | K3: 920624.36 | L3: =G3-K3 -> -378243.3 | M3: =L3/G3 -> -0.69737556 | O3: =G3+I3 -> 542381.07
C4: 2 | D4: Alto | E4: Alto Building, Entrance,Furniture, Corridors, Stairs, Handrails, Walls, Elevators, Ceiling, Roofs and Roads, Parking, Asphalt, Walk Ways, as well as Littering in public landscape. | F4: 12 | G4: 254129.55 | H4: =G4*F4 -> 3049554.6 | I4: =G4*$Q$42 -> 0 | K4: 371983.73 | L4: =G4-K4 -> -117854.18 | M4: =L4/G4 -> -0.46375632 | O4: =G4+I4 -> 254129.55
C5: 3 | D5: Aurora | E5: Aurora Building, Entrance,Furniture, Corridors, Stairs, Handrails, Walls, Elevators, Ceiling, Roofs and Roads, Parking, Asphalt, Walk Ways, as well as Littering in public landscape. | F5: 12 | G5: 261177.99 | H5: =G5*F5 -> 3134135.9 | I5: =G5*$Q$42 -> 0 | K5: 368133.47 | L5: =G5-K5 -> -106955.47 | M5: =L5/G5 -> -0.40951181 | O5: =G5+I5 -> 261177.99
C6: 4 | D6: Fourteen | E6: Fourteen Building, Entrance,Furniture, Corridors, Stairs, Handrails, Walls, Elevators, Ceiling, Roofs and Roads, Parking, Asphalt, Walk Ways, as well as Littering in public landscape. | F6: 12 | G6: 509704.58 | H6: =G6*F6 -> 6116455 | I6: =G6*$Q$42 -> 0 | K6: 806193.75 | L6: =G6-K6 -> -296489.16 | M6: =L6/G6 -> -0.58168824 | O6: =G6+I6 -> 509704.58
C7: 5 | D7: Reyna | E7: Reyna Village Roads, Parking, Asphalt, Walk Ways, Pergolas , play court as well as Littering in public landscape. | F7: 12 | G7: 105677.85 | H7: =G7*F7 -> 1268134.2 | I7: =G7*$Q$42 -> 0 | K7: 132229.96 | L7: =G7-K7 -> -26552.105 | M7: =L7/G7 -> -0.25125515 | O7: =G7+I7 -> 105677.85
C8: 6 | D8: Eleva | E8: Eleva Village Roads, Parking, Asphalt, Walk Ways,Pergolas as well as Littering in public landscape. | F8: 12 | G8: 81202.219 | H8: =G8*F8 -> 974426.62 | I8: =G8*$Q$42 -> 0 | K8: 102178.85 | L8: =G8-K8 -> -20976.629 | M8: =L8/G8 -> -0.25832581 | O8: =G8+I8 -> 81202.219
C9: 7 | D9: Isadore | E9: Isadore Village Roads, Parking, Asphalt, Walk Ways, Pergolas as well as Littering in public landscape. | F9: 12 | G9: 62204.856 | H9: =G9*F9 -> 746458.27 | I9: =G9*$Q$42 -> 0 | K9: 78508.912 | L9: =G9-K9 -> -16304.056 | M9: =L9/G9 -> -0.26210263 | O9: =G9+I9 -> 62204.856
C10: 8 | D10: Alba's Aliyah | E10: Alba Aliyah Village Roads, Parking, Asphalt, Walk Ways, as well as Littering in public landscape. | F10: 12 | G10: 79759.014 | H10: =G10*F10 -> 957108.17 | I10: =G10*$Q$42 -> 0 | K10: 100410.82 | L10: =G10-K10 -> -20651.81 | M10: =L10/G10 -> -0.2589276 | O10: =G10+I10 -> 79759.014
C11: 9 | D11: Alba's Spendia | E11: Alba Spendia Village Roads, Parking, Asphalt, Walk Ways, as well as Littering in public landscape. | F11: 12 | G11: 79288.988 | H11: =G11*F11 -> 951467.85 | I11: =G11*$Q$42 -> 0 | K11: 99151.035 | L11: =G11-K11 -> -19862.047 | M11: =L11/G11 -> -0.25050196 | O11: =G11+I11 -> 79288.988
C12: 10 | D12: Commercial Area "UTC-Golf club house | E12: UTC-Golf club house : Building, Entrance,Furniture, Corridors, Stairs, Handrails, Walls, Elevators, Ceiling, Roofs and Parking, Asphalt, Walk Ways, Littering in public landscape, Marble floor, Bathrooms, 3 Hubs at golf Area and golf Office | F12: 12 | G12: 227995.47 | H12: =G12*F12 -> 2735945.6 | K12: 276777.38 | L12: =G12-K12 -> -48781.913 | M12: =L12/G12 -> -0.21396001 | O12: =G12+I12 -> 227995.47
C13: 11 | D13: Public Roads | E13: Road 7, Parking, Landscape areas, utility bulidings,Walkways,Security guardhouse and Kiosks | F13: 12 | G13: 21772.409 | H13: =G13*F13 -> 261268.9 | K13: 27043.411 | L13: =G13-K13 -> -5271.0024 | M13: =L13/G13 -> -0.24209551 | O13: =G13+I13 -> 21772.409
C14: 12 | D14: Crossing gates | E14: all Consutation gates on site , Walkways,Security guardhouse and Kiosks | F14: 12 | G14: 116671.73 | H14: =G14*F14 -> 1400060.7 | K14: 142784.13 | L14: =G14-K14 -> -26112.399 | M14: =L14/G14 -> -0.22381085 | O14: =G14+I14 -> 116671.73
C15: 13 | D15: Mobilization areas " water station " | E15: Mobilization areas, with Caravans, public area | F15: 12 | G15: 19590.072 | H15: =G15*F15 -> 235080.86 | K15: 24358.381 | L15: =G15-K15 -> -4768.3089 | M15: =L15/G15 -> -0.24340436 | O15: =G15+I15 -> 19590.072
C16: 14 | D16: Managament"sales center" | E16: Head Quarter (Management building - sale center - customer excellence area - mock up apartments - garage - parking - public areas - landscape area - waste collection area) | F16: 12 | G16: 593243.93 | H16: =G16*F16 -> 7118927.2 | K16: 811438.67 | L16: =G16-K16 -> -218194.74 | M16: =L16/G16 -> -0.36779936 | O16: =G16+I16 -> 593243.93
C17: Total Basic Incl. VAT. | G17: =SUM(G3:G16) -> 2954799.7 | H17: =SUM(H3:H16) -> 35457597 | K17: =SUM(K3:K16) -> 4261816.8 | L17: =G17-K17 -> -1307017.1 | M17: =L17/G17 -> -0.44233696 | O17: =SUM(O3:O16) -> 2954799.7
B19: Optional Scope | C19: 1 | D19: Sierras | E19: Sierras Community Centre 1 : Swimming Spots, Community Buildings, Bathrooms , Pool area, Kids Area, Deck and Walk Ways, Litter Picking from Surroundings and Landscape . | F19: 12 | H19: =G19*F19 -> 0
C20: 2 | E20: Sierras Community Centre 15: Swimming Spots, Community Buildings, Bathrooms , Pool area, Kids Area, Deck and Walk Ways, Litter Picking from Surroundings and Landscape . | F20: 12 | H20: =G20*F20 -> 0
C21: 3 | E21: Sierras Community Centre 15: Swimming Spots, , Pool area, Kids Area, and Walk Ways, Litter Picking from Surroundings and Landscape . | F21: 12 | H21: =G21*F21 -> 0
C22: 4 | D22: Fourteen | E22: Fourteen Community Centre 15: Swimming Spots, Community Buildings, Bathrooms , Pool area, Kids Area, Deck and Walk Ways, Litter Picking from Surroundings and Landscape . | F22: 12 | H22: =G22*F22 -> 0
C23: 5 | E23: Fourteen Community Centre 15: Swimming Spots, , Pool area, Kids Area, and Walk Ways, Litter Picking from Surroundings and Landscape . | F23: 12 | H23: =G23*F23 -> 0
C24: 6 | D24: Alto | E24: Alto community center Swimming Spots, Community Buildings, Bathrooms , Pool area, Kids Area, Deck and Walk Ways, Litter Picking from Surroundings and Landscape . | F24: 12 | H24: =G24*F24 -> 0
C25: 7 | D25: Aurora | E25: Aurora Community Centre: Swimming Spots, Community Buildings, Bathrooms , Pool area, Kids Area, Deck and Walk Ways, Litter Picking from Surroundings and Landscape . | F25: 12 | H25: =G25*F25 -> 0
C26: 8 | D26: Reyna | E26: Reyna Community Centre: Swimming Spots, Community Buildings, Bathrooms , Pool area, Kids Area, Deck and Walk Ways, Litter Picking from Surroundings and Landscape . . | F26: 12 | H26: =G26*F26 -> 0
C27: 9 | D27: Eleva | E27: Eleva Community Centre: Swimming Spots, Community Buildings, Bathrooms , Pool area, Kids Area, Deck and Walk Ways, Litter Picking from Surroundings and Landscape . | F27: 12 | H27: =G27*F27 -> 0
C28: 10 | D28: Isadore | E28: Isadore Community Centre :Swimming Spots, Community Buildings, Bathrooms , Pool area, Kids Area, Deck and Walk Ways, Litter Picking from Surroundings and Landscape . | F28: 12 | H28: =G28*F28 -> 0
C29: 11 | D29: Alba's | E29: Alba Spendia Community Centre:Swimming Spots, Community Buildings, Bathrooms , Pool area, Kids Area, Deck and Walk Ways, Litter Picking from Surroundings and Landscape . | F29: 12 | H29: =G29*F29 -> 0
C30: 12 | D30: Fountain Side | E30: Fountain Side Community Centre :Swimming Spots, Community Buildings, Bathrooms , Pool area, Kids Area, Deck and Walk Ways, Litter Picking from Surroundings and Landscape . | F30: 12 | H30: =G30*F30 -> 0
C31: 13 | D31: Celesta | E31: Celesta Community Centre :Swimming Spots, Community Buildings, Bathrooms , Pool area, Kids Area, Deck and Walk Ways, Litter Picking from Surroundings and Landscape . | F31: 12 | H31: =G31*F31 -> 0
C32: 14 | D32: Terencia | E32: Terencia Community Centre :Swimming Spots, Community Buildings, Bathrooms , Pool area, Kids Area, Deck and Walk Ways, Litter Picking from Surroundings and Landscape . | F32: 12 | H32: =G32*F32 -> 0
C33: 15 | D33: Levana | E33: Levana Community Centre :Swimming Spots, Community Buildings, Bathrooms , Pool area, Kids Area, Deck and Walk Ways, Litter Picking from Surroundings and Landscape . | F33: 12 | H33: =G33*F33 -> 0
C34: 16 | D34: Commercial Area "UTC-Plaza" | E34: UTC-Plaza, Parking, Asphalt, Walk Ways, Littering in public landscape, Marble floor, Bathrooms, Football pitch | F34: 12 | H34: =G34*F34 -> 0
C35: 17 | D35: Commercial Area "UTC-Golf Plaza" | E35: UTC- Golf Plaza, Parking, Asphalt, Walk Ways, Littering in public landscape, Marble floor, Bathrooms, Football pitch | F35: 12 | H35: =G35*F35 -> 0
... C38: 20 | D38: Azzurra | E38: Azzura Village Roads, Parking, Asphalt, Walk Ways, as well as Littering in public landscape. | F38: 12 | H38: =G38*F38 -> 0
C39: 21 | D39: Azzurra | E39: Azzurra Community Centre :Swimming Spots, Community Buildings, Bathrooms , Pool area, Kids Area, Deck and Walk Ways, Litter Picking from Surroundings and Landscape .
C40: 22 | D40: Polo club | F40: 12 | H40: =G40*F40 -> 0
C41: Total Basic Incl. VAT. | H41: =SUM(H19:H40) -> 0
B42: First Year Main Scope | G42: =G17 -> 2954799.7 | H42: =G42*12 -> 35457597 | I42: =H42-J42 -> 0 | J42: =G42*12 -> 35457597 | K42: 4261816.8 | L42: =G42-K42 -> -1307017.1 | M42: =L42/G42 -> -0.44233696 | O42: ='BOQ Basic -Residential (2)'!D49-'BOQ A (2)'!G42 -> 0 | P42: =G3+G4+G5+G6+G7+G8+G9+G10+G11 -> 1975526.1 | Q42: =O42/P42 -> 0
B43: First Year Optional Scope | G43: =G41 -> 0 | H43: =G43*12 -> 0 | I43: =H43-J43 -> 0 | J43: =G43*12 -> 0 | K43: 0 | L43: =G43-K43 -> 0 | M43: =L43/G43 -> #DIV/0!
B44: First Year (Main+Optional) Scope | G44: =SUM(G42:G43) -> 2954799.7 | H44: =SUM(H42:H43) -> 35457597 | I44: =H44-J44 -> 0 | J44: =G44*12 -> 35457597 | K44: 4261816.8 | L44: =G44-K44 -> -1307017.1 | M44: =L44/G44 -> -0.44233696
B45: Second Year Main Scope | G45: =G42*1.12 -> 3309375.7 | H45: =G45*12 -> 39712508 | I45: =H45-J45 -> 0 | J45: =G45*12 -> 39712508 | K45: 4773234.9 | L45: =G45-K45 -> -1463859.2 | M45: =L45/G45 -> -0.44233696
B46: Second Year Optional Scope | G46: =G43*1.12 -> 0 | H46: =G46*12 -> 0 | I46: =H46-J46 -> 0 | J46: =G46*12 -> 0 | K46: 0 | L46: =G46-K46 -> 0 | M46: =L46/G46 -> #DIV/0!
B47: Second Year (Main+Optional) Scope | G47: =SUM(G45:G46) -> 3309375.7 | H47: =SUM(H45:H46) -> 39712508 | I47: =H47-J47 -> 0 | J47: =G47*12 -> 39712508 | K47: 4773234.9 | L47: =G47-K47 -> -1463859.2 | M47: =L47/G47 -> -0.44233696
B48: Third Year Main Scope | G48: =G45*1.12 -> 3706500.8 | H48: =G48*12 -> 44478009 | I48: =H48-J48 -> 0 | J48: =G48*12 -> 44478009 | K48: 5346023.1 | L48: =G48-K48 -> -1639522.3 | M48: =L48/G48 -> -0.44233696
B49: Third Year Optional Scope | G49: =G46*1.12 -> 0 | H49: =G49*12 -> 0 | I49: =H49-J49 -> 0 | J49: =G49*12 -> 0 | K49: 0 | L49: =G49-K49 -> 0 | M49: =L49/G49 -> #DIV/0!
B50: Third Year (Main+Optional) Scope | G50: =SUM(G48:G49) -> 3706500.8 | H50: =SUM(H48:H49) -> 44478009 | I50: =H50-J50 -> 0 | J50: =G50*12 -> 44478009 | K50: 5346023.1 | L50: =G50-K50 -> -1639522.3 | M50: =L50/G50 -> -0.44233696
B51: Contract Amount Main Scope | G51: =G48+G45+G42 -> 9970676.2 | H51: =H48+H45+H42 -> 1.1964811e+08 | I51: =H51-J51 -> 0 | J51: =G51*12 -> 1.1964811e+08 | K51: 14381075 | L51: =G51-K51 -> -4410398.6 | M51: =L51/G51 -> -0.44233696
B52: Contract Amount Optional Scope | G52: =G49+G46+G43 -> 0 | H52: =H49+H46+H43 -> 0 | I52: =H52-J52 -> 0 | J52: =G52*12 -> 0 | K52: 0 | L52: =G52-K52 -> 0 | M52: =L52/G52 -> #DIV/0!
B53: Contract Amount (Main+Optional) Scope | G53: =SUM(G51:G52) -> 9970676.2 | H53: =SUM(H51:H52) -> 1.1964811e+08 | I53: =H53-J53 -> 0 | J53: =G53*12 -> 1.1964811e+08 | K53: 14381075 | L53: =G53-K53 -> -4410398.6 | M53: =L53/G53 -> -0.44233696
D58: # | E58: Optional Scope (Other) | F58: Notes | G58: Rate
D59: 1 | E59: High Pressure Set with Driver, 5K Liters / Month
D60: 2 | E60: High Pressure Set with Driver, 1K Liter / Month
D61: 3 | E61: Boom Lift 15 M / Month
D62: 4 | E62: Man Lift 15 M / Month
D63: 5 | E63: Ride On (Sweeping), with 7000 square meter capacity per hour / Month
D64: 6 | E64: Ride On (Mobbing), with 7000 square meter capacity per hour / Month
D65: 7 | E65: Club Car / Month
D66: 8 | E66: Pick up car with Driver / Month
D67: 9 | E67: Driver / Month
D68: 10 | E68: Supervisor / Month
D69: 11 | E69: Employee / Month
D70: 12 | E70: Employee with Washroom Amenities / Month
... D75: 17 | E75: Car Wash / Unit
D76: # | E76: Optional Scope (Paid Service) | F76: Notes | G76: Rate
D77: 1 | E77: Apartment up to 85 m² (1 Bedroom) | F77: General Cleaning
D78: 2 | E78: Apartments more than 85 m² and up to 120 m² (2 Bedroom)
D79: 3 | E79: Apartment more than 120 m² and up to 200 m² (3 Bedroom and with Pent House)
D80: 4 | E80: Villa or Townhouse more than 200 m² and up to 300 m² (V1 or TH )
D81: 5 | E81: Villas more than 300 m² and up to 420 m² (V2)
D82: 6 | E82: Villas more than 420 m² and up to 600 m² (V3)
D83: 7 | E83: Villas more than 600 m² and up to 850 m² (V4)
D84: 8 | E84: Apartment up to 85 m² (1 Bedroom) | F84: Deep Cleaning
D85: 9 | E85: Apartments more than 85 m² and up to 120 m² (2 Bedroom)
D86: 10 | E86: Apartment more than 120 m² and up to 200 m² (3 Bedroom and with Pent House)
D87: 11 | E87: Villa or Townhouse more than 200 m² and up to 300 m² (V1 or TH )
D88: 12 | E88: Villas more than 300 m² and up to 420 m² (V2)
D89: 13 | E89: Villas more than 420 m² and up to 600 m² (V3)
D90: 14 | E90: Villas more than 600 m² and up to 850 m² (V4)
D93: # | E93: General Notes:
D94: 1 | E94: Company must be BICSc certified | G94: Confirmed
D95: 2 | E95: Tools, chemicals & cleaning methods to be according to BICSc standard | G95: Confirmed
D96: 3 | E96: One of the requested pick up care is to be dedicated for litter piking from main roads every two hours | G96: Confirmed

Sheet Sheet1
B4: 11101135
B5: ='BOQ Basic -Residential'!D50-Sheet1!B4 -> 24057887
B10: 15000

Sheet BOQ Basic -Residential
A4: Basic Scope Residential | B4: All Season | C4: Unit Rate | D4: Monthly Fee
A5: Item | B5: QTY
A6: Labors | B6: 94 | C6: ='HK Budget (2)'!J25 -> 8739.4853 | D6: =C6*$B6 -> 821511.62 | E6: 8894.1264 | F6: 836047.89
A7: Supervisor | B7: 11 | C7: ='HK Budget (2)'!J27 -> 15031.362 | D7: =C7*$B7 -> 165344.98 | E7: 15297.335 | F7: 168270.68
A8: Labors Night Shift | B8: 14 | C8: ='HK Budget (2)'!J26 -> 8739.4853 | D8: =C8*$B8 -> 122352.79 | E8: 8894.1264 | F8: 124517.77
A9: Supervisor Night Shift | B9: 3 | C9: ='HK Budget (2)'!J28 -> 15031.362 | D9: =C9*$B9 -> 45094.085 | E9: 15297.335 | F9: 45892.004
A10: Site Manager | B10: 1 | C10: ='HK Budget (2)'!J31 -> 49130.948 | D10: =C10*$B10 -> 49130.948 | E10: 50337.077 | F10: 50337.077
A11: Site Assistant | B11: 3 | C11: ='HK Budget (2)'!J30 -> 20617.971 | D11: =C11*$B11 -> 61853.913 | E11: 21187.751 | F11: 63563.252
A12: Site Admin | B12: 2 | C12: ='HK Budget (2)'!J29 -> 17859.237 | D12: =C12*$B12 -> 35718.474 | E12: 18277.725 | F12: 36555.45
A13: Sales Center Labor- Morning Shift | B13: 19 | C13: ='HK Budget (2)'!J32 -> 9430.9002 | D13: =C13*$B13 -> 179187.1 | E13: 9597.7757 | F13: 182357.74 | H13: In House team Mandatory
A14: Sales Center Labor- Night Shift | B14: 11 | C14: ='HK Budget (2)'!J32 -> 9430.9002 | D14: =C14*$B14 -> 103739.9 | E14: 9597.7757 | F14: 105575.53
A15: Sales Center supervisor- Morning Shift | B15: 2 | C15: ='HK Budget (2)'!J33 -> 15722.777 | D15: =C15*$B15 -> 31445.553 | E15: 16000.984 | F15: 32001.968
A16: Sales Center supervisor- Night Shift | B16: 1 | C16: ='HK Budget (2)'!J33 -> 15722.777 | D16: =C16*$B16 -> 15722.777 | E16: 16000.984 | F16: 16000.984
A17: Sales Center Assistant Manager | B17: 1 | C17: ='HK Budget (2)'!J34 -> 21309.386 | D17: =C17*$B17 -> 21309.386 | E17: 21891.4 | F17: 21891.4
A18: Transportation | B18: LS | C18: ='HK Budget (2)'!C49 -> 460673.18 | D18: =C18 -> 460673.18 | E18: 469204.16 | F18: 469204.16
A19: Manpower | D19: =SUM(D6:D18) -> 2113084.7 | F19: 2152215.9
A20: Façade Cleaning service " as per site need max. 168 buildings per year" | B20: 14 | C20: ='Facades Cleaning Cost'!G22 -> 12016.204 | D20: =C20*$B20 -> 168226.86 | E20: 12238.727 | F20: 171342.17 | H20: Total Buildings 56 & 3 times per year
A21: Single disk | B21: 5 | C21: ='Equipment & Tools Cost'!AU6 -> 1249 | D21: =C21*$B21 -> 6245 | E21: 1272 | F21: 6360
A22: Vacuum | B22: 6 | C22: ='Equipment & Tools Cost'!AU8 -> 729 | D22: =C22*$B22 -> 4374 | E22: 742 | F22: 4452
A23: Manual sweeper | B23: 10 | C23: ='Equipment & Tools Cost'!AU11 -> 937 | D23: =C23*$B23 -> 9370 | E23: 954 | F23: 9540
A24: McClean Trolley | B24: 14 | C24: ='Equipment & Tools Cost'!AU12 -> 387 | D24: =C24*$B24 -> 5418 | E24: 394 | F24: 5516
A25: Black Broom and Closed Ban | B25: 23 | C25: ='Equipment & Tools Cost'!AU13 -> 94 | D25: =C25*$B25 -> 2162 | E25: 96 | F25: 2208
A26: Litter Picking Steak | B26: 12 | C26: ='Equipment & Tools Cost'!AU14 -> 105 | D26: =C26*$B26 -> 1260 | E26: 106 | F26: 1272
A27: Mob Bucket with Cotton Cloth | B27: 25 | C27: ='Equipment & Tools Cost'!AU15 -> 63 | D27: =C27*$B27 -> 1575 | E27: 64 | F27: 1600
A28: Water Fed Telescope (20 Meter) | B28: 2 | C28: ='Equipment & Tools Cost'!AU17 -> 7907 | D28: =C28*$B28 -> 15814 | E28: 8054 | F28: 16108
A29: High Pressure Set One Car, Driver, 1K Liter tank" -30 days" | B29: 2 | C29: ='Equipment & Tools Cost'!AU18 -> 63818 | D29: =C29*$B29 -> 127636 | E29: 64999 | F29: 129998
A30: Man Lift 15M" *30 days" | B30: 2 | C30: ='Equipment & Tools Cost'!AU19 -> 67716 | D30: =C30*$B30 -> 135432 | E30: 68970 | F30: 137940
A31: Pick up Car with driver | B31: 2 | C31: ='Equipment & Tools Cost'!AU20 -> 52435 | D31: =C31*$B31 -> 104870 | E31: 53406 | F31: 106812
A32: Public trolly for Building | B32: 25 | C32: ='Equipment & Tools Cost'!AU10 -> 278 | D32: =C32*$B32 -> 6950 | E32: 283 | F32: 7075
A33: Cary cady " As per site Need" | B33: 56 | C33: ='Equipment & Tools Cost'!AU16 -> 16 | D33: =C33*$B33 -> 896 | E33: 16 | F33: 896
A34: Consumables & tools & Chemical Rates | B34: 1 | C34: ='Equipment & Tools Cost'!M65 -> 149437.37 | D34: =C34*$B34 -> 149437.37 | E34: 152238.24 | F34: 152238.24
A35: Sales Center - Single disk | B35: 3 | C35: ='Equipment & Tools Cost'!AU6 -> 1249 | D35: =C35*$B35 -> 3747 | E35: 1272 | F35: 3816
A36: Sales Center - Vacuum | B36: 2 | C36: ='Equipment & Tools Cost'!AU8 -> 729 | D36: =C36*$B36 -> 1458 | E36: 742 | F36: 1484
A37: Sales Center - Manual sweeper | B37: 2 | C37: ='Equipment & Tools Cost'!AU11 -> 937 | D37: =C37*$B37 -> 1874 | E37: 954 | F37: 1908
A38: Sales Center - McClean Trolley | B38: 3 | C38: ='Equipment & Tools Cost'!AU12 -> 387 | D38: =C38*$B38 -> 1161 | E38: 394 | F38: 1182
A39: Sales Center - Black Broom and Closed Ban | B39: 10 | C39: ='Equipment & Tools Cost'!AU13 -> 94 | D39: =C39*$B39 -> 940 | E39: 96 | F39: 960
A40: Sales Center - Litter Picking Steak | B40: 3 | C40: ='Equipment & Tools Cost'!AU14 -> 105 | D40: =C40*$B40 -> 315 | E40: 106 | F40: 318
A41: Sales Center - Mob Bucket with Cotton Cloth | B41: 10 | C41: ='Equipment & Tools Cost'!AU15 -> 63 | D41: =C41*$B41 -> 630 | E41: 64 | F41: 640
A42: Sales Center - Ladder | B42: 2 | C42: ='Equipment & Tools Cost'!AU22 -> 132 | D42: =C42*$B42 -> 264 | E42: 135 | F42: 270
A43: Sales Center - telescope | B43: 1 | C43: ='Equipment & Tools Cost'!AU24 -> 131 | D43: =C43*$B43 -> 131 | E43: 133 | F43: 133
A44: Sales Center - Public trolly | B44: 3 | C44: ='Equipment & Tools Cost'!AU10 -> 278 | D44: =C44*$B44 -> 834 | E44: 283 | F44: 849
A45: Sales Center - Cary cady | B45: 13 | C45: ='Equipment & Tools Cost'!AU16 -> 16 | D45: =C45*$B45 -> 208 | E45: 16 | F45: 208
A46: Sales Center - Steam Machine | B46: 1 | C46: ='Equipment & Tools Cost'!AU9 -> 1561 | D46: =C46*$B46 -> 1561 | E46: 1590 | F46: 1590
A47: Sales Center - Consumables & tools & Chemical Rates | B47: 1 | C47: ='Equipment & Tools Cost'!L65 -> 64044.588 | D47: =C47*$B47 -> 64044.588 | E47: 65244.96 | F47: 65244.96
A48: Equipment | D48: =SUM(D20:D47) -> 816833.82 | F48: 831960.37
A49: Grand Total | D49: =D48+D19 -> 2929918.5 | F49: 2984176.3
A50: First Year | D50: =D49*12 -> 35159022 | F50: 35810115
A51: Second Year | D51: =D50*1.1 -> 38674925
A52: Third Year | D52: =D51*1.1 -> 42542417
A53: Grand Total | D53: =SUM(D50:D52) -> 1.1637636e+08

Sheet BOQ A
B2: Scope | C2: # | D2: UPTWON CAIRO-ZONE A | E2: Description (Housekeeping) | F2: Duration | G2: Monthly Rate | H2: Amount
B3: Basic Scope | C3: 1 | D3: Sierras | E3: Sierras Building, Entrance,Furniture, Corridors, Stairs, Handrails, Walls, Elevators, Ceiling, Roofs and Roads, Parking, Asphalt, Walk Ways, as well as Littering in public landscape. | F3: 12 | G3: ='HK Budget (2)'!I19 -> 540231.81 | H3: =G3*F3 -> 6482781.8 | K3: 920624.36 | L3: =G3-K3 -> -380392.55 | M3: =L3/G3 -> -0.70412838
C4: 2 | D4: Alto | E4: Alto Building, Entrance,Furniture, Corridors, Stairs, Handrails, Walls, Elevators, Ceiling, Roofs and Roads, Parking, Asphalt, Walk Ways, as well as Littering in public landscape. | F4: 12 | G4: ='HK Budget (2)'!J19 -> 253122.53 | H4: =G4*F4 -> 3037470.3 | K4: 371983.73 | L4: =G4-K4 -> -118861.2 | M4: =L4/G4 -> -0.46957971
C5: 3 | D5: Aurora | E5: Aurora Building, Entrance,Furniture, Corridors, Stairs, Handrails, Walls, Elevators, Ceiling, Roofs and Roads, Parking, Asphalt, Walk Ways, as well as Littering in public landscape. | F5: 12 | G5: ='HK Budget (2)'!K19 -> 260143.04 | H5: =G5*F5 -> 3121716.5 | K5: 368133.47 | L5: =G5-K5 -> -107990.42 | M5: =L5/G5 -> -0.4151194
C6: 4 | D6: Fourteen | E6: Fourteen Building, Entrance,Furniture, Corridors, Stairs, Handrails, Walls, Elevators, Ceiling, Roofs and Roads, Parking, Asphalt, Walk Ways, as well as Littering in public landscape. | F6: 12 | G6: ='HK Budget (2)'!L19 -> 507684.82 | H6: =G6*F6 -> 6092217.8 | K6: 806193.75 | L6: =G6-K6 -> -298508.93 | M6: =L6/G6 -> -0.58798081
C7: 5 | D7: Reyna | E7: Reyna Village Roads, Parking, Asphalt, Walk Ways, Pergolas , play court as well as Littering in public landscape. | F7: 12 | G7: ='HK Budget (2)'!M19 -> 105259.09 | H7: =G7*F7 -> 1263109.1 | K7: 132229.96 | L7: =G7-K7 -> -26970.866 | M7: =L7/G7 -> -0.25623313
C8: 6 | D8: Eleva | E8: Eleva Village Roads, Parking, Asphalt, Walk Ways,Pergolas as well as Littering in public landscape. | F8: 12 | G8: ='HK Budget (2)'!N19 -> 80880.445 | H8: =G8*F8 -> 970565.34 | K8: 102178.85 | L8: =G8-K8 -> -21298.403 | M8: =L8/G8 -> -0.26333192
C9: 7 | D9: Isadore | E9: Isadore Village Roads, Parking, Asphalt, Walk Ways, Pergolas as well as Littering in public landscape. | F9: 12 | G9: ='HK Budget (2)'!O19 -> 61958.361 | H9: =G9*F9 -> 743500.33 | K9: 78508.912 | L9: =G9-K9 -> -16550.551 | M9: =L9/G9 -> -0.26712377
C10: 8 | D10: Alba's Aliyah | E10: Alba Aliyah Village Roads, Parking, Asphalt, Walk Ways, as well as Littering in public landscape. | F10: 12 | G10: ='HK Budget (2)'!P19 -> 79442.959 | H10: =G10*F10 -> 953315.51 | K10: 100410.82 | L10: =G10-K10 -> -20967.865 | M10: =L10/G10 -> -0.2639361
C11: 9 | D11: Alba's Spendia | E11: Alba Spendia Village Roads, Parking, Asphalt, Walk Ways, as well as Littering in public landscape. | F11: 12 | G11: ='HK Budget (2)'!Q19 -> 78974.795 | H11: =G11*F11 -> 947697.54 | K11: 99151.035 | L11: =G11-K11 -> -20176.24 | M11: =L11/G11 -> -0.25547695
C12: 10 | D12: Commercial Area "UTC-Golf club house | E12: UTC-Golf club house : Building, Entrance,Furniture, Corridors, Stairs, Handrails, Walls, Elevators, Ceiling, Roofs and Parking, Asphalt, Walk Ways, Littering in public landscape, Marble floor, Bathrooms, 3 Hubs at golf Area and golf Office | F12: 12 | G12: ='HK Budget (2)'!R19 -> 227995.47 | H12: =G12*F12 -> 2735945.6 | K12: 276777.38 | L12: =G12-K12 -> -48781.913 | M12: =L12/G12 -> -0.21396001
C13: 11 | D13: Public Roads | E13: Road 7, Parking, Landscape areas, utility bulidings,Walkways,Security guardhouse and Kiosks | F13: 12 | G13: ='HK Budget (2)'!S19 -> 21772.409 | H13: =G13*F13 -> 261268.9 | K13: 27043.411 | L13: =G13-K13 -> -5271.0024 | M13: =L13/G13 -> -0.24209551
C14: 12 | D14: Crossing gates | E14: all Consutation gates on site , Walkways,Security guardhouse and Kiosks | F14: 12 | G14: ='HK Budget (2)'!T19 -> 116671.73 | H14: =G14*F14 -> 1400060.7 | K14: 142784.13 | L14: =G14-K14 -> -26112.399 | M14: =L14/G14 -> -0.22381085
C15: 13 | D15: Mobilization areas " water station " | E15: Mobilization areas, with Caravans, public area | F15: 12 | G15: ='HK Budget (2)'!U19 -> 19590.072 | H15: =G15*F15 -> 235080.86 | K15: 24358.381 | L15: =G15-K15 -> -4768.3089 | M15: =L15/G15 -> -0.24340436
C16: 14 | D16: Managament"sales center" | E16: Head Quarter (Management building - sale center - customer excellence area - mock up apartments - garage - parking - public areas - landscape area - waste collection area) | F16: 12 | G16: ='HK Budget (2)'!V19 -> 593243.93 | H16: =G16*F16 -> 7118927.2 | K16: 811438.67 | L16: =G16-K16 -> -218194.74 | M16: =L16/G16 -> -0.36779936
C17: Total Basic Incl. VAT. | G17: =SUM(G3:G16) -> 2946971.5 | H17: =SUM(H3:H16) -> 35363657 | K17: =SUM(K3:K16) -> 4261816.8 | L17: =G17-K17 -> -1314845.4 | M17: =L17/G17 -> -0.44616835
B19: Optional Scope | C19: 1 | D19: Sierras | E19: Sierras Community Centre 1 : Swimming Spots, Community Buildings, Bathrooms , Pool area, Kids Area, Deck and Walk Ways, Litter Picking from Surroundings and Landscape . | F19: 12 | H19: =G19*F19 -> 0
C20: 2 | E20: Sierras Community Centre 15: Swimming Spots, Community Buildings, Bathrooms , Pool area, Kids Area, Deck and Walk Ways, Litter Picking from Surroundings and Landscape . | F20: 12 | H20: =G20*F20 -> 0
C21: 3 | E21: Sierras Community Centre 15: Swimming Spots, , Pool area, Kids Area, and Walk Ways, Litter Picking from Surroundings and Landscape . | F21: 12 | H21: =G21*F21 -> 0
C22: 4 | D22: Fourteen | E22: Fourteen Community Centre 15: Swimming Spots, Community Buildings, Bathrooms , Pool area, Kids Area, Deck and Walk Ways, Litter Picking from Surroundings and Landscape . | F22: 12 | H22: =G22*F22 -> 0
C23: 5 | E23: Fourteen Community Centre 15: Swimming Spots, , Pool area, Kids Area, and Walk Ways, Litter Picking from Surroundings and Landscape . | F23: 12 | H23: =G23*F23 -> 0
C24: 6 | D24: Alto | E24: Alto community center Swimming Spots, Community Buildings, Bathrooms , Pool area, Kids Area, Deck and Walk Ways, Litter Picking from Surroundings and Landscape . | F24: 12 | H24: =G24*F24 -> 0
C25: 7 | D25: Aurora | E25: Aurora Community Centre: Swimming Spots, Community Buildings, Bathrooms , Pool area, Kids Area, Deck and Walk Ways, Litter Picking from Surroundings and Landscape . | F25: 12 | H25: =G25*F25 -> 0
C26: 8 | D26: Reyna | E26: Reyna Community Centre: Swimming Spots, Community Buildings, Bathrooms , Pool area, Kids Area, Deck and Walk Ways, Litter Picking from Surroundings and Landscape . . | F26: 12 | H26: =G26*F26 -> 0
C27: 9 | D27: Eleva | E27: Eleva Community Centre: Swimming Spots, Community Buildings, Bathrooms , Pool area, Kids Area, Deck and Walk Ways, Litter Picking from Surroundings and Landscape . | F27: 12 | H27: =G27*F27 -> 0
C28: 10 | D28: Isadore | E28: Isadore Community Centre :Swimming Spots, Community Buildings, Bathrooms , Pool area, Kids Area, Deck and Walk Ways, Litter Picking from Surroundings and Landscape . | F28: 12 | H28: =G28*F28 -> 0
C29: 11 | D29: Alba's | E29: Alba Spendia Community Centre:Swimming Spots, Community Buildings, Bathrooms , Pool area, Kids Area, Deck and Walk Ways, Litter Picking from Surroundings and Landscape . | F29: 12 | H29: =G29*F29 -> 0
C30: 12 | D30: Fountain Side | E30: Fountain Side Community Centre :Swimming Spots, Community Buildings, Bathrooms , Pool area, Kids Area, Deck and Walk Ways, Litter Picking from Surroundings and Landscape . | F30: 12 | H30: =G30*F30 -> 0
C31: 13 | D31: Celesta | E31: Celesta Community Centre :Swimming Spots, Community Buildings, Bathrooms , Pool area, Kids Area, Deck and Walk Ways, Litter Picking from Surroundings and Landscape . | F31: 12 | H31: =G31*F31 -> 0
C32: 14 | D32: Terencia | E32: Terencia Community Centre :Swimming Spots, Community Buildings, Bathrooms , Pool area, Kids Area, Deck and Walk Ways, Litter Picking from Surroundings and Landscape . | F32: 12 | H32: =G32*F32 -> 0
C33: 15 | D33: Levana | E33: Levana Community Centre :Swimming Spots, Community Buildings, Bathrooms , Pool area, Kids Area, Deck and Walk Ways, Litter Picking from Surroundings and Landscape . | F33: 12 | H33: =G33*F33 -> 0
C34: 16 | D34: Commercial Area "UTC-Plaza" | E34: UTC-Plaza, Parking, Asphalt, Walk Ways, Littering in public landscape, Marble floor, Bathrooms, Football pitch | F34: 12 | H34: =G34*F34 -> 0
C35: 17 | D35: Commercial Area "UTC-Golf Plaza" | E35: UTC- Golf Plaza, Parking, Asphalt, Walk Ways, Littering in public landscape, Marble floor, Bathrooms, Football pitch | F35: 12 | H35: =G35*F35 -> 0
... C38: 20 | D38: Azzurra | E38: Azzura Village Roads, Parking, Asphalt, Walk Ways, as well as Littering in public landscape. | F38: 12 | H38: =G38*F38 -> 0
C39: 21 | D39: Azzurra | E39: Azzurra Community Centre :Swimming Spots, Community Buildings, Bathrooms , Pool area, Kids Area, Deck and Walk Ways, Litter Picking from Surroundings and Landscape .
C40: 22 | D40: Polo club | F40: 12 | H40: =G40*F40 -> 0
C41: Total Basic Incl. VAT. | H41: =SUM(H19:H40) -> 0
B42: First Year Main Scope | G42: =G17 -> 2946971.5 | H42: =G42*12 -> 35363657 | I42: =H42-J42 -> 0 | J42: =G42*12 -> 35363657 | K42: 4261816.8 | L42: =G42-K42 -> -1314845.4 | M42: =L42/G42 -> -0.44616835
B43: First Year Optional Scope | G43: =G41 -> 0 | H43: =G43*12 -> 0 | I43: =H43-J43 -> 0 | J43: =G43*12 -> 0 | K43: 0 | L43: =G43-K43 -> 0 | M43: =L43/G43 -> #DIV/0!
B44: First Year (Main+Optional) Scope | G44: =SUM(G42:G43) -> 2946971.5 | H44: =SUM(H42:H43) -> 35363657 | I44: =H44-J44 -> 0 | J44: =G44*12 -> 35363657 | K44: 4261816.8 | L44: =G44-K44 -> -1314845.4 | M44: =L44/G44 -> -0.44616835
B45: Second Year Main Scope | G45: =G42*1.12 -> 3300608 | H45: =G45*12 -> 39607296 | I45: =H45-J45 -> 0 | J45: =G45*12 -> 39607296 | K45: 4773234.9 | L45: =G45-K45 -> -1472626.8 | M45: =L45/G45 -> -0.44616835
B46: Second Year Optional Scope | G46: =G43*1.12 -> 0 | H46: =G46*12 -> 0 | I46: =H46-J46 -> 0 | J46: =G46*12 -> 0 | K46: 0 | L46: =G46-K46 -> 0 | M46: =L46/G46 -> #DIV/0!
B47: Second Year (Main+Optional) Scope | G47: =SUM(G45:G46) -> 3300608 | H47: =SUM(H45:H46) -> 39607296 | I47: =H47-J47 -> 0 | J47: =G47*12 -> 39607296 | K47: 4773234.9 | L47: =G47-K47 -> -1472626.8 | M47: =L47/G47 -> -0.44616835
B48: Third Year Main Scope | G48: =G45*1.12 -> 3696681 | H48: =G48*12 -> 44360172 | I48: =H48-J48 -> 0 | J48: =G48*12 -> 44360172 | K48: 5346023.1 | L48: =G48-K48 -> -1649342.1 | M48: =L48/G48 -> -0.44616835
B49: Third Year Optional Scope | G49: =G46*1.12 -> 0 | H49: =G49*12 -> 0 | I49: =H49-J49 -> 0 | J49: =G49*12 -> 0 | K49: 0 | L49: =G49-K49 -> 0 | M49: =L49/G49 -> #DIV/0!
B50: Third Year (Main+Optional) Scope | G50: =SUM(G48:G49) -> 3696681 | H50: =SUM(H48:H49) -> 44360172 | I50: =H50-J50 -> 0 | J50: =G50*12 -> 44360172 | K50: 5346023.1 | L50: =G50-K50 -> -1649342.1 | M50: =L50/G50 -> -0.44616835
B51: Contract Amount Main Scope | G51: =G48+G45+G42 -> 9944260.5 | H51: =H48+H45+H42 -> 1.1933113e+08 | I51: =H51-J51 -> 0 | J51: =G51*12 -> 1.1933113e+08 | K51: 14381075 | L51: =G51-K51 -> -4436814.3 | M51: =L51/G51 -> -0.44616835
B52: Contract Amount Optional Scope | G52: =G49+G46+G43 -> 0 | H52: =H49+H46+H43 -> 0 | I52: =H52-J52 -> 0 | J52: =G52*12 -> 0 | K52: 0 | L52: =G52-K52 -> 0 | M52: =L52/G52 -> #DIV/0!
B53: Contract Amount (Main+Optional) Scope | G53: =SUM(G51:G52) -> 9944260.5 | H53: =SUM(H51:H52) -> 1.1933113e+08 | I53: =H53-J53 -> 0 | J53: =G53*12 -> 1.1933113e+08 | K53: 14381075 | L53: =G53-K53 -> -4436814.3 | M53: =L53/G53 -> -0.44616835
D58: # | E58: Optional Scope (Other) | F58: Notes | G58: Rate
D59: 1 | E59: High Pressure Set with Driver, 5K Liters / Month
D60: 2 | E60: High Pressure Set with Driver, 1K Liter / Month
D61: 3 | E61: Boom Lift 15 M / Month
D62: 4 | E62: Man Lift 15 M / Month
D63: 5 | E63: Ride On (Sweeping), with 7000 square meter capacity per hour / Month
D64: 6 | E64: Ride On (Mobbing), with 7000 square meter capacity per hour / Month
D65: 7 | E65: Club Car / Month
D66: 8 | E66: Pick up car with Driver / Month
D67: 9 | E67: Driver / Month
D68: 10 | E68: Supervisor / Month
D69: 11 | E69: Employee / Month
D70: 12 | E70: Employee with Washroom Amenities / Month
... D75: 17 | E75: Car Wash / Unit
D76: # | E76: Optional Scope (Paid Service) | F76: Notes | G76: Rate
D77: 1 | E77: Apartment up to 85 m² (1 Bedroom) | F77: General Cleaning
D78: 2 | E78: Apartments more than 85 m² and up to 120 m² (2 Bedroom)
D79: 3 | E79: Apartment more than 120 m² and up to 200 m² (3 Bedroom and with Pent House)
D80: 4 | E80: Villa or Townhouse more than 200 m² and up to 300 m² (V1 or TH )
D81: 5 | E81: Villas more than 300 m² and up to 420 m² (V2)
D82: 6 | E82: Villas more than 420 m² and up to 600 m² (V3)
D83: 7 | E83: Villas more than 600 m² and up to 850 m² (V4)
D84: 8 | E84: Apartment up to 85 m² (1 Bedroom) | F84: Deep Cleaning
D85: 9 | E85: Apartments more than 85 m² and up to 120 m² (2 Bedroom)
D86: 10 | E86: Apartment more than 120 m² and up to 200 m² (3 Bedroom and with Pent House)
D87: 11 | E87: Villa or Townhouse more than 200 m² and up to 300 m² (V1 or TH )
D88: 12 | E88: Villas more than 300 m² and up to 420 m² (V2)
D89: 13 | E89: Villas more than 420 m² and up to 600 m² (V3)
D90: 14 | E90: Villas more than 600 m² and up to 850 m² (V4)
D93: # | E93: General Notes:
D94: 1 | E94: Company must be BICSc certified | G94: Confirmed
D95: 2 | E95: Tools, chemicals & cleaning methods to be according to BICSc standard | G95: Confirmed
D96: 3 | E96: One of the requested pick up care is to be dedicated for litter piking from main roads every two hours | G96: Confirmed

Sheet Manpower Cost
B3: UTC HK Budget
B4: Items | C4: Head Count | D4: Net Salary | E4: CTC | F4: Total Amount/ Month | K4: Sierras | M4: Alto | O4: Aurora | Q4: Fourteen | S4: Reyna | U4: Eleva | W4: Isadore | Y4: Alba's Aliyah | AA4: Alba's Spendia | AC4: Commercial Area "UTC-Golf club house | AE4: Public Roads | AG4: Crossing gates | AI4: Mobilization areas " water station " | AK4: Managament"sales center" | AM4: Total Head Count Cost | AN4: Gross Margin | AO4: Total | AP4: Contingency | AQ4: Total | AR4: VAT | AS4: Total W VAT | AT4: Unit Rate
B5: Head Count | K5: Head Count | L5: Monthly Cost | M5: Head Count | N5: Monthly Cost | O5: Head Count | P5: Monthly Cost | Q5: Head Count | R5: Monthly Cost | S5: Head Count | T5: Monthly Cost | U5: Head Count | V5: Monthly Cost | W5: Head Count | X5: Monthly Cost | Y5: Head Count | Z5: Monthly Cost | AA5: Head Count | AB5: Monthly Cost | AC5: Head Count | AD5: Monthly Cost | AE5: Head Count | AF5: Monthly Cost | AG5: Head Count | AH5: Monthly Cost | AI5: Head Count | AJ5: Monthly Cost | AK5: Head Count | AL5: Monthly Cost
B6: ='Manpower CTC'!B5 -> Labors Morning Shift | C6: =K6+M6+O6+Q6+S6+U6+W6+Y6+AA6+AC6+AE6+AG6+AI6 -> 94 | E6: ='Manpower CTC'!C5 -> 6320 | F6: =C6*E6 -> 594080 | H6: =C6-(K6+M6+O6+Q6+S6+U6+W6+Y6+AA6+AC6+AE6+AG6+AI6+AK6) -> 0 | I6: =F6-(L6+N6+P6+R6+T6+V6+X6+Z6+AB6+AD6+AF6+AH6+AJ6+AL6) -> 0 | K6: =Maning!F6 -> 20 | L6: =E6*K6 -> 126400 | M6: =Maning!G6 -> 10 | N6: =M6*E6 -> 63200 | O6: =Maning!H6 -> 11 | P6: =O6*E6 -> 69520 | Q6: =Maning!I6 -> 20 | R6: =Q6*E6 -> 126400 | S6: =Maning!J6 -> 5 | T6: =S6*E6 -> 31600 | U6: =Maning!K6 -> 4 | V6: =U6*E6 -> 25280 | W6: =Maning!L6 -> 3 | X6: =W6*E6 -> 18960 | Y6: =Maning!M6 -> 4 | Z6: =Y6*E6 -> 25280 | AA6: =Maning!N6 -> 4 | AB6: =AA6*E6 -> 25280 | AC6: =Maning!O6 -> 5 | AD6: =AC6*E6 -> 31600 | AE6: =Maning!P6 -> 1 | AF6: =AE6*E6 -> 6320 | AG6: =Maning!Q6 -> 6 | AH6: =AG6*E6 -> 37920 | AI6: =Maning!R6 -> 1 | AJ6: =AI6*E6 -> 6320 | AK6: =Maning!S6 -> 0 | AL6: =AK6*E6 -> 0 | AM6: =SUM(L6+N6+P6+R6+T6+V6+X6+Z6+AB6+AD6+AF6+AH6+AJ6+AL6) -> 594080 | AN6: =AM6*$E$17 -> 47526.4 | AO6: =AM6+AN6 -> 641606.4 | AP6: =AO6*$E$19 -> 8982.4896 | AQ6: =AO6+AP6 -> 650588.89 | AR6: =AQ6*$E$21 -> 91082.445 | AS6: =AQ6+AR6 -> 741671.33 | AT6: =AS6/C6 -> 7890.1206
B7: ='Manpower CTC'!B6 -> Labors Noon Shift | C7: =K7+M7+O7+Q7+S7+U7+W7+Y7+AA7+AC7+AE7+AG7+AI7 -> 14 | E7: ='Manpower CTC'!C6 -> 6320 | F7: =C7*E7 -> 88480 | H7: =C7-(K7+M7+O7+Q7+S7+U7+W7+Y7+AA7+AC7+AE7+AG7+AI7+AK7) -> 0 | I7: =F7-(L7+N7+P7+R7+T7+V7+X7+Z7+AB7+AD7+AF7+AH7+AJ7+AL7) -> 0 | K7: =Maning!F7 -> 3.2553191 | L7: =E7*K7 -> 20573.617 | M7: =Maning!G7 -> 1.7234043 | N7: =M7*E7 -> 10891.915 | O7: =Maning!H7 -> 1.3404255 | P7: =O7*E7 -> 8471.4894 | Q7: =Maning!I7 -> 2.6808511 | R7: =Q7*E7 -> 16942.979 | S7: =Maning!J7 -> 0 | T7: =S7*E7 -> 0 | U7: =Maning!K7 -> 0 | V7: =U7*E7 -> 0 | W7: =Maning!L7 -> 0 | X7: =W7*E7 -> 0 | Y7: =Maning!M7 -> 0 | Z7: =Y7*E7 -> 0 | AA7: =Maning!N7 -> 0 | AB7: =AA7*E7 -> 0 | AC7: =Maning!O7 -> 5 | AD7: =AC7*E7 -> 31600 | AE7: =Maning!P7 -> 0 | AF7: =AE7*E7 -> 0 | AG7: =Maning!Q7 -> 0 | AH7: =AG7*E7 -> 0 | AI7: =Maning!R7 -> 0 | AJ7: =AI7*E7 -> 0 | AK7: =Maning!S7 -> 0 | AL7: =AK7*E7 -> 0 | AM7: =SUM(L7+N7+P7+R7+T7+V7+X7+Z7+AB7+AD7+AF7+AH7+AJ7+AL7) -> 88480 | AN7: =AM7*$E$17 -> 7078.4 | AO7: =AM7+AN7 -> 95558.4 | AP7: =AO7*$E$19 -> 1337.8176 | AQ7: =AO7+AP7 -> 96896.218 | AR7: =AQ7*$E$21 -> 13565.47 | AS7: =AQ7+AR7 -> 110461.69 | AT7: =AS7/C7 -> 7890.1206
B8: ='Manpower CTC'!B7 -> Supervisor Morning Shift | C8: =K8+M8+O8+Q8+S8+U8+W8+Y8+AA8+AC8+AE8+AG8+AI8 -> 11 | E8: ='Manpower CTC'!C7 -> 10870 | F8: =C8*E8 -> 119570 | H8: =C8-(K8+M8+O8+Q8+S8+U8+W8+Y8+AA8+AC8+AE8+AG8+AI8+AK8) -> 0 | I8: =F8-(L8+N8+P8+R8+T8+V8+X8+Z8+AB8+AD8+AF8+AH8+AJ8+AL8) -> 0 | K8: =Maning!F8 -> 2 | L8: =E8*K8 -> 21740 | M8: =Maning!G8 -> 1 | N8: =M8*E8 -> 10870 | O8: =Maning!H8 -> 1 | P8: =O8*E8 -> 10870 | Q8: =Maning!I8 -> 2 | R8: =Q8*E8 -> 21740 | S8: =Maning!J8 -> 1 | T8: =S8*E8 -> 10870 | U8: =Maning!K8 -> 0.57142857 | V8: =U8*E8 -> 6211.4286 | W8: =Maning!L8 -> 0.42857143 | X8: =W8*E8 -> 4658.5714 | Y8: =Maning!M8 -> 0.5 | Z8: =Y8*E8 -> 5435 | AA8: =Maning!N8 -> 0.5 | AB8: =AA8*E8 -> 5435 | AC8: =Maning!O8 -> 1 | AD8: =AC8*E8 -> 10870 | AE8: =Maning!P8 -> 0.125 | AF8: =AE8*E8 -> 1358.75 | AG8: =Maning!Q8 -> 0.75 | AH8: =AG8*E8 -> 8152.5 | AI8: =Maning!R8 -> 0.125 | AJ8: =AI8*E8 -> 1358.75 | AK8: =Maning!S8 -> 0 | AL8: =AK8*E8 -> 0 | AM8: =SUM(L8+N8+P8+R8+T8+V8+X8+Z8+AB8+AD8+AF8+AH8+AJ8+AL8) -> 119570 | AN8: =AM8*$E$17 -> 9565.6 | AO8: =AM8+AN8 -> 129135.6 | AP8: =AO8*$E$19 -> 1807.8984 | AQ8: =AO8+AP8 -> 130943.5 | AR8: =AQ8*$E$21 -> 18332.09 | AS8: =AQ8+AR8 -> 149275.59 | AT8: =AS8/C8 -> 13570.508
B9: ='Manpower CTC'!B8 -> Supervisor Noon Shift | C9: =K9+M9+O9+Q9+S9+U9+W9+Y9+AA9+AC9+AE9+AG9+AI9 -> 3 | E9: ='Manpower CTC'!C8 -> 10870 | F9: =C9*E9 -> 32610 | H9: =C9-(K9+M9+O9+Q9+S9+U9+W9+Y9+AA9+AC9+AE9+AG9+AI9+AK9) -> 0 | I9: =F9-(L9+N9+P9+R9+T9+V9+X9+Z9+AB9+AD9+AF9+AH9+AJ9+AL9) -> 0 | K9: =Maning!F9 -> 0.66666667 | L9: =E9*K9 -> 7246.6667 | M9: =Maning!G9 -> 0.33333333 | N9: =M9*E9 -> 3623.3333 | O9: =Maning!H9 -> 0.33333333 | P9: =O9*E9 -> 3623.3333 | Q9: =Maning!I9 -> 0.66666667 | R9: =Q9*E9 -> 7246.6667 | S9: =Maning!J9 -> 0 | T9: =S9*E9 -> 0 | U9: =Maning!K9 -> 0 | V9: =U9*E9 -> 0 | W9: =Maning!L9 -> 0 | X9: =W9*E9 -> 0 | Y9: =Maning!M9 -> 0 | Z9: =Y9*E9 -> 0 | AA9: =Maning!N9 -> 0 | AB9: =AA9*E9 -> 0 | AC9: =Maning!O9 -> 1 | AD9: =AC9*E9 -> 10870 | AE9: =Maning!P9 -> 0 | AF9: =AE9*E9 -> 0 | AG9: =Maning!Q9 -> 0 | AH9: =AG9*E9 -> 0 | AI9: =Maning!R9 -> 0 | AJ9: =AI9*E9 -> 0 | AK9: =Maning!S9 -> 0 | AL9: =AK9*E9 -> 0 | AM9: =SUM(L9+N9+P9+R9+T9+V9+X9+Z9+AB9+AD9+AF9+AH9+AJ9+AL9) -> 32610 | AN9: =AM9*$E$17 -> 2608.8 | AO9: =AM9+AN9 -> 35218.8 | AP9: =AO9*$E$19 -> 493.0632 | AQ9: =AO9+AP9 -> 35711.863 | AR9: =AQ9*$E$21 -> 4999.6608 | AS9: =AQ9+AR9 -> 40711.524 | AT9: =AS9/C9 -> 13570.508
B10: ='Manpower CTC'!B9 -> Site Admin | C10: =K10+M10+O10+Q10+S10+U10+W10+Y10+AA10+AC10+AE10+AG10+AI10 -> 2 | E10: ='Manpower CTC'!C9 -> 16920 | F10: =C10*E10 -> 33840 | H10: =C10-(K10+M10+O10+Q10+S10+U10+W10+Y10+AA10+AC10+AE10+AG10+AI10+AK10) -> 0 | I10: =F10-(L10+N10+P10+R10+T10+V10+X10+Z10+AB10+AD10+AF10+AH10+AJ10+AL10) -> 0 | K10: =Maning!F10 -> 0.43065406 | L10: =E10*K10 -> 7286.6667 | M10: =Maning!G10 -> 0.21710008 | N10: =M10*E10 -> 3673.3333 | O10: =Maning!H10 -> 0.2285264 | P10: =O10*E10 -> 3866.6667 | Q10: =Maning!I10 -> 0.42001576 | R10: =Q10*E10 -> 7106.6667 | S10: =Maning!J10 -> 0.092592593 | T10: =S10*E10 -> 1566.6667 | U10: =Maning!K10 -> 0.074074074 | V10: =U10*E10 -> 1253.3333 | W10: =Maning!L10 -> 0.055555556 | X10: =W10*E10 -> 940 | Y10: =Maning!M10 -> 0.074074074 | Z10: =Y10*E10 -> 1253.3333 | AA10: =Maning!N10 -> 0.074074074 | AB10: =AA10*E10 -> 1253.3333 | AC10: =Maning!O10 -> 0.18518519 | AD10: =AC10*E10 -> 3133.3333 | AE10: =Maning!P10 -> 0.018518519 | AF10: =AE10*E10 -> 313.33333 | AG10: =Maning!Q10 -> 0.11111111 | AH10: =AG10*E10 -> 1880 | AI10: =Maning!R10 -> 0.018518519 | AJ10: =AI10*E10 -> 313.33333 | AK10: =Maning!S10 -> 0 | AL10: =AK10*E10 -> 0 | AM10: =SUM(L10+N10+P10+R10+T10+V10+X10+Z10+AB10+AD10+AF10+AH10+AJ10+AL10) -> 33840 | AN10: =AM10*$E$17 -> 2707.2 | AO10: =AM10+AN10 -> 36547.2 | AP10: =AO10*$E$19 -> 511.6608 | AQ10: =AO10+AP10 -> 37058.861 | AR10: =AQ10*$E$21 -> 5188.2405 | AS10: =AQ10+AR10 -> 42247.101 | AT10: =AS10/C10 -> 21123.551
B11: ='Manpower CTC'!B10 -> Site Assistant | C11: =K11+M11+O11+Q11+S11+U11+W11+Y11+AA11+AC11+AE11+AG11+AI11 -> 3 | E11: ='Manpower CTC'!C10 -> 22920 | F11: =C11*E11 -> 68760 | H11: =C11-(K11+M11+O11+Q11+S11+U11+W11+Y11+AA11+AC11+AE11+AG11+AI11+AK11) -> 0 | I11: =F11-(L11+N11+P11+R11+T11+V11+X11+Z11+AB11+AD11+AF11+AH11+AJ11+AL11) -> 0 | K11: =Maning!F11 -> 0.64598109 | L11: =E11*K11 -> 14805.887 | M11: =Maning!G11 -> 0.32565012 | N11: =M11*E11 -> 7463.9007 | O11: =Maning!H11 -> 0.3427896 | P11: =O11*E11 -> 7856.7376 | Q11: =Maning!I11 -> 0.63002364 | R11: =Q11*E11 -> 14440.142 | S11: =Maning!J11 -> 0.13888889 | T11: =S11*E11 -> 3183.3333 | U11: =Maning!K11 -> 0.11111111 | V11: =U11*E11 -> 2546.6667 | W11: =Maning!L11 -> 0.083333333 | X11: =W11*E11 -> 1910 | Y11: =Maning!M11 -> 0.11111111 | Z11: =Y11*E11 -> 2546.6667 | AA11: =Maning!N11 -> 0.11111111 | AB11: =AA11*E11 -> 2546.6667 | AC11: =Maning!O11 -> 0.27777778 | AD11: =AC11*E11 -> 6366.6667 | AE11: =Maning!P11 -> 0.027777778 | AF11: =AE11*E11 -> 636.66667 | AG11: =Maning!Q11 -> 0.16666667 | AH11: =AG11*E11 -> 3820 | AI11: =Maning!R11 -> 0.027777778 | AJ11: =AI11*E11 -> 636.66667 | AK11: =Maning!S11 -> 0 | AL11: =AK11*E11 -> 0 | AM11: =SUM(L11+N11+P11+R11+T11+V11+X11+Z11+AB11+AD11+AF11+AH11+AJ11+AL11) -> 68760 | AN11: =AM11*$E$17 -> 5500.8 | AO11: =AM11+AN11 -> 74260.8 | AP11: =AO11*$E$19 -> 1039.6512 | AQ11: =AO11+AP11 -> 75300.451 | AR11: =AQ11*$E$21 -> 10542.063 | AS11: =AQ11+AR11 -> 85842.514 | AT11: =AS11/C11 -> 28614.171
B12: ='Manpower CTC'!B11 -> Site Manager | C12: =K12+M12+O12+Q12+S12+U12+W12+Y12+AA12+AC12+AE12+AG12+AI12 -> 1 | E12: ='Manpower CTC'!C11 -> 52170 | F12: =C12*E12 -> 52170 | H12: =C12-(K12+M12+O12+Q12+S12+U12+W12+Y12+AA12+AC12+AE12+AG12+AI12+AK12) -> 0 | I12: =F12-(L12+N12+P12+R12+T12+V12+X12+Z12+AB12+AD12+AF12+AH12+AJ12+AL12) -> 0 | K12: =Maning!F12 -> 0.21532703 | L12: =E12*K12 -> 11233.611 | M12: =Maning!G12 -> 0.10855004 | N12: =M12*E12 -> 5663.0556 | O12: =Maning!H12 -> 0.1142632 | P12: =O12*E12 -> 5961.1111 | Q12: =Maning!I12 -> 0.21000788 | R12: =Q12*E12 -> 10956.111 | S12: =Maning!J12 -> 0.046296296 | T12: =S12*E12 -> 2415.2778 | U12: =Maning!K12 -> 0.037037037 | V12: =U12*E12 -> 1932.2222 | W12: =Maning!L12 -> 0.027777778 | X12: =W12*E12 -> 1449.1667 | Y12: =Maning!M12 -> 0.037037037 | Z12: =Y12*E12 -> 1932.2222 | AA12: =Maning!N12 -> 0.037037037 | AB12: =AA12*E12 -> 1932.2222 | AC12: =Maning!O12 -> 0.092592593 | AD12: =AC12*E12 -> 4830.5556 | AE12: =Maning!P12 -> 0.0092592593 | AF12: =AE12*E12 -> 483.05556 | AG12: =Maning!Q12 -> 0.055555556 | AH12: =AG12*E12 -> 2898.3333 | AI12: =Maning!R12 -> 0.0092592593 | AJ12: =AI12*E12 -> 483.05556 | AK12: =Maning!S12 -> 0 | AL12: =AK12*E12 -> 0 | AM12: =SUM(L12+N12+P12+R12+T12+V12+X12+Z12+AB12+AD12+AF12+AH12+AJ12+AL12) -> 52170 | AN12: =AM12*$E$17 -> 4173.6 | AO12: =AM12+AN12 -> 56343.6 | AP12: =AO12*$E$19 -> 788.8104 | AQ12: =AO12+AP12 -> 57132.41 | AR12: =AQ12*$E$21 -> 7998.5375 | AS12: =AQ12+AR12 -> 65130.948 | AT12: =AS12/C12 -> 65130.948
B13: ='Manpower CTC'!B12 -> Sales Center Labor | C13: =AK13 -> 30 | E13: ='Manpower CTC'!C12 -> 6820 | F13: =C13*E13 -> 204600 | H13: =C13-(K13+M13+O13+Q13+S13+U13+W13+Y13+AA13+AC13+AE13+AG13+AI13+AK13) -> 0 | I13: =F13-(L13+N13+P13+R13+T13+V13+X13+Z13+AB13+AD13+AF13+AH13+AJ13+AL13) -> 0 | K13: =Maning!F13 -> 0 | L13: =E13*K13 -> 0 | M13: =Maning!G13 -> 0 | N13: =M13*E13 -> 0 | O13: =Maning!H13 -> 0 | P13: =O13*E13 -> 0 | Q13: =Maning!I13 -> 0 | R13: =Q13*E13 -> 0 | S13: =Maning!J13 -> 0 | T13: =S13*E13 -> 0 | U13: =Maning!K13 -> 0 | V13: =U13*E13 -> 0 | W13: =Maning!L13 -> 0 | X13: =W13*E13 -> 0 | Y13: =Maning!M13 -> 0 | Z13: =Y13*E13 -> 0 | AA13: =Maning!N13 -> 0 | AB13: =AA13*E13 -> 0 | AC13: =Maning!O13 -> 0 | AD13: =AC13*E13 -> 0 | AE13: =Maning!P13 -> 0 | AF13: =AE13*E13 -> 0 | AG13: =Maning!Q13 -> 0 | AH13: =AG13*E13 -> 0 | AI13: =Maning!R13 -> 0 | AJ13: =AI13*E13 -> 0 | AK13: =Maning!S13 -> 30 | AL13: =AK13*E13 -> 204600 | AM13: =SUM(L13+N13+P13+R13+T13+V13+X13+Z13+AB13+AD13+AF13+AH13+AJ13+AL13) -> 204600 | AN13: =AM13*$E$17 -> 16368 | AO13: =AM13+AN13 -> 220968 | AP13: =AO13*$E$19 -> 3093.552 | AQ13: =AO13+AP13 -> 224061.55 | AR13: =AQ13*$E$21 -> 31368.617 | AS13: =AQ13+AR13 -> 255430.17 | AT13: =AS13/C13 -> 8514.339
B14: ='Manpower CTC'!B13 -> Sales Center supervisor | C14: =AK14 -> 3 | E14: ='Manpower CTC'!C13 -> 11370 | F14: =C14*E14 -> 34110 | H14: =C14-(K14+M14+O14+Q14+S14+U14+W14+Y14+AA14+AC14+AE14+AG14+AI14+AK14) -> 0 | I14: =F14-(L14+N14+P14+R14+T14+V14+X14+Z14+AB14+AD14+AF14+AH14+AJ14+AL14) -> 0 | K14: =Maning!F14 -> 0 | L14: =E14*K14 -> 0 | M14: =Maning!G14 -> 0 | N14: =M14*E14 -> 0 | O14: =Maning!H14 -> 0 | P14: =O14*E14 -> 0 | Q14: =Maning!I14 -> 0 | R14: =Q14*E14 -> 0 | S14: =Maning!J14 -> 0 | T14: =S14*E14 -> 0 | U14: =Maning!K14 -> 0 | V14: =U14*E14 -> 0 | W14: =Maning!L14 -> 0 | X14: =W14*E14 -> 0 | Y14: =Maning!M14 -> 0 | Z14: =Y14*E14 -> 0 | AA14: =Maning!N14 -> 0 | AB14: =AA14*E14 -> 0 | AC14: =Maning!O14 -> 0 | AD14: =AC14*E14 -> 0 | AE14: =Maning!P14 -> 0 | AF14: =AE14*E14 -> 0 | AG14: =Maning!Q14 -> 0 | AH14: =AG14*E14 -> 0 | AI14: =Maning!R14 -> 0 | AJ14: =AI14*E14 -> 0 | AK14: =Maning!S14 -> 3 | AL14: =AK14*E14 -> 34110 | AM14: =SUM(L14+N14+P14+R14+T14+V14+X14+Z14+AB14+AD14+AF14+AH14+AJ14+AL14) -> 34110 | AN14: =AM14*$E$17 -> 2728.8 | AO14: =AM14+AN14 -> 36838.8 | AP14: =AO14*$E$19 -> 515.7432 | AQ14: =AO14+AP14 -> 37354.543 | AR14: =AQ14*$E$21 -> 5229.636 | AS14: =AQ14+AR14 -> 42584.179 | AT14: =AS14/C14 -> 14194.726
B15: ='Manpower CTC'!B14 -> Sales Center Assistant Manager | C15: =AK15 -> 1 | E15: ='Manpower CTC'!C14 -> 23420 | F15: =C15*E15 -> 23420 | H15: =C15-(K15+M15+O15+Q15+S15+U15+W15+Y15+AA15+AC15+AE15+AG15+AI15+AK15) -> 0 | I15: =F15-(L15+N15+P15+R15+T15+V15+X15+Z15+AB15+AD15+AF15+AH15+AJ15+AL15) -> 0 | K15: =Maning!F15 -> 0 | L15: =E15*K15 -> 0 | M15: =Maning!G15 -> 0 | N15: =M15*E15 -> 0 | O15: =Maning!H15 -> 0 | P15: =O15*E15 -> 0 | Q15: =Maning!I15 -> 0 | R15: =Q15*E15 -> 0 | S15: =Maning!J15 -> 0 | T15: =S15*E15 -> 0 | U15: =Maning!K15 -> 0 | V15: =U15*E15 -> 0 | W15: =Maning!L15 -> 0 | X15: =W15*E15 -> 0 | Y15: =Maning!M15 -> 0 | Z15: =Y15*E15 -> 0 | AA15: =Maning!N15 -> 0 | AB15: =AA15*E15 -> 0 | AC15: =Maning!O15 -> 0 | AD15: =AC15*E15 -> 0 | AE15: =Maning!P15 -> 0 | AF15: =AE15*E15 -> 0 | AG15: =Maning!Q15 -> 0 | AH15: =AG15*E15 -> 0 | AI15: =Maning!R15 -> 0 | AJ15: =AI15*E15 -> 0 | AK15: =Maning!S15 -> 1 | AL15: =AK15*E15 -> 23420 | AM15: =SUM(L15+N15+P15+R15+T15+V15+X15+Z15+AB15+AD15+AF15+AH15+AJ15+AL15) -> 23420 | AN15: =AM15*$E$17 -> 1873.6 | AO15: =AM15+AN15 -> 25293.6 | AP15: =AO15*$E$19 -> 354.1104 | AQ15: =AO15+AP15 -> 25647.71 | AR15: =AQ15*$E$21 -> 3590.6795 | AS15: =AQ15+AR15 -> 29238.39 | AT15: =AS15/C15 -> 29238.39
B16: Total Head Count | C16: =SUM(C6:C15) -> 162 | F16: =SUM(F6:F15) -> 1251640 | H16: =C16-(K16+M16+O16+Q16+S16+U16+W16+Y16+AA16+AC16+AE16+AG16+AI16+AK16) -> 0 | I16: =F16-(L16+N16+P16+R16+T16+V16+X16+Z16+AB16+AD16+AF16+AH16+AJ16+AL16) -> 0 | K16: =SUM(K6:K15) -> 27.213948 | L16: =SUM(L6:L15) -> 209286.45 | M16: =SUM(M6:M15) -> 13.708038 | N16: =SUM(N6:N15) -> 105385.54 | O16: =SUM(O6:O15) -> 14.359338 | P16: =SUM(P6:P15) -> 110169.34 | Q16: =SUM(Q6:Q15) -> 26.607565 | R16: =SUM(R6:R15) -> 204832.57 | ... AS16: =SUM(AS6:AS15) -> 1562593.4
B17: Gross Margin & Contingency | E17: ='HK Budget (2)'!C14 -> 0.08 | F17: =F16*$E$17 -> 100131.2 | H17: =C17-(K17+M17+O17+Q17+S17+U17+W17+Y17+AA17+AC17+AE17+AG17+AI17+AK17) -> 0 | I17: =F17-(L17+N17+P17+R17+T17+V17+X17+Z17+AB17+AD17+AF17+AH17+AJ17+AL17) -> 0 | L17: =L16*$E$17 -> 16742.916 | N17: =N16*$E$17 -> 8430.843 | P17: =P16*$E$17 -> 8813.547 | R17: =R16*$E$17 -> 16386.605 | T17: =T16*$E$17 -> 3970.8222 | V17: =V16*$E$17 -> 2977.8921 | X17: =X16*$E$17 -> 2233.419 | Z17: =Z16*$E$17 -> 2915.7778 | AB17: =AB16*$E$17 -> 2915.7778 | AD17: =AD16*$E$17 -> 7941.6444 | AF17: =AF16*$E$17 -> 728.94444 | AH17: =AH16*$E$17 -> 4373.6667 | AJ17: =AJ16*$E$17 -> 728.94444 | AL17: =AL16*$E$17 -> 20970.4
B18: Total | F18: =F16+F17 -> 1351771.2 | H18: =C18-(K18+M18+O18+Q18+S18+U18+W18+Y18+AA18+AC18+AE18+AG18+AI18+AK18) -> 0 | I18: =F18-(L18+N18+P18+R18+T18+V18+X18+Z18+AB18+AD18+AF18+AH18+AJ18+AL18) -> 0 | L18: =L16+L17 -> 226029.36 | N18: =N16+N17 -> 113816.38 | P18: =P16+P17 -> 118982.89 | R18: =R16+R17 -> 221219.17 | T18: =T16+T17 -> 53606.1 | V18: =V16+V17 -> 40201.543 | X18: =X16+X17 -> 30151.157 | Z18: =Z16+Z17 -> 39363 | AB18: =AB16+AB17 -> 39363 | AD18: =AD16+AD17 -> 107212.2 | AF18: =AF16+AF17 -> 9840.75 | AH18: =AH16+AH17 -> 59044.5 | AJ18: =AJ16+AJ17 -> 9840.75 | AL18: =AL16+AL17 -> 283100.4
B19: Insurance | E19: ='HK Budget (2)'!C16 -> 0.014 | F19: =F18*$E$19 -> 18924.797 | H19: =C19-(K19+M19+O19+Q19+S19+U19+W19+Y19+AA19+AC19+AE19+AG19+AI19+AK19) -> 0 | I19: =F19-(L19+N19+P19+R19+T19+V19+X19+Z19+AB19+AD19+AF19+AH19+AJ19+AL19) -> 0 | L19: =L18*$E$19 -> 3164.4111 | N19: =N18*$E$19 -> 1593.4293 | P19: =P18*$E$19 -> 1665.7604 | R19: =R18*$E$19 -> 3097.0684 | T19: =T18*$E$19 -> 750.4854 | V19: =V18*$E$19 -> 562.8216 | X19: =X18*$E$19 -> 422.1162 | Z19: =Z18*$E$19 -> 551.082 | AB19: =AB18*$E$19 -> 551.082 | AD19: =AD18*$E$19 -> 1500.9708 | AF19: =AF18*$E$19 -> 137.7705 | AH19: =AH18*$E$19 -> 826.623 | AJ19: =AJ18*$E$19 -> 137.7705 | AL19: =AL18*$E$19 -> 3963.4056
B20: Total Revenue | F20: =F18+F19 -> 1370696 | H20: =C20-(K20+M20+O20+Q20+S20+U20+W20+Y20+AA20+AC20+AE20+AG20+AI20+AK20) -> 0 | I20: =F20-(L20+N20+P20+R20+T20+V20+X20+Z20+AB20+AD20+AF20+AH20+AJ20+AL20) -> 0 | L20: =L18+L19 -> 229193.77 | N20: =N18+N19 -> 115409.81 | P20: =P18+P19 -> 120648.65 | R20: =R18+R19 -> 224316.24 | T20: =T18+T19 -> 54356.585 | V20: =V18+V19 -> 40764.364 | X20: =X18+X19 -> 30573.273 | Z20: =Z18+Z19 -> 39914.082 | AB20: =AB18+AB19 -> 39914.082 | AD20: =AD18+AD19 -> 108713.17 | AF20: =AF18+AF19 -> 9978.5205 | AH20: =AH18+AH19 -> 59871.123 | AJ20: =AJ18+AJ19 -> 9978.5205 | AL20: =AL18+AL19 -> 287063.81
B21: VAT | E21: 0.14 | F21: =F20*$E$21 -> 191897.44 | H21: =C21-(K21+M21+O21+Q21+S21+U21+W21+Y21+AA21+AC21+AE21+AG21+AI21+AK21) -> 0 | I21: =F21-(L21+N21+P21+R21+T21+V21+X21+Z21+AB21+AD21+AF21+AH21+AJ21+AL21) -> 0 | L21: =L20*$E$21 -> 32087.128 | N21: =N20*$E$21 -> 16157.373 | P21: =P20*$E$21 -> 16890.81 | R21: =R20*$E$21 -> 31404.273 | T21: =T20*$E$21 -> 7609.922 | V21: =V20*$E$21 -> 5707.011 | X21: =X20*$E$21 -> 4280.2583 | Z21: =Z20*$E$21 -> 5587.9715 | AB21: =AB20*$E$21 -> 5587.9715 | AD21: =AD20*$E$21 -> 15219.844 | AF21: =AF20*$E$21 -> 1396.9929 | AH21: =AH20*$E$21 -> 8381.9572 | AJ21: =AJ20*$E$21 -> 1396.9929 | AL21: =AL20*$E$21 -> 40188.933
B22: Total W VAT | F22: =F20+F21 -> 1562593.4 | H22: =C22-(K22+M22+O22+Q22+S22+U22+W22+Y22+AA22+AC22+AE22+AG22+AI22+AK22) -> 0 | I22: =F22-(L22+N22+P22+R22+T22+V22+X22+Z22+AB22+AD22+AF22+AH22+AJ22+AL22) -> 0 | L22: =L20+L21 -> 261280.9 | N22: =N20+N21 -> 131567.18 | P22: =P20+P21 -> 137539.46 | R22: =R20+R21 -> 255720.51 | T22: =T20+T21 -> 61966.507 | V22: =V20+V21 -> 46471.375 | X22: =X20+X21 -> 34853.532 | Z22: =Z20+Z21 -> 45502.053 | AB22: =AB20+AB21 -> 45502.053 | AD22: =AD20+AD21 -> 123933.01 | AF22: =AF20+AF21 -> 11375.513 | AH22: =AH20+AH21 -> 68253.08 | AJ22: =AJ20+AJ21 -> 11375.513 | AL22: =AL20+AL21 -> 327252.74
F24: ='Transportation Cost'!G20 -> 460673.18
F25: ='Mobilization & Over Head Cost'!G20 -> 43001.712
F26: ='Others Cost '!G18 -> 46816.38
F27: =F22+F24+F25+F26 -> 2113084.7

Sheet Equipment & Tools Cost
L3: 27.213948 | M3: 0 | N3: 13.708038 | O3: 0 | P3: 14.359338 | Q3: 0 | R3: 26.607565 | S3: 0 | T3: 6.2777778 | U3: 0 | V3: 4.7936508 | W3: 0 | X3: 3.5952381 | Y3: 0 | Z3: 4.7222222 | AA3: 0 | AB3: 4.7222222 | AC3: 0 | AD3: 12.555556 | AE3: 0 | AF3: 1.1805556 | AG3: 0 | AH3: 7.0833333 | AI3: 0 | AJ3: 1.1805556 | AK3: 0 | AL3: 34 | AM3: 0
B4: Items | C4: Head Count | D4: Depreciation / Month | E4: Price | F4: Unit Monthly Cost | G4: Total Amount/ Month | L4: Sierras | N4: Alto | P4: Aurora | R4: Fourteen | T4: Reyna | V4: Eleva | X4: Isadore | Z4: Alba's Aliyah | AB4: Alba's Spendia | AD4: Commercial Area "UTC-Golf club house | AF4: Public Roads | AH4: Crossing gates | AJ4: Mobilization areas " water station " | AL4: Managament"sales center" | AN4: Total Cost | AO4: Gross Margin | AP4: Total | AQ4: Contingency | AR4: Total | AS4: VAT | AT4: Total W VAT | AU4: Unit Rate
L5: QTY | M5: Monthly Cost | N5: Head Count | O5: Monthly Cost | P5: Head Count | Q5: Monthly Cost | R5: Head Count | S5: Monthly Cost | T5: Head Count | U5: Monthly Cost | V5: Head Count | W5: Monthly Cost | X5: Head Count | Y5: Monthly Cost | Z5: Head Count | AA5: Monthly Cost | AB5: Head Count | AC5: Monthly Cost | AD5: Head Count | AE5: Monthly Cost | AF5: Head Count | AG5: Monthly Cost | AH5: Head Count | AI5: Monthly Cost | AJ5: Head Count | AK5: Monthly Cost | AL5: Head Count | AM5: Monthly Cost
A6: 5 | B6: Single disk | C6: =L6+N6+P6+R6+T6+V6+X6+Z6+AB6+AD6+AF6+AH6+AJ6+AL6 -> 8 | D6: 60 | E6: ='[2]per item'!$B$5 -> 60000 | F6: =E6/D6 -> 1000 | G6: =C6*F6 -> 8000 | I6: =C6-(L6+N6+P6+R6+T6+V6+X6+Z6+AB6+AD6+AF6+AH6+AJ6+AL6) -> 0 | J6: =G6-(M6+O6+Q6+S6+U6+W6+Y6+AA6+AC6+AE6+AG6+AI6+AK6+AM6) -> 0 | L6: ='BOQ Zone A Equipment'!F5 -> 1 | M6: =F6*L6 -> 1000 | N6: ='BOQ Zone A Equipment'!G5 -> 1 | O6: =N6*F6 -> 1000 | P6: ='BOQ Zone A Equipment'!H5 -> 1 | Q6: =P6*F6 -> 1000 | R6: ='BOQ Zone A Equipment'!I5 -> 1 | S6: =R6*F6 -> 1000 | T6: ='BOQ Zone A Equipment'!J5 -> 0 | U6: =T6*F6 -> 0 | V6: ='BOQ Zone A Equipment'!K5 -> 0 | W6: =V6*F6 -> 0 | X6: ='BOQ Zone A Equipment'!L5 -> 0 | Y6: =X6*F6 -> 0 | Z6: ='BOQ Zone A Equipment'!M5 -> 0 | AA6: =Z6*F6 -> 0 | AB6: ='BOQ Zone A Equipment'!N5 -> 0 | AC6: =AB6*F6 -> 0 | AD6: ='BOQ Zone A Equipment'!O5 -> 1 | AE6: =AD6*F6 -> 1000 | AF6: ='BOQ Zone A Equipment'!P5 -> 0 | AG6: =AF6*F6 -> 0 | AH6: ='BOQ Zone A Equipment'!Q5 -> 0 | AI6: =AH6*F6 -> 0 | AJ6: ='BOQ Zone A Equipment'!R5 -> 0 | AK6: =AJ6*F6 -> 0 | AL6: ='BOQ Zone A Equipment'!S5 -> 3 | AM6: =AL6*F6 -> 3000 | AN6: =M6+O6+Q6+S6+U6+W6+Y6+AA6+AC6+AE6+AG6+AI6+AK6+AM6 -> 8000 | AO6: =AN6*$F$53 -> 640 | AP6: =AN6+AO6 -> 8640 | AQ6: =AP6*$F$55 -> 120.96 | AR6: =AP6+AQ6 -> 8760.96 | AS6: =AR6*$F$57 -> 1226.5344 | AT6: =AR6+AS6 -> 9987.4944 | AU6: =ROUNDUP(AT6/C6,0) -> 1249
B7: Walk behind | C7: =L7+N7+P7+R7+T7+V7+X7+Z7+AB7+AD7+AF7+AH7+AJ7+AL7 -> 0 | D7: 60 | E7: ='[2]Unit rates'!$D$24 -> 200000 | F7: =E7/D7 -> 3333.3333 | G7: =C7*F7 -> 0 | I7: =C7-(L7+N7+P7+R7+T7+V7+X7+Z7+AB7+AD7+AF7+AH7+AJ7+AL7) -> 0 | J7: =G7-(M7+O7+Q7+S7+U7+W7+Y7+AA7+AC7+AE7+AG7+AI7+AK7+AM7) -> 0 | L7: ='BOQ Zone A Equipment'!F6 -> 0 | M7: =F7*L7 -> 0 | N7: ='BOQ Zone A Equipment'!G6 -> 0 | O7: =N7*F7 -> 0 | P7: ='BOQ Zone A Equipment'!H6 -> 0 | Q7: =P7*F7 -> 0 | R7: ='BOQ Zone A Equipment'!I6 -> 0 | S7: =R7*F7 -> 0 | T7: ='BOQ Zone A Equipment'!J6 -> 0 | U7: =T7*F7 -> 0 | V7: ='BOQ Zone A Equipment'!K6 -> 0 | W7: =V7*F7 -> 0 | X7: ='BOQ Zone A Equipment'!L6 -> 0 | Y7: =X7*F7 -> 0 | Z7: ='BOQ Zone A Equipment'!M6 -> 0 | AA7: =Z7*F7 -> 0 | AB7: ='BOQ Zone A Equipment'!N6 -> 0 | AC7: =AB7*F7 -> 0 | AD7: ='BOQ Zone A Equipment'!O6 -> 0 | AE7: =AD7*F7 -> 0 | AF7: ='BOQ Zone A Equipment'!P6 -> 0 | AG7: =AF7*F7 -> 0 | AH7: ='BOQ Zone A Equipment'!Q6 -> 0 | AI7: =AH7*F7 -> 0 | AJ7: ='BOQ Zone A Equipment'!R6 -> 0 | AK7: =AJ7*F7 -> 0 | AL7: ='BOQ Zone A Equipment'!S6 -> 0 | AM7: =AL7*F7 -> 0 | AN7: =M7+O7+Q7+S7+U7+W7+Y7+AA7+AC7+AE7+AG7+AI7+AK7+AM7 -> 0 | AO7: =AN7*$F$53 -> 0 | AP7: =AN7+AO7 -> 0 | AQ7: =AP7*$F$55 -> 0 | AR7: =AP7+AQ7 -> 0 | AS7: =AR7*$F$57 -> 0 | AT7: =AR7+AS7 -> 0 | AU7: =ROUNDUP(AT7/C7,0) -> #DIV/0!
A8: 6 | B8: Vacuum | C8: =L8+N8+P8+R8+T8+V8+X8+Z8+AB8+AD8+AF8+AH8+AJ8+AL8 -> 8 | D8: 60 | E8: ='[2]per item'!$B$6 -> 35000 | F8: =E8/D8 -> 583.33333 | G8: =C8*F8 -> 4666.6667 | I8: =C8-(L8+N8+P8+R8+T8+V8+X8+Z8+AB8+AD8+AF8+AH8+AJ8+AL8) -> 0 | J8: =G8-(M8+O8+Q8+S8+U8+W8+Y8+AA8+AC8+AE8+AG8+AI8+AK8+AM8) -> 0 | L8: ='BOQ Zone A Equipment'!F7 -> 1 | M8: =F8*L8 -> 583.33333 | N8: ='BOQ Zone A Equipment'!G7 -> 1 | O8: =N8*F8 -> 583.33333 | P8: ='BOQ Zone A Equipment'!H7 -> 1 | Q8: =P8*F8 -> 583.33333 | R8: ='BOQ Zone A Equipment'!I7 -> 1 | S8: =R8*F8 -> 583.33333 | T8: ='BOQ Zone A Equipment'!J7 -> 1 | U8: =T8*F8 -> 583.33333 | V8: ='BOQ Zone A Equipment'!K7 -> 0 | W8: =V8*F8 -> 0 | X8: ='BOQ Zone A Equipment'!L7 -> 0 | Y8: =X8*F8 -> 0 | Z8: ='BOQ Zone A Equipment'!M7 -> 0 | AA8: =Z8*F8 -> 0 | AB8: ='BOQ Zone A Equipment'!N7 -> 0 | AC8: =AB8*F8 -> 0 | AD8: ='BOQ Zone A Equipment'!O7 -> 1 | AE8: =AD8*F8 -> 583.33333 | AF8: ='BOQ Zone A Equipment'!P7 -> 0 | AG8: =AF8*F8 -> 0 | AH8: ='BOQ Zone A Equipment'!Q7 -> 0 | AI8: =AH8*F8 -> 0 | AJ8: ='BOQ Zone A Equipment'!R7 -> 0 | AK8: =AJ8*F8 -> 0 | AL8: ='BOQ Zone A Equipment'!S7 -> 2 | AM8: =AL8*F8 -> 1166.6667 | AN8: =M8+O8+Q8+S8+U8+W8+Y8+AA8+AC8+AE8+AG8+AI8+AK8+AM8 -> 4666.6667 | AO8: =AN8*$F$53 -> 373.33333 | AP8: =AN8+AO8 -> 5040 | AQ8: =AP8*$F$55 -> 70.56 | AR8: =AP8+AQ8 -> 5110.56 | AS8: =AR8*$F$57 -> 715.4784 | AT8: =AR8+AS8 -> 5826.0384 | AU8: =ROUNDUP(AT8/C8,0) -> 729
B9: Steam Machine | C9: =L9+N9+P9+R9+T9+V9+X9+Z9+AB9+AD9+AF9+AH9+AJ9+AL9 -> 1 | D9: 60 | E9: 75000 | F9: =E9/D9 -> 1250 | G9: =C9*F9 -> 1250 | I9: =C9-(L9+N9+P9+R9+T9+V9+X9+Z9+AB9+AD9+AF9+AH9+AJ9+AL9) -> 0 | J9: =G9-(M9+O9+Q9+S9+U9+W9+Y9+AA9+AC9+AE9+AG9+AI9+AK9+AM9) -> 0 | L9: ='BOQ Zone A Equipment'!F8 -> 0 | M9: =F9*L9 -> 0 | N9: ='BOQ Zone A Equipment'!G8 -> 0 | O9: =N9*F9 -> 0 | P9: ='BOQ Zone A Equipment'!H8 -> 0 | Q9: =P9*F9 -> 0 | R9: ='BOQ Zone A Equipment'!I8 -> 0 | S9: =R9*F9 -> 0 | T9: ='BOQ Zone A Equipment'!J8 -> 0 | U9: =T9*F9 -> 0 | V9: ='BOQ Zone A Equipment'!K8 -> 0 | W9: =V9*F9 -> 0 | X9: ='BOQ Zone A Equipment'!L8 -> 0 | Y9: =X9*F9 -> 0 | Z9: ='BOQ Zone A Equipment'!M8 -> 0 | AA9: =Z9*F9 -> 0 | AB9: ='BOQ Zone A Equipment'!N8 -> 0 | AC9: =AB9*F9 -> 0 | AD9: ='BOQ Zone A Equipment'!O8 -> 0 | AE9: =AD9*F9 -> 0 | AF9: ='BOQ Zone A Equipment'!P8 -> 0 | AG9: =AF9*F9 -> 0 | AH9: ='BOQ Zone A Equipment'!Q8 -> 0 | AI9: =AH9*F9 -> 0 | AJ9: ='BOQ Zone A Equipment'!R8 -> 0 | AK9: =AJ9*F9 -> 0 | AL9: ='BOQ Zone A Equipment'!S8 -> 1 | AM9: =AL9*F9 -> 1250 | AN9: =M9+O9+Q9+S9+U9+W9+Y9+AA9+AC9+AE9+AG9+AI9+AK9+AM9 -> 1250 | AO9: =AN9*$F$53 -> 100 | AP9: =AN9+AO9 -> 1350 | AQ9: =AP9*$F$55 -> 18.9 | AR9: =AP9+AQ9 -> 1368.9 | AS9: =AR9*$F$57 -> 191.646 | AT9: =AR9+AS9 -> 1560.546 | AU9: =ROUNDUP(AT9/C9,0) -> 1561
B10: Public Trolly | C10: =L10+N10+P10+R10+T10+V10+X10+Z10+AB10+AD10+AF10+AH10+AJ10+AL10 -> 28 | D10: 36 | E10: ='[2]per item'!$B$16 -> 8000 | F10: =E10/D10 -> 222.22222 | G10: =C10*F10 -> 6222.2222 | I10: =C10-(L10+N10+P10+R10+T10+V10+X10+Z10+AB10+AD10+AF10+AH10+AJ10+AL10) -> 0 | J10: =G10-(M10+O10+Q10+S10+U10+W10+Y10+AA10+AC10+AE10+AG10+AI10+AK10+AM10) -> 0 | L10: ='BOQ Zone A Equipment'!F9 -> 10 | M10: =F10*L10 -> 2222.2222 | N10: ='BOQ Zone A Equipment'!G9 -> 4 | O10: =N10*F10 -> 888.88889 | P10: ='BOQ Zone A Equipment'!H9 -> 4 | Q10: =P10*F10 -> 888.88889 | R10: ='BOQ Zone A Equipment'!I9 -> 7 | S10: =R10*F10 -> 1555.5556 | T10: ='BOQ Zone A Equipment'!J9 -> 0 | U10: =T10*F10 -> 0 | V10: ='BOQ Zone A Equipment'!K9 -> 0 | W10: =V10*F10 -> 0 | X10: ='BOQ Zone A Equipment'!L9 -> 0 | Y10: =X10*F10 -> 0 | Z10: ='BOQ Zone A Equipment'!M9 -> 0 | AA10: =Z10*F10 -> 0 | AB10: ='BOQ Zone A Equipment'!N9 -> 0 | AC10: =AB10*F10 -> 0 | AD10: ='BOQ Zone A Equipment'!O9 -> 0 | AE10: =AD10*F10 -> 0 | AF10: ='BOQ Zone A Equipment'!P9 -> 0 | AG10: =AF10*F10 -> 0 | AH10: ='BOQ Zone A Equipment'!Q9 -> 0 | AI10: =AH10*F10 -> 0 | AJ10: ='BOQ Zone A Equipment'!R9 -> 0 | AK10: =AJ10*F10 -> 0 | AL10: ='BOQ Zone A Equipment'!S9 -> 3 | AM10: =AL10*F10 -> 666.66667 | AN10: =M10+O10+Q10+S10+U10+W10+Y10+AA10+AC10+AE10+AG10+AI10+AK10+AM10 -> 6222.2222 | AO10: =AN10*$F$53 -> 497.77778 | AP10: =AN10+AO10 -> 6720 | AQ10: =AP10*$F$55 -> 94.08 | AR10: =AP10+AQ10 -> 6814.08 | AS10: =AR10*$F$57 -> 953.9712 | AT10: =AR10+AS10 -> 7768.0512 | AU10: =ROUNDUP(AT10/C10,0) -> 278
A11: 10 | B11: Manual sweeper | C11: =L11+N11+P11+R11+T11+V11+X11+Z11+AB11+AD11+AF11+AH11+AJ11+AL11 -> 12 | D11: 60 | E11: ='[2]per item'!$B$7 -> 45000 | F11: =E11/D11 -> 750 | G11: =C11*F11 -> 9000 | I11: =C11-(L11+N11+P11+R11+T11+V11+X11+Z11+AB11+AD11+AF11+AH11+AJ11+AL11) -> 0 | J11: =G11-(M11+O11+Q11+S11+U11+W11+Y11+AA11+AC11+AE11+AG11+AI11+AK11+AM11) -> 0 | L11: ='BOQ Zone A Equipment'!F10 -> 1 | M11: =F11*L11 -> 750 | N11: ='BOQ Zone A Equipment'!G10 -> 1 | O11: =N11*F11 -> 750 | P11: ='BOQ Zone A Equipment'!H10 -> 1 | Q11: =P11*F11 -> 750 | R11: ='BOQ Zone A Equipment'!I10 -> 1 | S11: =R11*F11 -> 750 | T11: ='BOQ Zone A Equipment'!J10 -> 1 | U11: =T11*F11 -> 750 | V11: ='BOQ Zone A Equipment'!K10 -> 1 | W11: =V11*F11 -> 750 | X11: ='BOQ Zone A Equipment'!L10 -> 1 | Y11: =X11*F11 -> 750 | Z11: ='BOQ Zone A Equipment'!M10 -> 1 | AA11: =Z11*F11 -> 750 | AB11: ='BOQ Zone A Equipment'!N10 -> 0 | AC11: =AB11*F11 -> 0 | AD11: ='BOQ Zone A Equipment'!O10 -> 1 | AE11: =AD11*F11 -> 750 | AF11: ='BOQ Zone A Equipment'!P10 -> 1 | AG11: =AF11*F11 -> 750 | AH11: ='BOQ Zone A Equipment'!Q10 -> 0 | AI11: =AH11*F11 -> 0 | AJ11: ='BOQ Zone A Equipment'!R10 -> 0 | AK11: =AJ11*F11 -> 0 | AL11: ='BOQ Zone A Equipment'!S10 -> 2 | AM11: =AL11*F11 -> 1500 | AN11: =M11+O11+Q11+S11+U11+W11+Y11+AA11+AC11+AE11+AG11+AI11+AK11+AM11 -> 9000 | AO11: =AN11*$F$53 -> 720 | AP11: =AN11+AO11 -> 9720 | AQ11: =AP11*$F$55 -> 136.08 | AR11: =AP11+AQ11 -> 9856.08 | AS11: =AR11*$F$57 -> 1379.8512 | AT11: =AR11+AS11 -> 11235.931 | AU11: =ROUNDUP(AT11/C11,0) -> 937
A12: 12 | B12: McClean Trolley | C12: =L12+N12+P12+R12+T12+V12+X12+Z12+AB12+AD12+AF12+AH12+AJ12+AL12 -> 17 | D12: 36 | E12: ='[2]per item'!$B$8 -> 11150 | F12: =E12/D12 -> 309.72222 | G12: =C12*F12 -> 5265.2778 | I12: =C12-(L12+N12+P12+R12+T12+V12+X12+Z12+AB12+AD12+AF12+AH12+AJ12+AL12) -> 0 | J12: =G12-(M12+O12+Q12+S12+U12+W12+Y12+AA12+AC12+AE12+AG12+AI12+AK12+AM12) -> 0 | L12: ='BOQ Zone A Equipment'!F11 -> 2 | M12: =F12*L12 -> 619.44444 | N12: ='BOQ Zone A Equipment'!G11 -> 1 | O12: =N12*F12 -> 309.72222 | P12: ='BOQ Zone A Equipment'!H11 -> 2 | Q12: =P12*F12 -> 619.44444 | R12: ='BOQ Zone A Equipment'!I11 -> 2 | S12: =R12*F12 -> 619.44444 | T12: ='BOQ Zone A Equipment'!J11 -> 1 | U12: =T12*F12 -> 309.72222 | V12: ='BOQ Zone A Equipment'!K11 -> 1 | W12: =V12*F12 -> 309.72222 | X12: ='BOQ Zone A Equipment'!L11 -> 1 | Y12: =X12*F12 -> 309.72222 | Z12: ='BOQ Zone A Equipment'!M11 -> 1 | AA12: =Z12*F12 -> 309.72222 | AB12: ='BOQ Zone A Equipment'!N11 -> 1 | AC12: =AB12*F12 -> 309.72222 | AD12: ='BOQ Zone A Equipment'!O11 -> 1 | AE12: =AD12*F12 -> 309.72222 | AF12: ='BOQ Zone A Equipment'!P11 -> 1 | AG12: =AF12*F12 -> 309.72222 | AH12: ='BOQ Zone A Equipment'!Q11 -> 0 | AI12: =AH12*F12 -> 0 | AJ12: ='BOQ Zone A Equipment'!R11 -> 0 | AK12: =AJ12*F12 -> 0 | AL12: ='BOQ Zone A Equipment'!S11 -> 3 | AM12: =AL12*F12 -> 929.16667 | AN12: =M12+O12+Q12+S12+U12+W12+Y12+AA12+AC12+AE12+AG12+AI12+AK12+AM12 -> 5265.2778 | AO12: =AN12*$F$53 -> 421.22222 | AP12: =AN12+AO12 -> 5686.5 | AQ12: =AP12*$F$55 -> 79.611 | AR12: =AP12+AQ12 -> 5766.111 | AS12: =AR12*$F$57 -> 807.25554 | AT12: =AR12+AS12 -> 6573.3665 | AU12: =ROUNDUP(AT12/C12,0) -> 387
A13: 23 | B13: Black Broom and Closed Ban | C13: =L13+N13+P13+R13+T13+V13+X13+Z13+AB13+AD13+AF13+AH13+AJ13+AL13 -> 33 | D13: 6 | E13: ='[2]per item'!$B$9 -> 450 | F13: =E13/D13 -> 75 | G13: =C13*F13 -> 2475 | I13: =C13-(L13+N13+P13+R13+T13+V13+X13+Z13+AB13+AD13+AF13+AH13+AJ13+AL13) -> 0 | J13: =G13-(M13+O13+Q13+S13+U13+W13+Y13+AA13+AC13+AE13+AG13+AI13+AK13+AM13) -> 0 | L13: ='BOQ Zone A Equipment'!F12 -> 2 | M13: =F13*L13 -> 150 | N13: ='BOQ Zone A Equipment'!G12 -> 2 | O13: =N13*F13 -> 150 | P13: ='BOQ Zone A Equipment'!H12 -> 2 | Q13: =P13*F13 -> 150 | R13: ='BOQ Zone A Equipment'!I12 -> 2 | S13: =R13*F13 -> 150 | T13: ='BOQ Zone A Equipment'!J12 -> 2 | U13: =T13*F13 -> 150 | V13: ='BOQ Zone A Equipment'!K12 -> 2 | W13: =V13*F13 -> 150 | X13: ='BOQ Zone A Equipment'!L12 -> 2 | Y13: =X13*F13 -> 150 | Z13: ='BOQ Zone A Equipment'!M12 -> 2 | AA13: =Z13*F13 -> 150 | AB13: ='BOQ Zone A Equipment'!N12 -> 2 | AC13: =AB13*F13 -> 150 | AD13: ='BOQ Zone A Equipment'!O12 -> 4 | AE13: =AD13*F13 -> 300 | AF13: ='BOQ Zone A Equipment'!P12 -> 1 | AG13: =AF13*F13 -> 75 | AH13: ='BOQ Zone A Equipment'!Q12 -> 0 | AI13: =AH13*F13 -> 0 | AJ13: ='BOQ Zone A Equipment'!R12 -> 0 | AK13: =AJ13*F13 -> 0 | AL13: ='BOQ Zone A Equipment'!S12 -> 10 | AM13: =AL13*F13 -> 750 | AN13: =M13+O13+Q13+S13+U13+W13+Y13+AA13+AC13+AE13+AG13+AI13+AK13+AM13 -> 2475 | AO13: =AN13*$F$53 -> 198 | AP13: =AN13+AO13 -> 2673 | AQ13: =AP13*$F$55 -> 37.422 | AR13: =AP13+AQ13 -> 2710.422 | AS13: =AR13*$F$57 -> 379.45908 | AT13: =AR13+AS13 -> 3089.8811 | AU13: =ROUNDUP(AT13/C13,0) -> 94
A14: 12 | B14: Litter Picking Steak | C14: =L14+N14+P14+R14+T14+V14+X14+Z14+AB14+AD14+AF14+AH14+AJ14+AL14 -> 15 | D14: 6 | E14: ='[2]per item'!$B$10 -> 500 | F14: =E14/D14 -> 83.333333 | G14: =C14*F14 -> 1250 | I14: =C14-(L14+N14+P14+R14+T14+V14+X14+Z14+AB14+AD14+AF14+AH14+AJ14+AL14) -> 0 | J14: =G14-(M14+O14+Q14+S14+U14+W14+Y14+AA14+AC14+AE14+AG14+AI14+AK14+AM14) -> 0 | L14: ='BOQ Zone A Equipment'!F13 -> 2 | M14: =F14*L14 -> 166.66667 | N14: ='BOQ Zone A Equipment'!G13 -> 1 | O14: =N14*F14 -> 83.333333 | P14: ='BOQ Zone A Equipment'!H13 -> 1 | Q14: =P14*F14 -> 83.333333 | R14: ='BOQ Zone A Equipment'!I13 -> 1 | S14: =R14*F14 -> 83.333333 | T14: ='BOQ Zone A Equipment'!J13 -> 1 | U14: =T14*F14 -> 83.333333 | V14: ='BOQ Zone A Equipment'!K13 -> 1 | W14: =V14*F14 -> 83.333333 | X14: ='BOQ Zone A Equipment'!L13 -> 1 | Y14: =X14*F14 -> 83.333333 | Z14: ='BOQ Zone A Equipment'!M13 -> 1 | AA14: =Z14*F14 -> 83.333333 | AB14: ='BOQ Zone A Equipment'!N13 -> 1 | AC14: =AB14*F14 -> 83.333333 | AD14: ='BOQ Zone A Equipment'!O13 -> 1 | AE14: =AD14*F14 -> 83.333333 | AF14: ='BOQ Zone A Equipment'!P13 -> 1 | AG14: =AF14*F14 -> 83.333333 | AH14: ='BOQ Zone A Equipment'!Q13 -> 0 | AI14: =AH14*F14 -> 0 | AJ14: ='BOQ Zone A Equipment'!R13 -> 0 | AK14: =AJ14*F14 -> 0 | AL14: ='BOQ Zone A Equipment'!S13 -> 3 | AM14: =AL14*F14 -> 250 | AN14: =M14+O14+Q14+S14+U14+W14+Y14+AA14+AC14+AE14+AG14+AI14+AK14+AM14 -> 1250 | AO14: =AN14*$F$53 -> 100 | AP14: =AN14+AO14 -> 1350 | AQ14: =AP14*$F$55 -> 18.9 | AR14: =AP14+AQ14 -> 1368.9 | AS14: =AR14*$F$57 -> 191.646 | AT14: =AR14+AS14 -> 1560.546 | AU14: =ROUNDUP(AT14/C14,0) -> 105
A15: 25 | B15: Mob Bucket with Cotton Cloth | C15: =L15+N15+P15+R15+T15+V15+X15+Z15+AB15+AD15+AF15+AH15+AJ15+AL15 -> 35 | D15: 12 | E15: ='[2]per item'!$B$11 -> 600 | F15: =E15/D15 -> 50 | G15: =C15*F15 -> 1750 | I15: =C15-(L15+N15+P15+R15+T15+V15+X15+Z15+AB15+AD15+AF15+AH15+AJ15+AL15) -> 0 | J15: =G15-(M15+O15+Q15+S15+U15+W15+Y15+AA15+AC15+AE15+AG15+AI15+AK15+AM15) -> 0 | L15: ='BOQ Zone A Equipment'!F14 -> 10 | M15: =F15*L15 -> 500 | N15: ='BOQ Zone A Equipment'!G14 -> 6 | O15: =N15*F15 -> 300 | P15: ='BOQ Zone A Equipment'!H14 -> 3 | Q15: =P15*F15 -> 150 | R15: ='BOQ Zone A Equipment'!I14 -> 6 | S15: =R15*F15 -> 300 | T15: ='BOQ Zone A Equipment'!J14 -> 0 | U15: =T15*F15 -> 0 | V15: ='BOQ Zone A Equipment'!K14 -> 0 | W15: =V15*F15 -> 0 | X15: ='BOQ Zone A Equipment'!L14 -> 0 | Y15: =X15*F15 -> 0 | Z15: ='BOQ Zone A Equipment'!M14 -> 0 | AA15: =Z15*F15 -> 0 | AB15: ='BOQ Zone A Equipment'!N14 -> 0 | AC15: =AB15*F15 -> 0 | AD15: ='BOQ Zone A Equipment'!O14 -> 0 | AE15: =AD15*F15 -> 0 | AF15: ='BOQ Zone A Equipment'!P14 -> 0 | AG15: =AF15*F15 -> 0 | AH15: ='BOQ Zone A Equipment'!Q14 -> 0 | AI15: =AH15*F15 -> 0 | AJ15: ='BOQ Zone A Equipment'!R14 -> 0 | AK15: =AJ15*F15 -> 0 | AL15: ='BOQ Zone A Equipment'!S14 -> 10 | AM15: =AL15*F15 -> 500 | AN15: =M15+O15+Q15+S15+U15+W15+Y15+AA15+AC15+AE15+AG15+AI15+AK15+AM15 -> 1750 | AO15: =AN15*$F$53 -> 140 | AP15: =AN15+AO15 -> 1890 | AQ15: =AP15*$F$55 -> 26.46 | AR15: =AP15+AQ15 -> 1916.46 | AS15: =AR15*$F$57 -> 268.3044 | AT15: =AR15+AS15 -> 2184.7644 | AU15: =ROUNDUP(AT15/C15,0) -> 63
B16: Cary Cady | C16: =L16+N16+P16+R16+T16+V16+X16+Z16+AB16+AD16+AF16+AH16+AJ16+AL16 -> 69 | D16: 12 | E16: ='[2]per item'!$B$17 -> 150 | F16: =E16/D16 -> 12.5 | G16: =C16*F16 -> 862.5 | I16: =C16-(L16+N16+P16+R16+T16+V16+X16+Z16+AB16+AD16+AF16+AH16+AJ16+AL16) -> 0 | J16: =G16-(M16+O16+Q16+S16+U16+W16+Y16+AA16+AC16+AE16+AG16+AI16+AK16+AM16) -> 0 | L16: ='BOQ Zone A Equipment'!F15 -> 26 | M16: =F16*L16 -> 325 | N16: ='BOQ Zone A Equipment'!G15 -> 9 | O16: =N16*F16 -> 112.5 | P16: ='BOQ Zone A Equipment'!H15 -> 7 | Q16: =P16*F16 -> 87.5 | R16: ='BOQ Zone A Equipment'!I15 -> 14 | S16: =R16*F16 -> 175 | T16: ='BOQ Zone A Equipment'!J15 -> 0 | U16: =T16*F16 -> 0 | V16: ='BOQ Zone A Equipment'!K15 -> 0 | W16: =V16*F16 -> 0 | X16: ='BOQ Zone A Equipment'!L15 -> 0 | Y16: =X16*F16 -> 0 | Z16: ='BOQ Zone A Equipment'!M15 -> 0 | AA16: =Z16*F16 -> 0 | AB16: ='BOQ Zone A Equipment'!N15 -> 0 | AC16: =AB16*F16 -> 0 | AD16: ='BOQ Zone A Equipment'!O15 -> 0 | AE16: =AD16*F16 -> 0 | AF16: ='BOQ Zone A Equipment'!P15 -> 0 | AG16: =AF16*F16 -> 0 | AH16: ='BOQ Zone A Equipment'!Q15 -> 0 | AI16: =AH16*F16 -> 0 | AJ16: ='BOQ Zone A Equipment'!R15 -> 0 | AK16: =AJ16*F16 -> 0 | AL16: ='BOQ Zone A Equipment'!S15 -> 13 | AM16: =AL16*F16 -> 162.5 | AN16: =M16+O16+Q16+S16+U16+W16+Y16+AA16+AC16+AE16+AG16+AI16+AK16+AM16 -> 862.5 | AO16: =AN16*$F$53 -> 69 | AP16: =AN16+AO16 -> 931.5 | AQ16: =AP16*$F$55 -> 13.041 | AR16: =AP16+AQ16 -> 944.541 | AS16: =AR16*$F$57 -> 132.23574 | AT16: =AR16+AS16 -> 1076.7767 | AU16: =ROUNDUP(AT16/C16,0) -> 16
A17: 2 | B17: Water Fed Telescope (20 Meter) | C17: =L17+N17+P17+R17+T17+V17+X17+Z17+AB17+AD17+AF17+AH17+AJ17+AL17 -> 2 | D17: 60 | E17: ='[2]Unit rates'!$D$10 -> 380000 | F17: =E17/D17 -> 6333.3333 | G17: =C17*F17 -> 12666.667 | I17: =C17-(L17+N17+P17+R17+T17+V17+X17+Z17+AB17+AD17+AF17+AH17+AJ17+AL17) -> 0 | J17: =G17-(M17+O17+Q17+S17+U17+W17+Y17+AA17+AC17+AE17+AG17+AI17+AK17+AM17) -> 0 | L17: ='BOQ Zone A Equipment'!F16 -> 0.33703361 | M17: =F17*L17 -> 2134.5462 | N17: ='BOQ Zone A Equipment'!G16 -> 0.16990441 | O17: =N17*F17 -> 1076.0613 | P17: ='BOQ Zone A Equipment'!H16 -> 0.17884675 | Q17: =P17*F17 -> 1132.6961 | R17: ='BOQ Zone A Equipment'!I16 -> 0.32870799 | S17: =R17*F17 -> 2081.8172 | T17: ='BOQ Zone A Equipment'!J16 -> 0.072463768 | U17: =T17*F17 -> 458.9372 | V17: ='BOQ Zone A Equipment'!K16 -> 0.057971014 | W17: =V17*F17 -> 367.14976 | X17: ='BOQ Zone A Equipment'!L16 -> 0.043478261 | Y17: =X17*F17 -> 275.36232 | Z17: ='BOQ Zone A Equipment'!M16 -> 0.057971014 | AA17: =Z17*F17 -> 367.14976 | AB17: ='BOQ Zone A Equipment'!N16 -> 0.057971014 | AC17: =AB17*F17 -> 367.14976 | AD17: ='BOQ Zone A Equipment'!O16 -> 0.14492754 | AE17: =AD17*F17 -> 917.8744 | AF17: ='BOQ Zone A Equipment'!P16 -> 0.014492754 | AG17: =AF17*F17 -> 91.78744 | AH17: ='BOQ Zone A Equipment'!Q16 -> 0.086956522 | AI17: =AH17*F17 -> 550.72464 | AJ17: ='BOQ Zone A Equipment'!R16 -> 0.014492754 | AK17: =AJ17*F17 -> 91.78744 | AL17: ='BOQ Zone A Equipment'!S16 -> 0.43478261 | AM17: =AL17*F17 -> 2753.6232 | AN17: =M17+O17+Q17+S17+U17+W17+Y17+AA17+AC17+AE17+AG17+AI17+AK17+AM17 -> 12666.667 | AO17: =AN17*$F$53 -> 1013.3333 | AP17: =AN17+AO17 -> 13680 | AQ17: =AP17*$F$55 -> 191.52 | AR17: =AP17+AQ17 -> 13871.52 | AS17: =AR17*$F$57 -> 1942.0128 | AT17: =AR17+AS17 -> 15813.533 | AU17: =ROUNDUP(AT17/C17,0) -> 7907
A18: 1 | B18: High Pressure Set One Car, Driver, 1K Liter tank | C18: =L18+N18+P18+R18+T18+V18+X18+Z18+AB18+AD18+AF18+AH18+AJ18+AL18 -> 2 | D18: 1 | E18: ='Transportation Cost'!G36 -> 51833.333 | F18: =E18/D18 -> 51833.333 | G18: =C18*F18 -> 103666.67 | I18: =C18-(L18+N18+P18+R18+T18+V18+X18+Z18+AB18+AD18+AF18+AH18+AJ18+AL18) -> 0 | J18: =G18-(M18+O18+Q18+S18+U18+W18+Y18+AA18+AC18+AE18+AG18+AI18+AK18+AM18) -> 0 | L18: ='BOQ Zone A Equipment'!F17 -> 0.33703361 | M18: =F18*L18 -> 17469.575 | N18: ='BOQ Zone A Equipment'!G17 -> 0.16990441 | O18: =N18*F18 -> 8806.7119 | P18: ='BOQ Zone A Equipment'!H17 -> 0.17884675 | Q18: =P18*F18 -> 9270.223 | R18: ='BOQ Zone A Equipment'!I17 -> 0.32870799 | S18: =R18*F18 -> 17038.031 | T18: ='BOQ Zone A Equipment'!J17 -> 0.072463768 | U18: =T18*F18 -> 3756.0386 | V18: ='BOQ Zone A Equipment'!K17 -> 0.057971014 | W18: =V18*F18 -> 3004.8309 | X18: ='BOQ Zone A Equipment'!L17 -> 0.043478261 | Y18: =X18*F18 -> 2253.6232 | Z18: ='BOQ Zone A Equipment'!M17 -> 0.057971014 | AA18: =Z18*F18 -> 3004.8309 | AB18: ='BOQ Zone A Equipment'!N17 -> 0.057971014 | AC18: =AB18*F18 -> 3004.8309 | AD18: ='BOQ Zone A Equipment'!O17 -> 0.14492754 | AE18: =AD18*F18 -> 7512.0773 | AF18: ='BOQ Zone A Equipment'!P17 -> 0.014492754 | AG18: =AF18*F18 -> 751.20773 | AH18: ='BOQ Zone A Equipment'!Q17 -> 0.086956522 | AI18: =AH18*F18 -> 4507.2464 | AJ18: ='BOQ Zone A Equipment'!R17 -> 0.014492754 | AK18: =AJ18*F18 -> 751.20773 | AL18: ='BOQ Zone A Equipment'!S17 -> 0.43478261 | AM18: =AL18*F18 -> 22536.232 | AN18: =M18+O18+Q18+S18+U18+W18+Y18+AA18+AC18+AE18+AG18+AI18+AK18+AM18 -> 103666.67 | AO18: =AN18*$F$53 -> 8293.3333 | AP18: =AN18+AO18 -> 111960 | AR18: =AP18+AQ18 -> 111960 | AS18: =AR18*$F$57 -> 15674.4 | AT18: =AR18+AS18 -> 127634.4 | AU18: =ROUNDUP(AT18/C18,0) -> 63818
A19: 1 | B19: Man Lift 15M" with driver | C19: =L19+N19+P19+R19+T19+V19+X19+Z19+AB19+AD19+AF19+AH19+AJ19+AL19 -> 2 | D19: 1 | E19: 55000 | F19: =E19/D19 -> 55000 | G19: =C19*F19 -> 110000 | I19: =C19-(L19+N19+P19+R19+T19+V19+X19+Z19+AB19+AD19+AF19+AH19+AJ19+AL19) -> 0 | J19: =G19-(M19+O19+Q19+S19+U19+W19+Y19+AA19+AC19+AE19+AG19+AI19+AK19+AM19) -> 0 | L19: ='BOQ Zone A Equipment'!F18 -> 0.33703361 | M19: =F19*L19 -> 18536.849 | N19: ='BOQ Zone A Equipment'!G18 -> 0.16990441 | O19: =N19*F19 -> 9344.7425 | P19: ='BOQ Zone A Equipment'!H18 -> 0.17884675 | Q19: =P19*F19 -> 9836.5711 | R19: ='BOQ Zone A Equipment'!I18 -> 0.32870799 | S19: =R19*F19 -> 18078.939 | T19: ='BOQ Zone A Equipment'!J18 -> 0.072463768 | U19: =T19*F19 -> 3985.5072 | V19: ='BOQ Zone A Equipment'!K18 -> 0.057971014 | W19: =V19*F19 -> 3188.4058 | X19: ='BOQ Zone A Equipment'!L18 -> 0.043478261 | Y19: =X19*F19 -> 2391.3043 | Z19: ='BOQ Zone A Equipment'!M18 -> 0.057971014 | AA19: =Z19*F19 -> 3188.4058 | AB19: ='BOQ Zone A Equipment'!N18 -> 0.057971014 | AC19: =AB19*F19 -> 3188.4058 | AD19: ='BOQ Zone A Equipment'!O18 -> 0.14492754 | AE19: =AD19*F19 -> 7971.0145 | AF19: ='BOQ Zone A Equipment'!P18 -> 0.014492754 | AG19: =AF19*F19 -> 797.10145 | AH19: ='BOQ Zone A Equipment'!Q18 -> 0.086956522 | AI19: =AH19*F19 -> 4782.6087 | AJ19: ='BOQ Zone A Equipment'!R18 -> 0.014492754 | AK19: =AJ19*F19 -> 797.10145 | AL19: ='BOQ Zone A Equipment'!S18 -> 0.43478261 | AM19: =AL19*F19 -> 23913.043 | AN19: =M19+O19+Q19+S19+U19+W19+Y19+AA19+AC19+AE19+AG19+AI19+AK19+AM19 -> 110000 | AO19: =AN19*$F$53 -> 8800 | AP19: =AN19+AO19 -> 118800 | AR19: =AP19+AQ19 -> 118800 | AS19: =AR19*$F$57 -> 16632 | AT19: =AR19+AS19 -> 135432 | AU19: =ROUNDUP(AT19/C19,0) -> 67716
A20: 1 | B20: Pick up Car with dirver | C20: =L20+N20+P20+R20+T20+V20+X20+Z20+AB20+AD20+AF20+AH20+AJ20+AL20 -> 2 | D20: 1 | E20: =1400*30 -> 42000 | F20: =E20/D20 -> 42000 | G20: =C20*F20 -> 84000 | I20: =C20-(L20+N20+P20+R20+T20+V20+X20+Z20+AB20+AD20+AF20+AH20+AJ20+AL20) -> 0 | J20: =G20-(M20+O20+Q20+S20+U20+W20+Y20+AA20+AC20+AE20+AG20+AI20+AK20+AM20) -> 0 | L20: ='BOQ Zone A Equipment'!F20 -> 0.33703361 | M20: =F20*L20 -> 14155.412 | N20: ='BOQ Zone A Equipment'!G20 -> 0.16990441 | O20: =N20*F20 -> 7135.9852 | P20: ='BOQ Zone A Equipment'!H20 -> 0.17884675 | Q20: =P20*F20 -> 7511.5634 | R20: ='BOQ Zone A Equipment'!I20 -> 0.32870799 | S20: =R20*F20 -> 13805.735 | T20: ='BOQ Zone A Equipment'!J20 -> 0.072463768 | U20: =T20*F20 -> 3043.4783 | V20: ='BOQ Zone A Equipment'!K20 -> 0.057971014 | W20: =V20*F20 -> 2434.7826 | X20: ='BOQ Zone A Equipment'!L20 -> 0.043478261 | Y20: =X20*F20 -> 1826.087 | Z20: ='BOQ Zone A Equipment'!M20 -> 0.057971014 | AA20: =Z20*F20 -> 2434.7826 | AB20: ='BOQ Zone A Equipment'!N20 -> 0.057971014 | AC20: =AB20*F20 -> 2434.7826 | AD20: ='BOQ Zone A Equipment'!O20 -> 0.14492754 | AE20: =AD20*F20 -> 6086.9565 | AF20: ='BOQ Zone A Equipment'!P20 -> 0.014492754 | AG20: =AF20*F20 -> 608.69565 | AH20: ='BOQ Zone A Equipment'!Q20 -> 0.086956522 | AI20: =AH20*F20 -> 3652.1739 | AJ20: ='BOQ Zone A Equipment'!R20 -> 0.014492754 | AK20: =AJ20*F20 -> 608.69565 | AL20: ='BOQ Zone A Equipment'!S20 -> 0.43478261 | AM20: =AL20*F20 -> 18260.87 | AN20: =M20+O20+Q20+S20+U20+W20+Y20+AA20+AC20+AE20+AG20+AI20+AK20+AM20 -> 84000 | AO20: =AN20*$F$53 -> 6720 | AP20: =AN20+AO20 -> 90720 | AQ20: =AP20*$F$55 -> 1270.08 | AR20: =AP20+AQ20 -> 91990.08 | AS20: =AR20*$F$57 -> 12878.611 | AT20: =AR20+AS20 -> 104868.69 | AU20: =ROUNDUP(AT20/C20,0) -> 52435
B21: Mantinance Cost | C21: =L21+N21+P21+R21+T21+V21+X21+Z21+AB21+AD21+AF21+AH21+AJ21+AL21 -> 7.5 | D21: 1 | E21: 1500 | F21: =E21/D21 -> 1500 | G21: =C21*F21 -> 11250 | I21: =C21-(L21+N21+P21+R21+T21+V21+X21+Z21+AB21+AD21+AF21+AH21+AJ21+AL21) -> 0 | J21: =G21-(M21+O21+Q21+S21+U21+W21+Y21+AA21+AC21+AE21+AG21+AI21+AK21+AM21) -> 0 | L21: 1 | M21: =F21*L21 -> 1500 | N21: 1 | O21: =N21*F21 -> 1500 | P21: 1 | Q21: =P21*F21 -> 1500 | R21: 1 | S21: =R21*F21 -> 1500 | T21: 0.5 | U21: =T21*F21 -> 750 | V21: 0.5 | W21: =V21*F21 -> 750 | X21: 0.5 | Y21: =X21*F21 -> 750 | Z21: 0.25 | AA21: =Z21*F21 -> 375 | AB21: 0.25 | AC21: =AB21*F21 -> 375 | AD21: 0.5 | AE21: =AD21*F21 -> 750 | AG21: =AF21*F21 -> 0 | AI21: =AH21*F21 -> 0 | AK21: =AJ21*F21 -> 0 | AL21: 1 | AM21: =AL21*F21 -> 1500 | AN21: =M21+O21+Q21+S21+U21+W21+Y21+AA21+AC21+AE21+AG21+AI21+AK21+AM21 -> 11250 | AO21: =AN21*$F$53 -> 900 | AP21: =AN21+AO21 -> 12150 | AQ21: =AP21*$F$55 -> 170.1 | AR21: =AP21+AQ21 -> 12320.1 | AS21: =AR21*$F$57 -> 1724.814 | AT21: =AR21+AS21 -> 14044.914 | AU21: =ROUNDUP(AT21/C21,0) -> 1873
B22: Ladders 1.5 Meter | C22: =L22+N22+P22+R22+T22+V22+X22+Z22+AB22+AD22+AF22+AH22+AJ22+AL22 -> 15 | D22: 36 | E22: 3800 | F22: =E22/D22 -> 105.55556 | G22: =C22*F22 -> 1583.3333 | I22: =C22-(L22+N22+P22+R22+T22+V22+X22+Z22+AB22+AD22+AF22+AH22+AJ22+AL22) -> 0 | J22: =G22-(M22+O22+Q22+S22+U22+W22+Y22+AA22+AC22+AE22+AG22+AI22+AK22+AM22) -> 0 | L22: 2 | M22: =F22*L22 -> 211.11111 | N22: 2 | O22: =N22*F22 -> 211.11111 | P22: 2 | Q22: =P22*F22 -> 211.11111 | R22: 4 | S22: =R22*F22 -> 422.22222 | U22: =T22*F22 -> 0 | W22: =V22*F22 -> 0 | Y22: =X22*F22 -> 0 | AA22: =Z22*F22 -> 0 | AC22: =AB22*F22 -> 0 | AE22: =AD22*F22 -> 0 | AG22: =AF22*F22 -> 0 | AI22: =AH22*F22 -> 0 | AK22: =AJ22*F22 -> 0 | AL22: 5 | AM22: =AL22*F22 -> 527.77778 | AN22: =M22+O22+Q22+S22+U22+W22+Y22+AA22+AC22+AE22+AG22+AI22+AK22+AM22 -> 1583.3333 | AO22: =AN22*$F$53 -> 126.66667 | AP22: =AN22+AO22 -> 1710 | AQ22: =AP22*$F$55 -> 23.94 | AR22: =AP22+AQ22 -> 1733.94 | AS22: =AR22*$F$57 -> 242.7516 | AT22: =AR22+AS22 -> 1976.6916 | AU22: =ROUNDUP(AT22/C22,0) -> 132
B23: Ladders 3 Meter | C23: =L23+N23+P23+R23+T23+V23+X23+Z23+AB23+AD23+AF23+AH23+AJ23+AL23 -> 7 | D23: 36 | E23: 5800 | F23: =E23/D23 -> 161.11111 | G23: =C23*F23 -> 1127.7778 | I23: =C23-(L23+N23+P23+R23+T23+V23+X23+Z23+AB23+AD23+AF23+AH23+AJ23+AL23) -> 0 | J23: =G23-(M23+O23+Q23+S23+U23+W23+Y23+AA23+AC23+AE23+AG23+AI23+AK23+AM23) -> 0 | L23: 1 | M23: =F23*L23 -> 161.11111 | N23: 1 | O23: =N23*F23 -> 161.11111 | P23: 1 | Q23: =P23*F23 -> 161.11111 | R23: 1 | S23: =R23*F23 -> 161.11111 | U23: =T23*F23 -> 0 | W23: =V23*F23 -> 0 | Y23: =X23*F23 -> 0 | AA23: =Z23*F23 -> 0 | AC23: =AB23*F23 -> 0 | AD23: 1 | AE23: =AD23*F23 -> 161.11111 | AG23: =AF23*F23 -> 0 | AI23: =AH23*F23 -> 0 | AK23: =AJ23*F23 -> 0 | AL23: 2 | AM23: =AL23*F23 -> 322.22222 | AN23: =M23+O23+Q23+S23+U23+W23+Y23+AA23+AC23+AE23+AG23+AI23+AK23+AM23 -> 1127.7778 | AO23: =AN23*$F$53 -> 90.222222 | AP23: =AN23+AO23 -> 1218 | AQ23: =AP23*$F$55 -> 17.052 | AR23: =AP23+AQ23 -> 1235.052 | AS23: =AR23*$F$57 -> 172.90728 | AT23: =AR23+AS23 -> 1407.9593 | AU23: =ROUNDUP(AT23/C23,0) -> 202
B24: Telescope 9 M | C24: =L24+N24+P24+R24+T24+V24+X24+Z24+AB24+AD24+AF24+AH24+AJ24+AL24 -> 11 | D24: 12 | E24: 1250 | F24: =E24/D24 -> 104.16667 | G24: =C24*F24 -> 1145.8333 | I24: =C24-(L24+N24+P24+R24+T24+V24+X24+Z24+AB24+AD24+AF24+AH24+AJ24+AL24) -> 0 | J24: =G24-(M24+O24+Q24+S24+U24+W24+Y24+AA24+AC24+AE24+AG24+AI24+AK24+AM24) -> 0 | L24: 2 | M24: =F24*L24 -> 208.33333 | N24: 2 | O24: =N24*F24 -> 208.33333 | P24: 1 | Q24: =P24*F24 -> 104.16667 | R24: 2 | S24: =R24*F24 -> 208.33333 | U24: =T24*F24 -> 0 | W24: =V24*F24 -> 0 | Y24: =X24*F24 -> 0 | AA24: =Z24*F24 -> 0 | AC24: =AB24*F24 -> 0 | AD24: 1 | AE24: =AD24*F24 -> 104.16667 | AG24: =AF24*F24 -> 0 | AI24: =AH24*F24 -> 0 | AK24: =AJ24*F24 -> 0 | AL24: 3 | AM24: =AL24*F24 -> 312.5 | AN24: =M24+O24+Q24+S24+U24+W24+Y24+AA24+AC24+AE24+AG24+AI24+AK24+AM24 -> 1145.8333 | AO24: =AN24*$F$53 -> 91.666667 | AP24: =AN24+AO24 -> 1237.5 | AQ24: =AP24*$F$55 -> 17.325 | AR24: =AP24+AQ24 -> 1254.825 | AS24: =AR24*$F$57 -> 175.6755 | AT24: =AR24+AS24 -> 1430.5005 | AU24: =ROUNDUP(AT24/C24,0) -> 131
B25: Caution Wet Floor sign | C25: =L25+N25+P25+R25+T25+V25+X25+Z25+AB25+AD25+AF25+AH25+AJ25+AL25 -> 50 | D25: 12 | E25: 220 | F25: =E25/D25 -> 18.333333 | G25: =C25*F25 -> 916.66667 | I25: =C25-(L25+N25+P25+R25+T25+V25+X25+Z25+AB25+AD25+AF25+AH25+AJ25+AL25) -> 0 | J25: =G25-(M25+O25+Q25+S25+U25+W25+Y25+AA25+AC25+AE25+AG25+AI25+AK25+AM25) -> 0 | L25: 10 | M25: =F25*L25 -> 183.33333 | N25: 5 | O25: =N25*F25 -> 91.666667 | P25: 5 | Q25: =P25*F25 -> 91.666667 | R25: 10 | S25: =R25*F25 -> 183.33333 | T25: 1 | U25: =T25*F25 -> 18.333333 | V25: 1 | W25: =V25*F25 -> 18.333333 | X25: 1 | Y25: =X25*F25 -> 18.333333 | Z25: 1 | AA25: =Z25*F25 -> 18.333333 | AB25: 1 | AC25: =AB25*F25 -> 18.333333 | AD25: 5 | AE25: =AD25*F25 -> 91.666667 | AG25: =AF25*F25 -> 0 | AI25: =AH25*F25 -> 0 | AK25: =AJ25*F25 -> 0 | AL25: 10 | AM25: =AL25*F25 -> 183.33333 | AN25: =M25+O25+Q25+S25+U25+W25+Y25+AA25+AC25+AE25+AG25+AI25+AK25+AM25 -> 916.66667 | AO25: =AN25*$F$53 -> 73.333333 | AP25: =AN25+AO25 -> 990 | AQ25: =AP25*$F$55 -> 13.86 | AR25: =AP25+AQ25 -> 1003.86 | AS25: =AR25*$F$57 -> 140.5404 | AT25: =AR25+AS25 -> 1144.4004 | AU25: =ROUNDUP(AT25/C25,0) -> 23
B26: Microfiber Flat Mop | C26: =L26+N26+P26+R26+T26+V26+X26+Z26+AB26+AD26+AF26+AH26+AJ26+AL26 -> 64 | D26: 12 | E26: 350 | F26: =E26/D26 -> 29.166667 | G26: =C26*F26 -> 1866.6667 | I26: =C26-(L26+N26+P26+R26+T26+V26+X26+Z26+AB26+AD26+AF26+AH26+AJ26+AL26) -> 0 | J26: =G26-(M26+O26+Q26+S26+U26+W26+Y26+AA26+AC26+AE26+AG26+AI26+AK26+AM26) -> 0 | L26: 14 | M26: =F26*L26 -> 408.33333 | N26: 7 | O26: =N26*F26 -> 204.16667 | P26: 7 | Q26: =P26*F26 -> 204.16667 | R26: 14 | S26: =R26*F26 -> 408.33333 | T26: 1 | U26: =T26*F26 -> 29.166667 | V26: 1 | W26: =V26*F26 -> 29.166667 | X26: 1 | Y26: =X26*F26 -> 29.166667 | Z26: 1 | AA26: =Z26*F26 -> 29.166667 | AB26: 1 | AC26: =AB26*F26 -> 29.166667 | AD26: 5 | AE26: =AD26*F26 -> 145.83333 | AF26: 1 | AG26: =AF26*F26 -> 29.166667 | AI26: =AH26*F26 -> 0 | AJ26: 1 | AK26: =AJ26*F26 -> 29.166667 | AL26: 10 | AM26: =AL26*F26 -> 291.66667 | AN26: =M26+O26+Q26+S26+U26+W26+Y26+AA26+AC26+AE26+AG26+AI26+AK26+AM26 -> 1866.6667 | AO26: =AN26*$F$53 -> 149.33333 | AP26: =AN26+AO26 -> 2016 | AQ26: =AP26*$F$55 -> 28.224 | AR26: =AP26+AQ26 -> 2044.224 | AS26: =AR26*$F$57 -> 286.19136 | AT26: =AR26+AS26 -> 2330.4154 | AU26: =ROUNDUP(AT26/C26,0) -> 37
B27: Microfiber Flat Mop pads | C27: =L27+N27+P27+R27+T27+V27+X27+Z27+AB27+AD27+AF27+AH27+AJ27+AL27 -> 64 | D27: 1 | E27: 150 | F27: =E27/D27 -> 150 | G27: =C27*F27 -> 9600 | I27: =C27-(L27+N27+P27+R27+T27+V27+X27+Z27+AB27+AD27+AF27+AH27+AJ27+AL27) -> 0 | J27: =G27-(M27+O27+Q27+S27+U27+W27+Y27+AA27+AC27+AE27+AG27+AI27+AK27+AM27) -> 0 | L27: 14 | M27: =F27*L27 -> 2100 | N27: 7 | O27: =N27*F27 -> 1050 | P27: 7 | Q27: =P27*F27 -> 1050 | R27: 14 | S27: =R27*F27 -> 2100 | T27: 1 | U27: =T27*F27 -> 150 | V27: 1 | W27: =V27*F27 -> 150 | X27: 1 | Y27: =X27*F27 -> 150 | Z27: 1 | AA27: =Z27*F27 -> 150 | AB27: 1 | AC27: =AB27*F27 -> 150 | AD27: 5 | AE27: =AD27*F27 -> 750 | AF27: 1 | AG27: =AF27*F27 -> 150 | AI27: =AH27*F27 -> 0 | AJ27: 1 | AK27: =AJ27*F27 -> 150 | AL27: 10 | AM27: =AL27*F27 -> 1500 | AN27: =M27+O27+Q27+S27+U27+W27+Y27+AA27+AC27+AE27+AG27+AI27+AK27+AM27 -> 9600 | AO27: =AN27*$F$53 -> 768 | AP27: =AN27+AO27 -> 10368 | AQ27: =AP27*$F$55 -> 145.152 | AR27: =AP27+AQ27 -> 10513.152 | AS27: =AR27*$F$57 -> 1471.8413 | AT27: =AR27+AS27 -> 11984.993 | AU27: =ROUNDUP(AT27/C27,0) -> 188
B28: Dry Mop 100 cm | C28: =L28+N28+P28+R28+T28+V28+X28+Z28+AB28+AD28+AF28+AH28+AJ28+AL28 -> 64 | D28: 12 | E28: 350 | F28: =E28/D28 -> 29.166667 | G28: =C28*F28 -> 1866.6667 | I28: =C28-(L28+N28+P28+R28+T28+V28+X28+Z28+AB28+AD28+AF28+AH28+AJ28+AL28) -> 0 | J28: =G28-(M28+O28+Q28+S28+U28+W28+Y28+AA28+AC28+AE28+AG28+AI28+AK28+AM28) -> 0 | L28: 14 | M28: =F28*L28 -> 408.33333 | N28: 7 | O28: =N28*F28 -> 204.16667 | P28: 7 | Q28: =P28*F28 -> 204.16667 | R28: 14 | S28: =R28*F28 -> 408.33333 | T28: 1 | U28: =T28*F28 -> 29.166667 | V28: 1 | W28: =V28*F28 -> 29.166667 | X28: 1 | Y28: =X28*F28 -> 29.166667 | Z28: 1 | AA28: =Z28*F28 -> 29.166667 | AB28: 1 | AC28: =AB28*F28 -> 29.166667 | AD28: 5 | AE28: =AD28*F28 -> 145.83333 | AF28: 1 | AG28: =AF28*F28 -> 29.166667 | AI28: =AH28*F28 -> 0 | AJ28: 1 | AK28: =AJ28*F28 -> 29.166667 | AL28: 10 | AM28: =AL28*F28 -> 291.66667 | AN28: =M28+O28+Q28+S28+U28+W28+Y28+AA28+AC28+AE28+AG28+AI28+AK28+AM28 -> 1866.6667 | AO28: =AN28*$F$53 -> 149.33333 | AP28: =AN28+AO28 -> 2016 | AQ28: =AP28*$F$55 -> 28.224 | AR28: =AP28+AQ28 -> 2044.224 | AS28: =AR28*$F$57 -> 286.19136 | AT28: =AR28+AS28 -> 2330.4154 | AU28: =ROUNDUP(AT28/C28,0) -> 37
B29: Dry Mop Pads 100 cm | C29: =L29+N29+P29+R29+T29+V29+X29+Z29+AB29+AD29+AF29+AH29+AJ29+AL29 -> 64 | D29: 1 | E29: 125 | F29: =E29/D29 -> 125 | G29: =C29*F29 -> 8000 | I29: =C29-(L29+N29+P29+R29+T29+V29+X29+Z29+AB29+AD29+AF29+AH29+AJ29+AL29) -> 0 | J29: =G29-(M29+O29+Q29+S29+U29+W29+Y29+AA29+AC29+AE29+AG29+AI29+AK29+AM29) -> 0 | L29: 14 | M29: =F29*L29 -> 1750 | N29: 7 | O29: =N29*F29 -> 875 | P29: 7 | Q29: =P29*F29 -> 875 | R29: 14 | S29: =R29*F29 -> 1750 | T29: 1 | U29: =T29*F29 -> 125 | V29: 1 | W29: =V29*F29 -> 125 | X29: 1 | Y29: =X29*F29 -> 125 | Z29: 1 | AA29: =Z29*F29 -> 125 | AB29: 1 | AC29: =AB29*F29 -> 125 | AD29: 5 | AE29: =AD29*F29 -> 625 | AF29: 1 | AG29: =AF29*F29 -> 125 | AI29: =AH29*F29 -> 0 | AJ29: 1 | AK29: =AJ29*F29 -> 125 | AL29: 10 | AM29: =AL29*F29 -> 1250 | AN29: =M29+O29+Q29+S29+U29+W29+Y29+AA29+AC29+AE29+AG29+AI29+AK29+AM29 -> 8000 | AO29: =AN29*$F$53 -> 640 | AP29: =AN29+AO29 -> 8640 | AQ29: =AP29*$F$55 -> 120.96 | AR29: =AP29+AQ29 -> 8760.96 | AS29: =AR29*$F$57 -> 1226.5344 | AT29: =AR29+AS29 -> 9987.4944 | AU29: =ROUNDUP(AT29/C29,0) -> 157
B30: Hard Floor Brooms W/ Hand 60cm | C30: =L30+N30+P30+R30+T30+V30+X30+Z30+AB30+AD30+AF30+AH30+AJ30+AL30 -> 51 | D30: 3 | E30: 250 | F30: =E30/D30 -> 83.333333 | G30: =C30*F30 -> 4250 | I30: =C30-(L30+N30+P30+R30+T30+V30+X30+Z30+AB30+AD30+AF30+AH30+AJ30+AL30) -> 0 | J30: =G30-(M30+O30+Q30+S30+U30+W30+Y30+AA30+AC30+AE30+AG30+AI30+AK30+AM30) -> 0 | L30: 5 | M30: =F30*L30 -> 416.66667 | N30: 2 | O30: =N30*F30 -> 166.66667 | P30: 2 | Q30: =P30*F30 -> 166.66667 | R30: 5 | S30: =R30*F30 -> 416.66667 | T30: 5 | U30: =T30*F30 -> 416.66667 | V30: 4 | W30: =V30*F30 -> 333.33333 | X30: 2 | Y30: =X30*F30 -> 166.66667 | Z30: 4 | AA30: =Z30*F30 -> 333.33333 | AB30: 4 | AC30: =AB30*F30 -> 333.33333 | AD30: 5 | AE30: =AD30*F30 -> 416.66667 | AF30: 1 | AG30: =AF30*F30 -> 83.333333 | AH30: 6 | AI30: =AH30*F30 -> 500 | AJ30: 1 | AK30: =AJ30*F30 -> 83.333333 | AL30: 5 | AM30: =AL30*F30 -> 416.66667 | AN30: =M30+O30+Q30+S30+U30+W30+Y30+AA30+AC30+AE30+AG30+AI30+AK30+AM30 -> 4250 | AO30: =AN30*$F$53 -> 340 | AP30: =AN30+AO30 -> 4590 | AQ30: =AP30*$F$55 -> 64.26 | AR30: =AP30+AQ30 -> 4654.26 | AS30: =AR30*$F$57 -> 651.5964 | AT30: =AR30+AS30 -> 5305.8564 | AU30: =ROUNDUP(AT30/C30,0) -> 105
B31: Soft Floor Brooms W/ Hand 30cm | C31: =L31+N31+P31+R31+T31+V31+X31+Z31+AB31+AD31+AF31+AH31+AJ31+AL31 -> 84 | D31: 1 | E31: 60 | F31: =E31/D31 -> 60 | G31: =C31*F31 -> 5040 | I31: =C31-(L31+N31+P31+R31+T31+V31+X31+Z31+AB31+AD31+AF31+AH31+AJ31+AL31) -> 0 | J31: =G31-(M31+O31+Q31+S31+U31+W31+Y31+AA31+AC31+AE31+AG31+AI31+AK31+AM31) -> 0 | L31: 15 | M31: =F31*L31 -> 900 | N31: 7 | O31: =N31*F31 -> 420 | P31: 7 | Q31: =P31*F31 -> 420 | R31: 15 | S31: =R31*F31 -> 900 | T31: 5 | U31: =T31*F31 -> 300 | V31: 4 | W31: =V31*F31 -> 240 | X31: 2 | Y31: =X31*F31 -> 120 | Z31: 4 | AA31: =Z31*F31 -> 240 | AB31: 4 | AC31: =AB31*F31 -> 240 | AD31: 3 | AE31: =AD31*F31 -> 180 | AF31: 1 | AG31: =AF31*F31 -> 60 | AH31: 6 | AI31: =AH31*F31 -> 360 | AJ31: 1 | AK31: =AJ31*F31 -> 60 | AL31: 10 | AM31: =AL31*F31 -> 600 | AN31: =M31+O31+Q31+S31+U31+W31+Y31+AA31+AC31+AE31+AG31+AI31+AK31+AM31 -> 5040 | AO31: =AN31*$F$53 -> 403.2 | AP31: =AN31+AO31 -> 5443.2 | AQ31: =AP31*$F$55 -> 76.2048 | AR31: =AP31+AQ31 -> 5519.4048 | AS31: =AR31*$F$57 -> 772.71667 | AT31: =AR31+AS31 -> 6292.1215 | AU31: =ROUNDUP(AT31/C31,0) -> 75
B32: Floor Squeezer W/ Hand 30 cm | C32: =L32+N32+P32+R32+T32+V32+X32+Z32+AB32+AD32+AF32+AH32+AJ32+AL32 -> 72 | D32: 1 | E32: 60 | F32: =E32/D32 -> 60 | G32: =C32*F32 -> 4320 | I32: =C32-(L32+N32+P32+R32+T32+V32+X32+Z32+AB32+AD32+AF32+AH32+AJ32+AL32) -> 0 | J32: =G32-(M32+O32+Q32+S32+U32+W32+Y32+AA32+AC32+AE32+AG32+AI32+AK32+AM32) -> 0 | L32: 15 | M32: =F32*L32 -> 900 | N32: 7 | O32: =N32*F32 -> 420 | P32: 7 | Q32: =P32*F32 -> 420 | R32: 15 | S32: =R32*F32 -> 900 | T32: 1 | U32: =T32*F32 -> 60 | V32: 1 | W32: =V32*F32 -> 60 | X32: 1 | Y32: =X32*F32 -> 60 | Z32: 1 | AA32: =Z32*F32 -> 60 | AB32: 1 | AC32: =AB32*F32 -> 60 | AD32: 5 | AE32: =AD32*F32 -> 300 | AF32: 1 | AG32: =AF32*F32 -> 60 | AH32: 6 | AI32: =AH32*F32 -> 360 | AJ32: 1 | AK32: =AJ32*F32 -> 60 | AL32: 10 | AM32: =AL32*F32 -> 600 | AN32: =M32+O32+Q32+S32+U32+W32+Y32+AA32+AC32+AE32+AG32+AI32+AK32+AM32 -> 4320 | AO32: =AN32*$F$53 -> 345.6 | AP32: =AN32+AO32 -> 4665.6 | AQ32: =AP32*$F$55 -> 65.3184 | AR32: =AP32+AQ32 -> 4730.9184 | AS32: =AR32*$F$57 -> 662.32858 | AT32: =AR32+AS32 -> 5393.247 | AU32: =ROUNDUP(AT32/C32,0) -> 75
B33: Floor Squeezer W/ Metallic Hand 75 cm | C33: =L33+N33+P33+R33+T33+V33+X33+Z33+AB33+AD33+AF33+AH33+AJ33+AL33 -> 60 | D33: 2 | E33: 135 | F33: =E33/D33 -> 67.5 | G33: =C33*F33 -> 4050 | I33: =C33-(L33+N33+P33+R33+T33+V33+X33+Z33+AB33+AD33+AF33+AH33+AJ33+AL33) -> 0 | J33: =G33-(M33+O33+Q33+S33+U33+W33+Y33+AA33+AC33+AE33+AG33+AI33+AK33+AM33) -> 0 | L33: 5 | M33: =F33*L33 -> 337.5 | N33: 7 | O33: =N33*F33 -> 472.5 | P33: 7 | Q33: =P33*F33 -> 472.5 | R33: 5 | S33: =R33*F33 -> 337.5 | T33: 5 | U33: =T33*F33 -> 337.5 | V33: 2 | W33: =V33*F33 -> 135 | X33: 2 | Y33: =X33*F33 -> 135 | Z33: 2 | AA33: =Z33*F33 -> 135 | AB33: 2 | AC33: =AB33*F33 -> 135 | AD33: 5 | AE33: =AD33*F33 -> 337.5 | AF33: 1 | AG33: =AF33*F33 -> 67.5 | AH33: 6 | AI33: =AH33*F33 -> 405 | AJ33: 1 | AK33: =AJ33*F33 -> 67.5 | AL33: 10 | AM33: =AL33*F33 -> 675 | AN33: =M33+O33+Q33+S33+U33+W33+Y33+AA33+AC33+AE33+AG33+AI33+AK33+AM33 -> 4050 | AO33: =AN33*$F$53 -> 324 | AP33: =AN33+AO33 -> 4374 | AQ33: =AP33*$F$55 -> 61.236 | AR33: =AP33+AQ33 -> 4435.236 | AS33: =AR33*$F$57 -> 620.93304 | AT33: =AR33+AS33 -> 5056.169 | AU33: =ROUNDUP(AT33/C33,0) -> 85
B34: Ceiling Duster | C34: =L34+N34+P34+R34+T34+V34+X34+Z34+AB34+AD34+AF34+AH34+AJ34+AL34 -> 32 | D34: 1 | E34: 90 | F34: =E34/D34 -> 90 | G34: =C34*F34 -> 2880 | I34: =C34-(L34+N34+P34+R34+T34+V34+X34+Z34+AB34+AD34+AF34+AH34+AJ34+AL34) -> 0 | J34: =G34-(M34+O34+Q34+S34+U34+W34+Y34+AA34+AC34+AE34+AG34+AI34+AK34+AM34) -> 0 | L34: 4 | M34: =F34*L34 -> 360 | N34: 2 | O34: =N34*F34 -> 180 | P34: 2 | Q34: =P34*F34 -> 180 | R34: 4 | S34: =R34*F34 -> 360 | T34: 1 | U34: =T34*F34 -> 90 | V34: 1 | W34: =V34*F34 -> 90 | X34: 1 | Y34: =X34*F34 -> 90 | Z34: 1 | AA34: =Z34*F34 -> 90 | AB34: 1 | AC34: =AB34*F34 -> 90 | AD34: 5 | AE34: =AD34*F34 -> 450 | AG34: =AF34*F34 -> 0 | AI34: =AH34*F34 -> 0 | AK34: =AJ34*F34 -> 0 | AL34: 10 | AM34: =AL34*F34 -> 900 | AN34: =M34+O34+Q34+S34+U34+W34+Y34+AA34+AC34+AE34+AG34+AI34+AK34+AM34 -> 2880 | AO34: =AN34*$F$53 -> 230.4 | AP34: =AN34+AO34 -> 3110.4 | AQ34: =AP34*$F$55 -> 43.5456 | AR34: =AP34+AQ34 -> 3153.9456 | AS34: =AR34*$F$57 -> 441.55238 | AT34: =AR34+AS34 -> 3595.498 | AU34: =ROUNDUP(AT34/C34,0) -> 113
B35: Plastic Sprayer | C35: =L35+N35+P35+R35+T35+V35+X35+Z35+AB35+AD35+AF35+AH35+AJ35+AL35 -> 118 | D35: 1 | E35: 35 | F35: =E35/D35 -> 35 | G35: =C35*F35 -> 4130 | I35: =C35-(L35+N35+P35+R35+T35+V35+X35+Z35+AB35+AD35+AF35+AH35+AJ35+AL35) -> 0 | J35: =G35-(M35+O35+Q35+S35+U35+W35+Y35+AA35+AC35+AE35+AG35+AI35+AK35+AM35) -> 0 | L35: 25 | M35: =F35*L35 -> 875 | N35: 12 | O35: =N35*F35 -> 420 | P35: 12 | Q35: =P35*F35 -> 420 | R35: 25 | S35: =R35*F35 -> 875 | T35: 5 | U35: =T35*F35 -> 175 | V35: 3 | W35: =V35*F35 -> 105 | X35: 3 | Y35: =X35*F35 -> 105 | Z35: 3 | AA35: =Z35*F35 -> 105 | AB35: 3 | AC35: =AB35*F35 -> 105 | AD35: 10 | AE35: =AD35*F35 -> 350 | AF35: 1 | AG35: =AF35*F35 -> 35 | AI35: =AH35*F35 -> 0 | AJ35: 1 | AK35: =AJ35*F35 -> 35 | AL35: 15 | AM35: =AL35*F35 -> 525 | AN35: =M35+O35+Q35+S35+U35+W35+Y35+AA35+AC35+AE35+AG35+AI35+AK35+AM35 -> 4130 | AO35: =AN35*$F$53 -> 330.4 | AP35: =AN35+AO35 -> 4460.4 | AQ35: =AP35*$F$55 -> 62.4456 | AR35: =AP35+AQ35 -> 4522.8456 | AS35: =AR35*$F$57 -> 633.19838 | AT35: =AR35+AS35 -> 5156.044 | AU35: =ROUNDUP(AT35/C35,0) -> 44
B36: Floor Brush | C36: =L36+N36+P36+R36+T36+V36+X36+Z36+AB36+AD36+AF36+AH36+AJ36+AL36 -> 77 | D36: 1 | E36: 35 | F36: =E36/D36 -> 35 | G36: =C36*F36 -> 2695 | I36: =C36-(L36+N36+P36+R36+T36+V36+X36+Z36+AB36+AD36+AF36+AH36+AJ36+AL36) -> 0 | J36: =G36-(M36+O36+Q36+S36+U36+W36+Y36+AA36+AC36+AE36+AG36+AI36+AK36+AM36) -> 0 | L36: 15 | M36: =F36*L36 -> 525 | N36: 7 | O36: =N36*F36 -> 245 | P36: 7 | Q36: =P36*F36 -> 245 | R36: 15 | S36: =R36*F36 -> 525 | T36: 2 | U36: =T36*F36 -> 70 | V36: 2 | W36: =V36*F36 -> 70 | X36: 2 | Y36: =X36*F36 -> 70 | Z36: 2 | AA36: =Z36*F36 -> 70 | AB36: 2 | AC36: =AB36*F36 -> 70 | AD36: 10 | AE36: =AD36*F36 -> 350 | AF36: 1 | AG36: =AF36*F36 -> 35 | AH36: 6 | AI36: =AH36*F36 -> 210 | AJ36: 1 | AK36: =AJ36*F36 -> 35 | AL36: 5 | AM36: =AL36*F36 -> 175 | AN36: =M36+O36+Q36+S36+U36+W36+Y36+AA36+AC36+AE36+AG36+AI36+AK36+AM36 -> 2695 | AO36: =AN36*$F$53 -> 215.6 | AP36: =AN36+AO36 -> 2910.6 | AQ36: =AP36*$F$55 -> 40.7484 | AR36: =AP36+AQ36 -> 2951.3484 | AS36: =AR36*$F$57 -> 413.18878 | AT36: =AR36+AS36 -> 3364.5372 | AU36: =ROUNDUP(AT36/C36,0) -> 44
B37: Toilet Bowl Cleaners Broom | C37: =L37+N37+P37+R37+T37+V37+X37+Z37+AB37+AD37+AF37+AH37+AJ37+AL37 -> 21 | D37: 3 | E37: 65 | F37: =E37/D37 -> 21.666667 | G37: =C37*F37 -> 455 | I37: =C37-(L37+N37+P37+R37+T37+V37+X37+Z37+AB37+AD37+AF37+AH37+AJ37+AL37) -> 0 | J37: =G37-(M37+O37+Q37+S37+U37+W37+Y37+AA37+AC37+AE37+AG37+AI37+AK37+AM37) -> 0 | L37: 2 | M37: =F37*L37 -> 43.333333 | N37: 1 | O37: =N37*F37 -> 21.666667 | P37: 1 | Q37: =P37*F37 -> 21.666667 | R37: 2 | S37: =R37*F37 -> 43.333333 | T37: 1 | U37: =T37*F37 -> 21.666667 | V37: 1 | W37: =V37*F37 -> 21.666667 | X37: 1 | Y37: =X37*F37 -> 21.666667 | Z37: 1 | AA37: =Z37*F37 -> 21.666667 | AB37: 1 | AC37: =AB37*F37 -> 21.666667 | AD37: 5 | AE37: =AD37*F37 -> 108.33333 | AG37: =AF37*F37 -> 0 | AI37: =AH37*F37 -> 0 | AK37: =AJ37*F37 -> 0 | AL37: 5 | AM37: =AL37*F37 -> 108.33333 | AN37: =M37+O37+Q37+S37+U37+W37+Y37+AA37+AC37+AE37+AG37+AI37+AK37+AM37 -> 455 | AO37: =AN37*$F$53 -> 36.4 | AP37: =AN37+AO37 -> 491.4 | AQ37: =AP37*$F$55 -> 6.8796 | AR37: =AP37+AQ37 -> 498.2796 | AS37: =AR37*$F$57 -> 69.759144 | AT37: =AR37+AS37 -> 568.03874 | AU37: =ROUNDUP(AT37/C37,0) -> 28
B38: Dust Pans | C38: =L38+N38+P38+R38+T38+V38+X38+Z38+AB38+AD38+AF38+AH38+AJ38+AL38 -> 91 | D38: 1 | E38: 60 | F38: =E38/D38 -> 60 | G38: =C38*F38 -> 5460 | I38: =C38-(L38+N38+P38+R38+T38+V38+X38+Z38+AB38+AD38+AF38+AH38+AJ38+AL38) -> 0 | J38: =G38-(M38+O38+Q38+S38+U38+W38+Y38+AA38+AC38+AE38+AG38+AI38+AK38+AM38) -> 0 | L38: 15 | M38: =F38*L38 -> 900 | N38: 7 | O38: =N38*F38 -> 420 | P38: 7 | Q38: =P38*F38 -> 420 | R38: 15 | S38: =R38*F38 -> 900 | T38: 5 | U38: =T38*F38 -> 300 | V38: 4 | W38: =V38*F38 -> 240 | X38: 2 | Y38: =X38*F38 -> 120 | Z38: 4 | AA38: =Z38*F38 -> 240 | AB38: 4 | AC38: =AB38*F38 -> 240 | AD38: 5 | AE38: =AD38*F38 -> 300 | AF38: 1 | AG38: =AF38*F38 -> 60 | AH38: 6 | AI38: =AH38*F38 -> 360 | AJ38: 1 | AK38: =AJ38*F38 -> 60 | AL38: 15 | AM38: =AL38*F38 -> 900 | AN38: =M38+O38+Q38+S38+U38+W38+Y38+AA38+AC38+AE38+AG38+AI38+AK38+AM38 -> 5460 | AO38: =AN38*$F$53 -> 436.8 | AP38: =AN38+AO38 -> 5896.8 | AQ38: =AP38*$F$55 -> 82.5552 | AR38: =AP38+AQ38 -> 5979.3552 | AS38: =AR38*$F$57 -> 837.10973 | AT38: =AR38+AS38 -> 6816.4649 | AU38: =ROUNDUP(AT38/C38,0) -> 75
B39: Water Bucket | C39: =L39+N39+P39+R39+T39+V39+X39+Z39+AB39+AD39+AF39+AH39+AJ39+AL39 -> 71 | D39: 6 | E39: 220 | F39: =E39/D39 -> 36.666667 | G39: =C39*F39 -> 2603.3333 | I39: =C39-(L39+N39+P39+R39+T39+V39+X39+Z39+AB39+AD39+AF39+AH39+AJ39+AL39) -> 0 | J39: =G39-(M39+O39+Q39+S39+U39+W39+Y39+AA39+AC39+AE39+AG39+AI39+AK39+AM39) -> 0 | L39: 15 | M39: =F39*L39 -> 550 | N39: 7 | O39: =N39*F39 -> 256.66667 | P39: 7 | Q39: =P39*F39 -> 256.66667 | R39: 15 | S39: =R39*F39 -> 550 | T39: 2 | U39: =T39*F39 -> 73.333333 | V39: 2 | W39: =V39*F39 -> 73.333333 | X39: 2 | Y39: =X39*F39 -> 73.333333 | Z39: 2 | AA39: =Z39*F39 -> 73.333333 | AB39: 2 | AC39: =AB39*F39 -> 73.333333 | AD39: 5 | AE39: =AD39*F39 -> 183.33333 | AF39: 1 | AG39: =AF39*F39 -> 36.666667 | AI39: =AH39*F39 -> 0 | AJ39: 1 | AK39: =AJ39*F39 -> 36.666667 | AL39: 10 | AM39: =AL39*F39 -> 366.66667 | AN39: =M39+O39+Q39+S39+U39+W39+Y39+AA39+AC39+AE39+AG39+AI39+AK39+AM39 -> 2603.3333 | AO39: =AN39*$F$53 -> 208.26667 | AP39: =AN39+AO39 -> 2811.6 | AQ39: =AP39*$F$55 -> 39.3624 | AR39: =AP39+AQ39 -> 2850.9624 | AS39: =AR39*$F$57 -> 399.13474 | AT39: =AR39+AS39 -> 3250.0971 | AU39: =ROUNDUP(AT39/C39,0) -> 46
B40: Floor Scraper | C40: =L40+N40+P40+R40+T40+V40+X40+Z40+AB40+AD40+AF40+AH40+AJ40+AL40 -> 71 | D40: 1 | E40: 25 | F40: =E40/D40 -> 25 | G40: =C40*F40 -> 1775 | I40: =C40-(L40+N40+P40+R40+T40+V40+X40+Z40+AB40+AD40+AF40+AH40+AJ40+AL40) -> 0 | J40: =G40-(M40+O40+Q40+S40+U40+W40+Y40+AA40+AC40+AE40+AG40+AI40+AK40+AM40) -> 0 | L40: 15 | M40: =F40*L40 -> 375 | N40: 7 | O40: =N40*F40 -> 175 | P40: 7 | Q40: =P40*F40 -> 175 | R40: 15 | S40: =R40*F40 -> 375 | T40: 2 | U40: =T40*F40 -> 50 | V40: 2 | W40: =V40*F40 -> 50 | X40: 2 | Y40: =X40*F40 -> 50 | Z40: 2 | AA40: =Z40*F40 -> 50 | AB40: 2 | AC40: =AB40*F40 -> 50 | AD40: 5 | AE40: =AD40*F40 -> 125 | AF40: 1 | AG40: =AF40*F40 -> 25 | AI40: =AH40*F40 -> 0 | AJ40: 1 | AK40: =AJ40*F40 -> 25 | AL40: 10 | AM40: =AL40*F40 -> 250 | AN40: =M40+O40+Q40+S40+U40+W40+Y40+AA40+AC40+AE40+AG40+AI40+AK40+AM40 -> 1775 | AO40: =AN40*$F$53 -> 142 | AP40: =AN40+AO40 -> 1917 | AQ40: =AP40*$F$55 -> 26.838 | AR40: =AP40+AQ40 -> 1943.838 | AS40: =AR40*$F$57 -> 272.13732 | AT40: =AR40+AS40 -> 2215.9753 | AU40: =ROUNDUP(AT40/C40,0) -> 32
B41: Glass Scraper | C41: =L41+N41+P41+R41+T41+V41+X41+Z41+AB41+AD41+AF41+AH41+AJ41+AL41 -> 64 | D41: 1 | E41: 35 | F41: =E41/D41 -> 35 | G41: =C41*F41 -> 2240 | I41: =C41-(L41+N41+P41+R41+T41+V41+X41+Z41+AB41+AD41+AF41+AH41+AJ41+AL41) -> 0 | J41: =G41-(M41+O41+Q41+S41+U41+W41+Y41+AA41+AC41+AE41+AG41+AI41+AK41+AM41) -> 0 | L41: 15 | M41: =F41*L41 -> 525 | N41: 7 | O41: =N41*F41 -> 245 | P41: 7 | Q41: =P41*F41 -> 245 | R41: 15 | S41: =R41*F41 -> 525 | T41: 1 | U41: =T41*F41 -> 35 | V41: 1 | W41: =V41*F41 -> 35 | X41: 1 | Y41: =X41*F41 -> 35 | Z41: 1 | AA41: =Z41*F41 -> 35 | AB41: 1 | AC41: =AB41*F41 -> 35 | AD41: 5 | AE41: =AD41*F41 -> 175 | AG41: =AF41*F41 -> 0 | AI41: =AH41*F41 -> 0 | AK41: =AJ41*F41 -> 0 | AL41: 10 | AM41: =AL41*F41 -> 350 | AN41: =M41+O41+Q41+S41+U41+W41+Y41+AA41+AC41+AE41+AG41+AI41+AK41+AM41 -> 2240 | AO41: =AN41*$F$53 -> 179.2 | AP41: =AN41+AO41 -> 2419.2 | AQ41: =AP41*$F$55 -> 33.8688 | AR41: =AP41+AQ41 -> 2453.0688 | AS41: =AR41*$F$57 -> 343.42963 | AT41: =AR41+AS41 -> 2796.4984 | AU41: =ROUNDUP(AT41/C41,0) -> 44
B42: Spare Glass Scraper | C42: =L42+N42+P42+R42+T42+V42+X42+Z42+AB42+AD42+AF42+AH42+AJ42+AL42 -> 21 | D42: 1 | E42: 150 | F42: =E42/D42 -> 150 | G42: =C42*F42 -> 3150 | I42: =C42-(L42+N42+P42+R42+T42+V42+X42+Z42+AB42+AD42+AF42+AH42+AJ42+AL42) -> 0 | J42: =G42-(M42+O42+Q42+S42+U42+W42+Y42+AA42+AC42+AE42+AG42+AI42+AK42+AM42) -> 0 | L42: 5 | M42: =F42*L42 -> 750 | N42: 2 | O42: =N42*F42 -> 300 | P42: 2 | Q42: =P42*F42 -> 300 | R42: 5 | S42: =R42*F42 -> 750 | U42: =T42*F42 -> 0 | W42: =V42*F42 -> 0 | Y42: =X42*F42 -> 0 | AA42: =Z42*F42 -> 0 | AC42: =AB42*F42 -> 0 | AD42: 5 | AE42: =AD42*F42 -> 750 | AG42: =AF42*F42 -> 0 | AI42: =AH42*F42 -> 0 | AK42: =AJ42*F42 -> 0 | AL42: 2 | AM42: =AL42*F42 -> 300 | AN42: =M42+O42+Q42+S42+U42+W42+Y42+AA42+AC42+AE42+AG42+AI42+AK42+AM42 -> 3150 | AO42: =AN42*$F$53 -> 252 | AP42: =AN42+AO42 -> 3402 | AQ42: =AP42*$F$55 -> 47.628 | AR42: =AP42+AQ42 -> 3449.628 | AS42: =AR42*$F$57 -> 482.94792 | AT42: =AR42+AS42 -> 3932.5759 | AU42: =ROUNDUP(AT42/C42,0) -> 188
B43: Glass Squeezer 35cm | C43: =L43+N43+P43+R43+T43+V43+X43+Z43+AB43+AD43+AF43+AH43+AJ43+AL43 -> 26 | D43: 2 | E43: 120 | F43: =E43/D43 -> 60 | G43: =C43*F43 -> 1560 | I43: =C43-(L43+N43+P43+R43+T43+V43+X43+Z43+AB43+AD43+AF43+AH43+AJ43+AL43) -> 0 | J43: =G43-(M43+O43+Q43+S43+U43+W43+Y43+AA43+AC43+AE43+AG43+AI43+AK43+AM43) -> 0 | L43: 5 | M43: =F43*L43 -> 300 | N43: 2 | O43: =N43*F43 -> 120 | P43: 2 | Q43: =P43*F43 -> 120 | R43: 5 | S43: =R43*F43 -> 300 | T43: 2 | U43: =T43*F43 -> 120 | V43: 1 | W43: =V43*F43 -> 60 | X43: 1 | Y43: =X43*F43 -> 60 | Z43: 1 | AA43: =Z43*F43 -> 60 | AB43: 1 | AC43: =AB43*F43 -> 60 | AD43: 1 | AE43: =AD43*F43 -> 60 | AG43: =AF43*F43 -> 0 | AI43: =AH43*F43 -> 0 | AK43: =AJ43*F43 -> 0 | AL43: 5 | AM43: =AL43*F43 -> 300 | AN43: =M43+O43+Q43+S43+U43+W43+Y43+AA43+AC43+AE43+AG43+AI43+AK43+AM43 -> 1560 | AO43: =AN43*$F$53 -> 124.8 | AP43: =AN43+AO43 -> 1684.8 | AQ43: =AP43*$F$55 -> 23.5872 | AR43: =AP43+AQ43 -> 1708.3872 | AS43: =AR43*$F$57 -> 239.17421 | AT43: =AR43+AS43 -> 1947.5614 | AU43: =ROUNDUP(AT43/C43,0) -> 75
B44: Window Washer 35cm | C44: =L44+N44+P44+R44+T44+V44+X44+Z44+AB44+AD44+AF44+AH44+AJ44+AL44 -> 30 | D44: 2 | E44: 95 | F44: =E44/D44 -> 47.5 | G44: =C44*F44 -> 1425 | I44: =C44-(L44+N44+P44+R44+T44+V44+X44+Z44+AB44+AD44+AF44+AH44+AJ44+AL44) -> 0 | J44: =G44-(M44+O44+Q44+S44+U44+W44+Y44+AA44+AC44+AE44+AG44+AI44+AK44+AM44) -> 0 | L44: 5 | M44: =F44*L44 -> 237.5 | N44: 2 | O44: =N44*F44 -> 95 | P44: 2 | Q44: =P44*F44 -> 95 | R44: 5 | S44: =R44*F44 -> 237.5 | T44: 2 | U44: =T44*F44 -> 95 | V44: 1 | W44: =V44*F44 -> 47.5 | X44: 1 | Y44: =X44*F44 -> 47.5 | Z44: 1 | AA44: =Z44*F44 -> 47.5 | AB44: 1 | AC44: =AB44*F44 -> 47.5 | AD44: 5 | AE44: =AD44*F44 -> 237.5 | AG44: =AF44*F44 -> 0 | AI44: =AH44*F44 -> 0 | AK44: =AJ44*F44 -> 0 | AL44: 5 | AM44: =AL44*F44 -> 237.5 | AN44: =M44+O44+Q44+S44+U44+W44+Y44+AA44+AC44+AE44+AG44+AI44+AK44+AM44 -> 1425 | AO44: =AN44*$F$53 -> 114 | AP44: =AN44+AO44 -> 1539 | AQ44: =AP44*$F$55 -> 21.546 | AR44: =AP44+AQ44 -> 1560.546 | AS44: =AR44*$F$57 -> 218.47644 | AT44: =AR44+AS44 -> 1779.0224 | AU44: =ROUNDUP(AT44/C44,0) -> 60
B45: Spare Glass Squeezer 35cm | C45: =L45+N45+P45+R45+T45+V45+X45+Z45+AB45+AD45+AF45+AH45+AJ45+AL45 -> 30 | D45: 1 | E45: 35 | F45: =E45/D45 -> 35 | G45: =C45*F45 -> 1050 | I45: =C45-(L45+N45+P45+R45+T45+V45+X45+Z45+AB45+AD45+AF45+AH45+AJ45+AL45) -> 0 | J45: =G45-(M45+O45+Q45+S45+U45+W45+Y45+AA45+AC45+AE45+AG45+AI45+AK45+AM45) -> 0 | L45: 5 | M45: =F45*L45 -> 175 | N45: 2 | O45: =N45*F45 -> 70 | P45: 2 | Q45: =P45*F45 -> 70 | R45: 5 | S45: =R45*F45 -> 175 | T45: 2 | U45: =T45*F45 -> 70 | V45: 1 | W45: =V45*F45 -> 35 | X45: 1 | Y45: =X45*F45 -> 35 | Z45: 1 | AA45: =Z45*F45 -> 35 | AB45: 1 | AC45: =AB45*F45 -> 35 | AD45: 5 | AE45: =AD45*F45 -> 175 | AG45: =AF45*F45 -> 0 | AI45: =AH45*F45 -> 0 | AK45: =AJ45*F45 -> 0 | AL45: 5 | AM45: =AL45*F45 -> 175 | AN45: =M45+O45+Q45+S45+U45+W45+Y45+AA45+AC45+AE45+AG45+AI45+AK45+AM45 -> 1050 | AO45: =AN45*$F$53 -> 84 | AP45: =AN45+AO45 -> 1134 | AQ45: =AP45*$F$55 -> 15.876 | AR45: =AP45+AQ45 -> 1149.876 | AS45: =AR45*$F$57 -> 160.98264 | AT45: =AR45+AS45 -> 1310.8586 | AU45: =ROUNDUP(AT45/C45,0) -> 44
B46: Spare Window Washer 35cm | C46: =L46+N46+P46+R46+T46+V46+X46+Z46+AB46+AD46+AF46+AH46+AJ46+AL46 -> 30 | D46: 1 | E46: 45 | F46: =E46/D46 -> 45 | G46: =C46*F46 -> 1350 | I46: =C46-(L46+N46+P46+R46+T46+V46+X46+Z46+AB46+AD46+AF46+AH46+AJ46+AL46) -> 0 | J46: =G46-(M46+O46+Q46+S46+U46+W46+Y46+AA46+AC46+AE46+AG46+AI46+AK46+AM46) -> 0 | L46: 5 | M46: =F46*L46 -> 225 | N46: 2 | O46: =N46*F46 -> 90 | P46: 2 | Q46: =P46*F46 -> 90 | R46: 5 | S46: =R46*F46 -> 225 | T46: 2 | U46: =T46*F46 -> 90 | V46: 1 | W46: =V46*F46 -> 45 | X46: 1 | Y46: =X46*F46 -> 45 | Z46: 1 | AA46: =Z46*F46 -> 45 | AB46: 1 | AC46: =AB46*F46 -> 45 | AD46: 5 | AE46: =AD46*F46 -> 225 | AG46: =AF46*F46 -> 0 | AI46: =AH46*F46 -> 0 | AK46: =AJ46*F46 -> 0 | AL46: 5 | AM46: =AL46*F46 -> 225 | AN46: =M46+O46+Q46+S46+U46+W46+Y46+AA46+AC46+AE46+AG46+AI46+AK46+AM46 -> 1350 | AO46: =AN46*$F$53 -> 108 | AP46: =AN46+AO46 -> 1458 | AQ46: =AP46*$F$55 -> 20.412 | AR46: =AP46+AQ46 -> 1478.412 | AS46: =AR46*$F$57 -> 206.97768 | AT46: =AR46+AS46 -> 1685.3897 | AU46: =ROUNDUP(AT46/C46,0) -> 57
B47: Red Pads 17mm | C47: =L47+N47+P47+R47+T47+V47+X47+Z47+AB47+AD47+AF47+AH47+AJ47+AL47 -> 7 | D47: 1 | E47: 390 | F47: =E47/D47 -> 390 | G47: =C47*F47 -> 2730 | I47: =C47-(L47+N47+P47+R47+T47+V47+X47+Z47+AB47+AD47+AF47+AH47+AJ47+AL47) -> 0 | J47: =G47-(M47+O47+Q47+S47+U47+W47+Y47+AA47+AC47+AE47+AG47+AI47+AK47+AM47) -> 0 | L47: 1 | M47: =F47*L47 -> 390 | N47: 1 | O47: =N47*F47 -> 390 | P47: 1 | Q47: =P47*F47 -> 390 | R47: 1 | S47: =R47*F47 -> 390 | U47: =T47*F47 -> 0 | W47: =V47*F47 -> 0 | Y47: =X47*F47 -> 0 | AA47: =Z47*F47 -> 0 | AC47: =AB47*F47 -> 0 | AD47: 1 | AE47: =AD47*F47 -> 390 | AG47: =AF47*F47 -> 0 | AI47: =AH47*F47 -> 0 | AK47: =AJ47*F47 -> 0 | AL47: 2 | AM47: =AL47*F47 -> 780 | AN47: =M47+O47+Q47+S47+U47+W47+Y47+AA47+AC47+AE47+AG47+AI47+AK47+AM47 -> 2730 | AO47: =AN47*$F$53 -> 218.4 | AP47: =AN47+AO47 -> 2948.4 | AQ47: =AP47*$F$55 -> 41.2776 | AR47: =AP47+AQ47 -> 2989.6776 | AS47: =AR47*$F$57 -> 418.55486 | AT47: =AR47+AS47 -> 3408.2325 | AU47: =ROUNDUP(AT47/C47,0) -> 487
B48: White Pads 17mm | C48: =L48+N48+P48+R48+T48+V48+X48+Z48+AB48+AD48+AF48+AH48+AJ48+AL48 -> 7 | D48: 1 | E48: 390 | F48: =E48/D48 -> 390 | G48: =C48*F48 -> 2730 | I48: =C48-(L48+N48+P48+R48+T48+V48+X48+Z48+AB48+AD48+AF48+AH48+AJ48+AL48) -> 0 | J48: =G48-(M48+O48+Q48+S48+U48+W48+Y48+AA48+AC48+AE48+AG48+AI48+AK48+AM48) -> 0 | L48: 1 | M48: =F48*L48 -> 390 | N48: 1 | O48: =N48*F48 -> 390 | P48: 1 | Q48: =P48*F48 -> 390 | R48: 1 | S48: =R48*F48 -> 390 | U48: =T48*F48 -> 0 | W48: =V48*F48 -> 0 | Y48: =X48*F48 -> 0 | AA48: =Z48*F48 -> 0 | AC48: =AB48*F48 -> 0 | AD48: 1 | AE48: =AD48*F48 -> 390 | AG48: =AF48*F48 -> 0 | AI48: =AH48*F48 -> 0 | AK48: =AJ48*F48 -> 0 | AL48: 2 | AM48: =AL48*F48 -> 780 | AN48: =M48+O48+Q48+S48+U48+W48+Y48+AA48+AC48+AE48+AG48+AI48+AK48+AM48 -> 2730 | AO48: =AN48*$F$53 -> 218.4 | AP48: =AN48+AO48 -> 2948.4 | AQ48: =AP48*$F$55 -> 41.2776 | AR48: =AP48+AQ48 -> 2989.6776 | AS48: =AR48*$F$57 -> 418.55486 | AT48: =AR48+AS48 -> 3408.2325 | AU48: =ROUNDUP(AT48/C48,0) -> 487
B49: Black Pads 17mm | C49: =L49+N49+P49+R49+T49+V49+X49+Z49+AB49+AD49+AF49+AH49+AJ49+AL49 -> 5 | D49: 1 | E49: 390 | F49: =E49/D49 -> 390 | G49: =C49*F49 -> 1950 | I49: =C49-(L49+N49+P49+R49+T49+V49+X49+Z49+AB49+AD49+AF49+AH49+AJ49+AL49) -> 0 | J49: =G49-(M49+O49+Q49+S49+U49+W49+Y49+AA49+AC49+AE49+AG49+AI49+AK49+AM49) -> 0 | L49: 1 | M49: =F49*L49 -> 390 | O49: =N49*F49 -> 0 | Q49: =P49*F49 -> 0 | R49: 1 | S49: =R49*F49 -> 390 | U49: =T49*F49 -> 0 | W49: =V49*F49 -> 0 | Y49: =X49*F49 -> 0 | AA49: =Z49*F49 -> 0 | AC49: =AB49*F49 -> 0 | AD49: 1 | AE49: =AD49*F49 -> 390 | AG49: =AF49*F49 -> 0 | AI49: =AH49*F49 -> 0 | AK49: =AJ49*F49 -> 0 | AL49: 2 | AM49: =AL49*F49 -> 780 | AN49: =M49+O49+Q49+S49+U49+W49+Y49+AA49+AC49+AE49+AG49+AI49+AK49+AM49 -> 1950 | AO49: =AN49*$F$53 -> 156 | AP49: =AN49+AO49 -> 2106 | AQ49: =AP49*$F$55 -> 29.484 | AR49: =AP49+AQ49 -> 2135.484 | AS49: =AR49*$F$57 -> 298.96776 | AT49: =AR49+AS49 -> 2434.4518 | AU49: =ROUNDUP(AT49/C49,0) -> 487
B50: Electric Cable | C50: =L50+N50+P50+R50+T50+V50+X50+Z50+AB50+AD50+AF50+AH50+AJ50+AL50 -> 10 | D50: 12 | E50: 2250 | F50: =E50/D50 -> 187.5 | G50: =C50*F50 -> 1875 | I50: =C50-(L50+N50+P50+R50+T50+V50+X50+Z50+AB50+AD50+AF50+AH50+AJ50+AL50) -> 0 | J50: =G50-(M50+O50+Q50+S50+U50+W50+Y50+AA50+AC50+AE50+AG50+AI50+AK50+AM50) -> 0 | L50: 2 | M50: =F50*L50 -> 375 | N50: 1 | O50: =N50*F50 -> 187.5 | P50: 1 | Q50: =P50*F50 -> 187.5 | R50: 2 | S50: =R50*F50 -> 375 | U50: =T50*F50 -> 0 | W50: =V50*F50 -> 0 | Y50: =X50*F50 -> 0 | AA50: =Z50*F50 -> 0 | AC50: =AB50*F50 -> 0 | AD50: 2 | AE50: =AD50*F50 -> 375 | AG50: =AF50*F50 -> 0 | AI50: =AH50*F50 -> 0 | AK50: =AJ50*F50 -> 0 | AL50: 2 | AM50: =AL50*F50 -> 375 | AN50: =M50+O50+Q50+S50+U50+W50+Y50+AA50+AC50+AE50+AG50+AI50+AK50+AM50 -> 1875 | AO50: =AN50*$F$53 -> 150 | AP50: =AN50+AO50 -> 2025 | AQ50: =AP50*$F$55 -> 28.35 | AR50: =AP50+AQ50 -> 2053.35 | AS50: =AR50*$F$57 -> 287.469 | AT50: =AR50+AS50 -> 2340.819 | AU50: =ROUNDUP(AT50/C50,0) -> 235
B51: Hose 50 m | C51: =L51+N51+P51+R51+T51+V51+X51+Z51+AB51+AD51+AF51+AH51+AJ51+AL51 -> 5 | D51: 3 | E51: 1200 | F51: =E51/D51 -> 400 | G51: =C51*F51 -> 2000 | I51: =C51-(L51+N51+P51+R51+T51+V51+X51+Z51+AB51+AD51+AF51+AH51+AJ51+AL51) -> 0 | J51: =G51-(M51+O51+Q51+S51+U51+W51+Y51+AA51+AC51+AE51+AG51+AI51+AK51+AM51) -> 0 | L51: 1 | M51: =F51*L51 -> 400 | O51: =N51*F51 -> 0 | Q51: =P51*F51 -> 0 | R51: 1 | S51: =R51*F51 -> 400 | U51: =T51*F51 -> 0 | W51: =V51*F51 -> 0 | Y51: =X51*F51 -> 0 | AA51: =Z51*F51 -> 0 | AC51: =AB51*F51 -> 0 | AD51: 2 | AE51: =AD51*F51 -> 800 | AG51: =AF51*F51 -> 0 | AI51: =AH51*F51 -> 0 | AK51: =AJ51*F51 -> 0 | AL51: 1 | AM51: =AL51*F51 -> 400 | AN51: =M51+O51+Q51+S51+U51+W51+Y51+AA51+AC51+AE51+AG51+AI51+AK51+AM51 -> 2000 | AO51: =AN51*$F$53 -> 160 | AP51: =AN51+AO51 -> 2160 | AQ51: =AP51*$F$55 -> 30.24 | AR51: =AP51+AQ51 -> 2190.24 | AS51: =AR51*$F$57 -> 306.6336 | AT51: =AR51+AS51 -> 2496.8736 | AU51: =ROUNDUP(AT51/C51,0) -> 500
B52: Total Cost | G52: =SUM(G6:G51) -> 448150.28 | I52: =C52-(L52+N52+P52+R52+T52+V52+X52+Z52+AB52+AD52+AF52+AH52+AJ52+AL52) -> 0 | J52: =G52-(M52+O52+Q52+S52+U52+W52+Y52+AA52+AC52+AE52+AG52+AI52+AK52+AM52) -> 0 | M52: =SUM(M6:M51) -> 75883.604 | O52: =SUM(O6:O51) -> 40131.834 | Q52: =SUM(Q6:Q51) -> 41549.942 | S52: =SUM(S6:S51) -> 73702.856 | U52: =SUM(U6:U51) -> 16526.184 | W52: =SUM(W6:W51) -> 13030.725 | Y52: =SUM(Y6:Y51) -> 10375.266 | AA52: =SUM(AA6:AA51) -> 12655.725 | AC52: =SUM(AC6:AC51) -> 11905.725 | AE52: =SUM(AE6:AE51) -> 35356.256 | AG52: =SUM(AG6:AG51) -> 4262.6812 | AI52: =SUM(AI6:AI51) -> 15687.754 | AK52: =SUM(AK6:AK51) -> 3044.6256 | AM52: =SUM(AM6:AM51) -> 94037.101 | AN52: =SUM(AN6:AN51) -> 448150.28 | AO52: =SUM(AO6:AO51) -> 35852.022 | AP52: =SUM(AP6:AP51) -> 484002.3 | AQ52: =SUM(AQ6:AQ51) -> 3545.3922 | AR52: =SUM(AR6:AR51) -> 487547.69 | AS52: =SUM(AS6:AS51) -> 68256.677 | AT52: =SUM(AT6:AT51) -> 555804.37
B53: Gross Margin & Contingency | F53: ='HK Budget (2)'!C14 -> 0.08 | G53: =G52*$F$53 -> 35852.022 | J53: =G53-(M53+O53+Q53+S53+U53+W53+Y53+AA53+AC53+AE53+AG53+AI53+AK53+AM53) -> 0 | M53: =M52*$F$53 -> 6070.6883 | O53: =O52*$F$53 -> 3210.5467 | Q53: =Q52*$F$53 -> 3323.9954 | S53: =S52*$F$53 -> 5896.2285 | U53: =U52*$F$53 -> 1322.0947 | W53: =W52*$F$53 -> 1042.458 | Y53: =Y52*$F$53 -> 830.02126 | AA53: =AA52*$F$53 -> 1012.458 | AC53: =AC52*$F$53 -> 952.45797 | AE53: =AE52*$F$53 -> 2828.5005 | AG53: =AG52*$F$53 -> 341.01449 | AI53: =AI52*$F$53 -> 1255.0203 | AK53: =AK52*$F$53 -> 243.57005 | AM53: =AM52*$F$53 -> 7522.9681
B54: Total | G54: =G52+G53 -> 484002.3 | J54: =G54-(M54+O54+Q54+S54+U54+W54+Y54+AA54+AC54+AE54+AG54+AI54+AK54+AM54) -> 0 | M54: =M52+M53 -> 81954.293 | O54: =O52+O53 -> 43342.381 | Q54: =Q52+Q53 -> 44873.938 | S54: =S52+S53 -> 79599.084 | U54: =U52+U53 -> 17848.278 | W54: =W52+W53 -> 14073.183 | Y54: =Y52+Y53 -> 11205.287 | AA54: =AA52+AA53 -> 13668.183 | AC54: =AC52+AC53 -> 12858.183 | AE54: =AE52+AE53 -> 38184.757 | AG54: =AG52+AG53 -> 4603.6957 | AI54: =AI52+AI53 -> 16942.774 | AK54: =AK52+AK53 -> 3288.1957 | AM54: =AM52+AM53 -> 101560.07
B55: Insurance | F55: ='HK Budget (2)'!C16 -> 0.014 | G55: =G54*$F$55 -> 6776.0322 | J55: =G55-(M55+O55+Q55+S55+U55+W55+Y55+AA55+AC55+AE55+AG55+AI55+AK55+AM55) -> 0 | M55: =M54*$F$55 -> 1147.3601 | O55: =O54*$F$55 -> 606.79333 | Q55: =Q54*$F$55 -> 628.23513 | S55: =S54*$F$55 -> 1114.3872 | U55: =U54*$F$55 -> 249.8759 | W55: =W54*$F$55 -> 197.02456 | Y55: =Y54*$F$55 -> 156.87402 | AA55: =AA54*$F$55 -> 191.35456 | AC55: =AC54*$F$55 -> 180.01456 | AE55: =AE54*$F$55 -> 534.58659 | AG55: =AG54*$F$55 -> 64.451739 | AI55: =AI54*$F$55 -> 237.19883 | AK55: =AK54*$F$55 -> 46.034739 | AM55: =AM54*$F$55 -> 1421.841
B56: Total Revenue | G56: =G54+G55 -> 490778.33 | J56: =G56-(M56+O56+Q56+S56+U56+W56+Y56+AA56+AC56+AE56+AG56+AI56+AK56+AM56) -> 0 | M56: =M54+M55 -> 83101.653 | O56: =O54+O55 -> 43949.174 | Q56: =Q54+Q55 -> 45502.173 | S56: =S54+S55 -> 80713.472 | U56: =U54+U55 -> 18098.154 | W56: =W54+W55 -> 14270.207 | Y56: =Y54+Y55 -> 11362.161 | AA56: =AA54+AA55 -> 13859.537 | AC56: =AC54+AC55 -> 13038.197 | AE56: =AE54+AE55 -> 38719.343 | AG56: =AG54+AG55 -> 4668.1474 | AI56: =AI54+AI55 -> 17179.973 | AK56: =AK54+AK55 -> 3334.2304 | AM56: =AM54+AM55 -> 102981.91
B57: VAT | F57: 0.14 | G57: =G56*$F$57 -> 68708.967 | J57: =G57-(M57+O57+Q57+S57+U57+W57+Y57+AA57+AC57+AE57+AG57+AI57+AK57+AM57) -> 0 | M57: =M56*$F$57 -> 11634.231 | O57: =O56*$F$57 -> 6152.8844 | Q57: =Q56*$F$57 -> 6370.3042 | S57: =S56*$F$57 -> 11299.886 | U57: =U56*$F$57 -> 2533.7416 | W57: =W56*$F$57 -> 1997.829 | Y57: =Y56*$F$57 -> 1590.7025 | AA57: =AA56*$F$57 -> 1940.3352 | AC57: =AC56*$F$57 -> 1825.3476 | AE57: =AE56*$F$57 -> 5420.708 | AG57: =AG56*$F$57 -> 653.54063 | AI57: =AI56*$F$57 -> 2405.1962 | AK57: =AK56*$F$57 -> 466.79225 | AM57: =AM56*$F$57 -> 14417.467
B58: Total W VAT | G58: =G56+G57 -> 559487.3 | J58: =G58-(M58+O58+Q58+S58+U58+W58+Y58+AA58+AC58+AE58+AG58+AI58+AK58+AM58) -> 0 | M58: =M56+M57 -> 94735.884 | O58: =O56+O57 -> 50102.059 | Q58: =Q56+Q57 -> 51872.477 | S58: =S56+S57 -> 92013.358 | U58: =U56+U57 -> 20631.896 | W58: =W56+W57 -> 16268.036 | Y58: =Y56+Y57 -> 12952.864 | AA58: =AA56+AA57 -> 15799.872 | AC58: =AC56+AC57 -> 14863.545 | AE58: =AE56+AE57 -> 44140.051 | AG58: =AG56+AG57 -> 5321.688 | AI58: =AI56+AI57 -> 19585.169 | AK58: =AK56+AK57 -> 3801.0226 | AM58: =AM56+AM57 -> 117399.38
G61: ='Consumables Cost '!G39 -> 89119.661
AM62: =AM58+'Consumables Cost '!AM39 -> 135532.92
E64: =E76+E77+F73+F74 -> 648606.96 | G64: =G58+G61 -> 648606.96 | AM64: =#REF!+#REF!+#REF!+#REF!+#REF!+#REF!+#REF!+#REF!+#REF!+#REF!+#REF!+#REF! -> #REF!
F65: =E64-F75 -> 213481.96 | G65: 0.3 | L65: =F65*G65 -> 64044.588 | M65: =F65*L66 -> 149437.37
L66: =1-G65 -> 0.7 | AM66: =AM62-AM64 -> #REF!
E67: Consumables | F67: Equipment
B68: All Locations | E68: ='Consumables Cost '!G39-'Consumables Cost '!AM39 -> 70986.116 | F68: =G58-AM58 -> 442087.92 | G68: =E68+F68 -> 513074.04
B69: Sales | E69: ='Consumables Cost '!AM39 -> 18133.545 | F69: =AM58 -> 117399.38 | G69: =E69+F69 -> 135532.92
E70: =E68+E69 -> 89119.661 | F70: =F68+F69 -> 559487.3 | G70: =E70+F70 -> 648606.96
AH71: =G58+'Consumables Cost '!G39 -> 648606.96 | AI71: 762207.81 | AK71: =AH71-AI71 -> -113600.85
B73: All Locations Items | F73: ='BOQ Basic -Residential'!D21+'BOQ Basic -Residential'!D22+'BOQ Basic -Residential'!D23+'BOQ Basic -Residential'!D24+'BOQ Basic -Residential'!D25+'BOQ Basic -Residential'!D26+'BOQ Basic -Residential'!D27+'BOQ Basic -Residential'!D28+'BOQ Basic -Residential'!D29+'BOQ Basic -Residential'!D30+'BOQ Basic -Residential'!D31+'BOQ Basic -Residential'!D32+'BOQ Basic -Residential'!D33 -> 422002 | G73: =F68-F73 -> 20085.921 | AH73: =#REF!+#REF!+#REF!+#REF!+#REF!+#REF!+#REF!+#REF!+#REF!+#REF!+#REF!+#REF!+#REF! -> #REF! | AI73: =G58-(AH74+AI74) -> #REF! | AJ73: =AH71-(AI73+AI74+AJ74) -> #REF! | AK73: =AJ73+AJ74+AK71 -> #REF!
B74: Sales Items | F74: ='BOQ Basic -Residential'!D35+'BOQ Basic -Residential'!D36+'BOQ Basic -Residential'!D37+'BOQ Basic -Residential'!D38+'BOQ Basic -Residential'!D39+'BOQ Basic -Residential'!D40+'BOQ Basic -Residential'!D41+'BOQ Basic -Residential'!D42+'BOQ Basic -Residential'!D43+'BOQ Basic -Residential'!D44+'BOQ Basic -Residential'!D45+'BOQ Basic -Residential'!D46 -> 13123 | G74: =F69-F74 -> 104276.38 | AH74: =#REF!+#REF!+#REF!+#REF!+#REF!+#REF!+#REF!+#REF!+#REF!+#REF!+#REF!+#REF! -> #REF! | AI74: =AM58-(AM18+AM19+AM20) -> 52689.233 | AJ74: ='Consumables Cost '!AM39 -> 18133.545
F75: =SUM(F73:F74) -> 435125
E76: =E68+G73 -> 91072.037
E77: =E69+G74 -> 122409.92 | F77: =E77-AM18+AM19+AM20 -> 142047.6 | AH77: =AH71-(AH73+AH74) -> #REF!
E79: 196009 | F79: =E64-E79 -> 452597.96

Sheet Consumables Cost 
L3: 27.213948 | M3: 0 | N3: 13.708038 | O3: 0 | P3: 14.359338 | Q3: 0 | R3: 26.607565 | S3: 0 | T3: 6.2777778 | U3: 0 | V3: 4.7936508 | W3: 0 | X3: 3.5952381 | Y3: 0 | Z3: 4.7222222 | AA3: 0 | AB3: 4.7222222 | AC3: 0 | AD3: 12.555556 | AE3: 0 | AF3: 1.1805556 | AG3: 0 | AH3: 7.0833333 | AI3: 0 | AJ3: 1.1805556 | AK3: 0 | AL3: 34 | AM3: 0
B4: Items | C4: Head Count | D4: Depreciation / Month | E4: Price | F4: Unit Monthly Cost | G4: Total Amount/ Month | L4: Sierras | N4: Alto | P4: Aurora | R4: Fourteen | T4: Reyna | V4: Eleva | X4: Isadore | Z4: Alba's Aliyah | AB4: Alba's Spendia | AD4: Commercial Area "UTC-Golf club house | AF4: Public Roads | AH4: Crossing gates | AJ4: Mobilization areas " water station " | AL4: Managament"sales center" | AN4: Total Cost | AO4: Gross Margin | AP4: Total | AQ4: Contingency | AR4: Total | AS4: VAT | AT4: Total W VAT | AU4: Unit Rate
L5: QTY | M5: Monthly Cost | N5: Head Count | O5: Monthly Cost | P5: Head Count | Q5: Monthly Cost | R5: Head Count | S5: Monthly Cost | T5: Head Count | U5: Monthly Cost | V5: Head Count | W5: Monthly Cost | X5: Head Count | Y5: Monthly Cost | Z5: Head Count | AA5: Monthly Cost | AB5: Head Count | AC5: Monthly Cost | AD5: Head Count | AE5: Monthly Cost | AF5: Head Count | AG5: Monthly Cost | AH5: Head Count | AI5: Monthly Cost | AJ5: Head Count | AK5: Monthly Cost | AL5: Head Count | AM5: Monthly Cost
B6: Liquid Soap TCL | C6: =L6+N6+P6+R6+T6+V6+X6+Z6+AB6+AD6+AF6+AH6+AJ6+AL6 -> 50 | D6: 1 | E6: 110 | F6: =E6/D6 -> 110 | G6: =C6*F6 -> 5500 | I6: =C6-(L6+N6+P6+R6+T6+V6+X6+Z6+AB6+AD6+AF6+AH6+AJ6+AL6) -> 0 | J6: =G6-(M6+O6+Q6+S6+U6+W6+Y6+AA6+AC6+AE6+AG6+AI6+AK6+AM6) -> 0 | L6: 10 | M6: =F6*L6 -> 1100 | N6: 5 | O6: =N6*F6 -> 550 | P6: 5 | Q6: =P6*F6 -> 550 | R6: 10 | S6: =R6*F6 -> 1100 | U6: =T6*F6 -> 0 | W6: =V6*F6 -> 0 | Y6: =X6*F6 -> 0 | AA6: =Z6*F6 -> 0 | AC6: =AB6*F6 -> 0 | AD6: 10 | AE6: =AD6*F6 -> 1100 | AG6: =AF6*F6 -> 0 | AI6: =AH6*F6 -> 0 | AK6: =AJ6*F6 -> 0 | AL6: 10 | AM6: =AL6*F6 -> 1100 | AN6: =M6+O6+Q6+S6+U6+W6+Y6+AA6+AC6+AE6+AG6+AI6+AK6+AM6 -> 5500 | AO6: =AN6*$F$34 -> 440 | AP6: =AN6+AO6 -> 5940 | AQ6: =AP6*$F$36 -> 83.16 | AR6: =AP6+AQ6 -> 6023.16 | AS6: =AR6*$F$38 -> 843.2424 | AT6: =AR6+AS6 -> 6866.4024 | AU6: =AT6/C6 -> 137.32805
B7: Liquid Soap | C7: =L7+N7+P7+R7+T7+V7+X7+Z7+AB7+AD7+AF7+AH7+AJ7+AL7 -> 120 | D7: 1 | E7: 65 | F7: =E7/D7 -> 65 | G7: =C7*F7 -> 7800 | I7: =C7-(L7+N7+P7+R7+T7+V7+X7+Z7+AB7+AD7+AF7+AH7+AJ7+AL7) -> 0 | J7: =G7-(M7+O7+Q7+S7+U7+W7+Y7+AA7+AC7+AE7+AG7+AI7+AK7+AM7) -> 0 | L7: 20 | M7: =F7*L7 -> 1300 | N7: 10 | O7: =N7*F7 -> 650 | P7: 10 | Q7: =P7*F7 -> 650 | R7: 20 | S7: =R7*F7 -> 1300 | T7: 5 | U7: =T7*F7 -> 325 | V7: 5 | W7: =V7*F7 -> 325 | X7: 5 | Y7: =X7*F7 -> 325 | Z7: 5 | AA7: =Z7*F7 -> 325 | AB7: 5 | AC7: =AB7*F7 -> 325 | AD7: 10 | AE7: =AD7*F7 -> 650 | AG7: =AF7*F7 -> 0 | AH7: 5 | AI7: =AH7*F7 -> 325 | AK7: =AJ7*F7 -> 0 | AL7: 20 | AM7: =AL7*F7 -> 1300 | AN7: =M7+O7+Q7+S7+U7+W7+Y7+AA7+AC7+AE7+AG7+AI7+AK7+AM7 -> 7800 | AO7: =AN7*$F$34 -> 624 | AP7: =AN7+AO7 -> 8424 | AQ7: =AP7*$F$36 -> 117.936 | AR7: =AP7+AQ7 -> 8541.936 | AS7: =AR7*$F$38 -> 1195.871 | AT7: =AR7+AS7 -> 9737.807 | AU7: =AT7/C7 -> 81.148392
B8: Liquid Air Freshener TCL | C8: =L8+N8+P8+R8+T8+V8+X8+Z8+AB8+AD8+AF8+AH8+AJ8+AL8 -> 40 | D8: 1 | E8: 60 | F8: =E8/D8 -> 60 | G8: =C8*F8 -> 2400 | I8: =C8-(L8+N8+P8+R8+T8+V8+X8+Z8+AB8+AD8+AF8+AH8+AJ8+AL8) -> 0 | J8: =G8-(M8+O8+Q8+S8+U8+W8+Y8+AA8+AC8+AE8+AG8+AI8+AK8+AM8) -> 0 | L8: 10 | M8: =F8*L8 -> 600 | N8: 5 | O8: =N8*F8 -> 300 | P8: 5 | Q8: =P8*F8 -> 300 | R8: 10 | S8: =R8*F8 -> 600 | U8: =T8*F8 -> 0 | W8: =V8*F8 -> 0 | Y8: =X8*F8 -> 0 | AA8: =Z8*F8 -> 0 | AC8: =AB8*F8 -> 0 | AD8: 10 | AE8: =AD8*F8 -> 600 | AG8: =AF8*F8 -> 0 | AI8: =AH8*F8 -> 0 | AK8: =AJ8*F8 -> 0 | AM8: =AL8*F8 -> 0 | AN8: =M8+O8+Q8+S8+U8+W8+Y8+AA8+AC8+AE8+AG8+AI8+AK8+AM8 -> 2400 | AO8: =AN8*$F$34 -> 192 | AP8: =AN8+AO8 -> 2592 | AQ8: =AP8*$F$36 -> 36.288 | AR8: =AP8+AQ8 -> 2628.288 | AS8: =AR8*$F$38 -> 367.96032 | AT8: =AR8+AS8 -> 2996.2483 | AU8: =AT8/C8 -> 74.906208
B9: Glass Cleaner TCL | C9: =L9+N9+P9+R9+T9+V9+X9+Z9+AB9+AD9+AF9+AH9+AJ9+AL9 -> 61 | D9: 1 | E9: 60 | F9: =E9/D9 -> 60 | G9: =C9*F9 -> 3660 | I9: =C9-(L9+N9+P9+R9+T9+V9+X9+Z9+AB9+AD9+AF9+AH9+AJ9+AL9) -> 0 | J9: =G9-(M9+O9+Q9+S9+U9+W9+Y9+AA9+AC9+AE9+AG9+AI9+AK9+AM9) -> 0 | L9: 10 | M9: =F9*L9 -> 600 | N9: 5 | O9: =N9*F9 -> 300 | P9: 5 | Q9: =P9*F9 -> 300 | R9: 10 | S9: =R9*F9 -> 600 | T9: 3 | U9: =T9*F9 -> 180 | V9: 2 | W9: =V9*F9 -> 120 | X9: 2 | Y9: =X9*F9 -> 120 | Z9: 2 | AA9: =Z9*F9 -> 120 | AB9: 2 | AC9: =AB9*F9 -> 120 | AD9: 10 | AE9: =AD9*F9 -> 600 | AG9: =AF9*F9 -> 0 | AI9: =AH9*F9 -> 0 | AK9: =AJ9*F9 -> 0 | AL9: 10 | AM9: =AL9*F9 -> 600 | AN9: =M9+O9+Q9+S9+U9+W9+Y9+AA9+AC9+AE9+AG9+AI9+AK9+AM9 -> 3660 | AO9: =AN9*$F$34 -> 292.8 | AP9: =AN9+AO9 -> 3952.8 | AQ9: =AP9*$F$36 -> 55.3392 | AR9: =AP9+AQ9 -> 4008.1392 | AS9: =AR9*$F$38 -> 561.13949 | AT9: =AR9+AS9 -> 4569.2787 | AU9: =AT9/C9 -> 74.906208
B10: Sanitizer TCL | C10: =L10+N10+P10+R10+T10+V10+X10+Z10+AB10+AD10+AF10+AH10+AJ10+AL10 -> 0 | D10: 1 | E10: 135 | F10: =E10/D10 -> 135 | G10: =C10*F10 -> 0 | I10: =C10-(L10+N10+P10+R10+T10+V10+X10+Z10+AB10+AD10+AF10+AH10+AJ10+AL10) -> 0 | J10: =G10-(M10+O10+Q10+S10+U10+W10+Y10+AA10+AC10+AE10+AG10+AI10+AK10+AM10) -> 0 | M10: =F10*L10 -> 0 | O10: =N10*F10 -> 0 | Q10: =P10*F10 -> 0 | S10: =R10*F10 -> 0 | U10: =T10*F10 -> 0 | W10: =V10*F10 -> 0 | Y10: =X10*F10 -> 0 | AA10: =Z10*F10 -> 0 | AC10: =AB10*F10 -> 0 | AE10: =AD10*F10 -> 0 | AG10: =AF10*F10 -> 0 | AI10: =AH10*F10 -> 0 | AK10: =AJ10*F10 -> 0 | AM10: =AL10*F10 -> 0 | AN10: =M10+O10+Q10+S10+U10+W10+Y10+AA10+AC10+AE10+AG10+AI10+AK10+AM10 -> 0 | AO10: =AN10*$F$34 -> 0 | AP10: =AN10+AO10 -> 0 | AQ10: =AP10*$F$36 -> 0 | AR10: =AP10+AQ10 -> 0 | AS10: =AR10*$F$38 -> 0 | AT10: =AR10+AS10 -> 0 | AU10: =AT10/C10 -> #DIV/0!
B11: Wooden Polisher TCL | C11: =L11+N11+P11+R11+T11+V11+X11+Z11+AB11+AD11+AF11+AH11+AJ11+AL11 -> 25 | D11: 1 | E11: 135 | F11: =E11/D11 -> 135 | G11: =C11*F11 -> 3375 | I11: =C11-(L11+N11+P11+R11+T11+V11+X11+Z11+AB11+AD11+AF11+AH11+AJ11+AL11) -> 0 | J11: =G11-(M11+O11+Q11+S11+U11+W11+Y11+AA11+AC11+AE11+AG11+AI11+AK11+AM11) -> 0 | L11: 5 | M11: =F11*L11 -> 675 | N11: 2 | O11: =N11*F11 -> 270 | P11: 3 | Q11: =P11*F11 -> 405 | R11: 5 | S11: =R11*F11 -> 675 | U11: =T11*F11 -> 0 | W11: =V11*F11 -> 0 | Y11: =X11*F11 -> 0 | AA11: =Z11*F11 -> 0 | AC11: =AB11*F11 -> 0 | AD11: 5 | AE11: =AD11*F11 -> 675 | AG11: =AF11*F11 -> 0 | AI11: =AH11*F11 -> 0 | AK11: =AJ11*F11 -> 0 | AL11: 5 | AM11: =AL11*F11 -> 675 | AN11: =M11+O11+Q11+S11+U11+W11+Y11+AA11+AC11+AE11+AG11+AI11+AK11+AM11 -> 3375 | AO11: =AN11*$F$34 -> 270 | AP11: =AN11+AO11 -> 3645 | AQ11: =AP11*$F$36 -> 51.03 | AR11: =AP11+AQ11 -> 3696.03 | AS11: =AR11*$F$38 -> 517.4442 | AT11: =AR11+AS11 -> 4213.4742 | AU11: =AT11/C11 -> 168.53897
B12: Stainless steel Polisher TCL | C12: =L12+N12+P12+R12+T12+V12+X12+Z12+AB12+AD12+AF12+AH12+AJ12+AL12 -> 41 | D12: 1 | E12: 110 | F12: =E12/D12 -> 110 | G12: =C12*F12 -> 4510 | I12: =C12-(L12+N12+P12+R12+T12+V12+X12+Z12+AB12+AD12+AF12+AH12+AJ12+AL12) -> 0 | J12: =G12-(M12+O12+Q12+S12+U12+W12+Y12+AA12+AC12+AE12+AG12+AI12+AK12+AM12) -> 0 | L12: 5 | M12: =F12*L12 -> 550 | N12: 2 | O12: =N12*F12 -> 220 | P12: 3 | Q12: =P12*F12 -> 330 | R12: 5 | S12: =R12*F12 -> 550 | T12: 3 | U12: =T12*F12 -> 330 | V12: 2 | W12: =V12*F12 -> 220 | X12: 2 | Y12: =X12*F12 -> 220 | Z12: 2 | AA12: =Z12*F12 -> 220 | AB12: 2 | AC12: =AB12*F12 -> 220 | AD12: 10 | AE12: =AD12*F12 -> 1100 | AG12: =AF12*F12 -> 0 | AI12: =AH12*F12 -> 0 | AK12: =AJ12*F12 -> 0 | AL12: 5 | AM12: =AL12*F12 -> 550 | AN12: =M12+O12+Q12+S12+U12+W12+Y12+AA12+AC12+AE12+AG12+AI12+AK12+AM12 -> 4510 | AO12: =AN12*$F$34 -> 360.8 | AP12: =AN12+AO12 -> 4870.8 | AQ12: =AP12*$F$36 -> 68.1912 | AR12: =AP12+AQ12 -> 4938.9912 | AS12: =AR12*$F$38 -> 691.45877 | AT12: =AR12+AS12 -> 5630.45 | AU12: =AT12/C12 -> 137.32805
B13: Metallic Polisher TCL | C13: =L13+N13+P13+R13+T13+V13+X13+Z13+AB13+AD13+AF13+AH13+AJ13+AL13 -> 39 | D13: 1 | E13: 125 | F13: =E13/D13 -> 125 | G13: =C13*F13 -> 4875 | I13: =C13-(L13+N13+P13+R13+T13+V13+X13+Z13+AB13+AD13+AF13+AH13+AJ13+AL13) -> 0 | J13: =G13-(M13+O13+Q13+S13+U13+W13+Y13+AA13+AC13+AE13+AG13+AI13+AK13+AM13) -> 0 | L13: 5 | M13: =F13*L13 -> 625 | N13: 2 | O13: =N13*F13 -> 250 | P13: 3 | Q13: =P13*F13 -> 375 | R13: 5 | S13: =R13*F13 -> 625 | T13: 3 | U13: =T13*F13 -> 375 | V13: 2 | W13: =V13*F13 -> 250 | X13: 2 | Y13: =X13*F13 -> 250 | Z13: 2 | AA13: =Z13*F13 -> 250 | AB13: 5 | AC13: =AB13*F13 -> 625 | AD13: 5 | AE13: =AD13*F13 -> 625 | AG13: =AF13*F13 -> 0 | AI13: =AH13*F13 -> 0 | AK13: =AJ13*F13 -> 0 | AL13: 5 | AM13: =AL13*F13 -> 625 | AN13: =M13+O13+Q13+S13+U13+W13+Y13+AA13+AC13+AE13+AG13+AI13+AK13+AM13 -> 4875 | AO13: =AN13*$F$34 -> 390 | AP13: =AN13+AO13 -> 5265 | AQ13: =AP13*$F$36 -> 73.71 | AR13: =AP13+AQ13 -> 5338.71 | AS13: =AR13*$F$38 -> 747.4194 | AT13: =AR13+AS13 -> 6086.1294 | AU13: =AT13/C13 -> 156.0546
B14: Parquet Polisher TCL | C14: =L14+N14+P14+R14+T14+V14+X14+Z14+AB14+AD14+AF14+AH14+AJ14+AL14 -> 0 | D14: 1 | E14: 125 | F14: =E14/D14 -> 125 | G14: =C14*F14 -> 0 | I14: =C14-(L14+N14+P14+R14+T14+V14+X14+Z14+AB14+AD14+AF14+AH14+AJ14+AL14) -> 0 | J14: =G14-(M14+O14+Q14+S14+U14+W14+Y14+AA14+AC14+AE14+AG14+AI14+AK14+AM14) -> 0 | M14: =F14*L14 -> 0 | O14: =N14*F14 -> 0 | Q14: =P14*F14 -> 0 | S14: =R14*F14 -> 0 | U14: =T14*F14 -> 0 | W14: =V14*F14 -> 0 | Y14: =X14*F14 -> 0 | AA14: =Z14*F14 -> 0 | AC14: =AB14*F14 -> 0 | AE14: =AD14*F14 -> 0 | AG14: =AF14*F14 -> 0 | AI14: =AH14*F14 -> 0 | AK14: =AJ14*F14 -> 0 | AM14: =AL14*F14 -> 0 | AN14: =M14+O14+Q14+S14+U14+W14+Y14+AA14+AC14+AE14+AG14+AI14+AK14+AM14 -> 0 | AO14: =AN14*$F$34 -> 0 | AP14: =AN14+AO14 -> 0 | AQ14: =AP14*$F$36 -> 0 | AR14: =AP14+AQ14 -> 0 | AS14: =AR14*$F$38 -> 0 | AT14: =AR14+AS14 -> 0 | AU14: =AT14/C14 -> #DIV/0!
B15: Leather Polisher TCL | C15: =L15+N15+P15+R15+T15+V15+X15+Z15+AB15+AD15+AF15+AH15+AJ15+AL15 -> 10 | D15: 1 | E15: 125 | F15: =E15/D15 -> 125 | G15: =C15*F15 -> 1250 | I15: =C15-(L15+N15+P15+R15+T15+V15+X15+Z15+AB15+AD15+AF15+AH15+AJ15+AL15) -> 0 | J15: =G15-(M15+O15+Q15+S15+U15+W15+Y15+AA15+AC15+AE15+AG15+AI15+AK15+AM15) -> 0 | M15: =F15*L15 -> 0 | O15: =N15*F15 -> 0 | Q15: =P15*F15 -> 0 | S15: =R15*F15 -> 0 | U15: =T15*F15 -> 0 | W15: =V15*F15 -> 0 | Y15: =X15*F15 -> 0 | AA15: =Z15*F15 -> 0 | AC15: =AB15*F15 -> 0 | AD15: 5 | AE15: =AD15*F15 -> 625 | AG15: =AF15*F15 -> 0 | AI15: =AH15*F15 -> 0 | AK15: =AJ15*F15 -> 0 | AL15: 5 | AM15: =AL15*F15 -> 625 | AN15: =M15+O15+Q15+S15+U15+W15+Y15+AA15+AC15+AE15+AG15+AI15+AK15+AM15 -> 1250 | AO15: =AN15*$F$34 -> 100 | AP15: =AN15+AO15 -> 1350 | AQ15: =AP15*$F$36 -> 18.9 | AR15: =AP15+AQ15 -> 1368.9 | AS15: =AR15*$F$38 -> 191.646 | AT15: =AR15+AS15 -> 1560.546 | AU15: =AT15/C15 -> 156.0546
B16: Carpet Shampoo TCL | C16: =L16+N16+P16+R16+T16+V16+X16+Z16+AB16+AD16+AF16+AH16+AJ16+AL16 -> 25 | D16: 1 | E16: 125 | F16: =E16/D16 -> 125 | G16: =C16*F16 -> 3125 | I16: =C16-(L16+N16+P16+R16+T16+V16+X16+Z16+AB16+AD16+AF16+AH16+AJ16+AL16) -> 0 | J16: =G16-(M16+O16+Q16+S16+U16+W16+Y16+AA16+AC16+AE16+AG16+AI16+AK16+AM16) -> 0 | L16: 5 | M16: =F16*L16 -> 625 | N16: 2 | O16: =N16*F16 -> 250 | P16: 3 | Q16: =P16*F16 -> 375 | R16: 5 | S16: =R16*F16 -> 625 | U16: =T16*F16 -> 0 | W16: =V16*F16 -> 0 | Y16: =X16*F16 -> 0 | AA16: =Z16*F16 -> 0 | AC16: =AB16*F16 -> 0 | AD16: 5 | AE16: =AD16*F16 -> 625 | AG16: =AF16*F16 -> 0 | AI16: =AH16*F16 -> 0 | AK16: =AJ16*F16 -> 0 | AL16: 5 | AM16: =AL16*F16 -> 625 | AN16: =M16+O16+Q16+S16+U16+W16+Y16+AA16+AC16+AE16+AG16+AI16+AK16+AM16 -> 3125 | AO16: =AN16*$F$34 -> 250 | AP16: =AN16+AO16 -> 3375 | AQ16: =AP16*$F$36 -> 47.25 | AR16: =AP16+AQ16 -> 3422.25 | AS16: =AR16*$F$38 -> 479.115 | AT16: =AR16+AS16 -> 3901.365 | AU16: =AT16/C16 -> 156.0546
B17: Carpet Spot Removal TCL | C17: =L17+N17+P17+R17+T17+V17+X17+Z17+AB17+AD17+AF17+AH17+AJ17+AL17 -> 10 | D17: 1 | E17: 125 | F17: =E17/D17 -> 125 | G17: =C17*F17 -> 1250 | I17: =C17-(L17+N17+P17+R17+T17+V17+X17+Z17+AB17+AD17+AF17+AH17+AJ17+AL17) -> 0 | J17: =G17-(M17+O17+Q17+S17+U17+W17+Y17+AA17+AC17+AE17+AG17+AI17+AK17+AM17) -> 0 | M17: =F17*L17 -> 0 | O17: =N17*F17 -> 0 | Q17: =P17*F17 -> 0 | S17: =R17*F17 -> 0 | U17: =T17*F17 -> 0 | W17: =V17*F17 -> 0 | Y17: =X17*F17 -> 0 | AA17: =Z17*F17 -> 0 | AC17: =AB17*F17 -> 0 | AD17: 5 | AE17: =AD17*F17 -> 625 | AG17: =AF17*F17 -> 0 | AI17: =AH17*F17 -> 0 | AK17: =AJ17*F17 -> 0 | AL17: 5 | AM17: =AL17*F17 -> 625 | AN17: =M17+O17+Q17+S17+U17+W17+Y17+AA17+AC17+AE17+AG17+AI17+AK17+AM17 -> 1250 | AO17: =AN17*$F$34 -> 100 | AP17: =AN17+AO17 -> 1350 | AQ17: =AP17*$F$36 -> 18.9 | AR17: =AP17+AQ17 -> 1368.9 | AS17: =AR17*$F$38 -> 191.646 | AT17: =AR17+AS17 -> 1560.546 | AU17: =AT17/C17 -> 156.0546
B18: Grease Remover TCL | C18: =L18+N18+P18+R18+T18+V18+X18+Z18+AB18+AD18+AF18+AH18+AJ18+AL18 -> 30 | D18: 1 | E18: 110 | F18: =E18/D18 -> 110 | G18: =C18*F18 -> 3300 | I18: =C18-(L18+N18+P18+R18+T18+V18+X18+Z18+AB18+AD18+AF18+AH18+AJ18+AL18) -> 0 | J18: =G18-(M18+O18+Q18+S18+U18+W18+Y18+AA18+AC18+AE18+AG18+AI18+AK18+AM18) -> 0 | L18: 5 | M18: =F18*L18 -> 550 | N18: 2 | O18: =N18*F18 -> 220 | P18: 3 | Q18: =P18*F18 -> 330 | R18: 5 | S18: =R18*F18 -> 550 | U18: =T18*F18 -> 0 | W18: =V18*F18 -> 0 | Y18: =X18*F18 -> 0 | AA18: =Z18*F18 -> 0 | AC18: =AB18*F18 -> 0 | AE18: =AD18*F18 -> 0 | AF18: 5 | AG18: =AF18*F18 -> 550 | AH18: 10 | AI18: =AH18*F18 -> 1100 | AK18: =AJ18*F18 -> 0 | AM18: =AL18*F18 -> 0 | AN18: =M18+O18+Q18+S18+U18+W18+Y18+AA18+AC18+AE18+AG18+AI18+AK18+AM18 -> 3300 | AO18: =AN18*$F$34 -> 264 | AP18: =AN18+AO18 -> 3564 | AQ18: =AP18*$F$36 -> 49.896 | AR18: =AP18+AQ18 -> 3613.896 | AS18: =AR18*$F$38 -> 505.94544 | AT18: =AR18+AS18 -> 4119.8414 | AU18: =AT18/C18 -> 137.32805
B19: Rust Remover TCL | C19: =L19+N19+P19+R19+T19+V19+X19+Z19+AB19+AD19+AF19+AH19+AJ19+AL19 -> 35 | D19: 1 | E19: 95 | F19: =E19/D19 -> 95 | G19: =C19*F19 -> 3325 | I19: =C19-(L19+N19+P19+R19+T19+V19+X19+Z19+AB19+AD19+AF19+AH19+AJ19+AL19) -> 0 | J19: =G19-(M19+O19+Q19+S19+U19+W19+Y19+AA19+AC19+AE19+AG19+AI19+AK19+AM19) -> 0 | L19: 5 | M19: =F19*L19 -> 475 | N19: 2 | O19: =N19*F19 -> 190 | P19: 3 | Q19: =P19*F19 -> 285 | R19: 5 | S19: =R19*F19 -> 475 | U19: =T19*F19 -> 0 | W19: =V19*F19 -> 0 | Y19: =X19*F19 -> 0 | AA19: =Z19*F19 -> 0 | AC19: =AB19*F19 -> 0 | AD19: 10 | AE19: =AD19*F19 -> 950 | AG19: =AF19*F19 -> 0 | AI19: =AH19*F19 -> 0 | AK19: =AJ19*F19 -> 0 | AL19: 10 | AM19: =AL19*F19 -> 950 | AN19: =M19+O19+Q19+S19+U19+W19+Y19+AA19+AC19+AE19+AG19+AI19+AK19+AM19 -> 3325 | AO19: =AN19*$F$34 -> 266 | AP19: =AN19+AO19 -> 3591 | AQ19: =AP19*$F$36 -> 50.274 | AR19: =AP19+AQ19 -> 3641.274 | AS19: =AR19*$F$38 -> 509.77836 | AT19: =AR19+AS19 -> 4151.0524 | AU19: =AT19/C19 -> 118.6015
B20: Harpic | C20: =L20+N20+P20+R20+T20+V20+X20+Z20+AB20+AD20+AF20+AH20+AJ20+AL20 -> 31 | D20: 1 | E20: 85 | F20: =E20/D20 -> 85 | G20: =C20*F20 -> 2635 | I20: =C20-(L20+N20+P20+R20+T20+V20+X20+Z20+AB20+AD20+AF20+AH20+AJ20+AL20) -> 0 | J20: =G20-(M20+O20+Q20+S20+U20+W20+Y20+AA20+AC20+AE20+AG20+AI20+AK20+AM20) -> 0 | M20: =F20*L20 -> 0 | O20: =N20*F20 -> 0 | Q20: =P20*F20 -> 0 | S20: =R20*F20 -> 0 | T20: 3 | U20: =T20*F20 -> 255 | V20: 2 | W20: =V20*F20 -> 170 | X20: 2 | Y20: =X20*F20 -> 170 | Z20: 2 | AA20: =Z20*F20 -> 170 | AB20: 2 | AC20: =AB20*F20 -> 170 | AD20: 10 | AE20: =AD20*F20 -> 850 | AG20: =AF20*F20 -> 0 | AI20: =AH20*F20 -> 0 | AK20: =AJ20*F20 -> 0 | AL20: 10 | AM20: =AL20*F20 -> 850 | AN20: =M20+O20+Q20+S20+U20+W20+Y20+AA20+AC20+AE20+AG20+AI20+AK20+AM20 -> 2635 | AO20: =AN20*$F$34 -> 210.8 | AP20: =AN20+AO20 -> 2845.8 | AQ20: =AP20*$F$36 -> 39.8412 | AR20: =AP20+AQ20 -> 2885.6412 | AS20: =AR20*$F$38 -> 403.98977 | AT20: =AR20+AS20 -> 3289.631 | AU20: =AT20/C20 -> 106.11713
B21: Blue Towels 50*100 | C21: =L21+N21+P21+R21+T21+V21+X21+Z21+AB21+AD21+AF21+AH21+AJ21+AL21 -> 89 | D21: 1 | E21: 25 | F21: =E21/D21 -> 25 | G21: =C21*F21 -> 2225 | I21: =C21-(L21+N21+P21+R21+T21+V21+X21+Z21+AB21+AD21+AF21+AH21+AJ21+AL21) -> 0 | J21: =G21-(M21+O21+Q21+S21+U21+W21+Y21+AA21+AC21+AE21+AG21+AI21+AK21+AM21) -> 0 | L21: 10 | M21: =F21*L21 -> 250 | N21: 5 | O21: =N21*F21 -> 125 | P21: 5 | Q21: =P21*F21 -> 125 | R21: 10 | S21: =R21*F21 -> 250 | T21: 5 | U21: =T21*F21 -> 125 | V21: 5 | W21: =V21*F21 -> 125 | X21: 5 | Y21: =X21*F21 -> 125 | Z21: 5 | AA21: =Z21*F21 -> 125 | AB21: 5 | AC21: =AB21*F21 -> 125 | AD21: 10 | AE21: =AD21*F21 -> 250 | AF21: 2 | AG21: =AF21*F21 -> 50 | AH21: 5 | AI21: =AH21*F21 -> 125 | AJ21: 2 | AK21: =AJ21*F21 -> 50 | AL21: 15 | AM21: =AL21*F21 -> 375 | AN21: =M21+O21+Q21+S21+U21+W21+Y21+AA21+AC21+AE21+AG21+AI21+AK21+AM21 -> 2225 | AO21: =AN21*$F$34 -> 178 | AP21: =AN21+AO21 -> 2403 | AQ21: =AP21*$F$36 -> 33.642 | AR21: =AP21+AQ21 -> 2436.642 | AS21: =AR21*$F$38 -> 341.12988 | AT21: =AR21+AS21 -> 2777.7719 | AU21: =AT21/C21 -> 31.21092
B22: Yellow Towels 30*30 | C22: =L22+N22+P22+R22+T22+V22+X22+Z22+AB22+AD22+AF22+AH22+AJ22+AL22 -> 89 | D22: 1 | E22: 15 | F22: =E22/D22 -> 15 | G22: =C22*F22 -> 1335 | I22: =C22-(L22+N22+P22+R22+T22+V22+X22+Z22+AB22+AD22+AF22+AH22+AJ22+AL22) -> 0 | J22: =G22-(M22+O22+Q22+S22+U22+W22+Y22+AA22+AC22+AE22+AG22+AI22+AK22+AM22) -> 0 | L22: 10 | M22: =F22*L22 -> 150 | N22: 5 | O22: =N22*F22 -> 75 | P22: 5 | Q22: =P22*F22 -> 75 | R22: 10 | S22: =R22*F22 -> 150 | T22: 5 | U22: =T22*F22 -> 75 | V22: 5 | W22: =V22*F22 -> 75 | X22: 5 | Y22: =X22*F22 -> 75 | Z22: 5 | AA22: =Z22*F22 -> 75 | AB22: 5 | AC22: =AB22*F22 -> 75 | AD22: 10 | AE22: =AD22*F22 -> 150 | AF22: 2 | AG22: =AF22*F22 -> 30 | AH22: 5 | AI22: =AH22*F22 -> 75 | AJ22: 2 | AK22: =AJ22*F22 -> 30 | AL22: 15 | AM22: =AL22*F22 -> 225 | AN22: =M22+O22+Q22+S22+U22+W22+Y22+AA22+AC22+AE22+AG22+AI22+AK22+AM22 -> 1335 | AO22: =AN22*$F$34 -> 106.8 | AP22: =AN22+AO22 -> 1441.8 | AQ22: =AP22*$F$36 -> 20.1852 | AR22: =AP22+AQ22 -> 1461.9852 | AS22: =AR22*$F$38 -> 204.67793 | AT22: =AR22+AS22 -> 1666.6631 | AU22: =AT22/C22 -> 18.726552
B23: White Towels 30*30 | C23: =L23+N23+P23+R23+T23+V23+X23+Z23+AB23+AD23+AF23+AH23+AJ23+AL23 -> 89 | D23: 1 | E23: 25 | F23: =E23/D23 -> 25 | G23: =C23*F23 -> 2225 | I23: =C23-(L23+N23+P23+R23+T23+V23+X23+Z23+AB23+AD23+AF23+AH23+AJ23+AL23) -> 0 | J23: =G23-(M23+O23+Q23+S23+U23+W23+Y23+AA23+AC23+AE23+AG23+AI23+AK23+AM23) -> 0 | L23: 10 | M23: =F23*L23 -> 250 | N23: 5 | O23: =N23*F23 -> 125 | P23: 5 | Q23: =P23*F23 -> 125 | R23: 10 | S23: =R23*F23 -> 250 | T23: 5 | U23: =T23*F23 -> 125 | V23: 5 | W23: =V23*F23 -> 125 | X23: 5 | Y23: =X23*F23 -> 125 | Z23: 5 | AA23: =Z23*F23 -> 125 | AB23: 5 | AC23: =AB23*F23 -> 125 | AD23: 10 | AE23: =AD23*F23 -> 250 | AF23: 2 | AG23: =AF23*F23 -> 50 | AH23: 5 | AI23: =AH23*F23 -> 125 | AJ23: 2 | AK23: =AJ23*F23 -> 50 | AL23: 15 | AM23: =AL23*F23 -> 375 | AN23: =M23+O23+Q23+S23+U23+W23+Y23+AA23+AC23+AE23+AG23+AI23+AK23+AM23 -> 2225 | AO23: =AN23*$F$34 -> 178 | AP23: =AN23+AO23 -> 2403 | AQ23: =AP23*$F$36 -> 33.642 | AR23: =AP23+AQ23 -> 2436.642 | AS23: =AR23*$F$38 -> 341.12988 | AT23: =AR23+AS23 -> 2777.7719 | AU23: =AT23/C23 -> 31.21092
B24: Microfiber red color | C24: =L24+N24+P24+R24+T24+V24+X24+Z24+AB24+AD24+AF24+AH24+AJ24+AL24 -> 45 | D24: 1 | E24: 30 | F24: =E24/D24 -> 30 | G24: =C24*F24 -> 1350 | I24: =C24-(L24+N24+P24+R24+T24+V24+X24+Z24+AB24+AD24+AF24+AH24+AJ24+AL24) -> 0 | J24: =G24-(M24+O24+Q24+S24+U24+W24+Y24+AA24+AC24+AE24+AG24+AI24+AK24+AM24) -> 0 | L24: 5 | M24: =F24*L24 -> 150 | N24: 5 | O24: =N24*F24 -> 150 | P24: 5 | Q24: =P24*F24 -> 150 | R24: 5 | S24: =R24*F24 -> 150 | U24: =T24*F24 -> 0 | W24: =V24*F24 -> 0 | Y24: =X24*F24 -> 0 | AA24: =Z24*F24 -> 0 | AC24: =AB24*F24 -> 0 | AD24: 10 | AE24: =AD24*F24 -> 300 | AG24: =AF24*F24 -> 0 | AI24: =AH24*F24 -> 0 | AK24: =AJ24*F24 -> 0 | AL24: 15 | AM24: =AL24*F24 -> 450 | AN24: =M24+O24+Q24+S24+U24+W24+Y24+AA24+AC24+AE24+AG24+AI24+AK24+AM24 -> 1350 | AO24: =AN24*$F$34 -> 108 | AP24: =AN24+AO24 -> 1458 | AQ24: =AP24*$F$36 -> 20.412 | AR24: =AP24+AQ24 -> 1478.412 | AS24: =AR24*$F$38 -> 206.97768 | AT24: =AR24+AS24 -> 1685.3897 | AU24: =AT24/C24 -> 37.453104
B25: Microfiber blue color | C25: =L25+N25+P25+R25+T25+V25+X25+Z25+AB25+AD25+AF25+AH25+AJ25+AL25 -> 104 | D25: 1 | E25: 30 | F25: =E25/D25 -> 30 | G25: =C25*F25 -> 3120 | I25: =C25-(L25+N25+P25+R25+T25+V25+X25+Z25+AB25+AD25+AF25+AH25+AJ25+AL25) -> 0 | J25: =G25-(M25+O25+Q25+S25+U25+W25+Y25+AA25+AC25+AE25+AG25+AI25+AK25+AM25) -> 0 | L25: 15 | M25: =F25*L25 -> 450 | N25: 5 | O25: =N25*F25 -> 150 | P25: 5 | Q25: =P25*F25 -> 150 | R25: 20 | S25: =R25*F25 -> 600 | T25: 5 | U25: =T25*F25 -> 150 | V25: 5 | W25: =V25*F25 -> 150 | X25: 5 | Y25: =X25*F25 -> 150 | Z25: 5 | AA25: =Z25*F25 -> 150 | AB25: 5 | AC25: =AB25*F25 -> 150 | AD25: 10 | AE25: =AD25*F25 -> 300 | AF25: 2 | AG25: =AF25*F25 -> 60 | AH25: 5 | AI25: =AH25*F25 -> 150 | AJ25: 2 | AK25: =AJ25*F25 -> 60 | AL25: 15 | AM25: =AL25*F25 -> 450 | AN25: =M25+O25+Q25+S25+U25+W25+Y25+AA25+AC25+AE25+AG25+AI25+AK25+AM25 -> 3120 | AO25: =AN25*$F$34 -> 249.6 | AP25: =AN25+AO25 -> 3369.6 | AQ25: =AP25*$F$36 -> 47.1744 | AR25: =AP25+AQ25 -> 3416.7744 | AS25: =AR25*$F$38 -> 478.34842 | AT25: =AR25+AS25 -> 3895.1228 | AU25: =AT25/C25 -> 37.453104
B26: Microfiber green color | C26: =L26+N26+P26+R26+T26+V26+X26+Z26+AB26+AD26+AF26+AH26+AJ26+AL26 -> 45 | D26: 1 | E26: 30 | F26: =E26/D26 -> 30 | G26: =C26*F26 -> 1350 | I26: =C26-(L26+N26+P26+R26+T26+V26+X26+Z26+AB26+AD26+AF26+AH26+AJ26+AL26) -> 0 | J26: =G26-(M26+O26+Q26+S26+U26+W26+Y26+AA26+AC26+AE26+AG26+AI26+AK26+AM26) -> 0 | L26: 5 | M26: =F26*L26 -> 150 | N26: 5 | O26: =N26*F26 -> 150 | P26: 5 | Q26: =P26*F26 -> 150 | R26: 5 | S26: =R26*F26 -> 150 | U26: =T26*F26 -> 0 | W26: =V26*F26 -> 0 | Y26: =X26*F26 -> 0 | AA26: =Z26*F26 -> 0 | AC26: =AB26*F26 -> 0 | AD26: 10 | AE26: =AD26*F26 -> 300 | AG26: =AF26*F26 -> 0 | AI26: =AH26*F26 -> 0 | AK26: =AJ26*F26 -> 0 | AL26: 15 | AM26: =AL26*F26 -> 450 | AN26: =M26+O26+Q26+S26+U26+W26+Y26+AA26+AC26+AE26+AG26+AI26+AK26+AM26 -> 1350 | AO26: =AN26*$F$34 -> 108 | AP26: =AN26+AO26 -> 1458 | AQ26: =AP26*$F$36 -> 20.412 | AR26: =AP26+AQ26 -> 1478.412 | AS26: =AR26*$F$38 -> 206.97768 | AT26: =AR26+AS26 -> 1685.3897 | AU26: =AT26/C26 -> 37.453104
B27: Hard Sponges | C27: =L27+N27+P27+R27+T27+V27+X27+Z27+AB27+AD27+AF27+AH27+AJ27+AL27 -> 110 | D27: 1 | E27: 10 | F27: =E27/D27 -> 10 | G27: =C27*F27 -> 1100 | I27: =C27-(L27+N27+P27+R27+T27+V27+X27+Z27+AB27+AD27+AF27+AH27+AJ27+AL27) -> 0 | J27: =G27-(M27+O27+Q27+S27+U27+W27+Y27+AA27+AC27+AE27+AG27+AI27+AK27+AM27) -> 0 | L27: 15 | M27: =F27*L27 -> 150 | N27: 10 | O27: =N27*F27 -> 100 | P27: 10 | Q27: =P27*F27 -> 100 | R27: 15 | S27: =R27*F27 -> 150 | T27: 5 | U27: =T27*F27 -> 50 | V27: 5 | W27: =V27*F27 -> 50 | X27: 5 | Y27: =X27*F27 -> 50 | Z27: 5 | AA27: =Z27*F27 -> 50 | AB27: 5 | AC27: =AB27*F27 -> 50 | AD27: 10 | AE27: =AD27*F27 -> 100 | AF27: 2 | AG27: =AF27*F27 -> 20 | AH27: 5 | AI27: =AH27*F27 -> 50 | AJ27: 3 | AK27: =AJ27*F27 -> 30 | AL27: 15 | AM27: =AL27*F27 -> 150 | AN27: =M27+O27+Q27+S27+U27+W27+Y27+AA27+AC27+AE27+AG27+AI27+AK27+AM27 -> 1100 | AO27: =AN27*$F$34 -> 88 | AP27: =AN27+AO27 -> 1188 | AQ27: =AP27*$F$36 -> 16.632 | AR27: =AP27+AQ27 -> 1204.632 | AS27: =AR27*$F$38 -> 168.64848 | AT27: =AR27+AS27 -> 1373.2805 | AU27: =AT27/C27 -> 12.484368
B28: Soft Sponges | C28: =L28+N28+P28+R28+T28+V28+X28+Z28+AB28+AD28+AF28+AH28+AJ28+AL28 -> 110 | D28: 1 | E28: 10 | F28: =E28/D28 -> 10 | G28: =C28*F28 -> 1100 | I28: =C28-(L28+N28+P28+R28+T28+V28+X28+Z28+AB28+AD28+AF28+AH28+AJ28+AL28) -> 0 | J28: =G28-(M28+O28+Q28+S28+U28+W28+Y28+AA28+AC28+AE28+AG28+AI28+AK28+AM28) -> 0 | L28: 15 | M28: =F28*L28 -> 150 | N28: 10 | O28: =N28*F28 -> 100 | P28: 10 | Q28: =P28*F28 -> 100 | R28: 15 | S28: =R28*F28 -> 150 | T28: 5 | U28: =T28*F28 -> 50 | V28: 5 | W28: =V28*F28 -> 50 | X28: 5 | Y28: =X28*F28 -> 50 | Z28: 5 | AA28: =Z28*F28 -> 50 | AB28: 5 | AC28: =AB28*F28 -> 50 | AD28: 10 | AE28: =AD28*F28 -> 100 | AF28: 2 | AG28: =AF28*F28 -> 20 | AH28: 5 | AI28: =AH28*F28 -> 50 | AJ28: 3 | AK28: =AJ28*F28 -> 30 | AL28: 15 | AM28: =AL28*F28 -> 150 | AN28: =M28+O28+Q28+S28+U28+W28+Y28+AA28+AC28+AE28+AG28+AI28+AK28+AM28 -> 1100 | AO28: =AN28*$F$34 -> 88 | AP28: =AN28+AO28 -> 1188 | AQ28: =AP28*$F$36 -> 16.632 | AR28: =AP28+AQ28 -> 1204.632 | AS28: =AR28*$F$38 -> 168.64848 | AT28: =AR28+AS28 -> 1373.2805 | AU28: =AT28/C28 -> 12.484368
B29: Aluminum mesh | C29: =L29+N29+P29+R29+T29+V29+X29+Z29+AB29+AD29+AF29+AH29+AJ29+AL29 -> 45 | D29: 1 | E29: 150 | F29: =E29/D29 -> 150 | G29: =C29*F29 -> 6750 | I29: =C29-(L29+N29+P29+R29+T29+V29+X29+Z29+AB29+AD29+AF29+AH29+AJ29+AL29) -> 0 | J29: =G29-(M29+O29+Q29+S29+U29+W29+Y29+AA29+AC29+AE29+AG29+AI29+AK29+AM29) -> 0 | L29: 5 | M29: =F29*L29 -> 750 | N29: 5 | O29: =N29*F29 -> 750 | P29: 5 | Q29: =P29*F29 -> 750 | R29: 5 | S29: =R29*F29 -> 750 | U29: =T29*F29 -> 0 | W29: =V29*F29 -> 0 | Y29: =X29*F29 -> 0 | AA29: =Z29*F29 -> 0 | AC29: =AB29*F29 -> 0 | AD29: 10 | AE29: =AD29*F29 -> 1500 | AG29: =AF29*F29 -> 0 | AI29: =AH29*F29 -> 0 | AK29: =AJ29*F29 -> 0 | AL29: 15 | AM29: =AL29*F29 -> 2250 | AN29: =M29+O29+Q29+S29+U29+W29+Y29+AA29+AC29+AE29+AG29+AI29+AK29+AM29 -> 6750 | AO29: =AN29*$F$34 -> 540 | AP29: =AN29+AO29 -> 7290 | AQ29: =AP29*$F$36 -> 102.06 | AR29: =AP29+AQ29 -> 7392.06 | AS29: =AR29*$F$38 -> 1034.8884 | AT29: =AR29+AS29 -> 8426.9484 | AU29: =AT29/C29 -> 187.26552
B30: Garbage Bags 120 L | C30: =L30+N30+P30+R30+T30+V30+X30+Z30+AB30+AD30+AF30+AH30+AJ30+AL30 -> 65 | D30: 1 | E30: 45 | F30: =E30/D30 -> 45 | G30: =C30*F30 -> 2925 | I30: =C30-(L30+N30+P30+R30+T30+V30+X30+Z30+AB30+AD30+AF30+AH30+AJ30+AL30) -> 0 | J30: =G30-(M30+O30+Q30+S30+U30+W30+Y30+AA30+AC30+AE30+AG30+AI30+AK30+AM30) -> 0 | L30: 10 | M30: =F30*L30 -> 450 | N30: 5 | O30: =N30*F30 -> 225 | P30: 5 | Q30: =P30*F30 -> 225 | R30: 10 | S30: =R30*F30 -> 450 | T30: 3 | U30: =T30*F30 -> 135 | V30: 2 | W30: =V30*F30 -> 90 | X30: 2 | Y30: =X30*F30 -> 90 | Z30: 2 | AA30: =Z30*F30 -> 90 | AB30: 2 | AC30: =AB30*F30 -> 90 | AD30: 10 | AE30: =AD30*F30 -> 450 | AF30: 2 | AG30: =AF30*F30 -> 90 | AH30: 5 | AI30: =AH30*F30 -> 225 | AJ30: 2 | AK30: =AJ30*F30 -> 90 | AL30: 5 | AM30: =AL30*F30 -> 225 | AN30: =M30+O30+Q30+S30+U30+W30+Y30+AA30+AC30+AE30+AG30+AI30+AK30+AM30 -> 2925 | AO30: =AN30*$F$34 -> 234 | AP30: =AN30+AO30 -> 3159 | AQ30: =AP30*$F$36 -> 44.226 | AR30: =AP30+AQ30 -> 3203.226 | AS30: =AR30*$F$38 -> 448.45164 | AT30: =AR30+AS30 -> 3651.6776 | AU30: =AT30/C30 -> 56.179656
B31: Garbage Bags 60 L | C31: =L31+N31+P31+R31+T31+V31+X31+Z31+AB31+AD31+AF31+AH31+AJ31+AL31 -> 10 | D31: 1 | E31: 45 | F31: =E31/D31 -> 45 | G31: =C31*F31 -> 450 | I31: =C31-(L31+N31+P31+R31+T31+V31+X31+Z31+AB31+AD31+AF31+AH31+AJ31+AL31) -> 0 | J31: =G31-(M31+O31+Q31+S31+U31+W31+Y31+AA31+AC31+AE31+AG31+AI31+AK31+AM31) -> 0 | M31: =F31*L31 -> 0 | O31: =N31*F31 -> 0 | Q31: =P31*F31 -> 0 | S31: =R31*F31 -> 0 | U31: =T31*F31 -> 0 | W31: =V31*F31 -> 0 | Y31: =X31*F31 -> 0 | AA31: =Z31*F31 -> 0 | AC31: =AB31*F31 -> 0 | AE31: =AD31*F31 -> 0 | AG31: =AF31*F31 -> 0 | AI31: =AH31*F31 -> 0 | AK31: =AJ31*F31 -> 0 | AL31: 10 | AM31: =AL31*F31 -> 450 | AN31: =M31+O31+Q31+S31+U31+W31+Y31+AA31+AC31+AE31+AG31+AI31+AK31+AM31 -> 450 | AO31: =AN31*$F$34 -> 36 | AP31: =AN31+AO31 -> 486 | AQ31: =AP31*$F$36 -> 6.804 | AR31: =AP31+AQ31 -> 492.804 | AS31: =AR31*$F$38 -> 68.99256 | AT31: =AR31+AS31 -> 561.79656 | AU31: =AT31/C31 -> 56.179656
B32: Garbage Bags 20 L | C32: =L32+N32+P32+R32+T32+V32+X32+Z32+AB32+AD32+AF32+AH32+AJ32+AL32 -> 10 | D32: 1 | E32: 45 | F32: =E32/D32 -> 45 | G32: =C32*F32 -> 450 | I32: =C32-(L32+N32+P32+R32+T32+V32+X32+Z32+AB32+AD32+AF32+AH32+AJ32+AL32) -> 0 | J32: =G32-(M32+O32+Q32+S32+U32+W32+Y32+AA32+AC32+AE32+AG32+AI32+AK32+AM32) -> 0 | M32: =F32*L32 -> 0 | O32: =N32*F32 -> 0 | Q32: =P32*F32 -> 0 | S32: =R32*F32 -> 0 | U32: =T32*F32 -> 0 | W32: =V32*F32 -> 0 | Y32: =X32*F32 -> 0 | AA32: =Z32*F32 -> 0 | AC32: =AB32*F32 -> 0 | AE32: =AD32*F32 -> 0 | AG32: =AF32*F32 -> 0 | AI32: =AH32*F32 -> 0 | AK32: =AJ32*F32 -> 0 | AL32: 10 | AM32: =AL32*F32 -> 450 | AN32: =M32+O32+Q32+S32+U32+W32+Y32+AA32+AC32+AE32+AG32+AI32+AK32+AM32 -> 450 | AO32: =AN32*$F$34 -> 36 | AP32: =AN32+AO32 -> 486 | AQ32: =AP32*$F$36 -> 6.804 | AR32: =AP32+AQ32 -> 492.804 | AS32: =AR32*$F$38 -> 68.99256 | AT32: =AR32+AS32 -> 561.79656 | AU32: =AT32/C32 -> 56.179656
B33: Total Cost | C33: =SUM(C6:C32) -> 1328 | G33: =SUM(G6:G32) -> 71385 | I33: =C33-(L33+N33+P33+R33+T33+V33+X33+Z33+AB33+AD33+AF33+AH33+AJ33+AL33) -> 0 | J33: =G33-(M33+O33+Q33+S33+U33+W33+Y33+AA33+AC33+AE33+AG33+AI33+AK33+AM33) -> 0 | L33: =SUM(L6:L32) -> 180 | M33: =SUM(M6:M32) -> 10000 | N33: =SUM(N6:N32) -> 97 | O33: =SUM(O6:O32) -> 5150 | P33: =SUM(P6:P32) -> 103 | Q33: =SUM(Q6:Q32) -> 5850 | R33: =SUM(R6:R32) -> 185 | S33: =SUM(S6:S32) -> 10150 | ... AT33: =SUM(AT6:AT32) -> 89119.661 | AV33: =SUM(AV6:AV32) -> 0
B34: Gross Margin & Contingency | F34: ='HK Budget (2)'!C14 -> 0.08 | G34: =G33*$F$34 -> 5710.8 | I34: =C34-(L34+N34+P34+R34+T34+V34+X34+Z34+AB34+AD34+AF34+AH34+AJ34+AL34) -> 0 | J34: =G34-(M34+O34+Q34+S34+U34+W34+Y34+AA34+AC34+AE34+AG34+AI34+AK34+AM34) -> 0 | M34: =M33*$F$34 -> 800 | O34: =O33*$F$34 -> 412 | Q34: =Q33*$F$34 -> 468 | S34: =S33*$F$34 -> 812 | U34: =U33*$F$34 -> 174 | W34: =W33*$F$34 -> 140 | Y34: =Y33*$F$34 -> 140 | AA34: =AA33*$F$34 -> 140 | AC34: =AC33*$F$34 -> 170 | AE34: =AE33*$F$34 -> 1018 | AG34: =AG33*$F$34 -> 69.6 | AI34: =AI33*$F$34 -> 178 | AK34: =AK33*$F$34 -> 27.2 | AM34: =AM33*$F$34 -> 1162
B35: Total | G35: =G33+G34 -> 77095.8 | I35: =C35-(L35+N35+P35+R35+T35+V35+X35+Z35+AB35+AD35+AF35+AH35+AJ35+AL35) -> 0 | J35: =G35-(M35+O35+Q35+S35+U35+W35+Y35+AA35+AC35+AE35+AG35+AI35+AK35+AM35) -> 0 | M35: =M33+M34 -> 10800 | O35: =O33+O34 -> 5562 | Q35: =Q33+Q34 -> 6318 | S35: =S33+S34 -> 10962 | U35: =U33+U34 -> 2349 | W35: =W33+W34 -> 1890 | Y35: =Y33+Y34 -> 1890 | AA35: =AA33+AA34 -> 1890 | AC35: =AC33+AC34 -> 2295 | AE35: =AE33+AE34 -> 13743 | AG35: =AG33+AG34 -> 939.6 | AI35: =AI33+AI34 -> 2403 | AK35: =AK33+AK34 -> 367.2 | AM35: =AM33+AM34 -> 15687
B36: Insurance | F36: ='HK Budget (2)'!C16 -> 0.014 | G36: =G35*$F$36 -> 1079.3412 | I36: =C36-(L36+N36+P36+R36+T36+V36+X36+Z36+AB36+AD36+AF36+AH36+AJ36+AL36) -> 0 | J36: =G36-(M36+O36+Q36+S36+U36+W36+Y36+AA36+AC36+AE36+AG36+AI36+AK36+AM36) -> 0 | M36: =M35*$F$36 -> 151.2 | O36: =O35*$F$36 -> 77.868 | Q36: =Q35*$F$36 -> 88.452 | S36: =S35*$F$36 -> 153.468 | U36: =U35*$F$36 -> 32.886 | W36: =W35*$F$36 -> 26.46 | Y36: =Y35*$F$36 -> 26.46 | AA36: =AA35*$F$36 -> 26.46 | AC36: =AC35*$F$36 -> 32.13 | AE36: =AE35*$F$36 -> 192.402 | AG36: =AG35*$F$36 -> 13.1544 | AI36: =AI35*$F$36 -> 33.642 | AK36: =AK35*$F$36 -> 5.1408 | AM36: =AM35*$F$36 -> 219.618
B37: Total Revenue | G37: =G35+G36 -> 78175.141 | I37: =C37-(L37+N37+P37+R37+T37+V37+X37+Z37+AB37+AD37+AF37+AH37+AJ37+AL37) -> 0 | J37: =G37-(M37+O37+Q37+S37+U37+W37+Y37+AA37+AC37+AE37+AG37+AI37+AK37+AM37) -> 0 | M37: =M35+M36 -> 10951.2 | O37: =O35+O36 -> 5639.868 | Q37: =Q35+Q36 -> 6406.452 | S37: =S35+S36 -> 11115.468 | U37: =U35+U36 -> 2381.886 | W37: =W35+W36 -> 1916.46 | Y37: =Y35+Y36 -> 1916.46 | AA37: =AA35+AA36 -> 1916.46 | AC37: =AC35+AC36 -> 2327.13 | AE37: =AE35+AE36 -> 13935.402 | AG37: =AG35+AG36 -> 952.7544 | AI37: =AI35+AI36 -> 2436.642 | AK37: =AK35+AK36 -> 372.3408 | AM37: =AM35+AM36 -> 15906.618
B38: VAT | F38: 0.14 | G38: =G37*$F$38 -> 10944.52 | I38: =C38-(L38+N38+P38+R38+T38+V38+X38+Z38+AB38+AD38+AF38+AH38+AJ38+AL38) -> 0 | J38: =G38-(M38+O38+Q38+S38+U38+W38+Y38+AA38+AC38+AE38+AG38+AI38+AK38+AM38) -> 0 | M38: =M37*$F$38 -> 1533.168 | O38: =O37*$F$38 -> 789.58152 | Q38: =Q37*$F$38 -> 896.90328 | S38: =S37*$F$38 -> 1556.1655 | U38: =U37*$F$38 -> 333.46404 | W38: =W37*$F$38 -> 268.3044 | Y38: =Y37*$F$38 -> 268.3044 | AA38: =AA37*$F$38 -> 268.3044 | AC38: =AC37*$F$38 -> 325.7982 | AE38: =AE37*$F$38 -> 1950.9563 | AG38: =AG37*$F$38 -> 133.38562 | AI38: =AI37*$F$38 -> 341.12988 | AK38: =AK37*$F$38 -> 52.127712 | AM38: =AM37*$F$38 -> 2226.9265
B39: Total W VAT | G39: =G37+G38 -> 89119.661 | I39: =C39-(L39+N39+P39+R39+T39+V39+X39+Z39+AB39+AD39+AF39+AH39+AJ39+AL39) -> 0 | J39: =G39-(M39+O39+Q39+S39+U39+W39+Y39+AA39+AC39+AE39+AG39+AI39+AK39+AM39) -> 0 | M39: =M37+M38 -> 12484.368 | O39: =O37+O38 -> 6429.4495 | Q39: =Q37+Q38 -> 7303.3553 | S39: =S37+S38 -> 12671.634 | U39: =U37+U38 -> 2715.35 | W39: =W37+W38 -> 2184.7644 | Y39: =Y37+Y38 -> 2184.7644 | AA39: =AA37+AA38 -> 2184.7644 | AC39: =AC37+AC38 -> 2652.9282 | AE39: =AE37+AE38 -> 15886.358 | AG39: =AG37+AG38 -> 1086.14 | AI39: =AI37+AI38 -> 2777.7719 | AK39: =AK37+AK38 -> 424.46851 | AM39: =AM37+AM38 -> 18133.545
G43: =G39+'Equipment & Tools Cost'!G58 -> 648606.96
G45: =G43-#REF! -> #REF!

Sheet Per Zone
A1: Main scope
A2: S. | B2: Residential Area | C2: active months | D2: All Seasons
D3: Y1 | E3: Y2 | F3: Y3
A4: 1 | B4: Sierras
A5: 2 | B5: Alto
A6: 3 | B6: Aurora
A7: 4 | B7: Fourteen
A8: 5 | B8: Reyna
A9: 6 | B9: Eleva
A10: 7 | B10: Isadore
A11: 8 | B11: Alba's Aliyah
A12: 9 | B12: Alba's Spendia
A13: 10 | B13: Commercial Area "UTC-Golf club house
A14: 11 | B14: Public Roads
A15: 12 | B15: Crossing gates
A16: 13 | B16: Mobilization areas " water station "
A19: Option scope
A20: S. | B20: Residential Area | C20: active months | D20: All Seasons
D21: Y1 | E21: Y2 | F21: Y3
A22: 1 | B22: Community center Sierras -1
A23: 2 | B23: Community center Sierras -7
A24: 3 | B24: Community center Sierras -15
A25: 4 | B25: Community center Fourteen 4
A26: 5 | B26: Community center Fourteen 6
A27: 6 | B27: Community center Alto
A28: 7 | B28: Community center Aurora
A29: 8 | B29: Community center Reyna
A30: 9 | B30: Community center Eleva
A31: 10 | B31: Community center Isadore
A32: 11 | B32: Community center Alba's
A33: 12 | B33: Community center Fountain Side
... A39: 18 | B39: Commercial Area "UTC-Sports Arena"

Sheet Items Pricelist
A1: No | B1: Item / English | C1: Unit | D1: Price
A2: 1 | B2: Garbage Bags/ small 35*50 Biodegrable | C2: KG | D2: ='Pricing Cost'!I4 -> 51 | E2: 54 | F2: =D2-E2 -> -3 | G2: =F2/D2 -> -0.058823529
A3: 2 | B3: Garbage Bags/ Medium-Black 60*90 Biodegrable | C3: KG | D3: ='Pricing Cost'!I5 -> 51 | E3: 54 | F3: =D3-E3 -> -3 | G3: =F3/D3 -> -0.058823529
A4: 3 | B4: Garbage Bags/ Jumpo-Black70*140 Biodegrable | C4: KG | D4: ='Pricing Cost'!I6 -> 51 | E4: 54 | F4: =D4-E4 -> -3 | G4: =F4/D4 -> -0.058823529
A5: 4 | B5: Garbage Bags/ 120*130 Biodegrable | C5: KG | D5: ='Pricing Cost'!I7 -> 51 | E5: 54 | F5: =D5-E5 -> -3 | G5: =F5/D5 -> -0.058823529
A6: 5 | B6: Garbage Bins 1100 LTR | C6: Each | D6: ='Pricing Cost'!I8 -> 17478 | E6: 18354 | F6: =D6-E6 -> -876 | G6: =F6/D6 -> -0.050120151
A7: 6 | B7: Garbage Bins 240 LTR | C7: Each | D7: ='Pricing Cost'!I9 -> 986 | E7: 1036 | F7: =D7-E7 -> -50 | G7: =F7/D7 -> -0.050709939
A8: 7 | B8: Garbage Bins 770 LTR | C8: Each | D8: ='Pricing Cost'!I10 -> 14981 | E8: 15732 | F8: =D8-E8 -> -751 | G8: =F8/D8 -> -0.050130165
A9: 8 | B9: Garbage Bins 120 LTR | C9: Each | D9: ='Pricing Cost'!I11 -> 737 | E9: 773 | F9: =D9-E9 -> -36 | G9: =F9/D9 -> -0.048846676
A10: 9 | B10: Trash bin steel 20 L | C10: Each | D10: ='Pricing Cost'!I12 -> 4370 | E10: 4589 | F10: =D10-E10 -> -219 | G10: =F10/D10 -> -0.050114416
A11: 10 | B11: Trash bin steel 5 L | C11: Each | D11: ='Pricing Cost'!I13 -> 1124 | E11: 1180 | F11: =D11-E11 -> -56 | G11: =F11/D11 -> -0.049822064
A12: 11 | B12: Basket bin240L- cover | C12: Each | D12: ='Pricing Cost'!I14 -> 236 | E12: 248 | F12: =D12-E12 -> -12 | G12: =F12/D12 -> -0.050847458
A13: 12 | B13: Basket bin120L- cover | C13: Each | D13: ='Pricing Cost'!I15 -> 142 | E13: 149 | F13: =D13-E13 -> -7 | G13: =F13/D13 -> -0.049295775
... A77: 76 | B77: Dry Mob | C77: Each | D77: ='Pricing Cost'!I79 -> 3121 | E77: 3278 | F77: =D77-E77 -> -157 | G77: =F77/D77 -> -0.05030439

Sheet Unit rates
A3: Equipment and Tools
A4: # | B4: Unit Rates (to be invoiced seperately upon request) | C4: Notes | D4: Monthly Cost
A5: 1 | B5: High Pressure Set with Driver, 5K Liters / Month | D5: ='Pricing Cost'!I82 -> 98496 | F5: 104880 | G5: =D5-F5 -> -6384 | H5: =G5/D5 -> -0.064814815
A6: 2 | B6: High Pressure Set with Driver, 1K Liter / Month | D6: ='Pricing Cost'!I83 -> #REF! | F6: 79544.015 | G6: =D6-F6 -> #REF! | H6: =G6/D6 -> #REF!
A7: 3 | B7: Boom Lift 15 M / Month | D7: ='Pricing Cost'!I84 -> 92340 | F7: 98325 | G7: =D7-F7 -> -5985 | H7: =G7/D7 -> -0.064814815
A8: 4 | B8: Man Lift 15 M / Month | D8: ='Pricing Cost'!I85 -> #REF! | F8: 87345.375 | G8: =D8-F8 -> #REF! | H8: =G8/D8 -> #REF!
A9: 5 | B9: Ride On (Sweeping), with 7000 square meter capacity per hour / Month | D9: ='Pricing Cost'!I86 -> 41614.56 | F9: 43700 | G9: =D9-F9 -> -2085.44 | H9: =G9/D9 -> -0.05011323
A10: 6 | B10: Ride On (Mobbing), with 7000 square meter capacity per hour / Month | D10: ='Pricing Cost'!I87 -> 31210.92 | F10: 32775 | G10: =D10-F10 -> -1564.08 | H10: =G10/D10 -> -0.05011323
A11: 7 | B11: Water Fed Telescope (20 Meter) / Month | D11: ='Pricing Cost'!I88 -> #REF! | F11: 10638.219 | G11: =D11-F11 -> #REF! | H11: =G11/D11 -> #REF!
A12: 8 | B12: Club Car / Month | D12: ='Pricing Cost'!I89 -> 62421.84 | F12: 65550 | G12: =D12-F12 -> -3128.16 | H12: =G12/D12 -> -0.05011323
A13: 9 | B13: Pick up car with Driver / Month | D13: ='Pricing Cost'!I90 -> #REF! | F13: 56438.55 | G13: =D13-F13 -> #REF! | H13: =G13/D13 -> #REF!
A14: 10 | B14: Single disk / Month | D14: ='Pricing Cost'!I91 -> #REF! | F14: 1679.7188 | G14: =D14-F14 -> #REF! | H14: =G14/D14 -> #REF!
A15: 11 | B15: Employee with Washroom Amenities / Month | D15: N/A | F15: N/A | G15: =D15-F15 -> #VALUE! | H15: =G15/D15 -> #VALUE!
A16: 12 | B16: Guest Consumable (Based on attached pricing template) | D16: N/A | F16: N/A | G16: =D16-F16 -> #VALUE! | H16: =G16/D16 -> #VALUE!
A17: 13 | B17: Marble Grinding / Meter | D17: ='Pricing Cost'!I94 -> 218 | F17: 229 | G17: =D17-F17 -> -11 | H17: =G17/D17 -> -0.050458716
A18: 14 | B18: Marble Polishing / Meter | D18: ='Pricing Cost'!I95 -> 206 | F18: 216 | G18: =D18-F18 -> -10 | H18: =G18/D18 -> -0.048543689
A19: 15 | B19: Marble Antique for Outdoor / Meter | D19: ='Pricing Cost'!I96 -> 125 | F19: 131 | G19: =D19-F19 -> -6 | H19: =G19/D19 -> -0.048
A20: 16 | B20: McClean Trolley | D20: ='Pricing Cost'!I97 -> #REF! | F20: 313 | G20: =D20-F20 -> #REF! | H20: =G20/D20 -> #REF!
A21: 17 | B21: Manual sweeper | D21: ='Pricing Cost'!I98 -> #REF! | F21: 1260 | G21: =D21-F21 -> #REF! | H21: =G21/D21 -> #REF!
A22: 18 | B22: Black Broom and Closed Ban | D22: ='Pricing Cost'!I99 -> #REF! | F22: 101 | G22: =D22-F22 -> #REF! | H22: =G22/D22 -> #REF!
A23: 19 | B23: Litter Picking Steak | D23: ='Pricing Cost'!I100 -> #REF! | F23: 112 | G23: =D23-F23 -> #REF! | H23: =G23/D23 -> #REF!
A24: 20 | B24: Vacuum 3 motors | D24: ='Pricing Cost'!I101 -> #REF! | F24: 980 | G24: =D24-F24 -> #REF! | H24: =G24/D24 -> #REF!
A25: 21 | B25: Walk behind | D25: ='Pricing Cost'!I102 -> 4167 | F25: 4167 | G25: =D25-F25 -> 0 | H25: =G25/D25 -> 0
A26: 22 | B26: Mob Bucket with Cotton Cloth | D26: ='Pricing Cost'!I103 -> #REF! | F26: 68 | G26: =D26-F26 -> #REF! | H26: =G26/D26 -> #REF!
A28: # | B28: Manpower | C28: Notes | D28: Monthly Cost
A29: 1 | B29: Site manager / Month | D29: ='Pricing Cost'!I105 -> #REF! | F29: 74002 | G29: =D29-F29 -> #REF! | H29: =G29/D29 -> #REF!
A30: 2 | B30: Assist. Site MGR / Month | D30: ='Pricing Cost'!I106 -> #REF! | F30: 46652 | G30: =D30-F30 -> #REF! | H30: =G30/D30 -> #REF!
A31: 3 | B31: Senior Supervisor / Month | D31: ='Pricing Cost'!I107 -> 27300 | F31: 27300 | G31: =D31-F31 -> 0 | H31: =G31/D31 -> 0
A32: 4 | B32: Supervisor / Month | D32: ='Pricing Cost'!I108 -> #REF! | F32: 24170.063 | G32: =D32-F32 -> #REF! | H32: =G32/D32 -> #REF!
A33: 5 | B33: Employee ( Janitor ) / Month | D33: ='Pricing Cost'!I109 -> #REF! | F33: 13533 | G33: =D33-F33 -> #REF! | H33: =G33/D33 -> #REF!
A34: 6 | B34: Driver / Month | D34: ='Pricing Cost'!I110 -> 16400 | F34: 16400 | G34: =D34-F34 -> 0 | H34: =G34/D34 -> 0
A35: 7 | B35: Facade cleaner / Month | D35: ='Pricing Cost'!I111 -> 14100 | F35: 14100 | G35: =D35-F35 -> 0 | H35: =G35/D35 -> 0
A39: # | B39: Paid Service (to be invoiced seperately upon request) | C39: Notes | D39: Cost per visit
A40: 1 | B40: Apartment up to 85 m² (1 Bedroom) | C40: General Cleaning | D40: ='Paid Services'!J4 -> 669 | F40: 669 | G40: =D40-F40 -> 0 | H40: =G40/D40 -> 0
A41: 2 | B41: Apartments more than 85 m² and up to 120 m² (2 Bedroom) | D41: ='Paid Services'!J5 -> 787 | F41: 787 | G41: =D41-F41 -> 0 | H41: =G41/D41 -> 0
A42: 3 | B42: Apartment more than 120 m² and up to 200 m² (3 Bedroom and with Pent House) | D42: ='Paid Services'!J6 -> 1049 | F42: 1049 | G42: =D42-F42 -> 0 | H42: =G42/D42 -> 0
A43: 4 | B43: Villa or Townhouse more than 200 m² and up to 300 m² (V1 or TH ) | D43: ='Paid Services'!J7 -> 1639 | F43: 1639 | G43: =D43-F43 -> 0 | H43: =G43/D43 -> 0
A44: 5 | B44: Villas more than 300 m² and up to 420 m² (V2) | D44: ='Paid Services'!J8 -> 2295 | F44: 2295 | G44: =D44-F44 -> 0 | H44: =G44/D44 -> 0
A45: 6 | B45: Villas more than 420 m² and up to 600 m² (V3) | D45: ='Paid Services'!J9 -> 2622 | F45: 2622 | G45: =D45-F45 -> 0 | H45: =G45/D45 -> 0
A46: 7 | B46: Villas more than 600 m² and up to 850 m² (V4) | D46: ='Paid Services'!J10 -> 3933 | F46: 3933 | G46: =D46-F46 -> 0 | H46: =G46/D46 -> 0
A47: 8 | B47: Apartment up to 85 m² (1 Bedroom) | C47: Deep Cleaning | D47: ='Paid Services'!J11 -> 1115 | F47: 1115 | G47: =D47-F47 -> 0 | H47: =G47/D47 -> 0
A48: 9 | B48: Apartments more than 85 m² and up to 120 m² (2 Bedroom) | D48: ='Paid Services'!J12 -> 1311 | F48: 1311 | G48: =D48-F48 -> 0 | H48: =G48/D48 -> 0
A49: 10 | B49: Apartment more than 120 m² and up to 200 m² (3 Bedroom and with Pent House) | D49: ='Paid Services'!J13 -> 1679 | F49: 1679 | G49: =D49-F49 -> 0 | H49: =G49/D49 -> 0
A50: 11 | B50: Villa or Townhouse more than 200 m² and up to 300 m² (V1 or TH ) | D50: ='Paid Services'!J14 -> 2622 | F50: 2622 | G50: =D50-F50 -> 0 | H50: =G50/D50 -> 0
A51: 12 | B51: Villas more than 300 m² and up to 420 m² (V2) | D51: ='Paid Services'!J15 -> 3671 | F51: 3671 | G51: =D51-F51 -> 0 | H51: =G51/D51 -> 0
A52: 13 | B52: Villas more than 420 m² and up to 600 m² (V3) | D52: ='Paid Services'!J16 -> 3933 | F52: 3933 | G52: =D52-F52 -> 0 | H52: =G52/D52 -> 0
A53: 14 | B53: Villas more than 600 m² and up to 850 m² (V4) | D53: ='Paid Services'!J17 -> 5900 | F53: 5900 | G53: =D53-F53 -> 0 | H53: =G53/D53 -> 0

Sheet Summery
A3: All Seasons
A4: Scope Name | B4: Mobilization & Overheads | C4: On site Manpower | D4: Equipement & tools | E4: Chemicals | F4: Staff Accomodation | G4: Staff Transpoetation | H4: Other (Façade Cleaning) | I4: Other (Insurance Certifications) | J4: Total
A5: ='BOQ A'!D3 -> Sierras | B5: ='Mobilization & Over Head Cost'!M20 -> 7246.5111 | C5: ='Manpower Cost'!L22 -> 261280.9 | D5: ='Equipment & Tools Cost'!M58 -> 94735.884 | E5: ='Consumables Cost '!M39 -> 12484.368 | F5: 0 | G5: ='Transportation Cost'!M20 -> 77631.173 | H5: ='Facades Cleaning Cost'!M20 -> 78963.628 | I5: ='Others Cost '!M18 -> 7889.3468 | J5: =SUM(B5:I5) -> 540231.81 | L5: 920624.36 | M5: =J5-L5 -> -380392.55 | N5: =M5/J5 -> -0.70412838
A6: ='BOQ A'!D4 -> Alto | B6: ='Mobilization & Over Head Cost'!O20 -> 3653.0902 | C6: ='Manpower Cost'!N22 -> 131567.18 | D6: ='Equipment & Tools Cost'!O58 -> 50102.059 | E6: ='Consumables Cost '!O39 -> 6429.4495 | F6: 0 | G6: ='Transportation Cost'!O20 -> 39135.202 | H6: ='Facades Cleaning Cost'!O20 -> 18258.388 | I6: ='Others Cost '!O18 -> 3977.1547 | J6: =SUM(B6:I6) -> 253122.53 | L6: 371983.73 | M6: =J6-L6 -> -118861.2 | N6: =M6/J6 -> -0.46957971
A7: ='BOQ A'!D5 -> Aurora | B7: ='Mobilization & Over Head Cost'!Q20 -> 3845.3581 | C7: ='Manpower Cost'!P22 -> 137539.46 | D7: ='Equipment & Tools Cost'!Q58 -> 51872.477 | E7: ='Consumables Cost '!Q39 -> 7303.3553 | F7: 0 | G7: ='Transportation Cost'!Q20 -> 41194.95 | H7: ='Facades Cleaning Cost'!Q20 -> 14200.969 | I7: ='Others Cost '!Q18 -> 4186.4786 | J7: =SUM(B7:I7) -> 260143.04 | L7: 368133.47 | M7: =J7-L7 -> -107990.42 | N7: =M7/J7 -> -0.4151194
A8: ='BOQ A'!D6 -> Fourteen | B8: ='Mobilization & Over Head Cost'!S20 -> 7067.5031 | C8: ='Manpower Cost'!R22 -> 255720.51 | D8: ='Equipment & Tools Cost'!S58 -> 92013.358 | E8: ='Consumables Cost '!S39 -> 12671.634 | F8: 0 | G8: ='Transportation Cost'!S20 -> 75713.477 | H8: ='Facades Cleaning Cost'!S20 -> 56803.874 | I8: ='Others Cost '!S18 -> 7694.459 | J8: =SUM(B8:I8) -> 507684.82 | L8: 806193.75 | M8: =J8-L8 -> -298508.93 | N8: =M8/J8 -> -0.58798081
A9: ='BOQ A'!D7 -> Reyna | B9: ='Mobilization & Over Head Cost'!U20 -> 1558.033 | C9: ='Manpower Cost'!T22 -> 61966.507 | D9: ='Equipment & Tools Cost'!U58 -> 20631.896 | E9: ='Consumables Cost '!U39 -> 2715.35 | F9: 0 | G9: ='Transportation Cost'!U20 -> 16691.057 | I9: ='Others Cost '!U18 -> 1696.2457 | J9: =SUM(B9:I9) -> 105259.09 | L9: 132229.96 | M9: =J9-L9 -> -26970.866 | N9: =M9/J9 -> -0.25623313
A10: ='BOQ A'!D8 -> Eleva | B10: ='Mobilization & Over Head Cost'!W20 -> 1246.4264 | C10: ='Manpower Cost'!V22 -> 46471.375 | D10: ='Equipment & Tools Cost'!W58 -> 16268.036 | E10: ='Consumables Cost '!W39 -> 2184.7644 | F10: 0 | G10: ='Transportation Cost'!W20 -> 13352.846 | I10: ='Others Cost '!W18 -> 1356.9965 | J10: =SUM(B10:I10) -> 80880.445 | L10: 102178.85 | M10: =J10-L10 -> -21298.403 | N10: =M10/J10 -> -0.26333192
A11: ='BOQ A'!D9 -> Isadore | B11: ='Mobilization & Over Head Cost'!Y20 -> 934.81983 | C11: ='Manpower Cost'!X22 -> 34853.532 | D11: ='Equipment & Tools Cost'!Y58 -> 12952.864 | E11: ='Consumables Cost '!Y39 -> 2184.7644 | F11: 0 | G11: ='Transportation Cost'!Y20 -> 10014.634 | I11: ='Others Cost '!Y18 -> 1017.7474 | J11: =SUM(B11:I11) -> 61958.361 | L11: 78508.912 | M11: =J11-L11 -> -16550.551 | N11: =M11/J11 -> -0.26712377
A12: ='BOQ A'!D10 -> Alba's Aliyah | B12: ='Mobilization & Over Head Cost'!AA20 -> 1246.4264 | C12: ='Manpower Cost'!Z22 -> 45502.053 | D12: ='Equipment & Tools Cost'!AA58 -> 15799.872 | E12: ='Consumables Cost '!AA39 -> 2184.7644 | F12: 0 | G12: ='Transportation Cost'!AA20 -> 13352.846 | I12: ='Others Cost '!AA18 -> 1356.9965 | J12: =SUM(B12:I12) -> 79442.959 | L12: 100410.82 | M12: =J12-L12 -> -20967.865 | N12: =M12/J12 -> -0.2639361
A13: ='BOQ A'!D11 -> Alba's Spendia | B13: ='Mobilization & Over Head Cost'!AC20 -> 1246.4264 | C13: ='Manpower Cost'!AB22 -> 45502.053 | D13: ='Equipment & Tools Cost'!AC58 -> 14863.545 | E13: ='Consumables Cost '!AC39 -> 2652.9282 | F13: 0 | G13: ='Transportation Cost'!AC20 -> 13352.846 | I13: ='Others Cost '!AC18 -> 1356.9965 | J13: =SUM(B13:I13) -> 78974.795 | L13: 99151.035 | M13: =J13-L13 -> -20176.24 | N13: =M13/J13 -> -0.25547695
A14: ='BOQ A'!D12 -> Commercial Area "UTC-Golf club house | B14: ='Mobilization & Over Head Cost'!AE20 -> 3116.0661 | C14: ='Manpower Cost'!AD22 -> 123933.01 | D14: ='Equipment & Tools Cost'!AE58 -> 44140.051 | E14: ='Consumables Cost '!AE39 -> 15886.358 | F14: 0 | G14: ='Transportation Cost'!AE20 -> 33382.114 | I14: ='Others Cost '!AE18 -> 3392.4913 | J14: =SUM(B14:I14) -> 223850.1 | L14: 276777.38 | M14: =J14-L14 -> -52927.285 | N14: =M14/J14 -> -0.23644075
A15: ='BOQ A'!D13 -> Public Roads | B15: ='Mobilization & Over Head Cost'!AG20 -> 311.60661 | C15: ='Manpower Cost'!AF22 -> 11375.513 | D15: ='Equipment & Tools Cost'!AG58 -> 5321.688 | E15: ='Consumables Cost '!AG39 -> 1086.14 | F15: 0 | G15: ='Transportation Cost'!AG20 -> 3338.2114 | I15: ='Others Cost '!AG18 -> 339.24913 | J15: =SUM(B15:I15) -> 21772.409 | L15: 27043.411 | M15: =J15-L15 -> -5271.0024 | N15: =M15/J15 -> -0.24209551
A16: ='BOQ A'!D14 -> Crossing gates | B16: ='Mobilization & Over Head Cost'!AI20 -> 1869.6397 | C16: ='Manpower Cost'!AH22 -> 68253.08 | D16: ='Equipment & Tools Cost'!AI58 -> 19585.169 | E16: ='Consumables Cost '!AI39 -> 2777.7719 | F16: 0 | G16: ='Transportation Cost'!AI20 -> 20029.269 | I16: ='Others Cost '!AI18 -> 2035.4948 | J16: =SUM(B16:I16) -> 114550.42 | L16: 142784.13 | M16: =J16-L16 -> -28233.703 | N16: =M16/J16 -> -0.24647402
A17: ='BOQ A'!D15 -> Mobilization areas " water station " | B17: ='Mobilization & Over Head Cost'!AK20 -> 311.60661 | C17: ='Manpower Cost'!AJ22 -> 11375.513 | D17: ='Equipment & Tools Cost'!AK58 -> 3801.0226 | E17: ='Consumables Cost '!AK39 -> 424.46851 | F17: 0 | G17: ='Transportation Cost'!AK20 -> 3338.2114 | I17: ='Others Cost '!AK18 -> 339.24913 | J17: =SUM(B17:I17) -> 19590.072 | L17: 24358.381 | M17: =J17-L17 -> -4768.3089 | N17: =M17/J17 -> -0.24340436
A18: ='BOQ A'!D16 -> Managament"sales center" | B18: ='Mobilization & Over Head Cost'!AM20 -> 9348.1983 | C18: ='Manpower Cost'!AL22 -> 327252.74 | D18: ='Equipment & Tools Cost'!AM58 -> 117399.38 | E18: ='Consumables Cost '!AM39 -> 18133.545 | F18: 0 | G18: ='Transportation Cost'!AM20 -> 100146.34 | I18: ='Others Cost '!AM18 -> 10177.474 | J18: =SUM(B18:I18) -> 582457.68 | L18: 811438.67 | M18: =J18-L18 -> -228980.99 | N18: =M18/J18 -> -0.39312898
A19: Total | B19: =SUM(B5:B18) -> 43001.712 | C19: =SUM(C5:C18) -> 1562593.4 | D19: =SUM(D5:D18) -> 559487.3 | E19: =SUM(E5:E18) -> 89119.661 | F19: =SUM(F5:F18) -> 0 | G19: =SUM(G5:G18) -> 460673.18 | H19: =SUM(H5:H18) -> 168226.86 | I19: =SUM(I5:I18) -> 46816.38 | J19: =SUM(J5:J18) -> 2929918.5 | L19: =SUM(L5:L18) -> 4261816.8 | M19: =J19-L19 -> -1331898.3 | N19: =M19/J19 -> -0.45458545
J20: =SUM(B19:I19) -> 2929918.5
J21: =J19-J20 -> 0

Sheet Facades Cleaning Cost
I1: v
I2: 38250
I3: 25000 | L3: 27.213948 | M3: 0 | N3: 13.708038 | O3: 0 | P3: 14.359338 | Q3: 0 | R3: 26.607565 | S3: 0 | T3: 6.2777778 | U3: 0 | V3: 4.7936508 | W3: 0 | X3: 3.5952381 | Y3: 0 | Z3: 4.7222222 | AA3: 0 | AB3: 4.7222222 | AC3: 0 | AD3: 12.555556 | AE3: 0 | AF3: 1.1805556 | AG3: 0 | AH3: 7.0833333 | AI3: 0 | AJ3: 1.1805556 | AK3: 0 | AL3: 34 | AM3: 0
B4: Items | C4: Total Buildings | D4: Depreciation / Month | E4: Price | F4: Unit Monthly Cost | G4: Total Amount/ Month | I4: =M14+O14+Q14+S14 -> 134750 | L4: Sierras | N4: Alto | P4: Aurora | R4: Fourteen | T4: Reyna | V4: Eleva | X4: Isadore | Z4: Alba's Aliyah | AB4: Alba's Spendia | AD4: Commercial Area "UTC-Golf club house | AF4: Public Roads | AH4: Crossing gates | AJ4: Mobilization areas " water station " | AL4: Managament"sales center" | AN4: Total Cost | AO4: Gross Margin | AP4: Total | AQ4: Contingency | AR4: Total | AS4: VAT | AT4: Total W VAT | AU4: Unit Rate
L5: Total Building | M5: Monthly Cost | N5: Total Building | O5: Monthly Cost | P5: Total Building | Q5: Monthly Cost | R5: Total Building | S5: Monthly Cost | T5: Total Building | V5: Total Building | W5: Monthly Cost | X5: Total Building | Y5: Monthly Cost | Z5: Total Building | AA5: Monthly Cost | AB5: Total Building | AC5: Monthly Cost | AD5: Total Building | AE5: Monthly Cost | AF5: Total Building | AG5: Monthly Cost | AH5: Total Building | AI5: Monthly Cost | AJ5: Total Building | AK5: Monthly Cost | AL5: Total Building | AM5: Monthly Cost
B6: Sierras Double "Subcontractor Cost*3 Times Annually" 9Building *2 *17,500 | C6: =L6 -> 4.5 | D6: 1 | E6: 8500 | G6: =C6*D6*E6 -> 38250 | I6: =C6-(L6+N6+P6+R6+T6+V6+X6+Z6+AB6+AD6+AF6+AH6+AJ6+AL6) -> 0 | J6: =G6-(M6+O6+Q6+S6+U6+W6+Y6+AA6+AC6+AE6+AG6+AI6+AK6+AM6) -> 0 | L6: =18*3/12 -> 4.5 | M6: =((L6*E6)*D6) -> 38250 | AN6: =M6+O6+Q6+S6+U6+W6+Y6+AA6+AC6+AE6+AG6+AI6+AK6+AM6 -> 38250 | AO6: =AN6*$F$15 -> 3060 | AP6: =AN6+AO6 -> 41310 | AQ6: =AP6*$F$17 -> 578.34 | AR6: =AP6+AQ6 -> 41888.34 | AS6: =AR6*$F$19 -> 5864.3676 | AT6: =AR6+AS6 -> 47752.708 | AU6: =AT6/C6 -> 10611.713
B7: Sierras Single "Subcontractor Cost*3 Times Annually" | C7: =L7 -> 2 | D7: 1 | E7: =25000*0.5 -> 12500 | G7: =C7*D7*E7 -> 25000 | I7: =C7-(L7+N7+P7+R7+T7+V7+X7+Z7+AB7+AD7+AF7+AH7+AJ7+AL7) -> 0 | J7: =G7-(M7+O7+Q7+S7+U7+W7+Y7+AA7+AC7+AE7+AG7+AI7+AK7+AM7) -> 0 | L7: =8*3/12 -> 2 | M7: =((L7*E7)*D7) -> 25000 | AN7: =M7+O7+Q7+S7+U7+W7+Y7+AA7+AC7+AE7+AG7+AI7+AK7+AM7 -> 25000 | AO7: =AN7*$F$15 -> 2000 | AP7: =AN7+AO7 -> 27000 | AQ7: =AP7*$F$17 -> 378 | AR7: =AP7+AQ7 -> 27378 | AS7: =AR7*$F$19 -> 3832.92 | AT7: =AR7+AS7 -> 31210.92 | AU7: =AT7/C7 -> 15605.46
B8: Alto "Subcontractor Cost*3 Times Annually" | C8: =N8 -> 2.25 | D8: 1 | E8: =13000*0.5 -> 6500 | G8: =C8*D8*E8 -> 14625 | I8: =C8-(L8+N8+P8+R8+T8+V8+X8+Z8+AB8+AD8+AF8+AH8+AJ8+AL8) -> 0 | J8: =G8-(M8+O8+Q8+S8+U8+W8+Y8+AA8+AC8+AE8+AG8+AI8+AK8+AM8) -> 0 | N8: =9*3/12 -> 2.25 | O8: =((N8*E8)*D8) -> 14625 | AN8: =M8+O8+Q8+S8+U8+W8+Y8+AA8+AC8+AE8+AG8+AI8+AK8+AM8 -> 14625 | AO8: =AN8*$F$15 -> 1170 | AP8: =AN8+AO8 -> 15795 | AQ8: =AP8*$F$17 -> 221.13 | AR8: =AP8+AQ8 -> 16016.13 | AS8: =AR8*$F$19 -> 2242.2582 | AT8: =AR8+AS8 -> 18258.388 | AU8: =AT8/C8 -> 8114.8392
B9: Aurora "Subcontractor Cost*3 Times Annually" | C9: =P9 -> 1.75 | D9: 1 | E9: =13000*0.5 -> 6500 | G9: =C9*D9*E9 -> 11375 | I9: =C9-(L9+N9+P9+R9+T9+V9+X9+Z9+AB9+AD9+AF9+AH9+AJ9+AL9) -> 0 | J9: =G9-(M9+O9+Q9+S9+U9+W9+Y9+AA9+AC9+AE9+AG9+AI9+AK9+AM9) -> 0 | P9: =7*3/12 -> 1.75 | Q9: =((P9*E9)*D9) -> 11375 | AN9: =M9+O9+Q9+S9+U9+W9+Y9+AA9+AC9+AE9+AG9+AI9+AK9+AM9 -> 11375 | AO9: =AN9*$F$15 -> 910 | AP9: =AN9+AO9 -> 12285 | AQ9: =AP9*$F$17 -> 171.99 | AR9: =AP9+AQ9 -> 12456.99 | AS9: =AR9*$F$19 -> 1743.9786 | AT9: =AR9+AS9 -> 14200.969 | AU9: =AT9/C9 -> 8114.8392
B10: Fourteen "Subcontractor Cost*3 Times Annually" | C10: =R10 -> 3.5 | D10: 1 | E10: 13000 | G10: =C10*D10*E10 -> 45500 | I10: =C10-(L10+N10+P10+R10+T10+V10+X10+Z10+AB10+AD10+AF10+AH10+AJ10+AL10) -> 0 | J10: =G10-(M10+O10+Q10+S10+U10+W10+Y10+AA10+AC10+AE10+AG10+AI10+AK10+AM10) -> 0 | R10: =14*3/12 -> 3.5 | S10: =((R10*E10)*D10) -> 45500 | AN10: =M10+O10+Q10+S10+U10+W10+Y10+AA10+AC10+AE10+AG10+AI10+AK10+AM10 -> 45500 | AO10: =AN10*$F$15 -> 3640 | AP10: =AN10+AO10 -> 49140 | AQ10: =AP10*$F$17 -> 687.96 | AR10: =AP10+AQ10 -> 49827.96 | AS10: =AR10*$F$19 -> 6975.9144 | AT10: =AR10+AS10 -> 56803.874 | AU10: =AT10/C10 -> 16229.678
B11: Golf Club House "Subcontractor Cost*3 Times Annually" | C11: =AD6 -> 0 | D11: 1 | G11: =C11*D11*E11 -> 0 | I11: =C11-(L11+N11+P11+R11+T11+V11+X11+Z11+AB11+AD11+AF11+AH11+AJ11+AL11) -> 0 | J11: =G11-(M11+O11+Q11+S11+U11+W11+Y11+AA11+AC11+AE11+AG11+AI11+AK11+AM11) -> 0 | AN11: =M11+O11+Q11+S11+U11+W11+Y11+AA11+AC11+AE11+AG11+AI11+AK11+AM11 -> 0 | AO11: =AN11*$F$15 -> 0 | AP11: =AN11+AO11 -> 0 | AQ11: =AP11*$F$17 -> 0 | AR11: =AP11+AQ11 -> 0 | AS11: =AR11*$F$19 -> 0 | AT11: =AR11+AS11 -> 0 | AU11: =AT11/C11 -> #DIV/0!
B12: Sales Center "Subcontractor Cost*3 Times Annually" | C12: =AL6 -> 0 | D12: 1 | G12: =C12*D12*E12 -> 0 | I12: =C12-(L12+N12+P12+R12+T12+V12+X12+Z12+AB12+AD12+AF12+AH12+AJ12+AL12) -> 0 | J12: =G12-(M12+O12+Q12+S12+U12+W12+Y12+AA12+AC12+AE12+AG12+AI12+AK12+AM12) -> 0 | AN12: =M12+O12+Q12+S12+U12+W12+Y12+AA12+AC12+AE12+AG12+AI12+AK12+AM12 -> 0 | AO12: =AN12*$F$15 -> 0 | AP12: =AN12+AO12 -> 0 | AQ12: =AP12*$F$17 -> 0 | AR12: =AP12+AQ12 -> 0 | AS12: =AR12*$F$19 -> 0 | AT12: =AR12+AS12 -> 0 | AU12: =AT12/C12 -> #DIV/0!
G13: =C13*D13*E13 -> 0 | I13: =C13-(L13+N13+P13+R13+T13+V13+X13+Z13+AB13+AD13+AF13+AH13+AJ13+AL13) -> 0 | J13: =G13-(M13+O13+Q13+S13+U13+W13+Y13+AA13+AC13+AE13+AG13+AI13+AK13+AM13) -> 0 | AN13: =M13+O13+Q13+S13+U13+W13+Y13+AA13+AC13+AE13+AG13+AI13+AK13+AM13 -> 0 | AO13: =AN13*$F$15 -> 0 | AP13: =AN13+AO13 -> 0 | AQ13: =AP13*$F$17 -> 0 | AR13: =AP13+AQ13 -> 0 | AS13: =AR13*$F$19 -> 0 | AT13: =AR13+AS13 -> 0 | AU13: =AT13/C13 -> #DIV/0!
B14: Total | C14: =SUM(C6:C13) -> 14 | G14: =SUM(G6:G13) -> 134750 | I14: =C14-(L14+N14+P14+R14+T14+V14+X14+Z14+AB14+AD14+AF14+AH14+AJ14+AL14) -> 0 | J14: =G14-(M14+O14+Q14+S14+U14+W14+Y14+AA14+AC14+AE14+AG14+AI14+AK14+AM14) -> 0 | L14: =SUM(L6:L13) -> 6.5 | M14: =SUM(M6:M13) -> 63250 | N14: =SUM(N6:N13) -> 2.25 | O14: =SUM(O6:O13) -> 14625 | P14: =SUM(P6:P13) -> 1.75 | Q14: =SUM(Q6:Q13) -> 11375 | R14: =SUM(R6:R13) -> 3.5 | S14: =SUM(S6:S13) -> 45500 | ... AU14: =SUM(AU6:AU13) -> #DIV/0!
B15: Gross Margin & Contingency | F15: ='HK Budget (2)'!C14 -> 0.08 | G15: =G14*$F$15 -> 10780 | I15: =C15-(L15+N15+P15+R15+T15+V15+X15+Z15+AB15+AD15+AF15+AH15+AJ15+AL15) -> 0 | J15: =G15-(M15+O15+Q15+S15+U15+W15+Y15+AA15+AC15+AE15+AG15+AI15+AK15+AM15) -> 0 | M15: =M14*$F$15 -> 5060 | O15: =O14*$F$15 -> 1170 | Q15: =Q14*$F$15 -> 910 | S15: =S14*$F$15 -> 3640 | U15: =U14*$F$15 -> 0 | W15: =W14*$F$15 -> 0 | Y15: =Y14*$F$15 -> 0 | AA15: =AA14*$F$15 -> 0 | AC15: =AC14*$F$15 -> 0 | AE15: =AE14*$F$15 -> 0 | AG15: =AG14*$F$15 -> 0 | AI15: =AI14*$F$15 -> 0 | AK15: =AK14*$F$15 -> 0 | AM15: =AM14*$F$15 -> 0
B16: Total | G16: =G14+G15 -> 145530 | I16: =C16-(L16+N16+P16+R16+T16+V16+X16+Z16+AB16+AD16+AF16+AH16+AJ16+AL16) -> 0 | J16: =G16-(M16+O16+Q16+S16+U16+W16+Y16+AA16+AC16+AE16+AG16+AI16+AK16+AM16) -> 0 | M16: =M14+M15 -> 68310 | O16: =O14+O15 -> 15795 | Q16: =Q14+Q15 -> 12285 | S16: =S14+S15 -> 49140 | U16: =U14+U15 -> 0 | W16: =W14+W15 -> 0 | Y16: =Y14+Y15 -> 0 | AA16: =AA14+AA15 -> 0 | AC16: =AC14+AC15 -> 0 | AE16: =AE14+AE15 -> 0 | AG16: =AG14+AG15 -> 0 | AI16: =AI14+AI15 -> 0 | AK16: =AK14+AK15 -> 0 | AM16: =AM14+AM15 -> 0
B17: Insurance | F17: ='HK Budget (2)'!C16 -> 0.014 | G17: =G16*$F$17 -> 2037.42 | I17: =C17-(L17+N17+P17+R17+T17+V17+X17+Z17+AB17+AD17+AF17+AH17+AJ17+AL17) -> 0 | J17: =G17-(M17+O17+Q17+S17+U17+W17+Y17+AA17+AC17+AE17+AG17+AI17+AK17+AM17) -> 0 | M17: =M16*$F$17 -> 956.34 | O17: =O16*$F$17 -> 221.13 | Q17: =Q16*$F$17 -> 171.99 | S17: =S16*$F$17 -> 687.96 | U17: =U16*$F$17 -> 0 | W17: =W16*$F$17 -> 0 | Y17: =Y16*$F$17 -> 0 | AA17: =AA16*$F$17 -> 0 | AC17: =AC16*$F$17 -> 0 | AE17: =AE16*$F$17 -> 0 | AG17: =AG16*$F$17 -> 0 | AI17: =AI16*$F$17 -> 0 | AK17: =AK16*$F$17 -> 0 | AM17: =AM16*$F$17 -> 0
B18: Total Revenue | G18: =G16+G17 -> 147567.42 | I18: =C18-(L18+N18+P18+R18+T18+V18+X18+Z18+AB18+AD18+AF18+AH18+AJ18+AL18) -> 0 | J18: =G18-(M18+O18+Q18+S18+U18+W18+Y18+AA18+AC18+AE18+AG18+AI18+AK18+AM18) -> 0 | M18: =M16+M17 -> 69266.34 | O18: =O16+O17 -> 16016.13 | Q18: =Q16+Q17 -> 12456.99 | S18: =S16+S17 -> 49827.96 | U18: =U16+U17 -> 0 | W18: =W16+W17 -> 0 | Y18: =Y16+Y17 -> 0 | AA18: =AA16+AA17 -> 0 | AC18: =AC16+AC17 -> 0 | AE18: =AE16+AE17 -> 0 | AG18: =AG16+AG17 -> 0 | AI18: =AI16+AI17 -> 0 | AK18: =AK16+AK17 -> 0 | AM18: =AM16+AM17 -> 0
B19: VAT | F19: 0.14 | G19: =G18*$F$19 -> 20659.439 | I19: =C19-(L19+N19+P19+R19+T19+V19+X19+Z19+AB19+AD19+AF19+AH19+AJ19+AL19) -> 0 | J19: =G19-(M19+O19+Q19+S19+U19+W19+Y19+AA19+AC19+AE19+AG19+AI19+AK19+AM19) -> 0 | M19: =M18*$F$19 -> 9697.2876 | O19: =O18*$F$19 -> 2242.2582 | Q19: =Q18*$F$19 -> 1743.9786 | S19: =S18*$F$19 -> 6975.9144 | U19: =U18*$F$19 -> 0 | W19: =W18*$F$19 -> 0 | Y19: =Y18*$F$19 -> 0 | AA19: =AA18*$F$19 -> 0 | AC19: =AC18*$F$19 -> 0 | AE19: =AE18*$F$19 -> 0 | AG19: =AG18*$F$19 -> 0 | AI19: =AI18*$F$19 -> 0 | AK19: =AK18*$F$19 -> 0 | AM19: =AM18*$F$19 -> 0
B20: Total W VAT | G20: =G18+G19 -> 168226.86 | I20: =C20-(L20+N20+P20+R20+T20+V20+X20+Z20+AB20+AD20+AF20+AH20+AJ20+AL20) -> 0 | J20: =G20-(M20+O20+Q20+S20+U20+W20+Y20+AA20+AC20+AE20+AG20+AI20+AK20+AM20) -> 0 | M20: =M18+M19 -> 78963.628 | O20: =O18+O19 -> 18258.388 | Q20: =Q18+Q19 -> 14200.969 | S20: =S18+S19 -> 56803.874 | U20: =U18+U19 -> 0 | W20: =W18+W19 -> 0 | Y20: =Y18+Y19 -> 0 | AA20: =AA18+AA19 -> 0 | AC20: =AC18+AC19 -> 0 | AE20: =AE18+AE19 -> 0 | AG20: =AG18+AG19 -> 0 | AI20: =AI18+AI19 -> 0 | AK20: =AK18+AK19 -> 0 | AM20: =AM18+AM19 -> 0
B22: Rate Per Building | G22: =G20/C14 -> 12016.204
C27: =C11*3/12 -> 0
C28: =C12*3/12 -> 0
C29: =C13*3/12 -> 0

Sheet Pricing Cost
E2: ='HK Budget (2)'!C14 -> 0.08 | G2: ='HK Budget (2)'!C16 -> 0.014 | H2: 0.14 | I2: Unit Rate
A3: No | B3: Item / English | C3: Unit | D3: Price | E3: Gross Margin | F3: Total | G3: Insurance | H3: VAT | I3: Total W VAT
A4: 1 | B4: Garbage Bags/ small 35*50 Biodegrable | C4: KG | D4: ='[2]Items Pricelist'!D2 -> 41 | E4: =D4*$E$2 -> 3.28 | F4: =D4+E4 -> 44.28 | G4: =F4*$G$2 -> 0.61992 | H4: =(F4+G4)*$H$2 -> 6.2859888 | I4: =ROUND(H4+G4+F4,0) -> 51
A5: 2 | B5: Garbage Bags/ Medium-Black 60*90 Biodegrable | C5: KG | D5: ='[2]Items Pricelist'!D3 -> 41 | E5: =D5*$E$2 -> 3.28 | F5: =D5+E5 -> 44.28 | G5: =F5*$G$2 -> 0.61992 | H5: =(F5+G5)*$H$2 -> 6.2859888 | I5: =ROUND(H5+G5+F5,0) -> 51
A6: 3 | B6: Garbage Bags/ Jumpo-Black70*140 Biodegrable | C6: KG | D6: ='[2]Items Pricelist'!D4 -> 41 | E6: =D6*$E$2 -> 3.28 | F6: =D6+E6 -> 44.28 | G6: =F6*$G$2 -> 0.61992 | H6: =(F6+G6)*$H$2 -> 6.2859888 | I6: =ROUND(H6+G6+F6,0) -> 51
A7: 4 | B7: Garbage Bags/ 120*130 Biodegrable | C7: KG | D7: ='[2]Items Pricelist'!D5 -> 41 | E7: =D7*$E$2 -> 3.28 | F7: =D7+E7 -> 44.28 | G7: =F7*$G$2 -> 0.61992 | H7: =(F7+G7)*$H$2 -> 6.2859888 | I7: =ROUND(H7+G7+F7,0) -> 51
A8: 5 | B8: Garbage Bins 1100 LTR | C8: Each | D8: ='[2]Items Pricelist'!D6 -> 14000 | E8: =D8*$E$2 -> 1120 | F8: =D8+E8 -> 15120 | G8: =F8*$G$2 -> 211.68 | H8: =(F8+G8)*$H$2 -> 2146.4352 | I8: =ROUND(H8+G8+F8,0) -> 17478
A9: 6 | B9: Garbage Bins 240 LTR | C9: Each | D9: ='[2]Items Pricelist'!D7 -> 790 | E9: =D9*$E$2 -> 63.2 | F9: =D9+E9 -> 853.2 | G9: =F9*$G$2 -> 11.9448 | H9: =(F9+G9)*$H$2 -> 121.12027 | I9: =ROUND(H9+G9+F9,0) -> 986
A10: 7 | B10: Garbage Bins 770 LTR | C10: Each | D10: ='[2]Items Pricelist'!D8 -> 12000 | E10: =D10*$E$2 -> 960 | F10: =D10+E10 -> 12960 | G10: =F10*$G$2 -> 181.44 | H10: =(F10+G10)*$H$2 -> 1839.8016 | I10: =ROUND(H10+G10+F10,0) -> 14981
A11: 8 | B11: Garbage Bins 120 LTR | C11: Each | D11: ='[2]Items Pricelist'!D9 -> 590 | E11: =D11*$E$2 -> 47.2 | F11: =D11+E11 -> 637.2 | G11: =F11*$G$2 -> 8.9208 | H11: =(F11+G11)*$H$2 -> 90.456912 | I11: =ROUND(H11+G11+F11,0) -> 737
A12: 9 | B12: Trash bin steel 20 L | C12: Each | D12: ='[2]Items Pricelist'!D10 -> 3500 | E12: =D12*$E$2 -> 280 | F12: =D12+E12 -> 3780 | G12: =F12*$G$2 -> 52.92 | H12: =(F12+G12)*$H$2 -> 536.6088 | I12: =ROUND(H12+G12+F12,0) -> 4370
A13: 10 | B13: Trash bin steel 5 L | C13: Each | D13: ='[2]Items Pricelist'!D11 -> 900 | E13: =D13*$E$2 -> 72 | F13: =D13+E13 -> 972 | G13: =F13*$G$2 -> 13.608 | H13: =(F13+G13)*$H$2 -> 137.98512 | I13: =ROUND(H13+G13+F13,0) -> 1124
A14: 11 | B14: Basket bin240L- cover | C14: Each | D14: ='[2]Items Pricelist'!D12 -> 189 | E14: =D14*$E$2 -> 15.12 | F14: =D14+E14 -> 204.12 | G14: =F14*$G$2 -> 2.85768 | H14: =(F14+G14)*$H$2 -> 28.976875 | I14: =ROUND(H14+G14+F14,0) -> 236
A15: 12 | B15: Basket bin120L- cover | C15: Each | D15: ='[2]Items Pricelist'!D13 -> 114 | E15: =D15*$E$2 -> 9.12 | F15: =D15+E15 -> 123.12 | G15: =F15*$G$2 -> 1.72368 | H15: =(F15+G15)*$H$2 -> 17.478115 | I15: =ROUND(H15+G15+F15,0) -> 142
... A75: 72 | B75: Marble polish powder | C75: Each | D75: ='[2]Items Pricelist'!D73 -> 195 | E75: =D75*$E$2 -> 15.6 | F75: =D75+E75 -> 210.6 | G75: =F75*$G$2 -> 2.9484 | H75: =(F75+G75)*$H$2 -> 29.896776 | I75: =ROUND(H75+G75+F75,0) -> 243
A76: 73 | B76: Microfiber green - red - yellow - Blue | C76: Each | D76: 28 | E76: =D76*$E$2 -> 2.24 | F76: =D76+E76 -> 30.24 | G76: =F76*$G$2 -> 0.42336 | H76: =(F76+G76)*$H$2 -> 4.2928704 | I76: =ROUND(H76+G76+F76,0) -> 35
A77: 74 | B77: Small bucket | C77: Each | D77: ='[2]Items Pricelist'!D75 -> 67 | E77: =D77*$E$2 -> 5.36 | F77: =D77+E77 -> 72.36 | G77: =F77*$G$2 -> 1.01304 | H77: =(F77+G77)*$H$2 -> 10.272226 | I77: =ROUND(H77+G77+F77,0) -> 84
A78: 75 | B78: Glass scrapper | C78: Each | D78: ='[2]Items Pricelist'!D76 -> 28 | E78: =D78*$E$2 -> 2.24 | F78: =D78+E78 -> 30.24 | G78: =F78*$G$2 -> 0.42336 | H78: =(F78+G78)*$H$2 -> 4.2928704 | I78: =ROUND(H78+G78+F78,0) -> 35
A79: 76 | B79: Dry Mob | C79: Each | D79: 2500 | E79: =D79*$E$2 -> 200 | F79: =D79+E79 -> 2700 | G79: =F79*$G$2 -> 37.8 | H79: =(F79+G79)*$H$2 -> 383.292 | I79: =ROUND(H79+G79+F79,0) -> 3121
E80: =D80*$E$2 -> 0 | F80: =D80+E80 -> 0 | G80: =F80*$G$2 -> 0 | H80: =(F80+G80)*$H$2 -> 0 | I80: =ROUND(H80+G80+F80,0) -> 0
B81: Unit Rates (to be invoiced seperately upon request) | E81: =D81*$E$2 -> 0 | F81: =D81+E81 -> 0 | G81: =F81*$G$2 -> 0 | H81: =(F81+G81)*$H$2 -> 0 | I81: =ROUND(H81+G81+F81,0) -> 0
B82: High Pressure Set with Driver, 5K Liters / Month | D82: 80000 | E82: =D82*$E$2 -> 6400 | F82: =D82+E82 -> 86400 | H82: =(F82+G82)*$H$2 -> 12096 | I82: =ROUND(H82+G82+F82,0) -> 98496
B83: High Pressure Set with Driver, 1K Liter / Month | D83: 50000 | E83: =D83*$E$2 -> 4000 | F83: =D83+E83 -> 54000 | G83: =F83*$G$2 -> 756 | H83: =(F83+G83)*$H$2 -> 7665.84 | I83: =#REF! -> #REF!
B84: Boom Lift 15 M / Month | D84: 75000 | E84: =D84*$E$2 -> 6000 | F84: =D84+E84 -> 81000 | H84: =(F84+G84)*$H$2 -> 11340 | I84: =F84+H84 -> 92340
